Workbook

Sheet log
A1: log
A2: Done. I read your comments in the log and Summary tabs and applied them. Your comments stay in the file; my answers are in the new columns (log: "My response"; Summary: columns G and H). What I produced - 5 Joomla import files, exact export format (checked by a round trip), only the products to update, nothing overlaps: 1 mason jar (MJ11-57, MJ102-53, AUMJ100-05, MJ100-17), 2 greenery (MJ100-07, DC-02A, DC112-01A), 3 colours (AU1211-04, AU1111-04, AU219-40), 4 title count (AU11-30), 5 containers and fruit (FBAU61-66, FBAU76-60). - AU-Recipe-Fixes-v1-control.xlsx: the Flag Jarrod lists, Before-After (1 row per SKU, red BEFORE and green AFTER per variant, plus added / removed / changed and Ingredient Price before and after) and Final recipes (all 36 Designer Collection products and every fixed SKU). - This workbook (v10): comments kept and answered, the lists as classes (Flag Jarrod x6, Wine products 18+, Title vs recipe linguistic, Labels removed), an Origin column in colour, and Bunches and Stems lines rewritten to be more inspiring. - AUS master MD v7, both skills v9, the rules artifact republished and the Claude Doc "AU Pricing Rules" updated (nothing held, wine rule for every wine product, container / colour / greenery rules, Joomla upload rules, PV1-PV6, voice codes V1-V19). Your questions - FBAU76-60 fruit: I did not lower it. Live is 6/8/12/15, Jarrod's file is 8/10/12/15. My earlier "Alejandro lowered it to 8" was an assumption I could not verify and I withdraw it. File 5 restores Jarrod's 8 and 10 (upload only, because Jarrod's recipe is right). - Containers: the issue is in Jarrod's file (Small Basket and Gift Basket Box on FBAU61-66 and FBAU76-60; also AU64-11, GBAU71-61, FBAU61-62, outside the five buckets, listed not fixed). I removed the Gift Basket Box in file 5; it looks like outer packaging, so confirm before uploading. - Colours: Jarrod had not fixed them. Replacements are carried. In the AU-Cost master the swaps are the same price, but not in Joomla's own unit costs (Roses Red 1.20 vs Yellow, White, light pink 1.01): AU1211-04's Ingredient Price rises by 1.71 to 3.42 per size; AU1111-04 and AU219-40 do not change. AU199-07's green is its ruscus, so no fix. I could not check KEN or COL (the Product Master has no such column), only the Full Ingredient List. - Greenery: caps do exist (A-C1 in the master file; the Doc said they were never given) and every addition is within them. MJ100-17 and MJ100-07 get 2 x Ruscus Israeli per size (rule G1 from another session today); DC-02A 2/3/3/4 and DC112-01A 2/2/3/3. - Item 2 vs 1b: 1b is a recipe with no jar; item 2 is a recipe that already has the vase or jar and the text had to name it, so nothing to notify. New rule: add the Mason Jar, not a vase. - Blooms vs stems: labels and rule deleted. Not on storefront: only AU11-14 is still N (the other three are live on 7 Oct). Wine: the 18+ notice now applies to all 64 live wine products (list in the log); legal wording first, brand adaptation only after legal agrees. Another session published rules v6 (J1-J5 and G1) while I worked; I merged it into the master file and followed it (Ingredient Price from Joomla unit costs, branch rule, G1). Needs your attention: AUMJ100-05 Petite is priced 39.95 but has no ingredient lines in Joomla, so I did not patch it (decision needed). AU11-30 now has Petite = Standard = 6.
A4: Your comments | B4: My response | C4: SKU | D4: Product title | E4: Bucket | F4: Class | G4: Origin of the problem | H4: Issue type | I4: Detail | J4: Source | K4: Owner / notify
A5: First apply what I mentioned in the summary and we will continue from there. | B5: Applied what you wrote in the Summary: jar added to every size that has a recipe in Joomla_import_1_mason_jar_v1. Petite is priced 39.95 but has no ingredient lines in live, so I did not touch it and flagged it. | C5: AUMJ100-05 | D5: Gerbera Daisies in Mason Jar | E5: Mason Jar | F5: Flag Jarrod: mason jar | G5: Jarrod file (his Standard has no Mason Jar) | H5: Mason jar | I5: Added: - | Removed: - | Changed: - | 7.22→7.54 | 11.3→11.62 | 15.65→15.97 | J5: Joomla_import_1_mason_jar_v1.xlsx | K5: Jarrod: list + upload (J4)
C6: MJ100-17 | D6: Thirty Blooms of Alstroemeria in Mason Jar | E6: Mason Jar | F6: Flag Jarrod: mason jar | G6: Jarrod file (his Standard has no Mason Jar) | H6: Mason jar | I6: Added: - | Removed: - | Changed: 7.85→10.53 | 10.49→13.17 | 13.13→15.81 | 15.77→18.45 | J6: Joomla_import_1_mason_jar_v1.xlsx | K6: Jarrod: list + upload (J4)
C7: MJ102-53 | D7: Make a Wish in Mason Jar Birthday Bundle | E7: Mason Jar | F7: Flag Jarrod: mason jar | G7: Jarrod file (his Standard has no Mason Jar) | H7: Mason jar | I7: Added: - | Removed: - | Changed: 13.73→14.05 | 15.85→16.17 | 18.61→18.93 | 22.13→22.45 | J7: Joomla_import_1_mason_jar_v1.xlsx | K7: Jarrod: list + upload (J4)
C8: MJ11-57 | D8: Half Dozen Assorted Roses in Mason Jar | E8: Mason Jar | F8: Flag Jarrod: mason jar | G8: Jarrod file (his Standard has no Mason Jar) | H8: Mason jar | I8: Added: - | Removed: - | Changed: 9.53→9.85 | 11.73→12.05 | 11.73→12.05 | 15.01→15.33 | J8: Joomla_import_1_mason_jar_v1.xlsx | K8: Jarrod: list + upload (J4)
C9: DC-02A | D9: Designer Collection Anniversary II | E9: Designer Collection | F9: Flag Jarrod: greenery | G9: Jarrod file (his Standard has no greenery) | H9: Greenery | I9: Added: - | Removed: - | Changed: 11.04→13.4 | 14.44→17.98 | 17.84→21.38 | 21.24→25.96 | J9: Joomla_import_2_greenery_v1.xlsx | K9: Jarrod: list + upload (J4)
C10: DC112-01A | D10: Designers Collection I | E10: Designer Collection | F10: Flag Jarrod: greenery | G10: Jarrod file (his Standard has no greenery) | H10: Greenery | I10: Added: - | Removed: - | Changed: 7.64→10.0 | 10.19→12.55 | 12.74→16.28 | 15.29→18.83 | J10: Joomla_import_2_greenery_v1.xlsx | K10: Jarrod: list + upload (J4)
C11: MJ100-07 | D11: Thirty Blooms Of Alstroemeria In Mason Jar | E11: Mason Jar | F11: Flag Jarrod: greenery | G11: Jarrod file (his Standard has no greenery) | H11: Greenery | I11: Added: - | Removed: - | Changed: 9.05→11.41 | 11.69→14.05 | 14.33→16.69 | 16.97→19.33 | J11: Joomla_import_2_greenery_v1.xlsx | K11: Jarrod: list + upload (J4)
C12: AU1111-04 | D12: 24 Pink and White Roses | E12: Bouquets | F12: Flag Jarrod: colour (title says two, recipe has one) | G12: Jarrod file (his Standard has the same colours as live) | H12: Colour | I12: Added: - | Removed: Petite: Roses White 18 → 9, Standard: Roses White 24 → 12, Deluxe: Roses White 30 → 15, Supersize: Roses White 36 → 18 | Changed: 25.57→25.57 | 33.89→33.89 | 39.95→39.95 | 47.19→47.19 | J12: Joomla_import_3_colours_v1.xlsx | K12: Jarrod: list + upload (J4)
C13: AU1211-04 | D13: 24 Red and Yellow Roses | E13: Roses | F13: Flag Jarrod: colour (title says two, recipe has one) | G13: Jarrod file (his Standard has the same colours as live) | H13: Colour | I13: Added: - | Removed: Petite: Roses Yellow 18 → 9, Standard: Roses Yellow 24 → 12, Deluxe: Roses Yellow 30 → 15, Supersize: Roses Yellow 36 → 18 | Changed: 25.57→27.28 | 33.89→36.17 | 41.13→43.98 | 49.45→52.87 | J13: Joomla_import_3_colours_v1.xlsx | K13: Jarrod: list + upload (J4)
A14: verify if we have that ingredient in KEN COL recipe (if we have then include it in the list of changes and in a separated file to udate wit the (mixed colors file this list (1c Title colours (AU1211-04, AU1111-04, AU219-40, AU199-07)) is in the instructions from the summary || Do the same the AU219-40 | B14: Checked the Full Ingredient List of the Product Master (it has no KEN or COL label, so I could not check those two lists): Roses light pink (ING-429, $1.30) = Roses Yellow ($1.30) and Mini Carnations Pink (ING-111, $0.95) = Mini Carnations Red ($0.95), both carried and same price. Jarrod's Standard has the same yellow and red, so he did not fix it. Swap applied in all sizes in Joomla_import_3_colours_v1. Listed here for you to notify Jarrod. | C14: AU219-40 | D14: Pink and Lavender Bouquet | E14: Bouquets | F14: Flag Jarrod: colour (title says two, recipe has one) | G14: Jarrod file (his Standard has the same colours as live) | H14: Colour | I14: Added: Petite: −2 × Roses Yellow, Standard: −3 × Roses Yellow, Deluxe: −4 × Roses Yellow, Supersize: −5 × Roses Yellow, Petite: −1 × Mini Carnations Red, Standard: −2 × Mini Carnations Red, Deluxe: −2 × Mini Carnations Red, Supersize: −3 × Mini Carnations Red | Removed: - | Changed: 13.3→13.3 | 19.04→19.04 | 25.02→25.02 | 31.94→31.94 | J14: Joomla_import_3_colours_v1.xlsx | K14: Jarrod: list + upload (J4)
C15: AU11-30 | D15: Half-Dozen Red Roses | E15: Bouquets | F15: Flag Jarrod: title count | G15: Jarrod file (his Standard is 12 roses, same as live) | H15: Title count | I15: Added: - | Removed: Standard: Roses Red 12 → 6 | Changed: 12.33→12.33 | 21.79→14.59 | 28.99→28.99 | 38.45→38.45 | J15: Joomla_import_4_title_count_v1.xlsx | K15: Jarrod: list + upload (J4)
C16: AU64-11 | D16: Christmas Glory | F16: Flag Jarrod: container / quantity | G16: Jarrod file has both Small Basket and Gift Basket Box | H16: Container (not in the five buckets) | I16: Same two-container issue; not fixed here because the product is outside the five buckets. Tell me if you want them in file 5 | J16: Recipe rules C1-C9 | K16: Jarrod (you notify manually)
C17: FBAU61-62 | D17: Fruit Lover Basket | F17: Flag Jarrod: container / quantity | G17: Jarrod file has both Small Basket and Gift Basket Box | H17: Container (not in the five buckets) | I17: Same two-container issue; not fixed here because the product is outside the five buckets. Tell me if you want them in file 5 | J17: Recipe rules C1-C9 | K17: Jarrod (you notify manually)
C18: GBAU71-61 | D18: Classic Collection II | F18: Flag Jarrod: container / quantity | G18: Jarrod file has both Small Basket and Gift Basket Box | H18: Container (not in the five buckets) | I18: Same two-container issue; not fixed here because the product is outside the five buckets. Tell me if you want them in file 5 | J18: Recipe rules C1-C9 | K18: Jarrod (you notify manually)
A19: Only one containre, Is the issue in Jarrod recipe ? If so as I mention in the cell E18 of summary tab, add those in the list of mason jar so I notify Jarrod manualy. But fix the recipe, include them in the file for the lsit and include it in the product export for joomla, (So I have the other file for me,) to control to learlty see the difference in the recipe, what it was what was missing what was added, the version of every variant in a secon tab, and the file to export the one that I'd need for joomla | B19: The issue is in Jarrod's file: his Petite to Supersize list both a Small Basket and a Gift Basket Box - Medium (same on AU64-11, GBAU71-61 and FBAU61-62, outside the five buckets, listed but not fixed). Fixed in Joomla_import_5 by removing the Gift Basket Box and keeping the Small Basket. The box looks like outer packaging, so confirm with Jarrod before uploading. What it was, what was missing and what was added per variant: AU-Recipe-Fixes-v1-control.xlsx (Before-After tab). | C19: FBAU61-66 | D19: European Sampler Basket | E19: Bouquets | F19: Flag Jarrod: container / quantity | G19: Jarrod file has both Small Basket and Gift Basket Box | H19: Container / fruit | I19: Added: Petite: −1 × Gift Basket Box - Medium, Standard: −1 × Gift Basket Box - Medium, Deluxe: −1 × Gift Basket Box - Medium, Supersize: −1 × Gift Basket Box - Medium | Removed: - | Changed: 18.29→17.29 | 22.29→21.29 | 26.29→25.29 | 30.29→29.29 | J19: Joomla_import_5_containers_fruit_v1.xlsx | K19: Jarrod: list + upload (J4)
A20: Leave my questions, create in from your response, why did we lower to 8? I don't see why this should be lowered, this should remain 8 10 … and so on as jarrods file if not explain me the reason, (review the rules and the AUS maste) | B20: I did not lower it on purpose. Live and master have fruit 6 / 8 / 12 / 15 (Petite to Supersize); Jarrod's file has 8 / 10 / 12 / 15. My earlier label 'Alejandro lowered it to 8' was an assumption I could not verify; I withdraw it. Rule: Jarrod's recipe is the base (A-R1), so Joomla_import_5 sets Petite 8 and Standard 10 (Deluxe and Supersize already match). Please ask Jarrod why live shows 6 / 8. Est. ING price +$4.00 on Petite and Standard. | C20: FBAU76-60 | D20: Fruits & Chocolates | E20: Bouquets | F20: Flag Jarrod: container / quantity | G20: Jarrod file has both Small Basket and Gift Basket Box; fruit: live 6/8 vs Jarrod 8/10 (live/master differs from Jarrod) | H20: Container / fruit | I20: Added: Petite: −1 × Gift Basket Box - Medium, Standard: −1 × Gift Basket Box - Medium, Deluxe: −1 × Gift Basket Box - Medium, Supersize: −1 × Gift Basket Box - Medium | Removed: Petite: Fresh Fruit 6 → 8, Standard: Fresh Fruit 8 → 10 | Changed: 16.29→19.29 | 20.29→23.29 | 30.29→29.29 | 36.29→35.29 | J20: Joomla_import_5_containers_fruit_v1.xlsx | K20: Jarrod: list + upload (J4)
C21: AUMJ100-05 | D21: Gerbera Daisies in Mason Jar | E21: Mason Jar | F21: Flag Jarrod: empty recipe on a priced size | G21: Live export | H21: Empty recipe | I21: Petite is priced 39.95 but has no ingredient lines; the fix was not applied to this size | J21: Joomla_import_1_mason_jar_v1.xlsx | K21: Jarrod (you notify manually)
C22: AU0511-17 | D22: Summer Blooms | E22: Bouquets | F22: Recipe fix: notify Jarrod | G22: Master / live | H22: Gate Item not carried ($0) removed per rule I4 | I22: 2 x Lisianthus Orange: ING-1155 is $0 in the catalogue, so it is removed, not replaced | J22: Recipe rules | K22: Jarrod / Benny
C23: RBC-02C | D23: Bunches Purply Pink Collection III | E23: Bouquets | F23: Recipe fix: notify Jarrod | G23: Master / live | H23: Gate Item not carried ($0) removed per rule I4 | I23: 3 x Carnations Purple: ING-1516 is $0 in the catalogue, so it is removed, not replaced | J23: Recipe rules | K23: Jarrod / Benny
C24: RBC-02C | D24: Bunches Purply Pink Collection III | E24: Bouquets | F24: Recipe fix: notify Jarrod | G24: Master / live | H24: Gate Quantity differs from Jarrod | I24: Israeli ruscus is 2 in the master; Jarrod typed two lines of 2 (4) | J24: Recipe rules | K24: Jarrod / Benny
C25: AU-ADD-BUNDLE-PREM-WINE-CHOC-5495 | D25: Bundle: Premium Wine + Chocolates | E25: (outside the five buckets) | F25: Wine products: 18+ notice | G25: Ashraf gate file / your rule | H25: Wine in the live recipe | I25: Live status N. notice NOT in the current text. Legal wording first (as live), brand adaptation only after legal OK | J25: Joomla export 7 Oct
C26: AU-ADD-BUNDLE-SPARK-CELEB-6995 | D26: Bundle: Sparkling Wine + Chocolates + Card | E26: (outside the five buckets) | F26: Wine products: 18+ notice | G26: Ashraf gate file / your rule | H26: Wine in the live recipe | I26: Live status N. notice NOT in the current text. Legal wording first (as live), brand adaptation only after legal OK | J26: Joomla export 7 Oct
C27: AU-ADD-BUNDLE-WB-CHOC-5995 | D27: Bundle: Wolf Blass Wine + Chocolates | E27: (outside the five buckets) | F27: Wine products: 18+ notice | G27: Ashraf gate file / your rule | H27: Wine in the live recipe | I27: Live status N. notice NOT in the current text. Legal wording first (as live), brand adaptation only after legal OK | J27: Joomla export 7 Oct
C28: AU-ADD-PREM-RED-WINE-4495 | D28: Premium Red Wine | E28: (outside the five buckets) | F28: Wine products: 18+ notice | G28: Ashraf gate file / your rule | H28: Wine in the live recipe | I28: Live status N. notice NOT in the current text. Legal wording first (as live), brand adaptation only after legal OK | J28: Joomla export 7 Oct
C29: AU-ADD-PREM-WHITE-WINE-4495 | D29: Premium White Wine | E29: (outside the five buckets) | F29: Wine products: 18+ notice | G29: Ashraf gate file / your rule | H29: Wine in the live recipe | I29: Live status N. notice NOT in the current text. Legal wording first (as live), brand adaptation only after legal OK | J29: Joomla export 7 Oct
C30: AU-ADD-RED-WINE-6995 | D30: Red Wine | E30: (outside the five buckets) | F30: Wine products: 18+ notice | G30: Ashraf gate file / your rule | H30: Wine in the live recipe | I30: Live status N. notice NOT in the current text. Legal wording first (as live), brand adaptation only after legal OK | J30: Joomla export 7 Oct
C31: AU-ADD-SPARKLING-WINE-5495 | D31: Sparkling White Wine | E31: (outside the five buckets) | F31: Wine products: 18+ notice | G31: Ashraf gate file / your rule | H31: Wine in the live recipe | I31: Live status N. notice NOT in the current text. Legal wording first (as live), brand adaptation only after legal OK | J31: Joomla export 7 Oct
C32: AU-ADD-WB-WHITE-WINE-4495 | D32: Wolf Blass White Wine | E32: (outside the five buckets) | F32: Wine products: 18+ notice | G32: Ashraf gate file / your rule | H32: Wine in the live recipe | I32: Live status N. notice NOT in the current text. Legal wording first (as live), brand adaptation only after legal OK | J32: Joomla export 7 Oct
C33: AU-ADD-WHITE-WINE-4495 | D33: White Wine | E33: (outside the five buckets) | F33: Wine products: 18+ notice | G33: Ashraf gate file / your rule | H33: Wine in the live recipe | I33: Live status N. notice NOT in the current text. Legal wording first (as live), brand adaptation only after legal OK | J33: Joomla export 7 Oct
C34: AU110-04 | D34: Dozen Mixed Colour Roses, Vase, Card & Chocolates | E34: (outside the five buckets) | F34: Wine products: 18+ notice | G34: Ashraf gate file / your rule | H34: Wine in the live recipe | I34: Live status Y. notice NOT in the current text. Legal wording first (as live), brand adaptation only after legal OK | J34: Joomla export 7 Oct
C35: AU115-03R | D35: 3 Red Roses and Red Wine Combo | E35: (outside the five buckets) | F35: Wine products: 18+ notice | G35: Ashraf gate file / your rule | H35: Wine in the live recipe | I35: Live status Y. notice NOT in the current text. Legal wording first (as live), brand adaptation only after legal OK | J35: Joomla export 7 Oct
C36: AU115-03W | D36: 3 Red Roses and White Wine Combo | E36: (outside the five buckets) | F36: Wine products: 18+ notice | G36: Ashraf gate file / your rule | H36: Wine in the live recipe | I36: Live status Y. notice NOT in the current text. Legal wording first (as live), brand adaptation only after legal OK | J36: Joomla export 7 Oct
... C88: WBLD-WW-VW | D88: Lindt & Chardonnay Basket | E88: (outside the five buckets) | F88: Wine products: 18+ notice | G88: Ashraf gate file / your rule | H88: Wine in the live recipe | I88: Live status Y. notice NOT in the current text. Legal wording first (as live), brand adaptation only after legal OK | J88: Joomla export 7 Oct
C89: AU1111-04 | D89: 24 Pink and White Roses | E89: Bouquets | F89: Ashraf gate item | G89: Ashraf gate file | H89: Gate: Approved split | I89: Half light pink / half white approved; ingredient carried, price unchanged. Master Standard still shows 24 white until updated (resolved) | J89: Ashraf gate file | K89: Benny (Jarrod from about 12 Oct)
C90: AUFS-11 | D90: Dozen Red Roses, Wine & Truffles | E90: Roses | F90: Ashraf gate item | G90: Ashraf gate file | H90: Gate: Confirm Classic build | I90: Wine and truffles are in the master Standard; Jarrod Standard lists only roses, baby's breath and ruscus | J90: Ashraf gate file | K90: Benny (Jarrod from about 12 Oct)
C91: AU0511-17 | D91: Summer Blooms | E91: Bouquets | F91: Ashraf gate item | G91: Ashraf gate file | H91: Gate: Item not carried ($0) removed per rule I4 | I91: 2 x Lisianthus Orange: ING-1155 is $0 in the catalogue, so it is removed, not replaced | J91: Ashraf gate file | K91: Benny (Jarrod from about 12 Oct)
C92: RBC-02C | D92: Bunches Purply Pink Collection III | E92: Bouquets | F92: Ashraf gate item | G92: Ashraf gate file | H92: Gate: Item not carried ($0) removed per rule I4 | I92: 3 x Carnations Purple: ING-1516 is $0 in the catalogue, so it is removed, not replaced | J92: Ashraf gate file | K92: Benny (Jarrod from about 12 Oct)
C93: AUSTRT-02 | D93: Ivory Grace Trio | E93: Bouquets | F93: Ashraf gate item | G93: Ashraf gate file | H93: Gate: Jar mention | I93: Mason Jar is in the master Standard; description must say "in a mason jar" (resolved) | J93: Ashraf gate file | K93: Alejandro
C94: AUSTRT-03 | D94: Blushing Rose Trio | E94: Bouquets | F94: Ashraf gate item | G94: Ashraf gate file | H94: Gate: Jar mention | I94: Mason Jar is in the master Standard; description must say "in a mason jar" (resolved) | J94: Ashraf gate file | K94: Alejandro
C95: RBC-02C | D95: Bunches Purply Pink Collection III | E95: Bouquets | F95: Ashraf gate item | G95: Ashraf gate file | H95: Gate: Quantity differs from Jarrod | I95: Israeli ruscus is 2 in the master; Jarrod typed two lines of 2 (4) | J95: Ashraf gate file | K95: Benny (Jarrod from about 12 Oct)
C96: AU15-50 | D96: 50 Blooms of Peruvian Lilies | E96: Bouquets | F96: Ashraf gate item | G96: Ashraf gate file | H96: Gate: Title blooms vs stems | I96: Title counts blooms, recipe counts stems; bridge wording needs blooms per stem from Alejandro/Benny | J96: Ashraf gate file
C97: MDA-01 | D97: 50 Blooms of Peruvian Lilies Set | E97: Bouquets | F97: Ashraf gate item | G97: Ashraf gate file | H97: Gate: Title blooms vs stems | I97: Title counts blooms, recipe counts stems; bridge wording needs blooms per stem from Alejandro/Benny | J97: Ashraf gate file
C98: MDA-03 | D98: 100 Peruvian Lilies Set | E98: Bouquets | F98: Ashraf gate item | G98: Ashraf gate file | H98: Gate: Title blooms vs stems | I98: Title counts blooms, recipe counts stems; bridge wording needs blooms per stem from Alejandro/Benny | J98: Ashraf gate file | K98: Alejandro, with Benny
C99: MJ100-17 | D99: Thirty Blooms of Alstroemeria in Mason Jar | E99: Mason Jar | F99: Ashraf gate item | G99: Ashraf gate file | H99: Gate: Title blooms vs stems | I99: Title counts blooms, recipe counts stems; bridge wording needs blooms per stem from Alejandro/Benny | J99: Ashraf gate file | K99: Benny (Jarrod from about 12 Oct)
C100: AUSC-02 | D100: Sweetheart Collection II | E100: Bouquets | F100: Ashraf gate item | G100: Ashraf gate file | H100: Gate: Vase mention | I100: Red Vase is in the master Standard; description must say "in a red vase" (resolved) | J100: Ashraf gate file | K100: Alejandro
C101: AUSC-03 | D101: Sweetheart Collection III | E101: Bouquets | F101: Ashraf gate item | G101: Ashraf gate file | H101: Gate: Vase mention | I101: Red Vase is in the master Standard; description must say "in a red vase" (resolved) | J101: Ashraf gate file | K101: Alejandro
C102: AUSC-04 | D102: Sweetheart Collection IV | E102: Bouquets | F102: Ashraf gate item | G102: Ashraf gate file | H102: Gate: Vase mention | I102: Red Vase is in the master Standard; description must say "in a red vase" (resolved) | J102: Ashraf gate file | K102: Alejandro
C103: LF15-10C | D103: Hugs and Kisses III | E103: Bouquets | F103: Ashraf gate item | G103: Ashraf gate file | H103: Gate: Vase mention | I103: Red Vase is in the master Standard; description must say "in a red vase" (resolved) | J103: Ashraf gate file | K103: Alejandro
C104: AU11-14 | D104: Two Dozen Pink Roses | E104: Roses | F104: Ashraf gate item | G104: Ashraf gate file | H104: Gate: confirm product status | I104: Not on the live storefront (Joomla export 7 Oct shows status N); skip upload if no longer sold | J104: Ashraf gate file / Joomla export | K104: Alejandro
C105: AUDNAT-01 | D105: Native Flowers Bouquet Designer Collection I | E105: Designer Collection | F105: Ashraf gate item | G105: Ashraf gate file | H105: Gate: native claim to confirm | I105: "native" left out until Benny confirms no protea or leucadendron | J105: Ashraf gate file | K105: Benny
C106: AUDNAT-02 | D106: Native Flowers Bouquet Designer Collection II | E106: Designer Collection | F106: Ashraf gate item | G106: Ashraf gate file | H106: Gate: native claim to confirm | I106: "native" left out until Benny confirms no protea or leucadendron | J106: Ashraf gate file | K106: Benny
C107: AUDNAT-03 | D107: Native Flowers Bouquet Designer Collection III | E107: Designer Collection | F107: Ashraf gate item | G107: Ashraf gate file | H107: Gate: native claim to confirm | I107: "native" left out until Benny confirms no protea or leucadendron | J107: Ashraf gate file | K107: Benny
C108: AUMJ-NW-005 | D108: Native Flowers Bouquet in Mason Jar | E108: Mason Jar | F108: Ashraf gate item | G108: Ashraf gate file | H108: Gate: native claim to confirm | I108: "native" left out until Benny confirms no protea or leucadendron | J108: Ashraf gate file | K108: Benny
C109: AU111-72 | D109: Joy and Harmony | E109: Bouquets | F109: Ashraf gate item | G109: Ashraf gate file | H109: Gate: voice (all-white chrysanthemum) | I109: Neutral occasion line used; Ashraf decides | J109: Ashraf gate file | K109: Ashraf
C110: AUMJ-NW-030 | D110: Cloud Nine Bouquet in Mason Jar | E110: Mason Jar | F110: Ashraf gate item | G110: Ashraf gate file | H110: Gate: voice (all-white chrysanthemum) | I110: Neutral occasion line used; Ashraf decides | J110: Ashraf gate file | K110: Ashraf
C111: AUSC-01 | D111: Sweetheart Collection I | E111: Bouquets | F111: Current text vs recipe | G111: Pre-existing (live text) | H111: Current text: Current description is empty | I111: Description is empty. | J111: Current description vs recipe
C112: MJ102-53 | D112: Make a Wish in Mason Jar Birthday Bundle | E112: Mason Jar | F112: Current text vs recipe | G112: Pre-existing (live text) | H112: Current text: Gift/container in recipe not mentioned: balloon | I112: Recipe includes balloon but the description doesn't mention it. | J112: Current description vs recipe
C113: AUBC-01 | D113: Birthday Combo I | E113: Bouquets | F113: Current text vs recipe | G113: Pre-existing (live text) | H113: Current text: Gift/container in recipe not mentioned: basket | I113: Recipe includes basket but the description doesn't mention it. | J113: Current description vs recipe
C114: AUBC-02 | D114: Birthday Combo II | E114: Bouquets | F114: Current text vs recipe | G114: Pre-existing (live text) | H114: Current text: Gift/container in recipe not mentioned: basket | I114: Recipe includes basket but the description doesn't mention it. | J114: Current description vs recipe
C115: AUBC-04 | D115: Birthday Combo IV | E115: Bouquets | F115: Current text vs recipe | G115: Pre-existing (live text) | H115: Current text: Gift/container in recipe not mentioned: basket | I115: Recipe includes basket but the description doesn't mention it. | J115: Current description vs recipe
C116: FBAU76-60 | D116: Fruits & Chocolates | E116: Bouquets | F116: Current text vs recipe | G116: Pre-existing (live text) | H116: Current text: Gift/container in recipe not mentioned: basket | I116: Recipe includes basket but the description doesn't mention it. | J116: Current description vs recipe
C117: AUFS-05 | D117: Dozen Mixed Roses Combo | E117: Bouquets | F117: Current text vs recipe | G117: Pre-existing (live text) | H117: Current text: Gift/container in recipe not mentioned: chocolates | I117: Recipe includes chocolates but the description doesn't mention it. | J117: Current description vs recipe
C118: AUFS-12 | D118: Dozen Mixed Roses Super Combo | E118: Bouquets | F118: Current text vs recipe | G118: Pre-existing (live text) | H118: Current text: Gift/container in recipe not mentioned: chocolates | I118: Recipe includes chocolates but the description doesn't mention it. | J118: Current description vs recipe
C119: AURP-B29 | D119: The Birthday Bundle | E119: Bouquets | F119: Current text vs recipe | G119: Pre-existing (live text) | H119: Current text: Gift/container in recipe not mentioned: chocolates | I119: Recipe includes chocolates but the description doesn't mention it. | J119: Current description vs recipe
C120: AUSC-03 | D120: Sweetheart Collection III | E120: Bouquets | F120: Current text vs recipe | G120: Pre-existing (live text) | H120: Current text: Gift/container in recipe not mentioned: chocolates | I120: Recipe includes chocolates but the description doesn't mention it. | J120: Current description vs recipe
C121: AUSC-04 | D121: Sweetheart Collection IV | E121: Bouquets | F121: Current text vs recipe | G121: Pre-existing (live text) | H121: Current text: Gift/container in recipe not mentioned: chocolates | I121: Recipe includes chocolates but the description doesn't mention it. | J121: Current description vs recipe
C122: LF15-10C | D122: Hugs and Kisses III | E122: Bouquets | F122: Current text vs recipe | G122: Pre-existing (live text) | H122: Current text: Gift/container in recipe not mentioned: chocolates | I122: Recipe includes chocolates but the description doesn't mention it. | J122: Current description vs recipe
... C330: MJ55-01 | D330: Radiant Roses in Mason Jar | E330: Mason Jar | F330: Current text vs recipe | G330: Pre-existing (live text) | H330: Current text: Wrong flower count: roses | I330: Says 14 roses — Classic recipe has 3. | J330: Current description vs recipe
C331: AL100-71AURP | D331: Full Heart | E331: Sympathy | F331: Copy: identical text | G331: Generated text | H331: Duplicate copy across SKUs (Aussie Blooms) | I331: Identical text with: AU100-71 | J331: Generated text check | K331: Alejandro
C332: AU100-71 | D332: Full Heart | E332: Sympathy | F332: Copy: identical text | G332: Generated text | H332: Duplicate copy across SKUs (Aussie Blooms) | I332: Identical text with: AL100-71AURP | J332: Generated text check | K332: Alejandro
C333: AUBC-01 | D333: Birthday Combo I | E333: Bouquets | F333: Copy: identical text | G333: Generated text | H333: Duplicate copy across SKUs (Bloomex AU) | I333: Identical text with: DC112-01A | J333: Generated text check | K333: Alejandro
C334: DC112-01 | D334: Designers Collection I | E334: Designer Collection | F334: Copy: identical text | G334: Generated text | H334: Duplicate copy across SKUs (Bloomex AU) | I334: Identical text with: DC112-03 | J334: Generated text check | K334: Alejandro
C335: DC112-01A | D335: Designers Collection I | E335: Designer Collection | F335: Copy: identical text | G335: Generated text | H335: Duplicate copy across SKUs (Bloomex AU) | I335: Identical text with: AUBC-01 | J335: Generated text check | K335: Alejandro
C336: DC112-03 | D336: Designers Collection III | E336: Designer Collection | F336: Copy: identical text | G336: Generated text | H336: Duplicate copy across SKUs (Bloomex AU) | I336: Identical text with: DC112-01 | J336: Generated text check | K336: Alejandro
C337: DCMJ-01 | D337: Designer Collection Mason Jar I | E337: Mason Jar | F337: Copy: identical text | G337: Generated text | H337: Duplicate copy across SKUs (Bloomex AU) | I337: Identical text with: DCMJ-02A | J337: Generated text check | K337: Alejandro
C338: DCMJ-01A | D338: Designer Collection Mason Jar I | E338: Mason Jar | F338: Copy: identical text | G338: Generated text | H338: Duplicate copy across SKUs (Bloomex AU) | I338: Identical text with: DCMJ-02 | J338: Generated text check | K338: Alejandro
C339: DCMJ-02 | D339: Designer Collection Mason Jar II | E339: Mason Jar | F339: Copy: identical text | G339: Generated text | H339: Duplicate copy across SKUs (Bloomex AU) | I339: Identical text with: DCMJ-01A | J339: Generated text check | K339: Alejandro
C340: DCMJ-02A | D340: Designer Collection Mason Jar II | E340: Mason Jar | F340: Copy: identical text | G340: Generated text | H340: Duplicate copy across SKUs (Bloomex AU) | I340: Identical text with: DCMJ-01 | J340: Generated text check | K340: Alejandro
C341: AU11-65 | D341: One Dozen Premium Red Roses | E341: Bouquets | F341: Copy: identical text | G341: Generated text | H341: Duplicate copy across SKUs (Bunches and Stems) | I341: Identical text with: AU9-99 | J341: Generated text check | K341: Alejandro
C342: AU9-99 | D342: 12 Long Stemmed Red Roses | E342: Bouquets | F342: Copy: identical text | G342: Generated text | H342: Duplicate copy across SKUs (Bunches and Stems) | I342: Identical text with: AU11-65 | J342: Generated text check | K342: Alejandro
C343: AU199-07 | D343: Green & White Heart | E343: Bouquets | F343: Label removed (your comment) | G343: Joomla export 7 Oct | H343: C3 title colour not in recipe | I343: Title says green -> recipe has 10 stems of Israeli ruscus (green foliage); live status N. Not a recipe problem | J343: Your comment 8 Oct
C344: AU15-50 | D344: 50 Blooms of Peruvian Lilies | E344: Bouquets | F344: Label removed (your comment) | G344: Your decision | H344: C7 Title blooms vs stems | I344: Title counts blooms, recipe counts stems: send blooms per stem so the wording can bridge them -> intentional strategy: titles count blooms, recipes count stems | J344: Your comment 8 Oct
C345: MDA-01 | D345: 50 Blooms of Peruvian Lilies Set | E345: Bouquets | F345: Label removed (your comment) | G345: Your decision | H345: C7 Title blooms vs stems | I345: Title counts blooms, recipe counts stems: send blooms per stem so the wording can bridge them -> intentional strategy: titles count blooms, recipes count stems | J345: Your comment 8 Oct
C346: MDA-03 | D346: 100 Peruvian Lilies Set | E346: Bouquets | F346: Label removed (your comment) | G346: Your decision | H346: C7 Title blooms vs stems | I346: Title counts blooms, recipe counts stems: send blooms per stem so the wording can bridge them -> intentional strategy: titles count blooms, recipes count stems | J346: Your comment 8 Oct
C347: MJ100-17 | D347: Thirty Blooms of Alstroemeria in Mason Jar | E347: Mason Jar | F347: Label removed (your comment) | G347: Your decision | H347: C7 Title blooms vs stems | I347: Title counts blooms, recipe counts stems: send blooms per stem so the wording can bridge them -> intentional strategy: titles count blooms, recipes count stems | J347: Your comment 8 Oct
C348: AU0511-18 | D348: Sue Elena | E348: Bouquets | F348: Label removed (live Joomla) | G348: Joomla export 7 Oct | H348: Bigger size has fewer items | I348: Supersize < Deluxe for Gerbera Daisies assorted. -> Live sizes: no bigger size has fewer items | J348: Joomla export 7 Oct
C349: AU1111-04 | D349: 24 Pink and White Roses | E349: Bouquets | F349: Label removed (live Joomla) | G349: Joomla export 7 Oct | H349: Bigger size has fewer items | I349: Deluxe < Standard for Roses White. -> Live sizes: no bigger size has fewer items | J349: Joomla export 7 Oct
C350: AU1111-04 | D350: 24 Pink and White Roses | E350: Bouquets | F350: Label removed (live Joomla) | G350: Joomla export 7 Oct | H350: Bigger size has fewer items | I350: Supersize < Deluxe for Roses light pink. -> Live sizes: no bigger size has fewer items | J350: Joomla export 7 Oct
C351: AU112-22 | D351: Romantic Getaway | E351: Bouquets | F351: Label removed (live Joomla) | G351: Joomla export 7 Oct | H351: Bigger size has fewer items | I351: Standard < Petite for Carnation White. -> Live sizes: no bigger size has fewer items | J351: Joomla export 7 Oct
C352: AU112-90 | D352: Simply Sweet | E352: Bouquets | F352: Label removed (live Joomla) | G352: Joomla export 7 Oct | H352: Bigger size has fewer items | I352: Supersize < Deluxe for Alstroemeria Pink. -> Live sizes: no bigger size has fewer items | J352: Joomla export 7 Oct
C353: AU213-60 | D353: Joyous Delight | E353: Bouquets | F353: Label removed (live Joomla) | G353: Joomla export 7 Oct | H353: Bigger size has fewer items | I353: Supersize < Deluxe for Carnations Cream. -> Live sizes: no bigger size has fewer items | J353: Joomla export 7 Oct
C354: AU51-01 | D354: Bestseller Combo I | E354: Bouquets | F354: Label removed (live Joomla) | G354: Joomla export 7 Oct | H354: Bigger size has fewer items | I354: Deluxe < Standard for Cellophane. -> Live sizes: no bigger size has fewer items | J354: Joomla export 7 Oct
... C428: AURP06 | D428: Teddy Bear | E428: Add-Ons | F428: Live differs from master | G428: Master vs live | H428: Text follows live | I428: small teddy bear: reviewed None, live 1; teddy bear: reviewed 1, live None | J428: Joomla export 7 Oct
A429: update this rules for pricing rules for the AUS Master skill and MD artifact fo geral rules for aus; | B429: Added as rules PV1 to PV6 (pricing verification) in the MD, both skills and the Doc. | F429: Rule added (pricing verification) | G429: Your pasted rules | H429: $0 IN AU-COST MASTER (NOT AVAILABLE) | I429: CRITICAL. The recipe uses an ingredient whose Price AUD is $0 or blank in the AU-Cost master, i.e. an item we don't have. A $0 ING price in products_list alone is not flagged. | J429: Your comment 8 Oct (rows 78-84)
F430: Rule added (pricing verification) | G430: Your pasted rules | H430: BIGGER SIZE HAS FEWER ITEMS | I430: An ingredient has a lower qty in a bigger size than in the size below, or disappears. Each item is listed as smaller→bigger qty. | J430: Your comment 8 Oct (rows 78-84)
F431: Rule added (pricing verification) | G431: Your pasted rules | H431: INGREDIENT MISMATCH | I431: Σ(qty × AU-Cost master price) for the variant ≠ ING price in products_list (tolerance $0.01). The Σ columns are live SUMIFS over the Recipe Lines tab. | J431: Your comment 8 Oct (rows 78-84)
F432: Rule added (pricing verification) | G432: Your pasted rules | H432: Not checked | I432: Retail price vs cost; single-size products. | J432: Your comment 8 Oct (rows 78-84)
...

Sheet Summary
A1: AU product descriptions v10: summary (counts are live formulas)
A3: A. Ashraf concerns and how each was handled | B3: SKUs | C3: How it was handled | D3: Where to check | E3: Questions alejandro | F3: Question 2 | G3: My response to column E | H3: My response to column F
A4: 1 Recipe accuracy (12 rows on the old hold list) | B4: =COUNTIF(log!$H$5:$H$989,"Gate: was on the hold list, now handled by rule") | C4: Nothing is held. Every old gate-hold row is now either fixed in a Joomla import file, listed under a Flag Jarrod class, or resolved by the live export (AU112-90, AUFS-11, AU111-41). | D4: log | E4: Yes fix the greenery following the caps, notify. Notify Jarrod, create a list of these products. | F4: From this document I should find, differences beetween the master sheet and the recipes loaded in Joomla. 2) I should see differences bettween the titles and the recipes (linguistic) Label and use colors for those problems (Use an additional label if the issue comes from Jarrod file or if it was there before). | G4: Yes, fixed in the Joomla files. The cap values have never been given (the Doc says so), so the additions are proposals by sibling pattern: Ruscus Israeli 1/1/2/2 on MJ100-17 and MJ100-07 (as MJ100-48), 2/3/3/4 on DC-02A and 2/2/3/3 on DC112-01A (as AUDC-01 and DC-03A). Joomla_import_1 (MJ100-17) and Joomla_import_2. Jarrod list: class Flag Jarrod: greenery. | H4: 1) Master vs Joomla: class 'Live differs from master' (9 SKUs). 2) Titles vs recipes: classes 'Flag Jarrod: ...' and 'Title vs recipe (linguistic)' (a flower named in the title that the recipe lacks). The 'Origin of the problem' column and its colour tell you whether it comes from Jarrod's file (orange), the master or live (blue), Ashraf's file (purple) or the Joomla export (green).
A5: 1b Mason jar missing (MJ100-17, MJ11-57, MJ102-53, AUMJ100-05) | B5: =COUNTIF(log!$F$5:$F$989,"Flag Jarrod: mason jar") | C5: Mason Jar x1 added to every size that has a recipe: Joomla_import_1. List = class Flag Jarrod: mason jar. | D5: log; Joomla_import_1 | E5: If the product says mason jar (verify that has it in the recipe) or at least a substitution. If not add it to the master, (and create a second joomla export with only the products with the fixies (meaning adding the 4 prodcuts that don't have a reciient in the list of ingredients (a document identically to export) | F5: Create a separated list with these 4 products | G5: Done: jar added in Joomla_import_1_mason_jar_v1 (MJ11-57, MJ102-53, AUMJ100-05, MJ100-17) in the identical export format. The Mason Jar (ING-1212, $0.50) is carried, so no substitution was needed. Jarrod's Standard has no jar on any of the four. | H5: List created: class 'Flag Jarrod: mason jar' (4 rows) in the log and in AU-Recipe-Fixes-v1-control.xlsx.
A6: 1c Title colours (AU1211-04, AU1111-04, AU219-40, AU199-07) | B6: =COUNTIF(log!$F$5:$F$989,"Flag Jarrod: colour (title says two, recipe has one)") | C6: Same-price swaps in Joomla_import_3 (AU199-07 is not a recipe problem: its green is the ruscus). | D6: log; Joomla_import_3 | E6: IF it's color,(first confirm if this wasn't fixed in the recipe by Jarrod) If not, fix it in the master, and create a list, usually we have the colors. Verify wit the list of ingerdients, if it has a substitution or the item is listed, then replace and if it has the same price) then create a separated product export for Joomla with only these products, and add them to other list as the past concernt. | F6: Verify prices, fix the master, create a product export with only those product for joomla, and create a list with this 4 products | G6: Checked first: Jarrod did not fix them (his Standard: AU1211-04 24 yellow, AU1111-04 24 white, AU219-40 no pink). Replacements are carried and same price: Roses Red = Roses Yellow ($1.30), Roses light pink = Roses White = Roses Yellow ($1.30), Mini Carnations Pink = Red ($0.95). AU1211-04 and AU1111-04 are split half and half in every size; AU219-40 swaps Roses Yellow for Roses light pink and Mini Carnations Red for Pink. Joomla_import_3_colours_v1 holds only these 3. AU199-07 is not a recipe problem (its green is 10 stems of ruscus, live N). | H6: Prices verified: the swaps are price-neutral, so the ING price does not move. Jar and greenery additions add cost: the Before-After tab of the control file shows the estimate per size (AU-Cost prices; Joomla recomputes on import). Retail prices are not changed. List of the colour products: class 'Flag Jarrod: colour'.
A7: 1d Title count (AU11-30 says 6, recipe 12) | B7: =COUNTIF(log!$F$5:$F$989,"Flag Jarrod: title count") | C7: Standard set to 6 in Joomla_import_4; Jarrod to be told (Petite is also 6). | D7: log; Joomla_import_4 | E7: Standar Must have 6 roses. Flagg, fix the recipe, notify jarrod, remind this and add it alon e in other list. | G7: Done: AU11-30 Standard set from 12 to 6 roses in Joomla_import_4_title_count_v1 (alone in its own file). Reminder for Jarrod: Petite is also 6, so Petite and Standard are now equal; Deluxe 18 and Supersize 24 are unchanged. It is in the Flag Jarrod: title count list.
A8: 1e Wine and truffles in AUFS-11 | B8: =COUNTIF(log!$H$5:$H$989,"Flag for Jarrod (confirm wine and truffles in the Classic build)") | C8: Live already has both: confirm label removed. 18+ notice kept. | D8: log, class Label removed | E8: Keep the 18+ notice on the four wine products (AU115-12, AUFS-10, AUFS-11 and AUFS-12). | F8: For all product descriptions with wine, (sabve this to the product description skill and update the artifact with instructions). Confirm if if we're having this artifact updated with all skills. Thisshould be updated in the artifact(https://claude.ai/artifact/14z2sKE33yXsoV5Z9EmYjH?sk=YMx0fnVdrPONIKfGPgpEJw#793324ab-7e56) and in the AUS master skill (that could use this artifact to function to read the ruless | G8: Kept: 18+ notice on AU115-12, AUFS-10, AUFS-11 and AUFS-12 in every brand text. | H8: Saved: the rule now covers every product whose recipe has wine (64 live products, list in the log, class Wine products: 18+ notice). Written into the MD (rule D3 and D3b), both skills and the Doc. To your question: I updated the rules artifact (4X1LU...) every round, but I had never edited the Claude Doc 'AU Pricing Rules' (14z2...) before this round; both are now updated from the same MD. AUFS-12's current text has no notice: it is in the wine list.
A9: 1f Blooms in the title vs stems in the recipe | B9: =COUNTIF(log!$H$5:$H$989,"C7 Title blooms vs stems") | C9: Intentional strategy (titles count blooms, recipes count stems): labels removed, rule C7 deleted. | D9: log | E9: Ignore this, we use blooms because it looks like more, and we deliver stems because is how we calculate. It's not a contradiction it's a strategy. | G9: Understood and applied: blooms-vs-stems labels removed and the C7 rule deleted. Rule C7 now reads: titles count blooms and recipes count stems on purpose, never flag it.
A10: 2 Missing vase or jar (AUSC-02/03/04, LF15-10C, AUSTRT-02/03) | B10: =COUNTIF(log!$H$5:$H$989,"Gate: Vase mention")+COUNTIF(log!$H$5:$H$989,"Gate: Jar mention") | C10: Master and live already have the line; every brand text names it. | D10: Products | E10: If master has the line (do I have to notify Jarrod) was this in jarrod's list? What's the difference with 1b mason jar missing. If they're the same add the mason jar (which is more polular and cheaper instead of a vase) The vase is best sold by separated | G10: Not the same as 1b. 1b = the recipe has no jar. Item 2 = the recipe already has the vase or the jar (red vase on AUSC-02/03/04 and LF15-10C, mason jar on AUSTRT-02/03) and only the text had to name it, so there is nothing to notify. They are in the live recipes. New rule C9: when a container is missing add the Mason Jar (cheaper and more popular); vases are sold separately as add-ons. I did not replace any existing vase.
A11: 3 Sending Solace moved to sympathy | B11: =COUNTIF(log!$H$5:$H$989,"Gate: moved to sympathy line") | C11: Sympathy tribute line / calm wording. | D11: Products | E11: OK
A12: 4 Brand voice (Bloomex AU texts inside 30-45 words) | B12: =COUNTIFS(Products!$N$2:$N$345,">=30",Products!$N$2:$N$345,"<=45") | C12: Voice codes V1-V19 now live in the MD (Part 4). Bunches and Stems lines rewritten. | D12: Products col N | E12: As the rest of the conditions caps and isntructions create a code for the instructions of brands voice, based iin Ashraf independent request, and the brand voice document creaetd before. | G12: Done: voice codes V1 to V19 in the MD (Part 4), built from the brand voice report and Ashraf's request (no delivery or price claims, numerals, 18+ wording rule). The skills load them from the MD.
A13: 5 All-white chrysanthemum designs | B13: =COUNTIF(log!$H$5:$H$989,"Gate: voice (all-white chrysanthemum)")+COUNTIF(log!$H$5:$H$989,"Voice: all-white chrysanthemum design") | C13: Neutral occasions used; Ashraf decides the two named rows. | D13: log
A14: 6 Designer wording / 'stemss' / native | B14: =COUNTIF(log!$H$5:$H$989,"Gate: designer wording applied") | C14: Stem count + florist's choice + illustrative picture. Greenery added to the 2 DC products that had none (Joomla_import_2); final DC recipes in the control file. | D14: Products; control file | E14: Remember me flag Jarod Include the greenery if possible using the cap and greenery instructions, (create a separated file to update joomla) and other Master for designer collections how the final recipe would look like (this view should have the SKU the product title and the recipe for each variant in different columns. Other tab with the recipe look like before and after the fixing for each variant same labeled (1 row per SKU) different columns (use different colors) | G14: Done: Greenery added to DC-02A and DC112-01A, the only two DC products without any (Joomla_import_2_greenery_v1). Control file AU-Recipe-Fixes-v1-control.xlsx: tab Final recipes = SKU, title and the final recipe per variant for all 36 DC products; tab Before-After = one row per SKU with BEFORE (red) and AFTER (green) columns per variant plus what was added, removed and changed. Flag Jarrod: greenery list is in both files.
A15: 7 18+ notice | B15: =COUNTIF(log!$F$5:$F$989,"Wine products: 18+ notice") | C15: Applies to every product with wine in the recipe (list = class Wine products: 18+ notice). Legal wording first. | D15: log | E15: The warning should either first follow legal instructions or 2) be adapted by each brand voice, create a separated list of these products. All lists that I requested should be in the master file with the instructions (What the artifact has) as updated as possible and its log. | G15: Legal wording first, verbatim as live: 'Disclaimer – Purchaser must be 18 years old or over to purchase this product. The recipient, by law, must be at least 18 years of age, with proof of age.' A brand-voice adaptation is only a proposal until legal agrees; proposals are in the MD (rule D3b). List of wine products: class 'Wine products: 18+ notice'.
A16: 8 Not on the live storefront | B16: =COUNTIF(Products!$D$2:$D$345,"CONFIRM STATUS") | C16: Only AU11-14 is live N on 7 Oct. | D16: log | E16: What happened with these products? Keep my questions in this file, repond in additional columns. | G16: AU11-14 is still live N in the 7 Oct export. AU100-71, AU112-56 and AU216-63 are live Y on 7 Oct, so I removed their label. I cannot see why they were reported missing on 6 Oct (re-activated in Joomla, or the storefront check differed from the Joomla status).
A17: 9 Identical copy on two pages | B17: =COUNTIF(log!$F$5:$F$989,"Copy: identical text") | C17: Phrasing variants; remaining pairs are listed. | D17: log | E17: Make a little bit more engagin and spiring the descriptionffor bucnhes and steams | G17: Done: Bunches and Stems closing lines rewritten to be warmer and more inspiring while staying dry and claim-free, e.g. 'Brings the colour in before anyone has said hello.' and 'Some things need no speech. Put these on the table and the message is delivered.'
E18: at the end I need independent list of products to flag jarrod (those that don't have mason jar, those that the recipe still include only one colorthogh the name says 2) etc, and thos that don't have greenery. (I will create the file with the fixes for these problems ) with independent files to upload in jooomla (that modifies only the products to update) equaliy formated. | G18: Delivered: independent Flag Jarrod lists (classes in the log and in the control file) and five Joomla import files, each only the products to update, format identical to the export (checked by round trip). Nothing overlaps, so uploading all five in any order is safe.
A20: B. Rules and conditions (full text in the MD, Part 1 to 5) | B20: SKUs | C20: Rule
A21: C1 One container per product | B21: =COUNTIF(log!$H$5:$H$989,"C1*")+COUNTIF(log!$F$5:$F$989,"Flag Jarrod: container / quantity") | C21: One container only; a Mason Jar title always gets the jar (added, Jarrod notified). Container list = Flag Jarrod: container.
A22: C2 Title count | B22: =COUNTIF(log!$H$5:$H$989,"title count") | C22: Standard follows the title count.
A23: C3 Title colours | B23: =COUNTIF(log!$H$5:$H$989,"colour*") | C23: Title colours must exist in the recipe; same-price swaps; half and half for X and Y roses.
A24: C5 Not carried ($0) | B24: =COUNTIF(log!$H$5:$H$989,"Gate: Item not carried*") | C24: Removed, never replaced (I4).
A25: C7 Blooms vs stems | B25: =COUNTIF(log!$H$5:$H$989,"C7*") | C25: Strategy, never flagged (labels removed).
A26: C9 Container to add | B26: =COUNTIF(log!$H$5:$H$989,"mason jar") | C26: Add the Mason Jar, not a vase.
A27: D1 Descriptions skip greenery and secondary flowers | B27: =COUNTA(Products!$A$2:$A$345) | C27: Exercise only.
A28: D3 18+ notice (every wine recipe) | B28: =COUNTIF(log!$F$5:$F$989,"Wine products: 18+ notice") | C28: Legal wording first; brand adaptation only after legal.
A29: J1 Joomla import files | B29: =5 | C29: Only changed products, identical format, one product per file, retail price unchanged.
A30: L1 Live check | B30: =COUNTIF(log!$F$5:$F$989,"Label removed*") | C30: Labels contradicted by live are removed, never added.
A31: PV1-PV6 Pricing verification | B31: =COUNTIF(log!$F$5:$F$989,"Rule added*") | C31: From your pasted rules: $0 in AU-Cost master, ingredient mismatch, bigger size fewer items, smaller size higher or same price, not checked, scope.
A33: C. Counts
A34: SKUs reviewed | B34: =COUNTA(Products!$A$2:$A$345)
A35: READY TO REVIEW | B35: =COUNTIF(Products!$D$2:$D$345,"READY TO REVIEW")
A36: READY - NOTIFY JARROD | B36: =COUNTIF(Products!$D$2:$D$345,"READY - NOTIFY JARROD")
A37: ADJUSTED - CONFIRM | B37: =COUNTIF(Products!$D$2:$D$345,"ADJUSTED - CONFIRM")
A38: CONFIRM STATUS | B38: =COUNTIF(Products!$D$2:$D$345,"CONFIRM STATUS")
A39: DECISION NEEDED | B39: =COUNTIF(Products!$D$2:$D$345,"DECISION NEEDED")
A41: Descriptions generated / auto-check ok
A42: Bloomex AU | B42: =COUNTIF(Products!$M$2:$M$345,"?*")-COUNTIF(Products!$M$2:$M$345,"n/a*") | C42: =COUNTIF(Products!$P$2:$P$345,"ok")&" ok"
A43: Aussie Blooms | B43: =COUNTIF(Products!$Q$2:$Q$345,"?*")-COUNTIF(Products!$Q$2:$Q$345,"n/a*") | C43: =COUNTIF(Products!$S$2:$S$345,"ok")&" ok"
A44: Bunches and Stems | B44: =COUNTIF(Products!$T$2:$T$345,"?*")-COUNTIF(Products!$T$2:$T$345,"n/a*") | C44: =COUNTIF(Products!$V$2:$V$345,"ok")&" ok"
A45: Mel's Flowers | B45: =COUNTIF(Products!$X$2:$X$345,"?*")-COUNTIF(Products!$X$2:$X$345,"n/a*") | C45: =COUNTIF(Products!$Z$2:$Z$345,"ok")&" ok"
A47: Rows in the log list by class
A48: Flag Jarrod: mason jar | B48: =COUNTIF(log!$F$5:$F$989,"Flag Jarrod: mason jar")
A49: Flag Jarrod: greenery | B49: =COUNTIF(log!$F$5:$F$989,"Flag Jarrod: greenery")
A50: Flag Jarrod: colour (title says two, recipe has one) | B50: =COUNTIF(log!$F$5:$F$989,"Flag Jarrod: colour (title says two, recipe has one)")
A51: Flag Jarrod: title count | B51: =COUNTIF(log!$F$5:$F$989,"Flag Jarrod: title count")
A52: Flag Jarrod: container / quantity | B52: =COUNTIF(log!$F$5:$F$989,"Flag Jarrod: container / quantity")
A53: Flag Jarrod: empty recipe on a priced size | B53: =COUNTIF(log!$F$5:$F$989,"Flag Jarrod: empty recipe on a priced size")
A54: Recipe fix: notify Jarrod | B54: =COUNTIF(log!$F$5:$F$989,"Recipe fix: notify Jarrod")
A55: Wine products: 18+ notice | B55: =COUNTIF(log!$F$5:$F$989,"Wine products: 18+ notice")
A56: Title vs recipe (linguistic) | B56: =COUNTIF(log!$F$5:$F$989,"Title vs recipe (linguistic)")
A57: Ashraf gate item | B57: =COUNTIF(log!$F$5:$F$989,"Ashraf gate item")
A58: Current text vs recipe | B58: =COUNTIF(log!$F$5:$F$989,"Current text vs recipe")
A59: Copy: identical text | B59: =COUNTIF(log!$F$5:$F$989,"Copy: identical text")
A60: Label removed (your comment) | B60: =COUNTIF(log!$F$5:$F$989,"Label removed (your comment)")
A61: Label removed (live Joomla) | B61: =COUNTIF(log!$F$5:$F$989,"Label removed (live Joomla)")
A62: Live differs from master | B62: =COUNTIF(log!$F$5:$F$989,"Live differs from master")
A63: Rule added (pricing verification) | B63: =COUNTIF(log!$F$5:$F$989,"Rule added (pricing verification)")
A64: Rule applied (no action) | B64: =COUNTIF(log!$F$5:$F$989,"Rule applied (no action)")
A65: Master note (info) | B65: =COUNTIF(log!$F$5:$F$989,"Master note (info)")
A66: Note | B66: =COUNTIF(log!$F$5:$F$989,"Note")
A67: Out of scope | B67: =COUNTIF(log!$F$5:$F$989,"Out of scope")

Sheet Products
A1: SKU | B1: Product title | C1: Bucket | D1: Upload status | E1: Current BLX description (Joomla 7 Oct if present, else Shopify 28 Sep) | F1: Current text source | G1: Jarrod recipe (Standard) | H1: Reviewed recipe (master + rules) | I1: Suggested final recipe (after the fixes) | J1: Live recipe (Joomla 7 Oct, Standard) | K1: Live status | L1: Needs before upload | M1: Bloomex AU: suggested text | N1: Bloomex AU: words | O1: Bloomex AU: HTML | P1: Bloomex AU: QA | Q1: Aussie Blooms: suggested text | R1: Aussie Blooms: HTML | S1: Aussie Blooms: QA | T1: Bunches and Stems: suggested text | U1: Bunches and Stems: HTML | V1: Bunches and Stems: QA | W1: Mel's: title (Product Master) | X1: Mel's: suggested text | Y1: Mel's: HTML | Z1: Mel's: QA | AA1: Global sales rank (flowers) | AB1: Net sales YTD 2026 (AUD) | AC1: Net items sold YTD | AD1: % of total flower revenue | AE1: % of category revenue | AF1: Rank within category
A2: MJ100-37 | B2: Pink Wink in Mason Jar | C2: Mason Jar | D2: READY TO REVIEW | F2: none | G2: 2 × Roses Pink; 2 × Carnation Pink; 3 × Alstroemeria Pink; 2 × Ruscus Israeli; 1 × Mason Jar; 2 × Statice Pink Pink; 2 × Mini Carnations Pink | H2: 2 × Roses Pink; 2 × Carnation Pink; 3 × Alstroemeria Pink; 2 × Ruscus Israeli; 1 × Mason Jar; 2 × Statice Pink; 2 × Mini Carnations Pink | I2: 2 × Roses Pink; 2 × Carnation Pink; 3 × Alstroemeria Pink; 2 × Ruscus Israeli; 1 × Mason Jar; 2 × Statice Pink; 2 × Mini Carnations Pink | J2: 2 × Ruscus Israeli; 2 × Mini Carnations Pink; 2 × Statice Pink; 1 × Mason Jar; 3 × Alstroemeria Pink; 2 × Carnation Pink; 2 × Roses Pink | K2: N | M2: A hand-arranged mason jar bouquet of 3 pink alstroemeria, 2 pink carnations and 2 pink roses. A warm gift for a birthday, a thank-you or a just-because moment, with a mason jar to keep once the flowers are gone. | N2: =LEN(TRIM(SUBSTITUTE(M2,CHAR(10)," ")))-LEN(SUBSTITUTE(TRIM(SUBSTITUTE(M2,CHAR(10)," "))," ",""))+1 | O2: <p>A hand-arranged mason jar bouquet of 3 pink alstroemeria, 2 pink carnations and 2 pink roses. A warm gift for a birthday, a thank-you or a just-because moment, with a mason jar to keep once the flowers are gone.</p> | P2: ok | Q2: Pink Wink in Mason Jar brings together 3 pink alstroemeria, 2 pink carnations and 2 pink roses, presented in a mason jar you can keep. It suits a birthday, a thank-you or a just-because moment. Pink tones say affection. We hand-arrange each one at Aussie Blooms so it looks the way you pictured it, ready for a Sunday lunch. Stems can vary with the season, while the pink palette stays. | R2: <p>Pink Wink in Mason Jar brings together 3 pink alstroemeria, 2 pink carnations and 2 pink roses, presented in a mason jar you can keep. It suits a birthday, a thank-you or a just-because moment.</p><p>Pink tones say affection. We hand-arrange each one at Aussie Blooms so it looks the way you pictured it, ready for a Sunday lunch. Stems can vary with the season, while the pink palette stays.</p> | S2: ok | T2: Inside the jar: 3 pink alstroemeria, 2 pink carnations and 2 pink roses. Calm colour for the kind of day that deserves a pause. | U2: <p>Inside the jar: 3 pink alstroemeria, 2 pink carnations and 2 pink roses. Calm colour for the kind of day that deserves a pause.</p> | V2: ok | W2: Rosy Rumour | X2: Rosy Rumour settles 3 pink alstroemeria, 2 pink carnations and 2 pink roses into a relaxed mason jar. Just right sitting on a bench where everyone can enjoy it. A good fit for a birthday, a thank-you or a just-because moment. | Y2: <p>Rosy Rumour settles 3 pink alstroemeria, 2 pink carnations and 2 pink roses into a relaxed mason jar. Just right sitting on a bench where everyone can enjoy it. A good fit for a birthday, a thank-you or a just-because moment.</p> | Z2: ok | AA2: no sales | AB2: 0 | AC2: 0 | AD2: 0 | AE2: 0 | AF2: no sales
A3: MJ22-10 | B3: Shades of Pink in Mason Jar | C3: Mason Jar | D3: READY TO REVIEW | E3: Eleven gerberas, ten alstroemeria and nine chrysanthemums in pretty shades of pink, nestled in a country-style mason jar. Fresh, feminine and full of charm, it's a lovely way to mark a birthday, celebrate good news or welcome someone to a new home. | F3: Shopify (28 Sep) | G3: 3 × Chrysanthemum Daisies Lavender; 3 × Gerbera Daisies Pink; 2 × Ruscus Israeli; 1 × Mason Jar; 3 × Alstroemeria Pink | H3: 3 × Chrysanthemum Daisies Lavender; 3 × Gerbera Daisies Pink; 2 × Ruscus Israeli; 1 × Mason Jar; 3 × Alstroemeria Pink | I3: 3 × Chrysanthemum Daisies Lavender; 3 × Gerbera Daisies Pink; 2 × Ruscus Israeli; 1 × Mason Jar; 3 × Alstroemeria Pink | J3: 2 × Ruscus Israeli; 3 × Alstroemeria Pink; 1 × Mason Jar; 3 × Gerbera Daisies Pink; 3 × Chrysanthemum Daisies Lavender | K3: Y | M3: A hand-arranged mason jar bouquet of 3 lavender chrysanthemum daisies, 3 pink alstroemeria and 3 pink gerberas. A lovely way to mark a birthday, a thank-you or a just-because moment, with a mason jar to keep once the flowers are gone. | N3: =LEN(TRIM(SUBSTITUTE(M3,CHAR(10)," ")))-LEN(SUBSTITUTE(TRIM(SUBSTITUTE(M3,CHAR(10)," "))," ",""))+1 | O3: <p>A hand-arranged mason jar bouquet of 3 lavender chrysanthemum daisies, 3 pink alstroemeria and 3 pink gerberas. A lovely way to mark a birthday, a thank-you or a just-because moment, with a mason jar to keep once the flowers are gone.</p> | P3: ok | Q3: Shades of Pink in Mason Jar brings together 3 lavender chrysanthemum daisies, 3 pink alstroemeria and 3 pink gerberas, presented in a mason jar you can keep. It suits a birthday, a thank-you or a just-because moment. Pink tones say affection. We hand-arrange each one at Aussie Blooms so it looks the way you pictured it, ready for a Sunday lunch. Stems can vary with the season, while the pink and lavender palette stays. | R3: <p>Shades of Pink in Mason Jar brings together 3 lavender chrysanthemum daisies, 3 pink alstroemeria and 3 pink gerberas, presented in a mason jar you can keep. It suits a birthday, a thank-you or a just-because moment.</p><p>Pink tones say affection. We hand-arrange each one at Aussie Blooms so it looks the way you pictured it, ready for a Sunday lunch. Stems can vary with the season, while the pink and lavender palette stays.</p> | S3: ok | T3: In the jar: 3 lavender chrysanthemum daisies, 3 pink alstroemeria and 3 pink gerberas. Soft colours that make a quiet room feel looked after. | U3: <p>In the jar: 3 lavender chrysanthemum daisies, 3 pink alstroemeria and 3 pink gerberas. Soft colours that make a quiet room feel looked after.</p> | V3: ok | W3: All the Pinks | X3: All the Pinks settles 3 lavender chrysanthemum daisies, 3 pink alstroemeria and 3 pink gerberas into a relaxed mason jar. Just right sitting on a bench where everyone can enjoy it. A good fit for a birthday, a thank-you or a just-because moment. A little wild, a little imperfect, the way a jar should be. | Y3: <p>All the Pinks settles 3 lavender chrysanthemum daisies, 3 pink alstroemeria and 3 pink gerberas into a relaxed mason jar. Just right sitting on a bench where everyone can enjoy it. A good fit for a birthday, a thank-you or a just-because moment. A little wild, a little imperfect, the way a jar should be.</p> | Z3: ok | AA3: 105 | AB3: 13672.72 | AC3: 192 | AD3: 0.0015665785 | AE3: 0.0039474106 | AF3: 34
A4: MJ79-16 | B4: Shades of Spring in Mason Jar | C4: Mason Jar | D4: READY TO REVIEW | F4: none | G4: 2 × Roses Spray Hot Pink; 2 × Chrysanthemum Daisies Lavender; 1 × Carnation Yellow; 2 × Ruscus Israeli; 1 × Mason Jar; 2 × Alstroemeria Yellow | H4: 2 × Roses Spray Hot Pink; 2 × Chrysanthemum Daisies Lavender; 1 × Carnation Yellow; 2 × Ruscus Israeli; 1 × Mason Jar; 2 × Alstroemeria Yellow | I4: 2 × Roses Spray Hot Pink; 2 × Chrysanthemum Daisies Lavender; 1 × Carnation Yellow; 2 × Ruscus Israeli; 1 × Mason Jar; 2 × Alstroemeria Yellow | J4: 1 × Carnation Yellow; 2 × Alstroemeria Yellow; 1 × Mason Jar; 2 × Ruscus Israeli; 2 × Chrysanthemum Daisies Lavender; 2 × Roses Spray Hot Pink | K4: N | M4: A mason jar arrangement of 2 hot pink spray roses, 2 lavender chrysanthemum daisies, 2 yellow alstroemeria and 1 yellow carnation. A thoughtful choice for a birthday, a thank-you or a just-because moment, and the mason jar stays useful long after. | N4: =LEN(TRIM(SUBSTITUTE(M4,CHAR(10)," ")))-LEN(SUBSTITUTE(TRIM(SUBSTITUTE(M4,CHAR(10)," "))," ",""))+1 | O4: <p>A mason jar arrangement of 2 hot pink spray roses, 2 lavender chrysanthemum daisies, 2 yellow alstroemeria and 1 yellow carnation. A thoughtful choice for a birthday, a thank-you or a just-because moment, and the mason jar stays useful long after.</p> | P4: ok | Q4: Shades of Spring in Mason Jar brings together 2 hot pink spray roses, 2 lavender chrysanthemum daisies, 2 yellow alstroemeria and 1 yellow carnation, presented in a mason jar you can keep. It suits a birthday, a thank-you or a just-because moment. Yellow tones say friendship and cheer. We hand-arrange each one at Aussie Blooms so it looks the way you pictured it, ready for the kitchen bench. Stems can vary with the season, while the yellow and hot pink palette stays. | R4: <p>Shades of Spring in Mason Jar brings together 2 hot pink spray roses, 2 lavender chrysanthemum daisies, 2 yellow alstroemeria and 1 yellow carnation, presented in a mason jar you can keep. It suits a birthday, a thank-you or a just-because moment.</p><p>Yellow tones say friendship and cheer. We hand-arrange each one at Aussie Blooms so it looks the way you pictured it, ready for the kitchen bench. Stems can vary with the season, while the yellow and hot pink palette stays.</p> | S4: ok | T4: The jar holds: 2 hot pink spray roses, 2 lavender chrysanthemum daisies, 2 yellow alstroemeria and 1 yellow carnation. Enough colour to turn an ordinary bench into the best spot in the house. | U4: <p>The jar holds: 2 hot pink spray roses, 2 lavender chrysanthemum daisies, 2 yellow alstroemeria and 1 yellow carnation. Enough colour to turn an ordinary bench into the best spot in the house.</p> | V4: ok | W4: September Garden | X4: September Garden gathers 2 hot pink spray roses, 2 lavender chrysanthemum daisies, 2 yellow alstroemeria and 1 yellow carnation into a relaxed mason jar. Right at home on a kitchen bench next to the morning cuppa. Made for a birthday, a thank-you or a just-because moment. A little wild, a little imperfect, the way a jar should be. | Y4: <p>September Garden gathers 2 hot pink spray roses, 2 lavender chrysanthemum daisies, 2 yellow alstroemeria and 1 yellow carnation into a relaxed mason jar. Right at home on a kitchen bench next to the morning cuppa. Made for a birthday, a thank-you or a just-because moment. A little wild, a little imperfect, the way a jar should be.</p> | Z4: ok | AA4: no sales | AB4: 0 | AC4: 0 | AD4: 0 | AE4: 0 | AF4: no sales
A5: MJ11-30 | B5: Sweetheart Roses in Mason Jar | C5: Mason Jar | D5: READY TO REVIEW | E5: Twenty-seven romantic roses gathered in a charming mason jar, blending rustic warmth with timeless beauty. A sweetheart gesture for an anniversary, birthday or a heartfelt just-because moment that says you care. | F5: Shopify (28 Sep) | G5: 6 × Roses Red; 1 × Baby's Breath; 2 × Ruscus Israeli; 1 × Mason Jar | H5: 6 × Roses Red; 1 × Baby's Breath; 2 × Ruscus Israeli; 1 × Mason Jar | I5: 6 × Roses Red; 1 × Baby's Breath; 2 × Ruscus Israeli; 1 × Mason Jar | J5: 2 × Ruscus Israeli; 1 × Mason Jar; 1 × Baby's Breath; 6 × Roses Red | K5: Y | M5: A mason jar arrangement of 6 red roses. A lovely way to mark an anniversary or a thank-you, and a bright moment when the door opens. | N5: =LEN(TRIM(SUBSTITUTE(M5,CHAR(10)," ")))-LEN(SUBSTITUTE(TRIM(SUBSTITUTE(M5,CHAR(10)," "))," ",""))+1 | O5: <p>A mason jar arrangement of 6 red roses. A lovely way to mark an anniversary or a thank-you, and a bright moment when the door opens.</p> | P5: ok | Q5: Sweetheart Roses in Mason Jar brings together 6 red roses, presented in a mason jar you can keep. It suits an anniversary or a thank-you. Red tones say love and devotion. We hand-arrange each one at Aussie Blooms so it looks the way you pictured it, ready for the kitchen bench. Stems can vary with the season, while the red palette stays. | R5: <p>Sweetheart Roses in Mason Jar brings together 6 red roses, presented in a mason jar you can keep. It suits an anniversary or a thank-you.</p><p>Red tones say love and devotion. We hand-arrange each one at Aussie Blooms so it looks the way you pictured it, ready for the kitchen bench. Stems can vary with the season, while the red palette stays.</p> | S5: ok | T5: The jar holds: 6 red roses. The classic, handed over without a single word of explanation. | U5: <p>The jar holds: 6 red roses. The classic, handed over without a single word of explanation.</p> | V5: ok | W5: Garden Romance | X5: Garden Romance gathers 6 red roses into a relaxed mason jar. Right at home on a kitchen bench next to the morning cuppa. Made for an anniversary or a thank-you. A little wild, a little imperfect, the way a jar should be. | Y5: <p>Garden Romance gathers 6 red roses into a relaxed mason jar. Right at home on a kitchen bench next to the morning cuppa. Made for an anniversary or a thank-you. A little wild, a little imperfect, the way a jar should be.</p> | Z5: ok | AA5: 165 | AB5: 4658.91 | AC5: 69 | AD5: 0.00053380376 | AE5: 0.0013450603 | AF5: 47
A6: MJ100-04 | B6: What a Treat in Mason Jar | C6: Mason Jar | D6: READY TO REVIEW | E6: A delightful mix of 7 roses, 6 chrysanthemums and 5 alstroemeria arranged in a rustic mason jar. A small but joyful treat to brighten a birthday, celebrate a win or send cheerful get-well wishes. | F6: Shopify (28 Sep) | G6: 2 × Roses Pink; 3 × Chrysanthemum Daisies White; 1 × Baby's Breath; 1 × Ruscus Israeli; 1 × Mason Jar; 2 × Alstroemeria Pink | H6: 2 × Roses Pink; 3 × Chrysanthemum Daisies White; 1 × Baby's Breath; 1 × Ruscus Israeli; 1 × Mason Jar; 2 × Alstroemeria Pink | I6: 2 × Roses Pink; 3 × Chrysanthemum Daisies White; 1 × Baby's Breath; 1 × Ruscus Israeli; 1 × Mason Jar; 2 × Alstroemeria Pink | J6: 1 × Baby's Breath; 2 × Alstroemeria Pink; 1 × Mason Jar; 1 × Ruscus Israeli; 3 × Chrysanthemum Daisies White; 2 × Roses Pink | K6: Y | M6: A mason jar arrangement of 3 white chrysanthemum daisies, 2 pink alstroemeria and 2 pink roses. A warm gift for a birthday, a thank-you or a just-because moment, and the mason jar stays useful long after. | N6: =LEN(TRIM(SUBSTITUTE(M6,CHAR(10)," ")))-LEN(SUBSTITUTE(TRIM(SUBSTITUTE(M6,CHAR(10)," "))," ",""))+1 | O6: <p>A mason jar arrangement of 3 white chrysanthemum daisies, 2 pink alstroemeria and 2 pink roses. A warm gift for a birthday, a thank-you or a just-because moment, and the mason jar stays useful long after.</p> | P6: ok | Q6: What a Treat in Mason Jar brings together 3 white chrysanthemum daisies, 2 pink alstroemeria and 2 pink roses, presented in a mason jar you can keep. It suits a birthday, a thank-you or a just-because moment. Pink tones say affection. We hand-arrange each one at Aussie Blooms so it looks the way you pictured it, ready for the bedside table. Stems can vary with the season, while the pink and white palette stays. | R6: <p>What a Treat in Mason Jar brings together 3 white chrysanthemum daisies, 2 pink alstroemeria and 2 pink roses, presented in a mason jar you can keep. It suits a birthday, a thank-you or a just-because moment.</p><p>Pink tones say affection. We hand-arrange each one at Aussie Blooms so it looks the way you pictured it, ready for the bedside table. Stems can vary with the season, while the pink and white palette stays.</p> | S6: ok | T6: Inside the jar: 3 white chrysanthemum daisies, 2 pink alstroemeria and 2 pink roses. Calm colour for the kind of day that deserves a pause. | U6: <p>Inside the jar: 3 white chrysanthemum daisies, 2 pink alstroemeria and 2 pink roses. Calm colour for the kind of day that deserves a pause.</p> | V6: ok | W6: Mel's Best Pick | X6: Mel's Best Pick nestles 3 white chrysanthemum daisies, 2 pink alstroemeria and 2 pink roses into a relaxed mason jar. Happy on a sunny windowsill. Made for a birthday, a thank-you or a just-because moment. A little wild, a little imperfect, the way a jar should be. | Y6: <p>Mel's Best Pick nestles 3 white chrysanthemum daisies, 2 pink alstroemeria and 2 pink roses into a relaxed mason jar. Happy on a sunny windowsill. Made for a birthday, a thank-you or a just-because moment. A little wild, a little imperfect, the way a jar should be.</p> | Z6: ok | AA6: 5 | AB6: 279924.76 | AC6: 5211 | AD6: 0.032072928 | AE6: 0.080816261 | AF6: 4
A7: MJ-01 | B7: Summer Breeze in Mason Jar | C7: Mason Jar | D7: READY TO REVIEW | F7: none | G7: 2 × Chrysanthemum Button Green; 2 × Chrysanthemum Daisies Lavender; 2 × Ruscus Israeli; 1 × Mason Jar; 3 × Carnation Yellow; 3 × Alstroemeria Red | H7: 2 × Chrysanthemum Button Green; 2 × Chrysanthemum Daisies Lavender; 2 × Ruscus Israeli; 1 × Mason Jar; 3 × Carnation Yellow; 3 × Alstroemeria Red | I7: 2 × Chrysanthemum Button Green; 2 × Chrysanthemum Daisies Lavender; 2 × Ruscus Israeli; 1 × Mason Jar; 3 × Carnation Yellow; 3 × Alstroemeria Red | J7: 2 × Ruscus Israeli; 3 × Alstroemeria Red; 3 × Carnation Yellow; 1 × Mason Jar; 2 × Chrysanthemum Daisies Lavender; 2 × Chrysanthemum Button Green | K7: N | M7: A hand-arranged mason jar bouquet of 3 red alstroemeria, 3 yellow carnations and 2 lavender chrysanthemum daisies. A thoughtful choice for a birthday, a thank-you or a just-because moment, with a mason jar to keep once the flowers are gone. | N7: =LEN(TRIM(SUBSTITUTE(M7,CHAR(10)," ")))-LEN(SUBSTITUTE(TRIM(SUBSTITUTE(M7,CHAR(10)," "))," ",""))+1 | O7: <p>A hand-arranged mason jar bouquet of 3 red alstroemeria, 3 yellow carnations and 2 lavender chrysanthemum daisies. A thoughtful choice for a birthday, a thank-you or a just-because moment, with a mason jar to keep once the flowers are gone.</p> | P7: ok | Q7: Summer Breeze in Mason Jar brings together 3 red alstroemeria, 3 yellow carnations and 2 lavender chrysanthemum daisies, presented in a mason jar you can keep. It suits a birthday, a thank-you or a just-because moment. Red tones say love and devotion. We hand-arrange each one at Aussie Blooms so it looks the way you pictured it, ready for a summer table. Stems can vary with the season, while the red and yellow palette stays. | R7: <p>Summer Breeze in Mason Jar brings together 3 red alstroemeria, 3 yellow carnations and 2 lavender chrysanthemum daisies, presented in a mason jar you can keep. It suits a birthday, a thank-you or a just-because moment.</p><p>Red tones say love and devotion. We hand-arrange each one at Aussie Blooms so it looks the way you pictured it, ready for a summer table. Stems can vary with the season, while the red and yellow palette stays.</p> | S7: ok | T7: The jar holds: 3 red alstroemeria, 3 yellow carnations and 2 lavender chrysanthemum daisies. Enough colour to turn an ordinary bench into the best spot in the house. | U7: <p>The jar holds: 3 red alstroemeria, 3 yellow carnations and 2 lavender chrysanthemum daisies. Enough colour to turn an ordinary bench into the best spot in the house.</p> | V7: ok | W7: Long Weekend | X7: Long Weekend tucks 3 red alstroemeria, 3 yellow carnations and 2 lavender chrysanthemum daisies into a relaxed mason jar. Lovely on a bedside table, or anywhere it can be seen. A good fit for a birthday, a thank-you or a just-because moment. A little wild, a little imperfect, the way a jar should be. | Y7: <p>Long Weekend tucks 3 red alstroemeria, 3 yellow carnations and 2 lavender chrysanthemum daisies into a relaxed mason jar. Lovely on a bedside table, or anywhere it can be seen. A good fit for a birthday, a thank-you or a just-because moment. A little wild, a little imperfect, the way a jar should be.</p> | Z7: ok | AA7: no sales | AB7: 0 | AC7: 0 | AD7: 0 | AE7: 0 | AF7: no sales
A8: MJ100-24 | B8: Assorted Roses in Mason Jar | C8: Mason Jar | D8: READY TO REVIEW | E8: Fourteen assorted roses gathered in a charming mason jar, blending romance with rustic, timeless appeal. A versatile and heartfelt arrangement that brings warmth and beauty to any room, and a lovely way to brighten someone's day just because. | F8: Shopify (28 Sep) | G8: 5 × Roses Assorted; 1 × Baby's Breath; 1 × Ruscus Israeli; 1 × Mason Jar | H8: 5 × Roses Assorted; 1 × Baby's Breath; 1 × Ruscus Israeli; 1 × Mason Jar | I8: 5 × Roses Assorted; 1 × Baby's Breath; 1 × Ruscus Israeli; 1 × Mason Jar | J8: 1 × Ruscus Israeli; 1 × Mason Jar; 1 × Baby's Breath; 5 × Roses Assorted | K8: Y | M8: A mason jar arrangement of 5 assorted-colour roses. A lovely way to mark a birthday, a thank-you or a just-because moment, and the mason jar stays useful long after. | N8: =LEN(TRIM(SUBSTITUTE(M8,CHAR(10)," ")))-LEN(SUBSTITUTE(TRIM(SUBSTITUTE(M8,CHAR(10)," "))," ",""))+1 | O8: <p>A mason jar arrangement of 5 assorted-colour roses. A lovely way to mark a birthday, a thank-you or a just-because moment, and the mason jar stays useful long after.</p> | P8: ok | Q8: Assorted Roses in Mason Jar brings together 5 assorted-colour roses, presented in a mason jar you can keep. It suits a birthday, a thank-you or a just-because moment. Mixed colours say thoughtfulness. We hand-arrange each one at Aussie Blooms so it looks the way you pictured it, ready for the kitchen bench. Stems can vary with the season, while the colourful palette stays. | R8: <p>Assorted Roses in Mason Jar brings together 5 assorted-colour roses, presented in a mason jar you can keep. It suits a birthday, a thank-you or a just-because moment.</p><p>Mixed colours say thoughtfulness. We hand-arrange each one at Aussie Blooms so it looks the way you pictured it, ready for the kitchen bench. Stems can vary with the season, while the colourful palette stays.</p> | S8: ok | T8: In the jar: 5 assorted-colour roses. Hand it over and watch the day get a little better. | U8: <p>In the jar: 5 assorted-colour roses. Hand it over and watch the day get a little better.</p> | V8: ok | W8: Mixed Callas | X8: Mixed Callas gathers 5 assorted-colour roses into a relaxed mason jar. Right at home on a kitchen bench next to the morning cuppa. Made for a birthday, a thank-you or a just-because moment. | Y8: <p>Mixed Callas gathers 5 assorted-colour roses into a relaxed mason jar. Right at home on a kitchen bench next to the morning cuppa. Made for a birthday, a thank-you or a just-because moment.</p> | Z8: ok | AA8: 150 | AB8: 6301.98 | AC8: 141 | AD8: 0.00072206207 | AE8: 0.0018194272 | AF8: 41
A9: MJ100-118 | B9: Blooms of Love in Mason Jar | C9: Mason Jar | D9: READY TO REVIEW | E9: A joyful gathering of alstroemeria, carnations and chrysanthemums arranged in a country-style mason jar, full of texture and colour. Warm and heartfelt, this cheerful bouquet is perfect for marking an anniversary, sending congratulations, or wishing someone a speedy recovery. | F9: Shopify (28 Sep) | G9: 2 × Chrysanthemum Spray White; 1 × Ruscus Israeli; 1 × Mason Jar; 3 × Carnations Hot Pink; 4 × Alstroemeria Purple | H9: 2 × Chrysanthemum Spray White; 1 × Ruscus Israeli; 1 × Mason Jar; 3 × Carnations Hot Pink; 4 × Alstroemeria Purple | I9: 2 × Chrysanthemum Spray White; 1 × Ruscus Israeli; 1 × Mason Jar; 3 × Carnations Hot Pink; 4 × Alstroemeria Purple | J9: 4 × Alstroemeria Purple; 3 × Carnations Hot Pink; 1 × Mason Jar; 1 × Ruscus Israeli; 2 × Chrysanthemum Spray White | K9: Y | M9: A hand-arranged mason jar bouquet of 4 purple alstroemeria, 3 hot pink carnations and 2 white spray chrysanthemums. A warm gift for an anniversary or a thank-you, with a mason jar to keep once the flowers are gone. | N9: =LEN(TRIM(SUBSTITUTE(M9,CHAR(10)," ")))-LEN(SUBSTITUTE(TRIM(SUBSTITUTE(M9,CHAR(10)," "))," ",""))+1 | O9: <p>A hand-arranged mason jar bouquet of 4 purple alstroemeria, 3 hot pink carnations and 2 white spray chrysanthemums. A warm gift for an anniversary or a thank-you, with a mason jar to keep once the flowers are gone.</p> | P9: ok | Q9: Blooms of Love in Mason Jar brings together 4 purple alstroemeria, 3 hot pink carnations and 2 white spray chrysanthemums, presented in a mason jar you can keep. It suits an anniversary or a thank-you. Purple tones say admiration. We hand-arrange each one at Aussie Blooms so it looks the way you pictured it, ready for a summer table. Stems can vary with the season, while the purple and hot pink palette stays. | R9: <p>Blooms of Love in Mason Jar brings together 4 purple alstroemeria, 3 hot pink carnations and 2 white spray chrysanthemums, presented in a mason jar you can keep. It suits an anniversary or a thank-you.</p><p>Purple tones say admiration. We hand-arrange each one at Aussie Blooms so it looks the way you pictured it, ready for a summer table. Stems can vary with the season, while the purple and hot pink palette stays.</p> | S9: ok | T9: Inside the jar: 4 purple alstroemeria, 3 hot pink carnations and 2 white spray chrysanthemums. Bright on purpose, and hard to walk past without smiling. | U9: <p>Inside the jar: 4 purple alstroemeria, 3 hot pink carnations and 2 white spray chrysanthemums. Bright on purpose, and hard to walk past without smiling.</p> | V9: ok | W9: Mixed Rose Garden | X9: Mixed Rose Garden tucks 4 purple alstroemeria, 3 hot pink carnations and 2 white spray chrysanthemums into a relaxed mason jar. Lovely on a bedside table, or anywhere it can be seen. A good fit for an anniversary or a thank-you. A little wild, a little imperfect, the way a jar should be. | Y9: <p>Mixed Rose Garden tucks 4 purple alstroemeria, 3 hot pink carnations and 2 white spray chrysanthemums into a relaxed mason jar. Lovely on a bedside table, or anywhere it can be seen. A good fit for an anniversary or a thank-you. A little wild, a little imperfect, the way a jar should be.</p> | Z9: ok | AA9: 25 | AB9: 92430.8 | AC9: 1189 | AD9: 0.01059044 | AE9: 0.026685427 | AF9: 12
A10: MJ100-111 | B10: Enchanted Cottage in Mason Jar | C10: Mason Jar | D10: READY TO REVIEW | E10: This delightful and popular bouquet is the perfect choice for a cottage, condo, or even a grand estate and is now available in a Mason Jar!. Its beauty will provide smiles to all who receive it! Choose this bouquet and send some enchantment today! Bouquet contains white roses and spray roses, lavender stock and waxflower, all beautifully arranged. Approximately 9" W x 16" H. Includes Mason Jar! | F10: Shopify (28 Sep) | G10: 5 × Roses White; 2 × Roses Spray White; 3 × Carnation Lavender; 1 × Baby's Breath; 2 × Ruscus Israeli; 1 × Mason Jar | H10: 5 × Roses White; 2 × Roses Spray White; 3 × Carnation Lavender; 1 × Baby's Breath; 2 × Ruscus Israeli; 1 × Mason Jar | I10: 5 × Roses White; 2 × Roses Spray White; 3 × Carnation Lavender; 1 × Baby's Breath; 2 × Ruscus Israeli; 1 × Mason Jar | J10: 3 × Carnation Lavender; 1 × Mason Jar; 2 × Ruscus Israeli; 1 × Baby's Breath; 2 × Roses Spray White; 5 × Roses White | K10: N | M10: A mason jar arrangement of 5 white roses, 3 lavender carnations and 2 white spray roses. A thoughtful choice for a birthday, a thank-you or a just-because moment, and the mason jar stays useful long after. | N10: =LEN(TRIM(SUBSTITUTE(M10,CHAR(10)," ")))-LEN(SUBSTITUTE(TRIM(SUBSTITUTE(M10,CHAR(10)," "))," ",""))+1 | O10: <p>A mason jar arrangement of 5 white roses, 3 lavender carnations and 2 white spray roses. A thoughtful choice for a birthday, a thank-you or a just-because moment, and the mason jar stays useful long after.</p> | P10: ok | Q10: Enchanted Cottage in Mason Jar brings together 5 white roses, 3 lavender carnations and 2 white spray roses, presented in a mason jar you can keep. It suits a birthday, a thank-you or a just-because moment. White tones say calm and a fresh start. We hand-arrange each one at Aussie Blooms so it looks the way you pictured it, ready for the kitchen bench. Stems can vary with the season, while the white and lavender palette stays. | R10: <p>Enchanted Cottage in Mason Jar brings together 5 white roses, 3 lavender carnations and 2 white spray roses, presented in a mason jar you can keep. It suits a birthday, a thank-you or a just-because moment.</p><p>White tones say calm and a fresh start. We hand-arrange each one at Aussie Blooms so it looks the way you pictured it, ready for the kitchen bench. Stems can vary with the season, while the white and lavender palette stays.</p> | S10: ok | T10: The jar holds: 5 white roses, 3 lavender carnations and 2 white spray roses. Gentle, easy on the eye, and ready for any table you give it. | U10: <p>The jar holds: 5 white roses, 3 lavender carnations and 2 white spray roses. Gentle, easy on the eye, and ready for any table you give it.</p> | V10: ok | W10: Love Letter | X10: Love Letter gathers 5 white roses, 3 lavender carnations and 2 white spray roses into a relaxed mason jar. Right at home on a kitchen bench next to the morning cuppa. Made for a birthday, a thank-you or a just-because moment. | Y10: <p>Love Letter gathers 5 white roses, 3 lavender carnations and 2 white spray roses into a relaxed mason jar. Right at home on a kitchen bench next to the morning cuppa. Made for a birthday, a thank-you or a just-because moment.</p> | Z10: ok | AA10: 152 | AB10: 6095.88 | AC10: 69 | AD10: 0.00069844742 | AE10: 0.0017599238 | AF10: 42
A11: MJ100-48 | B11: Gerbera Daisies in a Mason Jar | C11: Mason Jar | D11: READY TO REVIEW | F11: none | G11: 2 × Gerbera Daisies Yellow; 2 × Gerbera Daisies Red; 1 × Gerbera Daisies Orange; 1 × Ruscus Israeli; 1 × Mason Jar | H11: 2 × Gerbera Daisies Yellow; 2 × Gerbera Daisies Red; 1 × Gerbera Daisies Orange; 1 × Ruscus Israeli; 1 × Mason Jar | I11: 2 × Gerbera Daisies Yellow; 2 × Gerbera Daisies Red; 1 × Gerbera Daisies Orange; 1 × Ruscus Israeli; 1 × Mason Jar | J11: 1 × Gerbera Daisies Orange; 1 × Mason Jar; 1 × Ruscus Israeli; 2 × Gerbera Daisies Red; 2 × Gerbera Daisies Yellow | K11: N | M11: A mason jar arrangement of 2 red gerberas, 2 yellow gerberas and 1 orange gerbera. A thoughtful choice for a birthday, a thank-you or a just-because moment, and the mason jar stays useful long after. | N11: =LEN(TRIM(SUBSTITUTE(M11,CHAR(10)," ")))-LEN(SUBSTITUTE(TRIM(SUBSTITUTE(M11,CHAR(10)," "))," ",""))+1 | O11: <p>A mason jar arrangement of 2 red gerberas, 2 yellow gerberas and 1 orange gerbera. A thoughtful choice for a birthday, a thank-you or a just-because moment, and the mason jar stays useful long after.</p> | P11: ok | Q11: Gerbera Daisies in a Mason Jar brings together 2 red gerberas, 2 yellow gerberas and 1 orange gerbera, presented in a mason jar you can keep. It suits a birthday, a thank-you or a just-because moment. Red tones say love and devotion. We hand-arrange each one at Aussie Blooms so it looks the way you pictured it, ready for the bedside table. Stems can vary with the season, while the red and yellow palette stays. | R11: <p>Gerbera Daisies in a Mason Jar brings together 2 red gerberas, 2 yellow gerberas and 1 orange gerbera, presented in a mason jar you can keep. It suits a birthday, a thank-you or a just-because moment.</p><p>Red tones say love and devotion. We hand-arrange each one at Aussie Blooms so it looks the way you pictured it, ready for the bedside table. Stems can vary with the season, while the red and yellow palette stays.</p> | S11: ok | T11: The jar holds: 2 red gerberas, 2 yellow gerberas and 1 orange gerbera. Enough colour to turn an ordinary bench into the best spot in the house. | U11: <p>The jar holds: 2 red gerberas, 2 yellow gerberas and 1 orange gerbera. Enough colour to turn an ordinary bench into the best spot in the house.</p> | V11: ok | W11: Fresh Callas | X11: Fresh Callas nestles 2 red gerberas, 2 yellow gerberas and 1 orange gerbera into a relaxed mason jar. Happy on a sunny windowsill. Made for a birthday, a thank-you or a just-because moment. A little wild, a little imperfect, the way a jar should be. | Y11: <p>Fresh Callas nestles 2 red gerberas, 2 yellow gerberas and 1 orange gerbera into a relaxed mason jar. Happy on a sunny windowsill. Made for a birthday, a thank-you or a just-because moment. A little wild, a little imperfect, the way a jar should be.</p> | Z11: ok | AA11: 230 | AB11: 741.99 | AC11: 16 | AD11: 8.5014961e-05 | AE11: 0.00021421777 | AF11: 52
A12: MJ11-57 | B12: Half Dozen Assorted Roses in Mason Jar | C12: Mason Jar | D12: READY - NOTIFY JARROD | E12: A half dozen assorted roses nestled in a charming mason jar, blending classic romance with relaxed, rustic charm. A graceful gesture to celebrate an anniversary, offer congratulations, or send warm get-well wishes to someone special. | F12: Shopify (28 Sep) | G12: 6 × Roses Assorted; 1 × Baby's Breath; 2 × Ruscus Israeli | H12: 6 × Roses Assorted; 1 × Baby's Breath; 2 × Ruscus Israeli | I12: 2 × Ruscus Israeli; 1 × Baby's Breath; 6 × Roses Assorted; 1 × Mason Jar | J12: 2 × Ruscus Israeli; 1 × Baby's Breath; 6 × Roses Assorted | K12: Y | M12: A mason jar arrangement of 6 assorted-colour roses. A lovely way to mark a birthday, a thank-you or a just-because moment, and a bright moment when the door opens. | N12: =LEN(TRIM(SUBSTITUTE(M12,CHAR(10)," ")))-LEN(SUBSTITUTE(TRIM(SUBSTITUTE(M12,CHAR(10)," "))," ",""))+1 | O12: <p>A mason jar arrangement of 6 assorted-colour roses. A lovely way to mark a birthday, a thank-you or a just-because moment, and a bright moment when the door opens.</p> | P12: ok | Q12: Half Dozen Assorted Roses in Mason Jar brings together 6 assorted-colour roses, presented in a mason jar you can keep. It suits a birthday, a thank-you or a just-because moment. Mixed colours say thoughtfulness. We hand-arrange each one at Aussie Blooms so it looks the way you pictured it, ready for the bedside table. Stems can vary with the season, while the colourful palette stays. | R12: <p>Half Dozen Assorted Roses in Mason Jar brings together 6 assorted-colour roses, presented in a mason jar you can keep. It suits a birthday, a thank-you or a just-because moment.</p><p>Mixed colours say thoughtfulness. We hand-arrange each one at Aussie Blooms so it looks the way you pictured it, ready for the bedside table. Stems can vary with the season, while the colourful palette stays.</p> | S12: ok | T12: Inside the jar: 6 assorted-colour roses. Made for the moment someone opens the door and smiles. | U12: <p>Inside the jar: 6 assorted-colour roses. Made for the moment someone opens the door and smiles.</p> | V12: ok | W12: Christmas Morning | X12: Christmas Morning nestles 6 assorted-colour roses into a relaxed mason jar. Happy on a sunny windowsill. Made for a birthday, a thank-you or a just-because moment. | Y12: <p>Christmas Morning nestles 6 assorted-colour roses into a relaxed mason jar. Happy on a sunny windowsill. Made for a birthday, a thank-you or a just-because moment.</p> | Z12: ok | AA12: 163 | AB12: 4812.45 | AC12: 74 | AD12: 0.00055139556 | AE12: 0.0013893876 | AF12: 46
A13: MJ100-31 | B13: Hooray Bouquet in Mason Jar | C13: Mason Jar | D13: READY TO REVIEW | E13: Bright chrysanthemums and ruffled carnations come together in a cheerful mason jar, brimming with feel-good colour. This upbeat arrangement is a wonderful way to say congratulations, lift someone's spirits, or welcome a friend to their new home. | F13: Shopify (28 Sep) | G13: 2 × Chrysanthemum Daisies Yellow; 1 × Limonium Yellow; 1 × Chrysanthemum Daisies Purple; 1 × Chrysanthemum Button Green; 3 × Carnation Red; 2 × Ruscus Israeli; 1 × Mason Jar | H13: 2 × Chrysanthemum Daisies Yellow; 1 × Limonium Yellow; 1 × Chrysanthemum Daisies Purple; 1 × Chrysanthemum Button Green; 3 × Carnation Red; 2 × Ruscus Israeli; 1 × Mason Jar | I13: 2 × Chrysanthemum Daisies Yellow; 1 × Limonium Yellow; 1 × Chrysanthemum Daisies Purple; 1 × Chrysanthemum Button Green; 3 × Carnation Red; 2 × Ruscus Israeli; 1 × Mason Jar | J13: 1 × Chrysanthemum Button Green; 1 × Mason Jar; 2 × Ruscus Israeli; 3 × Carnation Red; 1 × Chrysanthemum Daisies Purple; 1 × Limonium Yellow; 2 × Chrysanthemum Daisies Yellow | K13: Y | M13: A mason jar arrangement of 3 red carnations, 2 yellow chrysanthemum daisies and 1 purple chrysanthemum daisy. A warm gift for a birthday or a thank-you, and the mason jar stays useful long after. | N13: =LEN(TRIM(SUBSTITUTE(M13,CHAR(10)," ")))-LEN(SUBSTITUTE(TRIM(SUBSTITUTE(M13,CHAR(10)," "))," ",""))+1 | O13: <p>A mason jar arrangement of 3 red carnations, 2 yellow chrysanthemum daisies and 1 purple chrysanthemum daisy. A warm gift for a birthday or a thank-you, and the mason jar stays useful long after.</p> | P13: ok | Q13: Hooray Bouquet in Mason Jar brings together 3 red carnations, 2 yellow chrysanthemum daisies and 1 purple chrysanthemum daisy, presented in a mason jar you can keep. It suits a birthday or a thank-you. Red tones say love and devotion. We hand-arrange each one at Aussie Blooms so it looks the way you pictured it, ready for the kitchen bench. Stems can vary with the season, while the red and yellow palette stays. | R13: <p>Hooray Bouquet in Mason Jar brings together 3 red carnations, 2 yellow chrysanthemum daisies and 1 purple chrysanthemum daisy, presented in a mason jar you can keep. It suits a birthday or a thank-you.</p><p>Red tones say love and devotion. We hand-arrange each one at Aussie Blooms so it looks the way you pictured it, ready for the kitchen bench. Stems can vary with the season, while the red and yellow palette stays.</p> | S13: ok | T13: Inside the jar: 3 red carnations, 2 yellow chrysanthemum daisies and 1 purple chrysanthemum daisy. Bright on purpose, and hard to walk past without smiling. | U13: <p>Inside the jar: 3 red carnations, 2 yellow chrysanthemum daisies and 1 purple chrysanthemum daisy. Bright on purpose, and hard to walk past without smiling.</p> | V13: ok | W13: Southern Stars | X13: Southern Stars gathers 3 red carnations, 2 yellow chrysanthemum daisies and 1 purple chrysanthemum daisy into a relaxed mason jar. Right at home on a kitchen bench next to the morning cuppa. Made for a birthday or a thank-you. | Y13: <p>Southern Stars gathers 3 red carnations, 2 yellow chrysanthemum daisies and 1 purple chrysanthemum daisy into a relaxed mason jar. Right at home on a kitchen bench next to the morning cuppa. Made for a birthday or a thank-you.</p> | Z13: ok | AA13: 113 | AB13: 11372.58 | AC13: 142 | AD13: 0.0013030355 | AE13: 0.0032833439 | AF13: 36
A14: MJ100-01 | B14: Love & Laughter in Mason Jar | C14: Mason Jar | D14: READY TO REVIEW | E14: A lively mix of chrysanthemums, carnations and roses arranged in a homely mason jar, radiating warmth and good cheer. Perfectly suited to celebrating happy news, sending get-well wishes, or marking a joyful housewarming. | F14: Shopify (28 Sep) | G14: 2 × Roses Lavender; 2 × Chrysanthemum Spray Lavender; 1 × Chrysanthemum Daisies Purple; 2 × Carnation Purple; 2 × Ruscus Israeli; 1 × Mason Jar; 1 × Mini Carnations Purple; 1 × Greeting Card | H14: 2 × Roses Lavender; 2 × Chrysanthemum Spray Lavender; 1 × Chrysanthemum Daisies Purple; 2 × Carnation Purple; 2 × Ruscus Israeli; 1 × Mason Jar; 1 × Mini Carnations Purple; 1 × Greeting Card | I14: 2 × Roses Lavender; 2 × Chrysanthemum Spray Lavender; 1 × Chrysanthemum Daisies Purple; 2 × Carnation Purple; 2 × Ruscus Israeli; 1 × Mason Jar; 1 × Mini Carnations Purple; 1 × Greeting Card | J14: 2 × Carnation Purple; 1 × Greeting Card; 1 × Mini Carnations Purple; 1 × Mason Jar; 2 × Ruscus Israeli; 1 × Chrysanthemum Daisies Purple; 2 × Chrysanthemum Spray Lavender; 2 × Roses Lavender | K14: Y | M14: A mason jar arrangement of 2 lavender roses, 2 lavender spray chrysanthemums, 2 purple carnations and 1 purple chrysanthemum daisy, plus a greeting card. A warm gift for an anniversary or a thank-you, and the mason jar stays useful long after. | N14: =LEN(TRIM(SUBSTITUTE(M14,CHAR(10)," ")))-LEN(SUBSTITUTE(TRIM(SUBSTITUTE(M14,CHAR(10)," "))," ",""))+1 | O14: <p>A mason jar arrangement of 2 lavender roses, 2 lavender spray chrysanthemums, 2 purple carnations and 1 purple chrysanthemum daisy, plus a greeting card. A warm gift for an anniversary or a thank-you, and the mason jar stays useful long after.</p> | P14: ok | Q14: Love & Laughter in Mason Jar brings together 2 lavender roses, 2 lavender spray chrysanthemums, 2 purple carnations and 1 purple chrysanthemum daisy, presented in a mason jar you can keep, plus a greeting card. It suits an anniversary or a thank-you. Lavender tones say thoughtfulness. We hand-arrange each one at Aussie Blooms so it looks the way you pictured it, ready for the bedside table. Stems can vary with the season, while the lavender and purple palette stays. | R14: <p>Love &amp; Laughter in Mason Jar brings together 2 lavender roses, 2 lavender spray chrysanthemums, 2 purple carnations and 1 purple chrysanthemum daisy, presented in a mason jar you can keep, plus a greeting card. It suits an anniversary or a thank-you.</p><p>Lavender tones say thoughtfulness. We hand-arrange each one at Aussie Blooms so it looks the way you pictured it, ready for the bedside table. Stems can vary with the season, while the lavender and purple palette stays.</p> | S14: ok | T14: Inside the jar: 2 lavender roses, 2 lavender spray chrysanthemums, 2 purple carnations and 1 purple chrysanthemum daisy, plus a greeting card. Calm colour for the kind of day that deserves a pause. | U14: <p>Inside the jar: 2 lavender roses, 2 lavender spray chrysanthemums, 2 purple carnations and 1 purple chrysanthemum daisy, plus a greeting card. Calm colour for the kind of day that deserves a pause.</p> | V14: ok | W14: Happy Hour Gerberas | X14: Happy Hour Gerberas nestles 2 lavender roses, 2 lavender spray chrysanthemums, 2 purple carnations and 1 purple chrysanthemum daisy into a relaxed mason jar, plus a greeting card. Happy on a sunny windowsill. Made for an anniversary or a thank-you. | Y14: <p>Happy Hour Gerberas nestles 2 lavender roses, 2 lavender spray chrysanthemums, 2 purple carnations and 1 purple chrysanthemum daisy into a relaxed mason jar, plus a greeting card. Happy on a sunny windowsill. Made for an anniversary or a thank-you.</p> | Z14: ok | AA14: 135 | AB14: 7922.68 | AC14: 93 | AD14: 0.00090775707 | AE14: 0.002287335 | AF14: 40
A15: MJ102-53 | B15: Make a Wish in Mason Jar Birthday Bundle | C15: Mason Jar | D15: READY - NOTIFY JARROD | E15: Alstroemeria, carnations and chrysanthemums gathered in a charming mason jar for a relaxed, country-fresh feel. A heartfelt birthday bundle that brings rustic warmth and a wish for a wonderful year ahead. | F15: Shopify (28 Sep) | G15: 1 × Carnation Orange; 3 × Carnation Red; 2 × Chrysanthemum Spray Lavender; 2 × Chrysanthemum Spray yellow; 2 × Ruscus Israeli; 1 × Small Chocolates; 1 × Alstroemeria orange; Birthday Balloon | H15: 1 × Carnation Orange; 3 × Carnation Red; 2 × Chrysanthemum Spray Lavender; 2 × Chrysanthemum Spray yellow; 2 × Ruscus Israeli; 1 × Small Chocolates; 1 × Alstroemeria orange; 1 × Birthday Balloon | I15: 2 × Chrysanthemum Spray yellow; 1 × Birthday Balloon; 1 × Alstroemeria orange; 1 × Small Chocolates; 2 × Ruscus Israeli; 2 × Chrysanthemum Spray Lavender; 3 × Carnation Red; 1 × Carnation Orange; 1 × Mason Jar | J15: 2 × Chrysanthemum Spray yellow; 1 × Birthday Balloon; 1 × Alstroemeria orange; 1 × Small Chocolates; 2 × Ruscus Israeli; 2 × Chrysanthemum Spray Lavender; 3 × Carnation Red; 1 × Carnation Orange | K15: Y | M15: A mason jar arrangement of 3 red carnations, 2 lavender spray chrysanthemums, 2 yellow spray chrysanthemums, 1 orange alstroemeria and 1 orange carnation, plus a birthday balloon and a box of small chocolates. A warm gift for a birthday or a thank-you. | N15: =LEN(TRIM(SUBSTITUTE(M15,CHAR(10)," ")))-LEN(SUBSTITUTE(TRIM(SUBSTITUTE(M15,CHAR(10)," "))," ",""))+1 | O15: <p>A mason jar arrangement of 3 red carnations, 2 lavender spray chrysanthemums, 2 yellow spray chrysanthemums, 1 orange alstroemeria and 1 orange carnation, plus a birthday balloon and a box of small chocolates. A warm gift for a birthday or a thank-you.</p> | P15: ok | Q15: Make a Wish in Mason Jar Birthday Bundle brings together 3 red carnations, 2 lavender spray chrysanthemums, 2 yellow spray chrysanthemums, 1 orange alstroemeria and 1 orange carnation, presented in a mason jar you can keep, plus a birthday balloon and a box of small chocolates. It suits a birthday or a thank-you. Red tones say love and devotion. We hand-arrange each one at Aussie Blooms so it looks the way you pictured it, ready for the bedside table. Stems can vary with the season, while the red and lavender palette stays. | R15: <p>Make a Wish in Mason Jar Birthday Bundle brings together 3 red carnations, 2 lavender spray chrysanthemums, 2 yellow spray chrysanthemums, 1 orange alstroemeria and 1 orange carnation, presented in a mason jar you can keep, plus a birthday balloon and a box of small chocolates. It suits a birthday or a thank-you.</p><p>Red tones say love and devotion. We hand-arrange each one at Aussie Blooms so it looks the way you pictured it, ready for the bedside table. Stems can vary with the season, while the red and lavender palette stays.</p> | S15: ok | T15: Inside the jar: 3 red carnations, 2 lavender spray chrysanthemums, 2 yellow spray chrysanthemums, 1 orange alstroemeria and 1 orange carnation, plus a birthday balloon and a box of small chocolates. Bright on purpose, and hard to walk past without smiling. | U15: <p>Inside the jar: 3 red carnations, 2 lavender spray chrysanthemums, 2 yellow spray chrysanthemums, 1 orange alstroemeria and 1 orange carnation, plus a birthday balloon and a box of small chocolates. Bright on purpose, and hard to walk past without smiling.</p> | V15: ok | W15: Six of Mel's Best | X15: Six of Mel's Best nestles 3 red carnations, 2 lavender spray chrysanthemums, 2 yellow spray chrysanthemums, 1 orange alstroemeria and 1 orange carnation into a relaxed mason jar, plus a birthday balloon and a box of small chocolates. Happy on a sunny windowsill. Made for a birthday or a thank-you. | Y15: <p>Six of Mel's Best nestles 3 red carnations, 2 lavender spray chrysanthemums, 2 yellow spray chrysanthemums, 1 orange alstroemeria and 1 orange carnation into a relaxed mason jar, plus a birthday balloon and a box of small chocolates. Happy on a sunny windowsill. Made for a birthday or a thank-you.</p> | Z15: ok | AA15: 159 | AB15: 5336.27 | AC15: 57 | AD15: 0.00061141407 | AE15: 0.0015406201 | AF15: 44
A16: MDMJ-03 | B16: Blooming Glory in Mason Jar | C16: Mason Jar | D16: READY TO REVIEW | E16: Eight elegant roses presented in a charming mason jar, a graceful blend of beauty and rustic warmth. A heartfelt way to celebrate a proud graduate and honour their hard-earned achievement with timeless style. | F16: Shopify (28 Sep) | G16: 2 × Roses Assorted; 8 × Designer Collection stems; 2 × Ruscus Israeli; 1 × Mason Jar; 1 × Greeting Card | H16: 2 × Roses Assorted; 8 × Designer Collection stems; 2 × Ruscus Israeli; 1 × Mason Jar; 1 × Greeting Card | I16: 2 × Roses Assorted; 8 × Designer Collection stems; 2 × Ruscus Israeli; 1 × Mason Jar; 1 × Greeting Card | J16: 2 × Ruscus Israeli; 1 × Greeting Card; 1 × Mason Jar; 8 × Designer Collection stems; 2 × Roses Assorted | K16: Y | M16: A florist-designed bouquet with 8 florist's choice stems and 2 assorted-colour roses, presented in a mason jar. Stems vary with the season, so the picture is illustrative and shows the style and colour, not the exact flowers. | N16: =LEN(TRIM(SUBSTITUTE(M16,CHAR(10)," ")))-LEN(SUBSTITUTE(TRIM(SUBSTITUTE(M16,CHAR(10)," "))," ",""))+1 | O16: <p>A florist-designed bouquet with 8 florist's choice stems and 2 assorted-colour roses, presented in a mason jar. Stems vary with the season, so the picture is illustrative and shows the style and colour, not the exact flowers.</p> | P16: ok | Q16: Blooming Glory in Mason Jar is an arrangement of 8 florist's choice stems and 2 assorted-colour roses, presented in a mason jar. Stems vary with the season, so the picture is illustrative and shows the style and colour, not the exact flowers. It suits a birthday, a thank-you or a just-because moment, or any day you want to bring a little colour to a summer table. | R16: <p>Blooming Glory in Mason Jar is an arrangement of 8 florist's choice stems and 2 assorted-colour roses, presented in a mason jar. Stems vary with the season, so the picture is illustrative and shows the style and colour, not the exact flowers.</p><p>It suits a birthday, a thank-you or a just-because moment, or any day you want to bring a little colour to a summer table.</p> | S16: ok | T16: In this bunch: 8 florist's choice stems and 2 assorted-colour roses in a mason jar. Stems vary with the season, so the picture is illustrative and shows the style and colour, not the exact flowers. | U16: <p>In this bunch: 8 florist's choice stems and 2 assorted-colour roses in a mason jar. Stems vary with the season, so the picture is illustrative and shows the style and colour, not the exact flowers.</p> | V16: ok | W16: Good News | X16: Good News gathers 8 florist's choice stems and 2 assorted-colour roses into a relaxed mason jar. Stems vary with the season, so the picture is illustrative and shows the style and colour, not the exact flowers. | Y16: <p>Good News gathers 8 florist's choice stems and 2 assorted-colour roses into a relaxed mason jar. Stems vary with the season, so the picture is illustrative and shows the style and colour, not the exact flowers.</p> | Z16: ok | AA16: 219 | AB16: 1365.84 | AC16: 17 | AD16: 0.0001564938 | AE16: 0.00039432769 | AF16: 50
A17: MJ100-62 | B17: Peaceful Clouds in Mason Jar | C17: Mason Jar | D17: READY TO REVIEW | E17: Soft alstroemeria and gentle roses arranged in a serene mason jar, evoking a sense of calm and quiet comfort. A tender choice for welcoming a new baby or offering heartfelt sympathy, these soothing blooms speak gently when words feel hard to find. | F17: Shopify (28 Sep) | G17: 2 × Roses Spray White; 3 × Roses White; 1 × Limonium White; 2 × Ruscus Israeli; 1 × Mason Jar; 2 × Alstroemeria White | H17: 2 × Roses Spray White; 3 × Roses White; 1 × Limonium White; 2 × Ruscus Israeli; 1 × Mason Jar; 2 × Alstroemeria White | I17: 2 × Roses Spray White; 3 × Roses White; 1 × Limonium White; 2 × Ruscus Israeli; 1 × Mason Jar; 2 × Alstroemeria White | J17: 1 × Limonium White; 2 × Alstroemeria White; 1 × Mason Jar; 2 × Ruscus Israeli; 3 × Roses White; 2 × Roses Spray White | K17: Y | M17: A mason jar arrangement of 3 white roses, 2 white alstroemeria and 2 white spray roses. A warm gift for a birthday, a thank-you or a just-because moment, and the mason jar stays useful long after. | N17: =LEN(TRIM(SUBSTITUTE(M17,CHAR(10)," ")))-LEN(SUBSTITUTE(TRIM(SUBSTITUTE(M17,CHAR(10)," "))," ",""))+1 | O17: <p>A mason jar arrangement of 3 white roses, 2 white alstroemeria and 2 white spray roses. A warm gift for a birthday, a thank-you or a just-because moment, and the mason jar stays useful long after.</p> | P17: ok | Q17: Peaceful Clouds in Mason Jar brings together 3 white roses, 2 white alstroemeria and 2 white spray roses, presented in a mason jar you can keep. It suits a birthday, a thank-you or a just-because moment. White tones say calm and a fresh start. We hand-arrange each one at Aussie Blooms so it looks the way you pictured it, ready for the kitchen bench. Stems can vary with the season, while the white palette stays. | R17: <p>Peaceful Clouds in Mason Jar brings together 3 white roses, 2 white alstroemeria and 2 white spray roses, presented in a mason jar you can keep. It suits a birthday, a thank-you or a just-because moment.</p><p>White tones say calm and a fresh start. We hand-arrange each one at Aussie Blooms so it looks the way you pictured it, ready for the kitchen bench. Stems can vary with the season, while the white palette stays.</p> | S17: ok | T17: Inside the jar: 3 white roses, 2 white alstroemeria and 2 white spray roses. Calm colour for the kind of day that deserves a pause. | U17: <p>Inside the jar: 3 white roses, 2 white alstroemeria and 2 white spray roses. Calm colour for the kind of day that deserves a pause.</p> | V17: ok | W17: The Hydrangea Bunch | X17: The Hydrangea Bunch gathers 3 white roses, 2 white alstroemeria and 2 white spray roses into a relaxed mason jar. Right at home on a kitchen bench next to the morning cuppa. Made for a birthday, a thank-you or a just-because moment. | Y17: <p>The Hydrangea Bunch gathers 3 white roses, 2 white alstroemeria and 2 white spray roses into a relaxed mason jar. Right at home on a kitchen bench next to the morning cuppa. Made for a birthday, a thank-you or a just-because moment.</p> | Z17: ok | AA17: 13 | AB17: 158872.91 | AC17: 2744 | AD17: 0.018203176 | AE17: 0.045867736 | AF17: 7
A18: CCS-APR | B18: Posh Pink in Mason Jar | C18: Mason Jar | D18: READY TO REVIEW | F18: none | G18: 1 × Roses Spray Pink; 2 × Roses Cream; 1 × Limonium Pink; 1 × Chrysanthemum Spray White; 2 × Ruscus Israeli; 1 × Mason Jar; 2 × Mini Carnations White; 1 × Limonium white; 1 × Alstroemeria Pink | H18: 1 × Roses Spray Pink; 2 × Roses Cream; 1 × Limonium Pink; 1 × Chrysanthemum Spray White; 2 × Ruscus Israeli; 1 × Mason Jar; 2 × Mini Carnations White; 1 × Limonium White; 1 × Alstroemeria Pink | I18: 1 × Roses Spray Pink; 2 × Roses Cream; 1 × Limonium Pink; 1 × Chrysanthemum Spray White; 2 × Ruscus Israeli; 1 × Mason Jar; 2 × Mini Carnations White; 1 × Limonium White; 1 × Alstroemeria Pink | J18: 1 × Chrysanthemum Spray White; 1 × Alstroemeria Pink; 1 × Limonium White; 2 × Mini Carnations White; 1 × Mason Jar; 2 × Ruscus Israeli; 1 × Limonium Pink; 2 × Roses Cream; 1 × Roses Spray Pink | K18: N | M18: A hand-arranged mason jar bouquet of 2 cream roses, 1 pink alstroemeria, 1 pink spray rose and 1 white spray chrysanthemum. A lovely way to mark a birthday, a thank-you or a just-because moment, with a mason jar to keep once the flowers are gone. | N18: =LEN(TRIM(SUBSTITUTE(M18,CHAR(10)," ")))-LEN(SUBSTITUTE(TRIM(SUBSTITUTE(M18,CHAR(10)," "))," ",""))+1 | O18: <p>A hand-arranged mason jar bouquet of 2 cream roses, 1 pink alstroemeria, 1 pink spray rose and 1 white spray chrysanthemum. A lovely way to mark a birthday, a thank-you or a just-because moment, with a mason jar to keep once the flowers are gone.</p> | P18: ok | Q18: Posh Pink in Mason Jar brings together 2 cream roses, 1 pink alstroemeria, 1 pink spray rose and 1 white spray chrysanthemum, presented in a mason jar you can keep. It suits a birthday, a thank-you or a just-because moment. White tones say calm and a fresh start. We hand-arrange each one at Aussie Blooms so it looks the way you pictured it, ready for a summer table. Stems can vary with the season, while the white and cream palette stays. | R18: <p>Posh Pink in Mason Jar brings together 2 cream roses, 1 pink alstroemeria, 1 pink spray rose and 1 white spray chrysanthemum, presented in a mason jar you can keep. It suits a birthday, a thank-you or a just-because moment.</p><p>White tones say calm and a fresh start. We hand-arrange each one at Aussie Blooms so it looks the way you pictured it, ready for a summer table. Stems can vary with the season, while the white and cream palette stays.</p> | S18: ok | T18: In the jar: 2 cream roses, 1 pink alstroemeria, 1 pink spray rose and 1 white spray chrysanthemum. Soft colours that make a quiet room feel looked after. | U18: <p>In the jar: 2 cream roses, 1 pink alstroemeria, 1 pink spray rose and 1 white spray chrysanthemum. Soft colours that make a quiet room feel looked after.</p> | V18: ok | W18: Loud and Lovely | X18: Loud and Lovely tucks 2 cream roses, 1 pink alstroemeria, 1 pink spray rose and 1 white spray chrysanthemum into a relaxed mason jar. Lovely on a bedside table, or anywhere it can be seen. A good fit for a birthday, a thank-you or a just-because moment. A little wild, a little imperfect, the way a jar should be. | Y18: <p>Loud and Lovely tucks 2 cream roses, 1 pink alstroemeria, 1 pink spray rose and 1 white spray chrysanthemum into a relaxed mason jar. Lovely on a bedside table, or anywhere it can be seen. A good fit for a birthday, a thank-you or a just-because moment. A little wild, a little imperfect, the way a jar should be.</p> | Z18: ok | AA18: 123 | AB18: 9065.81 | AC18: 95 | AD18: 0.001038733 | AE18: 0.0026173636 | AF18: 38
A19: MJ55-01 | B19: Radiant Roses in Mason Jar | C19: Mason Jar | D19: READY TO REVIEW | E19: Fourteen radiant roses arranged in a charming mason jar, where classic romance meets relaxed, rustic charm. A timeless gesture for an anniversary or birthday, or simply a beautiful way to tell someone you're thinking of them just because. | F19: Shopify (28 Sep) | G19: 3 × Roses Red; 1 × Baby's Breath; 1 × Ruscus Israeli; 1 × Mason Jar | H19: 3 × Roses Red; 1 × Baby's Breath; 1 × Ruscus Israeli; 1 × Mason Jar | I19: 3 × Roses Red; 1 × Baby's Breath; 1 × Ruscus Israeli; 1 × Mason Jar | J19: 3 × Roses Red; 1 × Mason Jar; 1 × Ruscus Israeli; 1 × Baby's Breath | K19: Y | M19: A mason jar arrangement of 3 red roses. A lovely way to mark an anniversary or a thank-you, and a bright moment when the door opens. | N19: =LEN(TRIM(SUBSTITUTE(M19,CHAR(10)," ")))-LEN(SUBSTITUTE(TRIM(SUBSTITUTE(M19,CHAR(10)," "))," ",""))+1 | O19: <p>A mason jar arrangement of 3 red roses. A lovely way to mark an anniversary or a thank-you, and a bright moment when the door opens.</p> | P19: ok | Q19: Radiant Roses in Mason Jar brings together 3 red roses, presented in a mason jar you can keep. It suits an anniversary or a thank-you. Red tones say love and devotion. We hand-arrange each one at Aussie Blooms so it looks the way you pictured it, ready for the bedside table. Stems can vary with the season, while the red palette stays. | R19: <p>Radiant Roses in Mason Jar brings together 3 red roses, presented in a mason jar you can keep. It suits an anniversary or a thank-you.</p><p>Red tones say love and devotion. We hand-arrange each one at Aussie Blooms so it looks the way you pictured it, ready for the bedside table. Stems can vary with the season, while the red palette stays.</p> | S19: ok | T19: The jar holds: 3 red roses. The classic, handed over without a single word of explanation. | U19: <p>The jar holds: 3 red roses. The classic, handed over without a single word of explanation.</p> | V19: ok | W19: Blow Out the Candles Bundle | X19: Blow Out the Candles Bundle nestles 3 red roses into a relaxed mason jar. Happy on a sunny windowsill. Made for an anniversary or a thank-you. A little wild, a little imperfect, the way a jar should be. | Y19: <p>Blow Out the Candles Bundle nestles 3 red roses into a relaxed mason jar. Happy on a sunny windowsill. Made for an anniversary or a thank-you. A little wild, a little imperfect, the way a jar should be.</p> | Z19: ok | AA19: 108 | AB19: 12932.2 | AC19: 212 | AD19: 0.0014817321 | AE19: 0.0037336175 | AF19: 35
A20: SB-01MJ | B20: Sweet Blossom in Mason Jar | C20: Mason Jar | D20: READY TO REVIEW | E20: A generous abundance of chrysanthemums fills this charming mason jar with sweet, blossoming colour and cheer. Bright and uplifting, it's a lovely way to send congratulations, brighten a recovery, or warmly welcome someone to their new home. | F20: Shopify (28 Sep) | G20: 4 × Chrysanthemum Spray White; 4 × Chrysanthemum Spray Lavender; 2 × Ruscus Israeli; 1 × Mason Jar | H20: 4 × Chrysanthemum Spray White; 4 × Chrysanthemum Spray Lavender; 2 × Ruscus Israeli; 1 × Mason Jar | I20: 4 × Chrysanthemum Spray White; 4 × Chrysanthemum Spray Lavender; 2 × Ruscus Israeli; 1 × Mason Jar | J20: 2 × Ruscus Israeli; 1 × Mason Jar; 4 × Chrysanthemum Spray Lavender; 4 × Chrysanthemum Spray White | K20: Y | M20: A hand-arranged mason jar bouquet of 4 lavender spray chrysanthemums and 4 white spray chrysanthemums. A thoughtful choice for a birthday, a thank-you or a just-because moment, with a mason jar to keep once the flowers are gone. | N20: =LEN(TRIM(SUBSTITUTE(M20,CHAR(10)," ")))-LEN(SUBSTITUTE(TRIM(SUBSTITUTE(M20,CHAR(10)," "))," ",""))+1 | O20: <p>A hand-arranged mason jar bouquet of 4 lavender spray chrysanthemums and 4 white spray chrysanthemums. A thoughtful choice for a birthday, a thank-you or a just-because moment, with a mason jar to keep once the flowers are gone.</p> | P20: ok | Q20: Sweet Blossom in Mason Jar brings together 4 lavender spray chrysanthemums and 4 white spray chrysanthemums, presented in a mason jar you can keep. It suits a birthday, a thank-you or a just-because moment. Lavender tones say thoughtfulness. We hand-arrange each one at Aussie Blooms so it looks the way you pictured it, ready for a summer table. Stems can vary with the season, while the lavender and white palette stays. | R20: <p>Sweet Blossom in Mason Jar brings together 4 lavender spray chrysanthemums and 4 white spray chrysanthemums, presented in a mason jar you can keep. It suits a birthday, a thank-you or a just-because moment.</p><p>Lavender tones say thoughtfulness. We hand-arrange each one at Aussie Blooms so it looks the way you pictured it, ready for a summer table. Stems can vary with the season, while the lavender and white palette stays.</p> | S20: ok | T20: The jar holds: 4 lavender spray chrysanthemums and 4 white spray chrysanthemums. Gentle, easy on the eye, and ready for any table you give it. | U20: <p>The jar holds: 4 lavender spray chrysanthemums and 4 white spray chrysanthemums. Gentle, easy on the eye, and ready for any table you give it.</p> | V20: ok | W20: Mel's Favourite | X20: Mel's Favourite tucks 4 lavender spray chrysanthemums and 4 white spray chrysanthemums into a relaxed mason jar. Lovely on a bedside table, or anywhere it can be seen. A good fit for a birthday, a thank-you or a just-because moment. A little wild, a little imperfect, the way a jar should be. | Y20: <p>Mel's Favourite tucks 4 lavender spray chrysanthemums and 4 white spray chrysanthemums into a relaxed mason jar. Lovely on a bedside table, or anywhere it can be seen. A good fit for a birthday, a thank-you or a just-because moment. A little wild, a little imperfect, the way a jar should be.</p> | Z20: ok | AA20: 130 | AB20: 8364.33 | AC20: 96 | AD20: 0.00095835976 | AE20: 0.0024148419 | AF20: 39
A21: MJ100-17 | B21: Thirty Blooms of Alstroemeria in Mason Jar | C21: Mason Jar | D21: READY - NOTIFY JARROD | E21: Thirty Blooms of Alstroemeria in Mason Jar sends cheerful colour in a practical display-ready gift. Choose it for birthdays, congratulations, thank-you notes, and get-well wishes. Alstroemeria brings a lively, layered look with many small blooms. The mason jar makes the arrangement easy to place at home or work. Bright mixed tones suit warm messages and everyday celebrations. Review the delivery date and add your card message at checkout. | F21: Shopify (28 Sep) | G21: 10 × Alstroemeria assorted | H21: 10 × Alstroemeria assorted | I21: 10 × Alstroemeria assorted; 1 × Mason Jar; 2 × Ruscus Israeli | J21: 10 × Alstroemeria assorted | K21: Y | L21: Title blooms vs stems: Title counts blooms, recipe counts stems; bridge wording needs blooms per stem from Alejandro/Benny | M21: A mason jar arrangement of 10 assorted-colour alstroemeria. A lovely way to mark a birthday, a thank-you or a just-because moment, and a bright moment when the door opens. | N21: =LEN(TRIM(SUBSTITUTE(M21,CHAR(10)," ")))-LEN(SUBSTITUTE(TRIM(SUBSTITUTE(M21,CHAR(10)," "))," ",""))+1 | O21: <p>A mason jar arrangement of 10 assorted-colour alstroemeria. A lovely way to mark a birthday, a thank-you or a just-because moment, and a bright moment when the door opens.</p> | P21: ok | Q21: Thirty Blooms of Alstroemeria in Mason Jar brings together 10 assorted-colour alstroemeria, presented in a mason jar you can keep. It suits a birthday, a thank-you or a just-because moment. Mixed colours say thoughtfulness. We hand-arrange each one at Aussie Blooms so it looks the way you pictured it, ready for the kitchen bench. Stems can vary with the season, while the colourful palette stays. | R21: <p>Thirty Blooms of Alstroemeria in Mason Jar brings together 10 assorted-colour alstroemeria, presented in a mason jar you can keep. It suits a birthday, a thank-you or a just-because moment.</p><p>Mixed colours say thoughtfulness. We hand-arrange each one at Aussie Blooms so it looks the way you pictured it, ready for the kitchen bench. Stems can vary with the season, while the colourful palette stays.</p> | S21: ok | T21: Inside the jar: 10 assorted-colour alstroemeria. Made for the moment someone opens the door and smiles. | U21: <p>Inside the jar: 10 assorted-colour alstroemeria. Made for the moment someone opens the door and smiles.</p> | V21: ok | W21: Soft Landing | X21: Soft Landing gathers 10 assorted-colour alstroemeria into a relaxed mason jar. Right at home on a kitchen bench next to the morning cuppa. Made for a birthday, a thank-you or a just-because moment. A little wild, a little imperfect, the way a jar should be. | Y21: <p>Soft Landing gathers 10 assorted-colour alstroemeria into a relaxed mason jar. Right at home on a kitchen bench next to the morning cuppa. Made for a birthday, a thank-you or a just-because moment. A little wild, a little imperfect, the way a jar should be.</p> | Z21: ok | AA21: 17 | AB21: 131407.94 | AC21: 2228 | AD21: 0.015056322 | AE21: 0.037938403 | AF21: 8
A22: MJ100-20 | B22: Beautiful in Blue in Mason Jar | C22: Mason Jar | D22: READY TO REVIEW | E22: In this lovely bouquet, the peace and beauty of blue combines with the purity and grace of white is a lovely gift for any ocassion but when sent in sympathy this arrangement will surely convey strength and support during a time of loss. Includes Mason Jar. The bouquet contains a beautiful selection of flower such as cream Roses, white Lilies, and Alstroemeria as well as white Chrysanthemums, Eucalyptus, and more. Approximately 15 1/2" W x 16 1/2" H. | F22: Shopify (28 Sep) | G22: 3 × Roses Cream; 1 × Eryngium; 2 × Carnation blue; 3 × Chrysanthemum Daisies White; 2 × Ruscus Israeli; 1 × Mason Jar; 2 × Alstroemeria White | H22: 3 × Roses Cream; 1 × Eryngium; 2 × Carnations Blue; 3 × Chrysanthemum Daisies White; 2 × Ruscus Israeli; 1 × Mason Jar; 2 × Alstroemeria White | I22: 3 × Roses Cream; 1 × Eryngium; 2 × Carnations Blue; 3 × Chrysanthemum Daisies White; 2 × Ruscus Israeli; 1 × Mason Jar; 2 × Alstroemeria White | J22: 3 × Chrysanthemum Daisies White; 2 × Alstroemeria White; 1 × Mason Jar; 2 × Ruscus Israeli; 2 × Carnations Blue; 1 × Eryngium; 3 × Roses Cream | K22: N | M22: A hand-arranged mason jar bouquet of 3 cream roses, 3 white chrysanthemum daisies, 2 blue carnations and 2 white alstroemeria. A warm gift for a birthday, a thank-you or a just-because moment, with a mason jar to keep once the flowers are gone. | N22: =LEN(TRIM(SUBSTITUTE(M22,CHAR(10)," ")))-LEN(SUBSTITUTE(TRIM(SUBSTITUTE(M22,CHAR(10)," "))," ",""))+1 | O22: <p>A hand-arranged mason jar bouquet of 3 cream roses, 3 white chrysanthemum daisies, 2 blue carnations and 2 white alstroemeria. A warm gift for a birthday, a thank-you or a just-because moment, with a mason jar to keep once the flowers are gone.</p> | P22: ok | Q22: Beautiful in Blue in Mason Jar brings together 3 cream roses, 3 white chrysanthemum daisies, 2 blue carnations and 2 white alstroemeria, presented in a mason jar you can keep. It suits a birthday, a thank-you or a just-because moment. White tones say calm and a fresh start. We hand-arrange each one at Aussie Blooms so it looks the way you pictured it, ready for a Sunday lunch. Stems can vary with the season, while the white and cream palette stays. | R22: <p>Beautiful in Blue in Mason Jar brings together 3 cream roses, 3 white chrysanthemum daisies, 2 blue carnations and 2 white alstroemeria, presented in a mason jar you can keep. It suits a birthday, a thank-you or a just-because moment.</p><p>White tones say calm and a fresh start. We hand-arrange each one at Aussie Blooms so it looks the way you pictured it, ready for a Sunday lunch. Stems can vary with the season, while the white and cream palette stays.</p> | S22: ok | T22: Inside the jar: 3 cream roses, 3 white chrysanthemum daisies, 2 blue carnations and 2 white alstroemeria. Calm colour for the kind of day that deserves a pause. | U22: <p>Inside the jar: 3 cream roses, 3 white chrysanthemum daisies, 2 blue carnations and 2 white alstroemeria. Calm colour for the kind of day that deserves a pause.</p> | V22: ok | W22: Blushing Hydrangeas | X22: Blushing Hydrangeas settles 3 cream roses, 3 white chrysanthemum daisies, 2 blue carnations and 2 white alstroemeria into a relaxed mason jar. Just right sitting on a bench where everyone can enjoy it. A good fit for a birthday, a thank-you or a just-because moment. A little wild, a little imperfect, the way a jar should be. | Y22: <p>Blushing Hydrangeas settles 3 cream roses, 3 white chrysanthemum daisies, 2 blue carnations and 2 white alstroemeria into a relaxed mason jar. Just right sitting on a bench where everyone can enjoy it. A good fit for a birthday, a thank-you or a just-because moment. A little wild, a little imperfect, the way a jar should be.</p> | Z22: ok | AA22: 36 | AB22: 58375.28 | AC22: 657 | AD22: 0.0066884623 | AE22: 0.016853357 | AF22: 16
A23: MJ100-12 | B23: Classic Whites In Mason Jar | C23: Mason Jar | D23: READY TO REVIEW | E23: A beautiful tribute to honour cherished memories. Classic Whites In Mason Jar expresses heartfelt condolences. A thoughtful tribute crafted with care to honour cherished memories. | F23: Shopify (28 Sep) | G23: 4 × Roses White; 3 × Gerbera Daisies White; 2 × Ruscus Israeli; 1 × Mason Jar; 2 × Alstroemeria White | H23: 4 × Roses White; 3 × Gerbera Daisies White; 2 × Ruscus Israeli; 1 × Mason Jar; 2 × Alstroemeria White | I23: 4 × Roses White; 3 × Gerbera Daisies White; 2 × Ruscus Israeli; 1 × Mason Jar; 2 × Alstroemeria White | J23: 2 × Ruscus Israeli; 2 × Alstroemeria White; 1 × Mason Jar; 3 × Gerbera Daisies White; 4 × Roses White | K23: Y | M23: A hand-arranged mason jar bouquet of 4 white roses, 3 white gerberas and 2 white alstroemeria. A thoughtful choice for a birthday, a thank-you or a just-because moment, with a mason jar to keep once the flowers are gone. | N23: =LEN(TRIM(SUBSTITUTE(M23,CHAR(10)," ")))-LEN(SUBSTITUTE(TRIM(SUBSTITUTE(M23,CHAR(10)," "))," ",""))+1 | O23: <p>A hand-arranged mason jar bouquet of 4 white roses, 3 white gerberas and 2 white alstroemeria. A thoughtful choice for a birthday, a thank-you or a just-because moment, with a mason jar to keep once the flowers are gone.</p> | P23: ok | Q23: Classic Whites In Mason Jar brings together 4 white roses, 3 white gerberas and 2 white alstroemeria, presented in a mason jar you can keep. It suits a birthday, a thank-you or a just-because moment. White tones say calm and a fresh start. We hand-arrange each one at Aussie Blooms so it looks the way you pictured it, ready for a Sunday lunch. Stems can vary with the season, while the white palette stays. | R23: <p>Classic Whites In Mason Jar brings together 4 white roses, 3 white gerberas and 2 white alstroemeria, presented in a mason jar you can keep. It suits a birthday, a thank-you or a just-because moment.</p><p>White tones say calm and a fresh start. We hand-arrange each one at Aussie Blooms so it looks the way you pictured it, ready for a Sunday lunch. Stems can vary with the season, while the white palette stays.</p> | S23: ok | T23: The jar holds: 4 white roses, 3 white gerberas and 2 white alstroemeria. Gentle, easy on the eye, and ready for any table you give it. | U23: <p>The jar holds: 4 white roses, 3 white gerberas and 2 white alstroemeria. Gentle, easy on the eye, and ready for any table you give it.</p> | V23: ok | W23: Fancy That | X23: Fancy That settles 4 white roses, 3 white gerberas and 2 white alstroemeria into a relaxed mason jar. Just right sitting on a bench where everyone can enjoy it. A good fit for a birthday, a thank-you or a just-because moment. | Y23: <p>Fancy That settles 4 white roses, 3 white gerberas and 2 white alstroemeria into a relaxed mason jar. Just right sitting on a bench where everyone can enjoy it. A good fit for a birthday, a thank-you or a just-because moment.</p> | Z23: ok | AA23: 218 | AB23: 1401 | AC23: 19 | AD23: 0.00016052233 | AE23: 0.00040447863 | AF23: 49
A24: MJ100-11 | B24: Breathtaking Blooms In Mason Jar | C24: Mason Jar | D24: READY TO REVIEW | F24: none | G24: 2 × Roses Pink; 1 × Gerbera Daisies Hot Pink; 2 × Ruscus Israeli; 1 × Mason Jar; 2 × Mini Carnations Pink; 2 × Alstroemeria White; 2 × Alstroemeria Pink | H24: 2 × Roses Pink; 1 × Gerbera Daisies Hot Pink; 2 × Ruscus Israeli; 1 × Mason Jar; 2 × Mini Carnations Pink; 2 × Alstroemeria White; 2 × Alstroemeria Pink | I24: 2 × Roses Pink; 1 × Gerbera Daisies Hot Pink; 2 × Ruscus Israeli; 1 × Mason Jar; 2 × Mini Carnations Pink; 2 × Alstroemeria White; 2 × Alstroemeria Pink | J24: 2 × Alstroemeria Pink; 2 × Alstroemeria White; 2 × Mini Carnations Pink; 1 × Mason Jar; 2 × Ruscus Israeli; 1 × Gerbera Daisies Hot Pink; 2 × Roses Pink | K24: Y | M24: A hand-arranged mason jar bouquet of 2 pink alstroemeria, 2 pink roses, 2 white alstroemeria and 1 hot pink gerbera. A thoughtful choice for a birthday, a thank-you or a just-because moment, with a mason jar to keep once the flowers are gone. | N24: =LEN(TRIM(SUBSTITUTE(M24,CHAR(10)," ")))-LEN(SUBSTITUTE(TRIM(SUBSTITUTE(M24,CHAR(10)," "))," ",""))+1 | O24: <p>A hand-arranged mason jar bouquet of 2 pink alstroemeria, 2 pink roses, 2 white alstroemeria and 1 hot pink gerbera. A thoughtful choice for a birthday, a thank-you or a just-because moment, with a mason jar to keep once the flowers are gone.</p> | P24: ok | Q24: Breathtaking Blooms In Mason Jar brings together 2 pink alstroemeria, 2 pink roses, 2 white alstroemeria and 1 hot pink gerbera, presented in a mason jar you can keep. It suits a birthday, a thank-you or a just-because moment. Pink tones say affection. We hand-arrange each one at Aussie Blooms so it looks the way you pictured it, ready for a Sunday lunch. Stems can vary with the season, while the pink and white palette stays. | R24: <p>Breathtaking Blooms In Mason Jar brings together 2 pink alstroemeria, 2 pink roses, 2 white alstroemeria and 1 hot pink gerbera, presented in a mason jar you can keep. It suits a birthday, a thank-you or a just-because moment.</p><p>Pink tones say affection. We hand-arrange each one at Aussie Blooms so it looks the way you pictured it, ready for a Sunday lunch. Stems can vary with the season, while the pink and white palette stays.</p> | S24: ok | T24: The jar holds: 2 pink alstroemeria, 2 pink roses, 2 white alstroemeria and 1 hot pink gerbera. Enough colour to turn an ordinary bench into the best spot in the house. | U24: <p>The jar holds: 2 pink alstroemeria, 2 pink roses, 2 white alstroemeria and 1 hot pink gerbera. Enough colour to turn an ordinary bench into the best spot in the house.</p> | V24: ok | W24: Sunday Roses | X24: Sunday Roses settles 2 pink alstroemeria, 2 pink roses, 2 white alstroemeria and 1 hot pink gerbera into a relaxed mason jar. Just right sitting on a bench where everyone can enjoy it. A good fit for a birthday, a thank-you or a just-because moment. | Y24: <p>Sunday Roses settles 2 pink alstroemeria, 2 pink roses, 2 white alstroemeria and 1 hot pink gerbera into a relaxed mason jar. Just right sitting on a bench where everyone can enjoy it. A good fit for a birthday, a thank-you or a just-because moment.</p> | Z24: ok | AA24: 4 | AB24: 301982.54 | AC24: 4556 | AD24: 0.034600242 | AE24: 0.0871845 | AF24: 3
A25: MJ100-10 | B25: Sweet Summer In Mason Jar | C25: Mason Jar | D25: READY TO REVIEW | E25: Nineteen cheerful roses mingle with nine bright gerberas and four sweet lilies in our charming Sweet Summer In Mason Jar. Rustic yet refined, it brings a burst of sunshine indoors and makes a lovely just-because surprise for someone who lights up your day. | F25: Shopify (28 Sep) | G25: 4 × Roses Pink; 2 × Calrnation White; 2 × Gerbera Daisies Light Pink; 1 × Gerbera Daisies Red; 2 × Ruscus Israeli; 1 × Mason Jar | H25: 4 × Roses Pink; 2 × Carnation White; 2 × Gerbera Daisies Light Pink; 1 × Gerbera Daisies Red; 2 × Ruscus Israeli; 1 × Mason Jar | I25: 4 × Roses Pink; 2 × Carnation White; 2 × Gerbera Daisies Light Pink; 1 × Gerbera Daisies Red; 2 × Ruscus Israeli; 1 × Mason Jar | J25: 2 × Gerbera Daisies Light Pink; 1 × Mason Jar; 2 × Ruscus Israeli; 1 × Gerbera Daisies Red; 2 × Carnation White; 4 × Roses Pink | K25: Y | M25: A mason jar arrangement of 4 pink roses, 2 light pink gerberas, 2 white carnations and 1 red gerbera. A thoughtful choice for a birthday, a thank-you or a just-because moment, and the mason jar stays useful long after. | N25: =LEN(TRIM(SUBSTITUTE(M25,CHAR(10)," ")))-LEN(SUBSTITUTE(TRIM(SUBSTITUTE(M25,CHAR(10)," "))," ",""))+1 | O25: <p>A mason jar arrangement of 4 pink roses, 2 light pink gerberas, 2 white carnations and 1 red gerbera. A thoughtful choice for a birthday, a thank-you or a just-because moment, and the mason jar stays useful long after.</p> | P25: ok | Q25: Sweet Summer In Mason Jar brings together 4 pink roses, 2 light pink gerberas, 2 white carnations and 1 red gerbera, presented in a mason jar you can keep. It suits a birthday, a thank-you or a just-because moment. Pink tones say affection. We hand-arrange each one at Aussie Blooms so it looks the way you pictured it, ready for the bedside table. Stems can vary with the season, while the pink and light pink palette stays. | R25: <p>Sweet Summer In Mason Jar brings together 4 pink roses, 2 light pink gerberas, 2 white carnations and 1 red gerbera, presented in a mason jar you can keep. It suits a birthday, a thank-you or a just-because moment.</p><p>Pink tones say affection. We hand-arrange each one at Aussie Blooms so it looks the way you pictured it, ready for the bedside table. Stems can vary with the season, while the pink and light pink palette stays.</p> | S25: ok | T25: The jar holds: 4 pink roses, 2 light pink gerberas, 2 white carnations and 1 red gerbera. Gentle, easy on the eye, and ready for any table you give it. | U25: <p>The jar holds: 4 pink roses, 2 light pink gerberas, 2 white carnations and 1 red gerbera. Gentle, easy on the eye, and ready for any table you give it.</p> | V25: ok | W25: Sunny Side | X25: Sunny Side nestles 4 pink roses, 2 light pink gerberas, 2 white carnations and 1 red gerbera into a relaxed mason jar. Happy on a sunny windowsill. Made for a birthday, a thank-you or a just-because moment. | Y25: <p>Sunny Side nestles 4 pink roses, 2 light pink gerberas, 2 white carnations and 1 red gerbera into a relaxed mason jar. Happy on a sunny windowsill. Made for a birthday, a thank-you or a just-because moment.</p> | Z25: ok | AA25: 244 | AB25: 149.91 | AC25: 2 | AD25: 1.7176233e-05 | AE25: 4.328008e-05 | AF25: 53
A26: MJ100-05 | B26: Gerbera Daisies in Mason Jar | C26: Mason Jar | D26: READY TO REVIEW | E26: Make their birthday unforgettable with Gerbera Daisies in Mason Jar. Make their birthday unforgettable with a beautiful arrangement. | F26: Shopify (28 Sep) | G26: 2 × Gerbera Daisies Yellow; 2 × Gerbera Daisies Orange; 2 × Gerbera Daisies Red; 1 × Ruscus Israeli; 1 × Mason Jar | H26: 2 × Gerbera Daisies Yellow; 2 × Gerbera Daisies Orange; 2 × Gerbera Daisies Red; 1 × Ruscus Israeli; 1 × Mason Jar | I26: 2 × Gerbera Daisies Yellow; 2 × Gerbera Daisies Orange; 2 × Gerbera Daisies Red; 1 × Ruscus Israeli; 1 × Mason Jar | J26: 2 × Gerbera Daisies Red; 1 × Mason Jar; 1 × Ruscus Israeli; 2 × Gerbera Daisies Orange; 2 × Gerbera Daisies Yellow | K26: Y | M26: A mason jar arrangement of 2 orange gerberas, 2 red gerberas and 2 yellow gerberas. A thoughtful choice for a birthday, a thank-you or a just-because moment, and the mason jar stays useful long after. | N26: =LEN(TRIM(SUBSTITUTE(M26,CHAR(10)," ")))-LEN(SUBSTITUTE(TRIM(SUBSTITUTE(M26,CHAR(10)," "))," ",""))+1 | O26: <p>A mason jar arrangement of 2 orange gerberas, 2 red gerberas and 2 yellow gerberas. A thoughtful choice for a birthday, a thank-you or a just-because moment, and the mason jar stays useful long after.</p> | P26: ok | Q26: Gerbera Daisies in Mason Jar brings together 2 orange gerberas, 2 red gerberas and 2 yellow gerberas, presented in a mason jar you can keep. It suits a birthday, a thank-you or a just-because moment. Orange tones say warmth and energy. We hand-arrange each one at Aussie Blooms so it looks the way you pictured it, ready for the bedside table. Stems can vary with the season, while the orange and red palette stays. | R26: <p>Gerbera Daisies in Mason Jar brings together 2 orange gerberas, 2 red gerberas and 2 yellow gerberas, presented in a mason jar you can keep. It suits a birthday, a thank-you or a just-because moment.</p><p>Orange tones say warmth and energy. We hand-arrange each one at Aussie Blooms so it looks the way you pictured it, ready for the bedside table. Stems can vary with the season, while the orange and red palette stays.</p> | S26: ok | T26: The jar holds: 2 orange gerberas, 2 red gerberas and 2 yellow gerberas. Enough colour to turn an ordinary bench into the best spot in the house. | U26: <p>The jar holds: 2 orange gerberas, 2 red gerberas and 2 yellow gerberas. Enough colour to turn an ordinary bench into the best spot in the house.</p> | V26: ok | W26: 30 Peruvian Lilies | X26: 30 Peruvian Lilies nestles 2 orange gerberas, 2 red gerberas and 2 yellow gerberas into a relaxed mason jar. Happy on a sunny windowsill. Made for a birthday, a thank-you or a just-because moment. A little wild, a little imperfect, the way a jar should be. | Y26: <p>30 Peruvian Lilies nestles 2 orange gerberas, 2 red gerberas and 2 yellow gerberas into a relaxed mason jar. Happy on a sunny windowsill. Made for a birthday, a thank-you or a just-because moment. A little wild, a little imperfect, the way a jar should be.</p> | Z26: ok | AA26: 230 | AB26: 741.99 | AC26: 16 | AD26: 8.5014961e-05 | AE26: 0.00021421777 | AF26: 52
A27: MJ100-06 | B27: Assorted Roses In Mason Jar | C27: Mason Jar | D27: READY TO REVIEW | F27: none | G27: 6 × Roses Assorted; 1 × Baby's Breath; 1 × Ruscus Israeli; 1 × Mason Jar | H27: 6 × Roses Assorted; 1 × Baby's Breath; 1 × Ruscus Israeli; 1 × Mason Jar | I27: 6 × Roses Assorted; 1 × Baby's Breath; 1 × Ruscus Israeli; 1 × Mason Jar | J27: 1 × Ruscus Israeli; 1 × Mason Jar; 1 × Baby's Breath; 6 × Roses Assorted | K27: Y | M27: A hand-arranged mason jar bouquet of 6 assorted-colour roses. A warm gift for a birthday, a thank-you or a just-because moment, with a mason jar to keep once the flowers are gone. | N27: =LEN(TRIM(SUBSTITUTE(M27,CHAR(10)," ")))-LEN(SUBSTITUTE(TRIM(SUBSTITUTE(M27,CHAR(10)," "))," ",""))+1 | O27: <p>A hand-arranged mason jar bouquet of 6 assorted-colour roses. A warm gift for a birthday, a thank-you or a just-because moment, with a mason jar to keep once the flowers are gone.</p> | P27: ok | Q27: Assorted Roses In Mason Jar brings together 6 assorted-colour roses, presented in a mason jar you can keep. It suits a birthday, a thank-you or a just-because moment. Mixed colours say thoughtfulness. We hand-arrange each one at Aussie Blooms so it looks the way you pictured it, ready for a summer table. Stems can vary with the season, while the colourful palette stays. | R27: <p>Assorted Roses In Mason Jar brings together 6 assorted-colour roses, presented in a mason jar you can keep. It suits a birthday, a thank-you or a just-because moment.</p><p>Mixed colours say thoughtfulness. We hand-arrange each one at Aussie Blooms so it looks the way you pictured it, ready for a summer table. Stems can vary with the season, while the colourful palette stays.</p> | S27: ok | T27: In the jar: 6 assorted-colour roses. Hand it over and watch the day get a little better. | U27: <p>In the jar: 6 assorted-colour roses. Hand it over and watch the day get a little better.</p> | V27: ok | W27: Something Blue | X27: Something Blue tucks 6 assorted-colour roses into a relaxed mason jar. Lovely on a bedside table, or anywhere it can be seen. A good fit for a birthday, a thank-you or a just-because moment. A little wild, a little imperfect, the way a jar should be. | Y27: <p>Something Blue tucks 6 assorted-colour roses into a relaxed mason jar. Lovely on a bedside table, or anywhere it can be seen. A good fit for a birthday, a thank-you or a just-because moment. A little wild, a little imperfect, the way a jar should be.</p> | Z27: ok | AA27: 150 | AB27: 6301.98 | AC27: 141 | AD27: 0.00072206207 | AE27: 0.0018194272 | AF27: 41
A28: MJ100-07 | B28: Thirty Blooms Of Alstroemeria In Mason Jar | C28: Mason Jar | D28: READY - NOTIFY JARROD | F28: none | G28: 1 × Mason Jar; 11 × Alstroemeria assorted | H28: 1 × Mason Jar; 11 × Alstroemeria assorted | I28: 1 × Mason Jar; 11 × Alstroemeria assorted; 2 × Ruscus Israeli | J28: 1 × Mason Jar; 11 × Alstroemeria assorted | K28: Y | M28: A hand-arranged mason jar bouquet of 11 assorted-colour alstroemeria. A thoughtful choice for a birthday, a thank-you or a just-because moment, with a mason jar to keep once the flowers are gone. | N28: =LEN(TRIM(SUBSTITUTE(M28,CHAR(10)," ")))-LEN(SUBSTITUTE(TRIM(SUBSTITUTE(M28,CHAR(10)," "))," ",""))+1 | O28: <p>A hand-arranged mason jar bouquet of 11 assorted-colour alstroemeria. A thoughtful choice for a birthday, a thank-you or a just-because moment, with a mason jar to keep once the flowers are gone.</p> | P28: ok | Q28: Thirty Blooms Of Alstroemeria In Mason Jar brings together 11 assorted-colour alstroemeria, presented in a mason jar you can keep. It suits a birthday, a thank-you or a just-because moment. Mixed colours say thoughtfulness. We hand-arrange each one at Aussie Blooms so it looks the way you pictured it, ready for a summer table. Stems can vary with the season, while the colourful palette stays. | R28: <p>Thirty Blooms Of Alstroemeria In Mason Jar brings together 11 assorted-colour alstroemeria, presented in a mason jar you can keep. It suits a birthday, a thank-you or a just-because moment.</p><p>Mixed colours say thoughtfulness. We hand-arrange each one at Aussie Blooms so it looks the way you pictured it, ready for a summer table. Stems can vary with the season, while the colourful palette stays.</p> | S28: ok | T28: The jar holds: 11 assorted-colour alstroemeria. A simple good turn for a birthday, a thank-you or no reason at all. | U28: <p>The jar holds: 11 assorted-colour alstroemeria. A simple good turn for a birthday, a thank-you or no reason at all.</p> | V28: ok | W28: Clean Whites | X28: Clean Whites tucks 11 assorted-colour alstroemeria into a relaxed mason jar. Lovely on a bedside table, or anywhere it can be seen. A good fit for a birthday, a thank-you or a just-because moment. | Y28: <p>Clean Whites tucks 11 assorted-colour alstroemeria into a relaxed mason jar. Lovely on a bedside table, or anywhere it can be seen. A good fit for a birthday, a thank-you or a just-because moment.</p> | Z28: ok | AA28: 17 | AB28: 120399.35 | AC28: 2023 | AD28: 0.013794992 | AE28: 0.034760145 | AF28: 8
A29: MJ11-10 | B29: Radiant Roses In A Mason Jar | C29: Mason Jar | D29: READY TO REVIEW | E29: Fourteen radiant roses arranged in a charming mason jar, Radiant Roses In A Mason Jar pairs classic romance with relaxed country charm. It is a warm, heartfelt gift that brightens a home and suits everything from anniversaries to a spontaneous gesture of love. | F29: Shopify (28 Sep) | G29: 7 × Roses Red; 1 × Baby's Breath; 1 × Ruscus Israeli; 1 × Mason Jar | H29: 7 × Roses Red; 1 × Baby's Breath; 1 × Ruscus Israeli; 1 × Mason Jar | I29: 7 × Roses Red; 1 × Baby's Breath; 1 × Ruscus Israeli; 1 × Mason Jar | J29: 1 × Ruscus Israeli; 1 × Mason Jar; 1 × Baby's Breath; 7 × Roses Red | K29: Y | M29: A mason jar arrangement of 7 red roses. A lovely way to mark an anniversary or a thank-you, and a bright moment when the door opens. | N29: =LEN(TRIM(SUBSTITUTE(M29,CHAR(10)," ")))-LEN(SUBSTITUTE(TRIM(SUBSTITUTE(M29,CHAR(10)," "))," ",""))+1 | O29: <p>A mason jar arrangement of 7 red roses. A lovely way to mark an anniversary or a thank-you, and a bright moment when the door opens.</p> | P29: ok | Q29: Radiant Roses In A Mason Jar brings together 7 red roses, presented in a mason jar you can keep. It suits an anniversary or a thank-you. Red tones say love and devotion. We hand-arrange each one at Aussie Blooms so it looks the way you pictured it, ready for the bedside table. Stems can vary with the season, while the red palette stays. | R29: <p>Radiant Roses In A Mason Jar brings together 7 red roses, presented in a mason jar you can keep. It suits an anniversary or a thank-you.</p><p>Red tones say love and devotion. We hand-arrange each one at Aussie Blooms so it looks the way you pictured it, ready for the bedside table. Stems can vary with the season, while the red palette stays.</p> | S29: ok | T29: Inside the jar: 7 red roses. Say it with flowers, and let the flowers do the talking. | U29: <p>Inside the jar: 7 red roses. Say it with flowers, and let the flowers do the talking.</p> | V29: ok | W29: Long Summer | X29: Long Summer nestles 7 red roses into a relaxed mason jar. Happy on a sunny windowsill. Made for an anniversary or a thank-you. A little wild, a little imperfect, the way a jar should be. | Y29: <p>Long Summer nestles 7 red roses into a relaxed mason jar. Happy on a sunny windowsill. Made for an anniversary or a thank-you. A little wild, a little imperfect, the way a jar should be.</p> | Z29: ok | AA29: 108 | AB29: 6769.21 | AC29: 143 | AD29: 0.00077559541 | AE29: 0.0019543186 | AF29: 35
A30: MJ22-10BNZ | B30: Shades Of Pink In Mason Jar | C30: Mason Jar | D30: READY TO REVIEW | F30: none | G30: 3 × Gerbera Daisies Light Pink; 3 × Gerbera Daisies Hot Pink; 2 × Ruscus Israeli; 1 × Mason Jar; 2 × Alstroemeria Pink | H30: 3 × Gerbera Daisies Light Pink; 3 × Gerbera Daisies Hot Pink; 2 × Ruscus Israeli; 1 × Mason Jar; 2 × Alstroemeria Pink | I30: 3 × Gerbera Daisies Light Pink; 3 × Gerbera Daisies Hot Pink; 2 × Ruscus Israeli; 1 × Mason Jar; 2 × Alstroemeria Pink | J30: 2 × Ruscus Israeli; 2 × Alstroemeria Pink; 1 × Mason Jar; 3 × Gerbera Daisies Hot Pink; 3 × Gerbera Daisies Light Pink | K30: Y | M30: A hand-arranged mason jar bouquet of 3 hot pink gerberas, 3 light pink gerberas and 2 pink alstroemeria. A warm gift for a birthday, a thank-you or a just-because moment, with a mason jar to keep once the flowers are gone. | N30: =LEN(TRIM(SUBSTITUTE(M30,CHAR(10)," ")))-LEN(SUBSTITUTE(TRIM(SUBSTITUTE(M30,CHAR(10)," "))," ",""))+1 | O30: <p>A hand-arranged mason jar bouquet of 3 hot pink gerberas, 3 light pink gerberas and 2 pink alstroemeria. A warm gift for a birthday, a thank-you or a just-because moment, with a mason jar to keep once the flowers are gone.</p> | P30: ok | Q30: Shades Of Pink In Mason Jar brings together 3 hot pink gerberas, 3 light pink gerberas and 2 pink alstroemeria, presented in a mason jar you can keep. It suits a birthday, a thank-you or a just-because moment. Hot pink tones say a bold, happy affection. We hand-arrange each one at Aussie Blooms so it looks the way you pictured it, ready for a Sunday lunch. Stems can vary with the season, while the hot pink and light pink palette stays. | R30: <p>Shades Of Pink In Mason Jar brings together 3 hot pink gerberas, 3 light pink gerberas and 2 pink alstroemeria, presented in a mason jar you can keep. It suits a birthday, a thank-you or a just-because moment.</p><p>Hot pink tones say a bold, happy affection. We hand-arrange each one at Aussie Blooms so it looks the way you pictured it, ready for a Sunday lunch. Stems can vary with the season, while the hot pink and light pink palette stays.</p> | S30: ok | T30: Inside the jar: 3 hot pink gerberas, 3 light pink gerberas and 2 pink alstroemeria. Bright on purpose, and hard to walk past without smiling. | U30: <p>Inside the jar: 3 hot pink gerberas, 3 light pink gerberas and 2 pink alstroemeria. Bright on purpose, and hard to walk past without smiling.</p> | V30: ok | W30: Autumn Arvo | X30: Autumn Arvo settles 3 hot pink gerberas, 3 light pink gerberas and 2 pink alstroemeria into a relaxed mason jar. Just right sitting on a bench where everyone can enjoy it. A good fit for a birthday, a thank-you or a just-because moment. A little wild, a little imperfect, the way a jar should be. | Y30: <p>Autumn Arvo settles 3 hot pink gerberas, 3 light pink gerberas and 2 pink alstroemeria into a relaxed mason jar. Just right sitting on a bench where everyone can enjoy it. A good fit for a birthday, a thank-you or a just-because moment. A little wild, a little imperfect, the way a jar should be.</p> | Z30: ok | AA30: 105 | AB30: 7257.71 | AC30: 103 | AD30: 0.00083156614 | AE30: 0.0020953517 | AF30: 34
A31: MJ11-30BNZ | B31: Sweetheart Roses In Mason Jar | C31: Mason Jar | D31: READY TO REVIEW | F31: none | G31: 6 × Roses Red; 2 × Limonium White; 2 × Ruscus Israeli; 1 × Mason Jar | H31: 6 × Roses Red; 2 × Limonium White; 2 × Ruscus Israeli; 1 × Mason Jar | I31: 6 × Roses Red; 2 × Limonium White; 2 × Ruscus Israeli; 1 × Mason Jar | J31: 2 × Ruscus Israeli; 1 × Mason Jar; 2 × Limonium White; 6 × Roses Red | K31: Y | M31: A mason jar arrangement of 6 red roses. A lovely way to mark an anniversary or a thank-you, and the mason jar stays useful long after. | N31: =LEN(TRIM(SUBSTITUTE(M31,CHAR(10)," ")))-LEN(SUBSTITUTE(TRIM(SUBSTITUTE(M31,CHAR(10)," "))," ",""))+1 | O31: <p>A mason jar arrangement of 6 red roses. A lovely way to mark an anniversary or a thank-you, and the mason jar stays useful long after.</p> | P31: ok | Q31: Sweetheart Roses In Mason Jar brings together 6 red roses, presented in a mason jar you can keep. It suits an anniversary or a thank-you. Red tones say love and devotion. We hand-arrange each one at Aussie Blooms so it looks the way you pictured it, ready for the kitchen bench. Stems can vary with the season, while the red palette stays. | R31: <p>Sweetheart Roses In Mason Jar brings together 6 red roses, presented in a mason jar you can keep. It suits an anniversary or a thank-you.</p><p>Red tones say love and devotion. We hand-arrange each one at Aussie Blooms so it looks the way you pictured it, ready for the kitchen bench. Stems can vary with the season, while the red palette stays.</p> | S31: ok | T31: In the jar: 6 red roses. Some things need no speech. Put these on the table and the message is delivered. | U31: <p>In the jar: 6 red roses. Some things need no speech. Put these on the table and the message is delivered.</p> | V31: delivery promise | W31: Mixed Rose Garden | X31: Mixed Rose Garden gathers 6 red roses into a relaxed mason jar. Right at home on a kitchen bench next to the morning cuppa. Made for an anniversary or a thank-you. A little wild, a little imperfect, the way a jar should be. | Y31: <p>Mixed Rose Garden gathers 6 red roses into a relaxed mason jar. Right at home on a kitchen bench next to the morning cuppa. Made for an anniversary or a thank-you. A little wild, a little imperfect, the way a jar should be.</p> | Z31: ok | AA31: 165 | AB31: 5147.89 | AC31: 81 | AD31: 0.0005898296 | AE31: 0.0014862323 | AF31: 47
A32: DCMJ-02 | B32: Designer Collection Mason Jar II | C32: Mason Jar | D32: READY TO REVIEW | F32: none | G32: 9 × Designer Collection stems; 2 × Ruscus Israeli; 1 × Greeting Card; 1 × Mason Jar | H32: 9 × Designer Collection stems; 2 × Ruscus Israeli; 1 × Greeting Card; 1 × Mason Jar | I32: 9 × Designer Collection stems; 2 × Ruscus Israeli; 1 × Greeting Card; 1 × Mason Jar | J32: 1 × Greeting Card; 1 × Mason Jar; 2 × Ruscus Israeli; 9 × Designer Collection stems | K32: Y | M32: A hand-arranged bouquet of 9 florist's choice stems, presented in a mason jar. Flowers change with the season, so the picture is illustrative and shows the style and colour, not the exact flowers you will receive. | N32: =LEN(TRIM(SUBSTITUTE(M32,CHAR(10)," ")))-LEN(SUBSTITUTE(TRIM(SUBSTITUTE(M32,CHAR(10)," "))," ",""))+1 | O32: <p>A hand-arranged bouquet of 9 florist's choice stems, presented in a mason jar. Flowers change with the season, so the picture is illustrative and shows the style and colour, not the exact flowers you will receive.</p> | P32: ok | Q32: Designer Collection Mason Jar II is an arrangement of 9 florist's choice stems, presented in a mason jar. Flowers change with the season, so the picture is illustrative and shows the style and colour, not the exact flowers you will receive. It suits a birthday, a thank-you or a just-because moment, or any day you want to bring a little colour to a summer table. | R32: <p>Designer Collection Mason Jar II is an arrangement of 9 florist's choice stems, presented in a mason jar. Flowers change with the season, so the picture is illustrative and shows the style and colour, not the exact flowers you will receive.</p><p>It suits a birthday, a thank-you or a just-because moment, or any day you want to bring a little colour to a summer table.</p> | S32: ok | T32: In this bunch: 9 florist's choice stems in a mason jar. Flowers change with the season, so the picture is illustrative and shows the style and colour, not the exact flowers you will receive. | U32: <p>In this bunch: 9 florist's choice stems in a mason jar. Flowers change with the season, so the picture is illustrative and shows the style and colour, not the exact flowers you will receive.</p> | V32: ok | W32: 30 Peruvian Lilies | X32: 30 Peruvian Lilies gathers 9 florist's choice stems into a relaxed mason jar. Flowers change with the season, so the picture is illustrative and shows the style and colour, not the exact flowers you will receive. | Y32: <p>30 Peruvian Lilies gathers 9 florist's choice stems into a relaxed mason jar. Flowers change with the season, so the picture is illustrative and shows the style and colour, not the exact flowers you will receive.</p> | Z32: ok | AA32: 60 | AB32: 36649.06 | AC32: 516 | AD32: 0.004199138 | AE32: 0.010580843 | AF32: 21
A33: DCMJ-03 | B33: Designer Collection Mason Jar III | C33: Mason Jar | D33: READY TO REVIEW | F33: none | G33: 8 × Designer Collection stems; 2 × Ruscus Israeli; 1 × Greeting Card; 1 × Mason Jar | H33: 8 × Designer Collection stems; 2 × Ruscus Israeli; 1 × Greeting Card; 1 × Mason Jar | I33: 8 × Designer Collection stems; 2 × Ruscus Israeli; 1 × Greeting Card; 1 × Mason Jar | J33: 1 × Mason Jar; 1 × Greeting Card; 2 × Ruscus Israeli; 8 × Designer Collection stems | K33: Y | M33: Designed by our florists, a bouquet of 8 florist's choice stems, presented in a mason jar. The florist chooses the flowers to suit the season, so the picture is illustrative and shows the style and colour, not the exact stems. | N33: =LEN(TRIM(SUBSTITUTE(M33,CHAR(10)," ")))-LEN(SUBSTITUTE(TRIM(SUBSTITUTE(M33,CHAR(10)," "))," ",""))+1 | O33: <p>Designed by our florists, a bouquet of 8 florist's choice stems, presented in a mason jar. The florist chooses the flowers to suit the season, so the picture is illustrative and shows the style and colour, not the exact stems.</p> | P33: ok | Q33: Designer Collection Mason Jar III is an arrangement of 8 florist's choice stems, presented in a mason jar. The florist chooses the flowers to suit the season, so the picture is illustrative and shows the style and colour, not the exact stems. It suits a birthday, a thank-you or a just-because moment, or any day you want to bring a little colour to a Sunday lunch. | R33: <p>Designer Collection Mason Jar III is an arrangement of 8 florist's choice stems, presented in a mason jar. The florist chooses the flowers to suit the season, so the picture is illustrative and shows the style and colour, not the exact stems.</p><p>It suits a birthday, a thank-you or a just-because moment, or any day you want to bring a little colour to a Sunday lunch.</p> | S33: ok | T33: In this bunch: 8 florist's choice stems in a mason jar. The florist chooses the flowers to suit the season, so the picture is illustrative and shows the style and colour, not the exact stems. | U33: <p>In this bunch: 8 florist's choice stems in a mason jar. The florist chooses the flowers to suit the season, so the picture is illustrative and shows the style and colour, not the exact stems.</p> | V33: ok | W33: Mixed Callas | X33: Mixed Callas gathers 8 florist's choice stems into a relaxed mason jar. The florist chooses the flowers to suit the season, so the picture is illustrative and shows the style and colour, not the exact stems. | Y33: <p>Mixed Callas gathers 8 florist's choice stems into a relaxed mason jar. The florist chooses the flowers to suit the season, so the picture is illustrative and shows the style and colour, not the exact stems.</p> | Z33: ok | AA33: 68 | AB33: 30490.92 | AC33: 382 | AD33: 0.0034935572 | AE33: 0.0088029453 | AF33: 26
A34: DCMJ-04 | B34: Designer Collection Mason Jar IV | C34: Mason Jar | D34: READY TO REVIEW | F34: none | G34: 9 × Designer Collection stems; 2 × Ruscus Israeli; 1 × Greeting Card; 1 × Mason Jar | H34: 9 × Designer Collection stems; 2 × Ruscus Israeli; 1 × Greeting Card; 1 × Mason Jar | I34: 9 × Designer Collection stems; 2 × Ruscus Israeli; 1 × Greeting Card; 1 × Mason Jar | J34: 1 × Mason Jar; 1 × Greeting Card; 2 × Ruscus Israeli; 9 × Designer Collection stems | K34: Y | M34: A florist-designed bouquet with 9 florist's choice stems, presented in a mason jar. Stems vary with the season, so the picture is illustrative and shows the style and colour, not the exact flowers. | N34: =LEN(TRIM(SUBSTITUTE(M34,CHAR(10)," ")))-LEN(SUBSTITUTE(TRIM(SUBSTITUTE(M34,CHAR(10)," "))," ",""))+1 | O34: <p>A florist-designed bouquet with 9 florist's choice stems, presented in a mason jar. Stems vary with the season, so the picture is illustrative and shows the style and colour, not the exact flowers.</p> | P34: ok | Q34: Designer Collection Mason Jar IV is an arrangement of 9 florist's choice stems, presented in a mason jar. Stems vary with the season, so the picture is illustrative and shows the style and colour, not the exact flowers. It suits a birthday, a thank-you or a just-because moment, or any day you want to bring a little colour to a summer table. | R34: <p>Designer Collection Mason Jar IV is an arrangement of 9 florist's choice stems, presented in a mason jar. Stems vary with the season, so the picture is illustrative and shows the style and colour, not the exact flowers.</p><p>It suits a birthday, a thank-you or a just-because moment, or any day you want to bring a little colour to a summer table.</p> | S34: ok | T34: In this bunch: 9 florist's choice stems in a mason jar. Stems vary with the season, so the picture is illustrative and shows the style and colour, not the exact flowers. | U34: <p>In this bunch: 9 florist's choice stems in a mason jar. Stems vary with the season, so the picture is illustrative and shows the style and colour, not the exact flowers.</p> | V34: ok | W34: Sunday Roses | X34: Sunday Roses gathers 9 florist's choice stems into a relaxed mason jar. Stems vary with the season, so the picture is illustrative and shows the style and colour, not the exact flowers. | Y34: <p>Sunday Roses gathers 9 florist's choice stems into a relaxed mason jar. Stems vary with the season, so the picture is illustrative and shows the style and colour, not the exact flowers.</p> | Z34: ok | AA34: 64 | AB34: 33508.58 | AC34: 394 | AD34: 0.0038393118 | AE34: 0.0096741657 | AF34: 24
A35: DCMJ-01 | B35: Designer Collection Mason Jar I | C35: Mason Jar | D35: READY TO REVIEW | F35: none | G35: 9 × Designer Collection stems; 2 × Ruscus Israeli; 1 × Greeting Card; 1 × Mason Jar | H35: 9 × Designer Collection stems; 2 × Ruscus Israeli; 1 × Greeting Card; 1 × Mason Jar | I35: 9 × Designer Collection stems; 2 × Ruscus Israeli; 1 × Greeting Card; 1 × Mason Jar | J35: 1 × Mason Jar; 1 × Greeting Card; 2 × Ruscus Israeli; 9 × Designer Collection stems | K35: Y | M35: Designed by our florists, a bouquet of 9 florist's choice stems, presented in a mason jar. The florist chooses the flowers to suit the season, so the picture is illustrative and shows the style and colour, not the exact stems. | N35: =LEN(TRIM(SUBSTITUTE(M35,CHAR(10)," ")))-LEN(SUBSTITUTE(TRIM(SUBSTITUTE(M35,CHAR(10)," "))," ",""))+1 | O35: <p>Designed by our florists, a bouquet of 9 florist's choice stems, presented in a mason jar. The florist chooses the flowers to suit the season, so the picture is illustrative and shows the style and colour, not the exact stems.</p> | P35: ok | Q35: Designer Collection Mason Jar I is an arrangement of 9 florist's choice stems, presented in a mason jar. Stems vary with the season, so the picture is illustrative and shows the style and colour, not the exact flowers. It suits a birthday, a thank-you or a just-because moment, or any day you want to bring a little colour to a Sunday lunch. | R35: <p>Designer Collection Mason Jar I is an arrangement of 9 florist's choice stems, presented in a mason jar. Stems vary with the season, so the picture is illustrative and shows the style and colour, not the exact flowers.</p><p>It suits a birthday, a thank-you or a just-because moment, or any day you want to bring a little colour to a Sunday lunch.</p> | S35: ok | T35: The bunch holds: 9 florist's choice stems in a mason jar. The florist chooses the flowers to suit the season, so the picture is illustrative and shows the style and colour, not the exact stems. | U35: <p>The bunch holds: 9 florist's choice stems in a mason jar. The florist chooses the flowers to suit the season, so the picture is illustrative and shows the style and colour, not the exact stems.</p> | V35: ok | W35: All the Pinks | X35: All the Pinks gathers 9 florist's choice stems into a relaxed mason jar. Stems vary with the season, so the picture is illustrative and shows the style and colour, not the exact flowers. | Y35: <p>All the Pinks gathers 9 florist's choice stems into a relaxed mason jar. Stems vary with the season, so the picture is illustrative and shows the style and colour, not the exact flowers.</p> | Z35: ok | AA35: 27 | AB35: 80994.01 | AC35: 1370 | AD35: 0.0092800475 | AE35: 0.023383544 | AF35: 14
A36: DCMJ-01A | B36: Designer Collection Mason Jar I | C36: Mason Jar | D36: READY TO REVIEW | E36: A designer arrangement of seasonal blooms presented in a charming mason jar, thoughtfully styled for effortless elegance. A versatile and graceful gift to celebrate an anniversary, mark a birthday, or send warm congratulations. | F36: Shopify (28 Sep) | G36: 9 × Designer Collection stems; 2 × Ruscus Israeli; 1 × Greeting Card; 1 × Mason Jar | H36: 9 × Designer Collection stems; 2 × Ruscus Israeli; 1 × Greeting Card; 1 × Mason Jar | I36: 9 × Designer Collection stems; 2 × Ruscus Israeli; 1 × Greeting Card; 1 × Mason Jar | J36: 1 × Mason Jar; 1 × Greeting Card; 2 × Ruscus Israeli; 9 × Designer Collection stems | K36: Y | M36: A hand-arranged bouquet of 9 florist's choice stems, presented in a mason jar. Flowers change with the season, so the picture is illustrative and shows the style and colour, not the exact flowers you will receive. | N36: =LEN(TRIM(SUBSTITUTE(M36,CHAR(10)," ")))-LEN(SUBSTITUTE(TRIM(SUBSTITUTE(M36,CHAR(10)," "))," ",""))+1 | O36: <p>A hand-arranged bouquet of 9 florist's choice stems, presented in a mason jar. Flowers change with the season, so the picture is illustrative and shows the style and colour, not the exact flowers you will receive.</p> | P36: ok | Q36: Designer Collection Mason Jar I is an arrangement of 9 florist's choice stems, presented in a mason jar. Stems vary with the season, so the picture is illustrative and shows the style and colour, not the exact flowers. It suits a birthday, a thank-you or a just-because moment, or any day you want to bring a little colour to a summer table. | R36: <p>Designer Collection Mason Jar I is an arrangement of 9 florist's choice stems, presented in a mason jar. Stems vary with the season, so the picture is illustrative and shows the style and colour, not the exact flowers.</p><p>It suits a birthday, a thank-you or a just-because moment, or any day you want to bring a little colour to a summer table.</p> | S36: ok | T36: The bunch holds: 9 florist's choice stems in a mason jar. Flowers change with the season, so the picture is illustrative and shows the style and colour, not the exact flowers you will receive. | U36: <p>The bunch holds: 9 florist's choice stems in a mason jar. Flowers change with the season, so the picture is illustrative and shows the style and colour, not the exact flowers you will receive.</p> | V36: ok | W36: Snap Happy | X36: Snap Happy gathers 9 florist's choice stems into a relaxed mason jar. Stems vary with the season, so the picture is illustrative and shows the style and colour, not the exact flowers. | Y36: <p>Snap Happy gathers 9 florist's choice stems into a relaxed mason jar. Stems vary with the season, so the picture is illustrative and shows the style and colour, not the exact flowers.</p> | Z36: ok | AA36: 27 | AB36: 74369.66 | AC36: 1276 | AD36: 0.0085210496 | AE36: 0.021471047 | AF36: 14
A37: DCMJ-02A | B37: Designer Collection Mason Jar II | C37: Mason Jar | D37: READY TO REVIEW | E37: Designer Collection Mason Jar II is a relaxed flower gift that arrives with a ready-to-display feel. Send it for birthdays, thanks, get-well wishes, or a friendly note that should feel easy and warm. Seasonal florist-choice blooms give each arrangement a fresh look. The mason jar presentation makes the gift simple to place and enjoy. Good for homes, desks, kitchens, and casual celebration sending. Choose add-ons and delivery options during checkout. | F37: Shopify (28 Sep) | G37: 9 × Designer Collection stems; 2 × Ruscus Israeli; 1 × Greeting Card; 1 × Mason Jar | H37: 9 × Designer Collection stems; 2 × Ruscus Israeli; 1 × Greeting Card; 1 × Mason Jar | I37: 9 × Designer Collection stems; 2 × Ruscus Israeli; 1 × Greeting Card; 1 × Mason Jar | J37: 1 × Mason Jar; 1 × Greeting Card; 2 × Ruscus Israeli; 9 × Designer Collection stems | K37: Y | M37: Designed by our florists, a bouquet of 9 florist's choice stems, presented in a mason jar. The florist chooses the flowers to suit the season, so the picture is illustrative and shows the style and colour, not the exact stems. | N37: =LEN(TRIM(SUBSTITUTE(M37,CHAR(10)," ")))-LEN(SUBSTITUTE(TRIM(SUBSTITUTE(M37,CHAR(10)," "))," ",""))+1 | O37: <p>Designed by our florists, a bouquet of 9 florist's choice stems, presented in a mason jar. The florist chooses the flowers to suit the season, so the picture is illustrative and shows the style and colour, not the exact stems.</p> | P37: ok | Q37: Designer Collection Mason Jar II is an arrangement of 9 florist's choice stems, presented in a mason jar. The florist chooses the flowers to suit the season, so the picture is illustrative and shows the style and colour, not the exact stems. It suits a birthday, a thank-you or a just-because moment, or any day you want to bring a little colour to the kitchen bench. | R37: <p>Designer Collection Mason Jar II is an arrangement of 9 florist's choice stems, presented in a mason jar. The florist chooses the flowers to suit the season, so the picture is illustrative and shows the style and colour, not the exact stems.</p><p>It suits a birthday, a thank-you or a just-because moment, or any day you want to bring a little colour to the kitchen bench.</p> | S37: ok | T37: The bunch holds: 9 florist's choice stems in a mason jar. Stems vary with the season, so the picture is illustrative and shows the style and colour, not the exact flowers. | U37: <p>The bunch holds: 9 florist's choice stems in a mason jar. Stems vary with the season, so the picture is illustrative and shows the style and colour, not the exact flowers.</p> | V37: ok | W37: Garden Romance | X37: Garden Romance gathers 9 florist's choice stems into a relaxed mason jar. The florist chooses the flowers to suit the season, so the picture is illustrative and shows the style and colour, not the exact stems. | Y37: <p>Garden Romance gathers 9 florist's choice stems into a relaxed mason jar. The florist chooses the flowers to suit the season, so the picture is illustrative and shows the style and colour, not the exact stems.</p> | Z37: ok | AA37: 60 | AB37: 36649.06 | AC37: 516 | AD37: 0.004199138 | AE37: 0.010580843 | AF37: 21
A38: DCMJ-03A | B38: Designer Collection Mason Jar III | C38: Mason Jar | D38: READY TO REVIEW | E38: An artfully styled designer arrangement of fresh seasonal blooms gathered in a charming mason jar, blending beauty with relaxed appeal. Perfect for marking a birthday, offering congratulations, or brightening a loved one's recovery. | F38: Shopify (28 Sep) | G38: 10 × Designer Collection stems; 3 × Ruscus Israeli; 1 × Greeting Card; 1 × Mason Jar | H38: 10 × Designer Collection stems; 3 × Ruscus Israeli; 1 × Greeting Card; 1 × Mason Jar | I38: 10 × Designer Collection stems; 3 × Ruscus Israeli; 1 × Greeting Card; 1 × Mason Jar | J38: 1 × Mason Jar; 1 × Greeting Card; 3 × Ruscus Israeli; 10 × Designer Collection stems | K38: Y | M38: Designed by our florists, a bouquet of 10 florist's choice stems, presented in a mason jar. The florist chooses the flowers to suit the season, so the picture is illustrative and shows the style and colour, not the exact stems. | N38: =LEN(TRIM(SUBSTITUTE(M38,CHAR(10)," ")))-LEN(SUBSTITUTE(TRIM(SUBSTITUTE(M38,CHAR(10)," "))," ",""))+1 | O38: <p>Designed by our florists, a bouquet of 10 florist's choice stems, presented in a mason jar. The florist chooses the flowers to suit the season, so the picture is illustrative and shows the style and colour, not the exact stems.</p> | P38: ok | Q38: Designer Collection Mason Jar III is an arrangement of 10 florist's choice stems, presented in a mason jar. The florist chooses the flowers to suit the season, so the picture is illustrative and shows the style and colour, not the exact stems. It suits a birthday, a thank-you or a just-because moment, or any day you want to bring a little colour to the kitchen bench. | R38: <p>Designer Collection Mason Jar III is an arrangement of 10 florist's choice stems, presented in a mason jar. The florist chooses the flowers to suit the season, so the picture is illustrative and shows the style and colour, not the exact stems.</p><p>It suits a birthday, a thank-you or a just-because moment, or any day you want to bring a little colour to the kitchen bench.</p> | S38: ok | T38: The bunch holds: 10 florist's choice stems in a mason jar. The florist chooses the flowers to suit the season, so the picture is illustrative and shows the style and colour, not the exact stems. | U38: <p>The bunch holds: 10 florist's choice stems in a mason jar. The florist chooses the flowers to suit the season, so the picture is illustrative and shows the style and colour, not the exact stems.</p> | V38: ok | W38: Mel's Garden Pick I | X38: Mel's Garden Pick I gathers 10 florist's choice stems into a relaxed mason jar. The florist chooses the flowers to suit the season, so the picture is illustrative and shows the style and colour, not the exact stems. | Y38: <p>Mel's Garden Pick I gathers 10 florist's choice stems into a relaxed mason jar. The florist chooses the flowers to suit the season, so the picture is illustrative and shows the style and colour, not the exact stems.</p> | Z38: ok | AA38: 68 | AB38: 33306.37 | AC38: 430 | AD38: 0.003816143 | AE38: 0.0096157857 | AF38: 26
A39: DCMJ-04A | B39: Designer Collection Mason Jar IV | C39: Mason Jar | D39: READY TO REVIEW | E39: A designer collection of seasonal flowers thoughtfully arranged in a country-style mason jar, radiating natural elegance and warmth. A lovely gesture for a birthday, a note of congratulations, or heartfelt get-well wishes. | F39: Shopify (28 Sep) | G39: 12 × Designer Collection stems; 2 × Ruscus Israeli; 1 × Greeting Card; 1 × Mason Jar | H39: 12 × Designer Collection stems; 2 × Ruscus Israeli; 1 × Greeting Card; 1 × Mason Jar | I39: 12 × Designer Collection stems; 2 × Ruscus Israeli; 1 × Greeting Card; 1 × Mason Jar | J39: 1 × Mason Jar; 1 × Greeting Card; 2 × Ruscus Israeli; 12 × Designer Collection stems | K39: Y | M39: A florist-designed bouquet with 12 florist's choice stems, presented in a mason jar. Stems vary with the season, so the picture is illustrative and shows the style and colour, not the exact flowers. | N39: =LEN(TRIM(SUBSTITUTE(M39,CHAR(10)," ")))-LEN(SUBSTITUTE(TRIM(SUBSTITUTE(M39,CHAR(10)," "))," ",""))+1 | O39: <p>A florist-designed bouquet with 12 florist's choice stems, presented in a mason jar. Stems vary with the season, so the picture is illustrative and shows the style and colour, not the exact flowers.</p> | P39: ok | Q39: Designer Collection Mason Jar IV is an arrangement of 12 florist's choice stems, presented in a mason jar. Stems vary with the season, so the picture is illustrative and shows the style and colour, not the exact flowers. It suits a birthday, a thank-you or a just-because moment, or any day you want to bring a little colour to a Sunday lunch. | R39: <p>Designer Collection Mason Jar IV is an arrangement of 12 florist's choice stems, presented in a mason jar. Stems vary with the season, so the picture is illustrative and shows the style and colour, not the exact flowers.</p><p>It suits a birthday, a thank-you or a just-because moment, or any day you want to bring a little colour to a Sunday lunch.</p> | S39: ok | T39: In this bunch: 12 florist's choice stems in a mason jar. Stems vary with the season, so the picture is illustrative and shows the style and colour, not the exact flowers. | U39: <p>In this bunch: 12 florist's choice stems in a mason jar. Stems vary with the season, so the picture is illustrative and shows the style and colour, not the exact flowers.</p> | V39: ok | W39: Mel's Garden Pick II | X39: Mel's Garden Pick II gathers 12 florist's choice stems into a relaxed mason jar. Stems vary with the season, so the picture is illustrative and shows the style and colour, not the exact flowers. | Y39: <p>Mel's Garden Pick II gathers 12 florist's choice stems into a relaxed mason jar. Stems vary with the season, so the picture is illustrative and shows the style and colour, not the exact flowers.</p> | Z39: ok | AA39: 64 | AB39: 34621.4 | AC39: 408 | AD39: 0.0039668153 | AE39: 0.0099954448 | AF39: 24
A40: AUSTRT-04 | B40: Ruby Rose Trio | C40: Mason Jar | D40: READY TO REVIEW | E40: Seventeen rich ruby roses gathered into an elegant, classic trio. Timelessly romantic yet beautifully understated, the Ruby Rose Trio is a heartfelt way to show someone just how much they mean to you. | F40: Shopify (28 Sep) | G40: 3 × Roses Red; 1 × Baby's Breath; 1 × Ruscus Israeli; 1 × Mason Jar | H40: 3 × Roses Red; 1 × Baby's Breath; 1 × Ruscus Israeli; 1 × Mason Jar | I40: 3 × Roses Red; 1 × Baby's Breath; 1 × Ruscus Israeli; 1 × Mason Jar | J40: 3 × Roses Red; 1 × Mason Jar; 1 × Ruscus Israeli; 1 × Baby's Breath | K40: Y | M40: A hand-arranged mason jar bouquet of 3 red roses. A lovely way to mark a thank-you or an anniversary, with a mason jar to keep once the flowers are gone. | N40: =LEN(TRIM(SUBSTITUTE(M40,CHAR(10)," ")))-LEN(SUBSTITUTE(TRIM(SUBSTITUTE(M40,CHAR(10)," "))," ",""))+1 | O40: <p>A hand-arranged mason jar bouquet of 3 red roses. A lovely way to mark a thank-you or an anniversary, with a mason jar to keep once the flowers are gone.</p> | P40: ok | Q40: Ruby Rose Trio brings together 3 red roses, presented in a mason jar you can keep. It suits an anniversary or a thank-you. Red tones say love and devotion. We hand-arrange each one at Aussie Blooms so it looks the way you pictured it, ready for the bedside table. Stems can vary with the season, while the red palette stays. | R40: <p>Ruby Rose Trio brings together 3 red roses, presented in a mason jar you can keep. It suits an anniversary or a thank-you.</p><p>Red tones say love and devotion. We hand-arrange each one at Aussie Blooms so it looks the way you pictured it, ready for the bedside table. Stems can vary with the season, while the red palette stays.</p> | S40: ok | T40: Inside the jar: 3 red roses. Say it with flowers, and let the flowers do the talking. | U40: <p>Inside the jar: 3 red roses. Say it with flowers, and let the flowers do the talking.</p> | V40: ok | W40: Mel's Garden Pick III | X40: Mel's Garden Pick III nestles 3 red roses into a relaxed mason jar. Happy on a sunny windowsill. Made for an anniversary or a thank-you. A little wild, a little imperfect, the way a jar should be. | Y40: <p>Mel's Garden Pick III nestles 3 red roses into a relaxed mason jar. Happy on a sunny windowsill. Made for an anniversary or a thank-you. A little wild, a little imperfect, the way a jar should be.</p> | Z40: ok | AA40: 169 | AB40: 4353.51 | AC40: 92 | AD40: 0.00049881207 | AE40: 0.0012568895 | AF40: 48
A41: AUSMJ100-11 | B41: Breathtaking Blooms In Mason Jar | C41: Mason Jar | D41: READY TO REVIEW | E41: Breathtaking Blooms In Mason Jar overflows with ruffled carnations, graceful alstroemeria and romantic roses, charmingly arranged in a rustic mason jar. A heartfelt, ready-to-display gift that brings instant warmth to any home. | F41: Shopify (28 Sep) | G41: 2 × Roses Peach; 2 × Carnation Orange; 2 × Ruscus Israeli; 1 × Mason Jar; 3 × Mini Carnations Pink; 3 × Alstroemeria Pink | H41: 2 × Roses Peach; 2 × Carnation Orange; 2 × Ruscus Israeli; 1 × Mason Jar; 3 × Mini Carnations Pink; 3 × Alstroemeria Pink | I41: 2 × Roses Peach; 2 × Carnation Orange; 2 × Ruscus Israeli; 1 × Mason Jar; 3 × Mini Carnations Pink; 3 × Alstroemeria Pink | J41: 2 × Ruscus Israeli; 3 × Alstroemeria Pink; 3 × Mini Carnations Pink; 1 × Mason Jar; 2 × Carnation Orange; 2 × Roses Peach | K41: Y | M41: A hand-arranged mason jar bouquet of 3 pink alstroemeria, 2 orange carnations and 2 peach roses. A lovely way to mark a birthday, a thank-you or a just-because moment, with a mason jar to keep once the flowers are gone. | N41: =LEN(TRIM(SUBSTITUTE(M41,CHAR(10)," ")))-LEN(SUBSTITUTE(TRIM(SUBSTITUTE(M41,CHAR(10)," "))," ",""))+1 | O41: <p>A hand-arranged mason jar bouquet of 3 pink alstroemeria, 2 orange carnations and 2 peach roses. A lovely way to mark a birthday, a thank-you or a just-because moment, with a mason jar to keep once the flowers are gone.</p> | P41: ok | Q41: Breathtaking Blooms In Mason Jar brings together 3 pink alstroemeria, 2 orange carnations and 2 peach roses, presented in a mason jar you can keep. It suits a birthday, a thank-you or a just-because moment. Pink tones say affection. We hand-arrange each one at Aussie Blooms so it looks the way you pictured it, ready for a Sunday lunch. Stems can vary with the season, while the pink and orange palette stays. | R41: <p>Breathtaking Blooms In Mason Jar brings together 3 pink alstroemeria, 2 orange carnations and 2 peach roses, presented in a mason jar you can keep. It suits a birthday, a thank-you or a just-because moment.</p><p>Pink tones say affection. We hand-arrange each one at Aussie Blooms so it looks the way you pictured it, ready for a Sunday lunch. Stems can vary with the season, while the pink and orange palette stays.</p> | S41: ok | T41: In the jar: 3 pink alstroemeria, 2 orange carnations and 2 peach roses. Brings the colour in before anyone has said hello. | U41: <p>In the jar: 3 pink alstroemeria, 2 orange carnations and 2 peach roses. Brings the colour in before anyone has said hello.</p> | V41: ok | W41: Mel's Garden Pick IV | X41: Mel's Garden Pick IV settles 3 pink alstroemeria, 2 orange carnations and 2 peach roses into a relaxed mason jar. Just right sitting on a bench where everyone can enjoy it. A good fit for a birthday, a thank-you or a just-because moment. | Y41: <p>Mel's Garden Pick IV settles 3 pink alstroemeria, 2 orange carnations and 2 peach roses into a relaxed mason jar. Just right sitting on a bench where everyone can enjoy it. A good fit for a birthday, a thank-you or a just-because moment.</p> | Z41: ok | AA41: 4 | AB41: 308392.47 | AC41: 4621 | AD41: 0.035334673 | AE41: 0.089035092 | AF41: 3
A42: AUMJ100-12 | B42: Classic Whites In Mason Jar | C42: Mason Jar | D42: READY TO REVIEW | F42: none | G42: 2 × Roses White; 3 × Gerbera Daisies White; 2 × Ruscus Israeli; 1 × Mason Jar; 2 × Alstroemeria White | H42: 2 × Roses White; 3 × Gerbera Daisies White; 2 × Ruscus Israeli; 1 × Mason Jar; 2 × Alstroemeria White | I42: 2 × Roses White; 3 × Gerbera Daisies White; 2 × Ruscus Israeli; 1 × Mason Jar; 2 × Alstroemeria White | J42: 2 × Ruscus Israeli; 2 × Alstroemeria White; 1 × Mason Jar; 3 × Gerbera Daisies White; 2 × Roses White | K42: Y | M42: A mason jar arrangement of 3 white gerberas, 2 white alstroemeria and 2 white roses. A thoughtful choice for a birthday, a thank-you or a just-because moment, and the mason jar stays useful long after. | N42: =LEN(TRIM(SUBSTITUTE(M42,CHAR(10)," ")))-LEN(SUBSTITUTE(TRIM(SUBSTITUTE(M42,CHAR(10)," "))," ",""))+1 | O42: <p>A mason jar arrangement of 3 white gerberas, 2 white alstroemeria and 2 white roses. A thoughtful choice for a birthday, a thank-you or a just-because moment, and the mason jar stays useful long after.</p> | P42: ok | Q42: Classic Whites In Mason Jar brings together 3 white gerberas, 2 white alstroemeria and 2 white roses, presented in a mason jar you can keep. It suits a birthday, a thank-you or a just-because moment. White tones say calm and a fresh start. We hand-arrange each one at Aussie Blooms so it looks the way you pictured it, ready for the kitchen bench. Stems can vary with the season, while the white palette stays. | R42: <p>Classic Whites In Mason Jar brings together 3 white gerberas, 2 white alstroemeria and 2 white roses, presented in a mason jar you can keep. It suits a birthday, a thank-you or a just-because moment.</p><p>White tones say calm and a fresh start. We hand-arrange each one at Aussie Blooms so it looks the way you pictured it, ready for the kitchen bench. Stems can vary with the season, while the white palette stays.</p> | S42: ok | T42: The jar holds: 3 white gerberas, 2 white alstroemeria and 2 white roses. Gentle, easy on the eye, and ready for any table you give it. | U42: <p>The jar holds: 3 white gerberas, 2 white alstroemeria and 2 white roses. Gentle, easy on the eye, and ready for any table you give it.</p> | V42: ok | W42: Mel's Garden Pick I | X42: Mel's Garden Pick I gathers 3 white gerberas, 2 white alstroemeria and 2 white roses into a relaxed mason jar. Right at home on a kitchen bench next to the morning cuppa. Made for a birthday, a thank-you or a just-because moment. A little wild, a little imperfect, the way a jar should be. | Y42: <p>Mel's Garden Pick I gathers 3 white gerberas, 2 white alstroemeria and 2 white roses into a relaxed mason jar. Right at home on a kitchen bench next to the morning cuppa. Made for a birthday, a thank-you or a just-because moment. A little wild, a little imperfect, the way a jar should be.</p> | Z42: ok | AA42: 218 | AB42: 4216.45 | AC42: 67 | AD42: 0.00048310804 | AE42: 0.001217319 | AF42: 49
A43: AUMJ100-05 | B43: Gerbera Daisies in Mason Jar | C43: Mason Jar | D43: READY - NOTIFY JARROD | F43: none | G43: 3 × Gerbera Daisies Assorted 1 x Ruscus Israeli | H43: 3 × Gerbera Daisies assorted; 1 × Ruscus Israeli | I43: 1 × Ruscus Israeli; 3 × Gerbera Daisies assorted; 1 × Mason Jar | J43: 1 × Ruscus Israeli; 3 × Gerbera Daisies assorted | K43: N | M43: A hand-arranged mason jar bouquet of 3 assorted-colour gerberas. A lovely way to mark a birthday, a thank-you or a just-because moment, with a mason jar to keep once the flowers are gone. | N43: =LEN(TRIM(SUBSTITUTE(M43,CHAR(10)," ")))-LEN(SUBSTITUTE(TRIM(SUBSTITUTE(M43,CHAR(10)," "))," ",""))+1 | O43: <p>A hand-arranged mason jar bouquet of 3 assorted-colour gerberas. A lovely way to mark a birthday, a thank-you or a just-because moment, with a mason jar to keep once the flowers are gone.</p> | P43: ok | Q43: Gerbera Daisies in Mason Jar brings together 3 assorted-colour gerberas, presented in a mason jar you can keep. It suits a birthday, a thank-you or a just-because moment. Mixed colours say thoughtfulness. We hand-arrange each one at Aussie Blooms so it looks the way you pictured it, ready for a summer table. Stems can vary with the season, while the colourful palette stays. | R43: <p>Gerbera Daisies in Mason Jar brings together 3 assorted-colour gerberas, presented in a mason jar you can keep. It suits a birthday, a thank-you or a just-because moment.</p><p>Mixed colours say thoughtfulness. We hand-arrange each one at Aussie Blooms so it looks the way you pictured it, ready for a summer table. Stems can vary with the season, while the colourful palette stays.</p> | S43: ok | T43: In the jar: 3 assorted-colour gerberas. Hand it over and watch the day get a little better. | U43: <p>In the jar: 3 assorted-colour gerberas. Hand it over and watch the day get a little better.</p> | V43: ok | W43: Mel's Garden Pick II | X43: Mel's Garden Pick II tucks 3 assorted-colour gerberas into a relaxed mason jar. Lovely on a bedside table, or anywhere it can be seen. A good fit for a birthday, a thank-you or a just-because moment. | Y43: <p>Mel's Garden Pick II tucks 3 assorted-colour gerberas into a relaxed mason jar. Lovely on a bedside table, or anywhere it can be seen. A good fit for a birthday, a thank-you or a just-because moment.</p> | Z43: ok | AA43: 230 | AB43: 2387.55 | AC43: 40 | AD43: 0.00027355823 | AE43: 0.00068930261 | AF43: 52
A44: AUMJ-NW-001 | B44: Purple Rain Bouquet in Mason Jar | C44: Mason Jar | D44: READY TO REVIEW | E44: Twenty-three roses and twenty-three carnations meet fourteen chrysanthemums in moody purple tones, nestled in a charming mason jar. Rich and romantic, Purple Rain makes a striking gift to surprise someone special or add depth to any room. | F44: Shopify (28 Sep) | G44: 3 × Roses Lavender; 2 × Carnation Lavender; 2 × Chrysanthemum Spray Lavender; 1 × Baby's Breath; 2 × Ruscus Israeli; 1 × Mason Jar; 1 × Mini Carnations Purple | H44: 3 × Roses Lavender; 2 × Carnation Lavender; 2 × Chrysanthemum Spray Lavender; 1 × Baby's Breath; 2 × Ruscus Israeli; 1 × Mason Jar; 1 × Mini Carnations Purple | I44: 3 × Roses Lavender; 2 × Carnation Lavender; 2 × Chrysanthemum Spray Lavender; 1 × Baby's Breath; 2 × Ruscus Israeli; 1 × Mason Jar; 1 × Mini Carnations Purple | J44: 2 × Chrysanthemum Spray Lavender; 1 × Baby's Breath; 2 × Ruscus Israeli; 1 × Mason Jar; 1 × Mini Carnations Purple; 3 × Roses Lavender; 2 × Carnation Lavender | K44: Y | M44: A hand-arranged mason jar bouquet of 3 lavender roses, 2 lavender carnations and 2 lavender spray chrysanthemums. A thoughtful choice for a birthday, a thank-you or a just-because moment, with a mason jar to keep once the flowers are gone. | N44: =LEN(TRIM(SUBSTITUTE(M44,CHAR(10)," ")))-LEN(SUBSTITUTE(TRIM(SUBSTITUTE(M44,CHAR(10)," "))," ",""))+1 | O44: <p>A hand-arranged mason jar bouquet of 3 lavender roses, 2 lavender carnations and 2 lavender spray chrysanthemums. A thoughtful choice for a birthday, a thank-you or a just-because moment, with a mason jar to keep once the flowers are gone.</p> | P44: ok | Q44: Purple Rain Bouquet in Mason Jar brings together 3 lavender roses, 2 lavender carnations and 2 lavender spray chrysanthemums, presented in a mason jar you can keep. It suits a birthday, a thank-you or a just-because moment. Lavender tones say thoughtfulness. We hand-arrange each one at Aussie Blooms so it looks the way you pictured it, ready for a Sunday lunch. Stems can vary with the season, while the lavender and purple palette stays. | R44: <p>Purple Rain Bouquet in Mason Jar brings together 3 lavender roses, 2 lavender carnations and 2 lavender spray chrysanthemums, presented in a mason jar you can keep. It suits a birthday, a thank-you or a just-because moment.</p><p>Lavender tones say thoughtfulness. We hand-arrange each one at Aussie Blooms so it looks the way you pictured it, ready for a Sunday lunch. Stems can vary with the season, while the lavender and purple palette stays.</p> | S44: ok | T44: The jar holds: 3 lavender roses, 2 lavender carnations and 2 lavender spray chrysanthemums. Gentle, easy on the eye, and ready for any table you give it. | U44: <p>The jar holds: 3 lavender roses, 2 lavender carnations and 2 lavender spray chrysanthemums. Gentle, easy on the eye, and ready for any table you give it.</p> | V44: ok | W44: Mel's Garden Pick III | X44: Mel's Garden Pick III settles 3 lavender roses, 2 lavender carnations and 2 lavender spray chrysanthemums into a relaxed mason jar. Just right sitting on a bench where everyone can enjoy it. A good fit for a birthday, a thank-you or a just-because moment. A little wild, a little imperfect, the way a jar should be. | Y44: <p>Mel's Garden Pick III settles 3 lavender roses, 2 lavender carnations and 2 lavender spray chrysanthemums into a relaxed mason jar. Just right sitting on a bench where everyone can enjoy it. A good fit for a birthday, a thank-you or a just-because moment. A little wild, a little imperfect, the way a jar should be.</p> | Z44: ok | AA44: 93 | AB44: 16495.49 | AC44: 166 | AD44: 0.0018900032 | AE44: 0.0047623649 | AF44: 32
A45: AUMJ-NW-002 | B45: Mason Jar of Joy Bouquet | C45: Mason Jar | D45: READY TO REVIEW | E45: Bright chrysanthemums, romantic roses, alstroemeria and soft carnations spill from a rustic mason jar in a burst of pure cheer. The Mason Jar of Joy is a happy companion for anniversaries, birthdays and every congratulations worth celebrating. | F45: Shopify (28 Sep) | G45: 3 × Roses Hot Pink; 1 × Chrysanthemum Spray White; 2 × Chrysanthemum button lavender; 1 × Baby's Breath; 1 × Ruscus Israeli; 1 × Mason Jar; 2 × Alstroemeria Yellow; 1 × Carnations Light Pink | H45: 3 × Roses Hot Pink; 1 × Chrysanthemum Spray White; 2 × Chrysanthemum button lavender; 1 × Baby's Breath; 1 × Ruscus Israeli; 1 × Mason Jar; 2 × Alstroemeria Yellow; 1 × Carnations Light Pink | I45: 3 × Roses Hot Pink; 1 × Chrysanthemum Spray White; 2 × Chrysanthemum button lavender; 1 × Baby's Breath; 1 × Ruscus Israeli; 1 × Mason Jar; 2 × Alstroemeria Yellow; 1 × Carnations Light Pink | J45: 1 × Baby's Breath; 1 × Carnations Light Pink; 2 × Alstroemeria Yellow; 1 × Mason Jar; 1 × Ruscus Israeli; 2 × Chrysanthemum button lavender; 1 × Chrysanthemum Spray White; 3 × Roses Hot Pink | K45: Y | M45: A mason jar arrangement of 3 hot pink roses, 2 yellow alstroemeria, 1 light pink carnation and 1 white spray chrysanthemum. A thoughtful choice for a birthday, a thank-you or a just-because moment, and the mason jar stays useful long after. | N45: =LEN(TRIM(SUBSTITUTE(M45,CHAR(10)," ")))-LEN(SUBSTITUTE(TRIM(SUBSTITUTE(M45,CHAR(10)," "))," ",""))+1 | O45: <p>A mason jar arrangement of 3 hot pink roses, 2 yellow alstroemeria, 1 light pink carnation and 1 white spray chrysanthemum. A thoughtful choice for a birthday, a thank-you or a just-because moment, and the mason jar stays useful long after.</p> | P45: ok | Q45: Mason Jar of Joy Bouquet brings together 3 hot pink roses, 2 yellow alstroemeria, 1 light pink carnation and 1 white spray chrysanthemum, presented in a mason jar you can keep. It suits a birthday, a thank-you or a just-because moment. Hot pink tones say a bold, happy affection. We hand-arrange each one at Aussie Blooms so it looks the way you pictured it, ready for the kitchen bench. Stems can vary with the season, while the hot pink and lavender palette stays. | R45: <p>Mason Jar of Joy Bouquet brings together 3 hot pink roses, 2 yellow alstroemeria, 1 light pink carnation and 1 white spray chrysanthemum, presented in a mason jar you can keep. It suits a birthday, a thank-you or a just-because moment.</p><p>Hot pink tones say a bold, happy affection. We hand-arrange each one at Aussie Blooms so it looks the way you pictured it, ready for the kitchen bench. Stems can vary with the season, while the hot pink and lavender palette stays.</p> | S45: ok | T45: The jar holds: 3 hot pink roses, 2 yellow alstroemeria, 1 light pink carnation and 1 white spray chrysanthemum. Enough colour to turn an ordinary bench into the best spot in the house. | U45: <p>The jar holds: 3 hot pink roses, 2 yellow alstroemeria, 1 light pink carnation and 1 white spray chrysanthemum. Enough colour to turn an ordinary bench into the best spot in the house.</p> | V45: ok | W45: Mel's Garden Pick IV | X45: Mel's Garden Pick IV gathers 3 hot pink roses, 2 yellow alstroemeria, 1 light pink carnation and 1 white spray chrysanthemum into a relaxed mason jar. Right at home on a kitchen bench next to the morning cuppa. Made for a birthday, a thank-you or a just-because moment. | Y45: <p>Mel's Garden Pick IV gathers 3 hot pink roses, 2 yellow alstroemeria, 1 light pink carnation and 1 white spray chrysanthemum into a relaxed mason jar. Right at home on a kitchen bench next to the morning cuppa. Made for a birthday, a thank-you or a just-because moment.</p> | Z45: ok | AA45: 61 | AB45: 35776.41 | AC45: 367 | AD45: 0.0040991524 | AE45: 0.010328903 | AF45: 22
A46: AUMJ-NW-003 | B46: 50 Blooms of Surprise Bud Roses in Mason Jar | C46: Mason Jar | D46: READY TO REVIEW | E46: A delightful gathering of surprise bud roses, beautifully arranged in a charming mason jar that's ready to display the moment it arrives. Sweet, abundant and full of personality, it's a lovely surprise for an anniversary, a birthday, or sharing happy news. | F46: Shopify (28 Sep) | G46: 9 × roses spray assorted; 2 × Baby's Breath; 2 × Ruscus Israeli; 1 × Mason Jar | H46: 9 × roses spray assorted; 2 × Baby's Breath; 2 × Ruscus Israeli; 1 × Mason Jar | I46: 9 × roses spray assorted; 2 × Baby's Breath; 2 × Ruscus Israeli; 1 × Mason Jar | J46: 2 × Ruscus Israeli; 1 × Mason Jar; 2 × Baby's Breath; 9 × roses spray assorted | K46: Y | M46: A hand-arranged mason jar bouquet of 9 assorted-colour spray roses. A thoughtful choice for a birthday, a thank-you or a just-because moment, with a mason jar to keep once the flowers are gone. | N46: =LEN(TRIM(SUBSTITUTE(M46,CHAR(10)," ")))-LEN(SUBSTITUTE(TRIM(SUBSTITUTE(M46,CHAR(10)," "))," ",""))+1 | O46: <p>A hand-arranged mason jar bouquet of 9 assorted-colour spray roses. A thoughtful choice for a birthday, a thank-you or a just-because moment, with a mason jar to keep once the flowers are gone.</p> | P46: ok | Q46: 50 Blooms of Surprise Bud Roses in Mason Jar brings together 9 assorted-colour spray roses, presented in a mason jar you can keep. It suits a birthday, a thank-you or a just-because moment. Mixed colours say thoughtfulness. We hand-arrange each one at Aussie Blooms so it looks the way you pictured it, ready for a Sunday lunch. Stems can vary with the season, while the colourful palette stays. | R46: <p>50 Blooms of Surprise Bud Roses in Mason Jar brings together 9 assorted-colour spray roses, presented in a mason jar you can keep. It suits a birthday, a thank-you or a just-because moment.</p><p>Mixed colours say thoughtfulness. We hand-arrange each one at Aussie Blooms so it looks the way you pictured it, ready for a Sunday lunch. Stems can vary with the season, while the colourful palette stays.</p> | S46: ok | T46: The jar holds: 9 assorted-colour spray roses. A simple good turn for a birthday, a thank-you or no reason at all. | U46: <p>The jar holds: 9 assorted-colour spray roses. A simple good turn for a birthday, a thank-you or no reason at all.</p> | V46: ok | W46: Festive Garden I | X46: Festive Garden I settles 9 assorted-colour spray roses into a relaxed mason jar. Just right sitting on a bench where everyone can enjoy it. A good fit for a birthday, a thank-you or a just-because moment. | Y46: <p>Festive Garden I settles 9 assorted-colour spray roses into a relaxed mason jar. Just right sitting on a bench where everyone can enjoy it. A good fit for a birthday, a thank-you or a just-because moment.</p> | Z46: ok | AA46: 18 | AB46: 129681.72 | AC46: 1529 | AD46: 0.014858538 | AE46: 0.037440032 | AF46: 9
A47: AUMJ-NW-004 | B47: Sending Solace Bouquet in Mason Jar | C47: Mason Jar | D47: READY TO REVIEW | E47: Eighteen roses, fourteen chrysanthemums and nine carnations arranged with quiet grace in a comforting mason jar. Gentle and reassuring, Sending Solace is a thoughtful way to offer comfort and let someone know they're held in your thoughts. | F47: Shopify (28 Sep) | G47: 3 × Roses White; 1 × Roses Spray White; 2 × Carnation White; 2 × Baby's Breath; 2 × Ruscus Israeli; 1 × Mason Jar; 2 × Chrysanthemum Cushion white | H47: 3 × Roses White; 1 × Roses Spray White; 2 × Carnation White; 2 × Baby's Breath; 2 × Ruscus Israeli; 1 × Mason Jar; 2 × Chrysanthemum Cushion white | I47: 3 × Roses White; 1 × Roses Spray White; 2 × Carnation White; 2 × Baby's Breath; 2 × Ruscus Israeli; 1 × Mason Jar; 2 × Chrysanthemum Cushion white | J47: 2 × Baby's Breath; 2 × Chrysanthemum Cushion white; 1 × Mason Jar; 2 × Ruscus Israeli; 2 × Carnation White; 1 × Roses Spray White; 3 × Roses White | K47: Y | M47: A mason jar arrangement of 3 white roses, 2 white carnations, 2 white cushion chrysanthemums and 1 white spray rose. A respectful, heartfelt tribute to express your condolences and share your support with those who are grieving. | N47: =LEN(TRIM(SUBSTITUTE(M47,CHAR(10)," ")))-LEN(SUBSTITUTE(TRIM(SUBSTITUTE(M47,CHAR(10)," "))," ",""))+1 | O47: <p>A mason jar arrangement of 3 white roses, 2 white carnations, 2 white cushion chrysanthemums and 1 white spray rose. A respectful, heartfelt tribute to express your condolences and share your support with those who are grieving.</p> | P47: ok | Q47: Sending Solace Bouquet in Mason Jar brings together 3 white roses, 2 white carnations, 2 white cushion chrysanthemums and 1 white spray rose, presented in a mason jar you can keep. It is made to honour a life and offer comfort to the family. White flowers carry remembrance and calm. We hand-arrange each tribute with care, from the team at Aussie Blooms. | R47: <p>Sending Solace Bouquet in Mason Jar brings together 3 white roses, 2 white carnations, 2 white cushion chrysanthemums and 1 white spray rose, presented in a mason jar you can keep. It is made to honour a life and offer comfort to the family.</p><p>White flowers carry remembrance and calm. We hand-arrange each tribute with care, from the team at Aussie Blooms.</p> | S47: ok | T47: Inside the jar: 3 white roses, 2 white carnations, 2 white cushion chrysanthemums and 1 white spray rose. Simple flowers for a hard day, sent to the service or the family home. | U47: <p>Inside the jar: 3 white roses, 2 white carnations, 2 white cushion chrysanthemums and 1 white spray rose. Simple flowers for a hard day, sent to the service or the family home.</p> | V47: ok | W47: Festive Garden II | X47: Festive Garden II gathers 3 white roses, 2 white carnations, 2 white cushion chrysanthemums and 1 white spray rose into a relaxed mason jar. A quiet gesture of comfort, with the jar to keep afterwards. | Y47: <p>Festive Garden II gathers 3 white roses, 2 white carnations, 2 white cushion chrysanthemums and 1 white spray rose into a relaxed mason jar. A quiet gesture of comfort, with the jar to keep afterwards.</p> | Z47: ok | AA47: 80 | AB47: 23597.6 | AC47: 271 | AD47: 0.0027037415 | AE47: 0.0068127947 | AF47: 29
