Workbook

Sheet Dashboard
A1: Refunds & Returns - Problem Product Report
A2: All stores | 2026-01-01 to 2026-10-10 | ranked by units, revenue impact and refund rate on own sales
B4: Gross sales (export) | D4: Refunds (all lines) | F4: …with NO SKU | H4: Refund rate (units) | J4: SKUs flagged HIGH RATE | L4: Top 25 SKUs = % of SKU refund $
B5: =Settings!$B$20 -> 12880888 | D5: =Settings!$B$21 -> 1045073.5 | F5: =Settings!$B$13 -> 542319.62 | H5: =Settings!$B$3 -> 0.030986151 | J5: =COUNTIF('SKU Data'!$X$2:$X$1780,"HIGH RATE") -> 60 | L5: =SUMIFS('SKU Data'!$H$2:$H$1780,'SKU Data'!$Z$2:$Z$1780,"<=25")/Settings!$B$16 -> 0.44728161
A8: Key findings (at export date)
A9: 1. $542,320 (52%) of all refunded sales carry NO SKU / product - cannot be attributed. Investigate first (see Review List #1).
A10: 2. AUMJ-NW-005 (Native Flowers Bouquet in Mason Jar) is the #1 refund $ and #1 units: $30,439, 335 units, 5.3% vs 3.1% baseline. The AU + AUMJ families = 51% of SKU-attributed refund $ with rates 4.3% / 4.8% (z>12): a family-wide issue, not isolated SKUs.
A11: 3. 60 SKUs have refund rates statistically above baseline; the top 25 SKUs hold 45% of SKU-attributed refund $ - fixing a short list moves the total. Worst high-ticket rate offenders: AU100-545 (11.7%), AU189-01 (11.3%), DC-02B (8.7%), AU501-05 (8.7%).
A12: 4. Best-in-class: MDM (2.1%), DCMJ (2.5%), AUDC (2.4%) are well below baseline - benchmark candidates. MJ family sits at baseline (3.1%) while AUMJ (similar mason-jar concept) is at 4.8%.
A13: 5. Date / month spikes could NOT be tested: the export has no date, store or brand column. Re-export with Month/Day + Store (see Anomalies tab, section A).
A15: Top 10 priority SKUs (full list: Priority SKUs tab)
A16: Rank | B16: SKU | C16: Product | D16: Brand | E16: Qty ordered | F16: Refunded units | G16: Refund rate | H16: Refund $ | I16: % of total revenue | J16: Tier
A17: ='Priority SKUs'!A5 -> 1 | B17: ='Priority SKUs'!C5 -> AUMJ-NW-008 | C17: ='Priority SKUs'!D5 -> Golden Hour Bouquet in Mason Jar | D17: ='Priority SKUs'!E5 -> AUMJ | E17: ='Priority SKUs'!F5 -> 503 | F17: ='Priority SKUs'!G5 -> 40 | G17: ='Priority SKUs'!H5 -> 0.079522863 | H17: ='Priority SKUs'!I5 -> 3723.61 | I17: ='Priority SKUs'!L5 -> 0.00028908023 | J17: ='Priority SKUs'!B5 -> 1 - Fix first
A18: ='Priority SKUs'!A6 -> 2 | B18: ='Priority SKUs'!C6 -> AU0511-17 | C18: ='Priority SKUs'!D6 -> Summer Blooms | D18: ='Priority SKUs'!E6 -> AU | E18: ='Priority SKUs'!F6 -> 1560 | F18: ='Priority SKUs'!G6 -> 97 | G18: ='Priority SKUs'!H6 -> 0.062179487 | H18: ='Priority SKUs'!I6 -> 5315.16 | I18: ='Priority SKUs'!L6 -> 0.00041263926 | J18: ='Priority SKUs'!B6 -> 1 - Fix first
A19: ='Priority SKUs'!A7 -> 3 | B19: ='Priority SKUs'!C7 -> AU501-05 | C19: ='Priority SKUs'!D7 -> Half Dozen Red Roses, Card & Teddy | D19: ='Priority SKUs'!E7 -> AU | E19: ='Priority SKUs'!F7 -> 390 | F19: ='Priority SKUs'!G7 -> 34 | G19: ='Priority SKUs'!H7 -> 0.087179487 | H19: ='Priority SKUs'!I7 -> 2661.08 | I19: ='Priority SKUs'!L7 -> 0.00020659135 | J19: ='Priority SKUs'!B7 -> 1 - Fix first
A20: ='Priority SKUs'!A8 -> 4 | B20: ='Priority SKUs'!C8 -> DC-02B | C20: ='Priority SKUs'!D8 -> Birthday Designer Collection II | D20: ='Priority SKUs'!E8 -> DC | E20: ='Priority SKUs'!F8 -> 322 | F20: ='Priority SKUs'!G8 -> 28 | G20: ='Priority SKUs'!H8 -> 0.086956522 | H20: ='Priority SKUs'!I8 -> 2889.28 | I20: ='Priority SKUs'!L8 -> 0.00022430752 | J20: ='Priority SKUs'!B8 -> 1 - Fix first
A21: ='Priority SKUs'!A9 -> 5 | B21: ='Priority SKUs'!C9 -> AUMJ-NW-019 | C21: ='Priority SKUs'!D9 -> Garden Party Bouquet in Mason Jar | D21: ='Priority SKUs'!E9 -> AUMJ | E21: ='Priority SKUs'!F9 -> 1250 | F21: ='Priority SKUs'!G9 -> 74 | G21: ='Priority SKUs'!H9 -> 0.0592 | H21: ='Priority SKUs'!I9 -> 8226.91 | I21: ='Priority SKUs'!L9 -> 0.00063869122 | J21: ='Priority SKUs'!B9 -> 1 - Fix first
A22: ='Priority SKUs'!A10 -> 6 | B22: ='Priority SKUs'!C10 -> AU100-545 | C22: ='Priority SKUs'!D10 -> Gentle Thoughts Spray | D22: ='Priority SKUs'!E10 -> AU | E22: ='Priority SKUs'!F10 -> 128 | F22: ='Priority SKUs'!G10 -> 15 | G22: ='Priority SKUs'!H10 -> 0.1171875 | H22: ='Priority SKUs'!I10 -> 2729.11 | I22: ='Priority SKUs'!L10 -> 0.00021187282 | J22: ='Priority SKUs'!B10 -> 1 - Fix first
A23: ='Priority SKUs'!A11 -> 7 | B23: ='Priority SKUs'!C11 -> AU11-10 | C23: ='Priority SKUs'!D11 -> Ten Long Stemmed Red Roses | D23: ='Priority SKUs'!E11 -> AU | E23: ='Priority SKUs'!F11 -> 651 | F23: ='Priority SKUs'!G11 -> 41 | G23: ='Priority SKUs'!H11 -> 0.062980031 | H23: ='Priority SKUs'!I11 -> 3718.19 | I23: ='Priority SKUs'!L11 -> 0.00028865945 | J23: ='Priority SKUs'!B11 -> 1 - Fix first
A24: ='Priority SKUs'!A12 -> 8 | B24: ='Priority SKUs'!C12 -> AU200-61 | C24: ='Priority SKUs'!D12 -> Country Roads | D24: ='Priority SKUs'!E12 -> AU | E24: ='Priority SKUs'!F12 -> 360 | F24: ='Priority SKUs'!G12 -> 25 | G24: ='Priority SKUs'!H12 -> 0.069444444 | H24: ='Priority SKUs'!I12 -> 3303.38 | I24: ='Priority SKUs'!L12 -> 0.00025645593 | J24: ='Priority SKUs'!B12 -> 1 - Fix first
A25: ='Priority SKUs'!A13 -> 9 | B25: ='Priority SKUs'!C13 -> AUMJ-NW-005 | C25: ='Priority SKUs'!D13 -> Native Flowers Bouquet in Mason Jar | D25: ='Priority SKUs'!E13 -> AUMJ | E25: ='Priority SKUs'!F13 -> 6304 | F25: ='Priority SKUs'!G13 -> 335 | G25: ='Priority SKUs'!H13 -> 0.053140863 | H25: ='Priority SKUs'!I13 -> 30439.34 | I25: ='Priority SKUs'!L13 -> 0.0023631399 | J25: ='Priority SKUs'!B13 -> 1 - Fix first
A26: ='Priority SKUs'!A14 -> 10 | B26: ='Priority SKUs'!C14 -> AUMJ-NW-015 | C26: ='Priority SKUs'!D14 -> Walking on Sunshine Bouquet in Mason Jar | D26: ='Priority SKUs'!E14 -> AUMJ | E26: ='Priority SKUs'!F14 -> 487 | F26: ='Priority SKUs'!G14 -> 33 | G26: ='Priority SKUs'!H14 -> 0.067761807 | H26: ='Priority SKUs'!I14 -> 2389.19 | I26: ='Priority SKUs'!L14 -> 0.00018548333 | J26: ='Priority SKUs'!B14 -> 1 - Fix first
A28: Charts
A89: Sheet guide: Priority SKUs (ranked list) | Rankings (qty / revenue / rate) | Brands + B-* tabs (brand notes) | Anomalies | Review List | Notes | Settings (editable thresholds) | Brand Map | SKU Data

Sheet Priority SKUs
A1: Priority SKUs - ranked by combined problem score
A2: Score = equal-weight blend of 3 percentile ranks: refunded units, refund $ (= % of total revenue), and refund rate on the SKU's own sales (shrunk so tiny-volume SKUs can't dominate). Weights/thresholds live in Settings. List is live: change Settings and the order/tiers update.
A4: Rank | B4: Tier | C4: SKU | D4: Product | E4: Brand / family | F4: Qty ordered | G4: Refunded units | H4: Refund rate (units) | I4: Refund $ | J4: Refund rate ($ own gross) | K4: % of total refund $ | L4: % of total revenue | M4: Rate vs baseline | N4: z-score | O4: Flag
A5: 1 | B5: =IFERROR(INDEX('SKU Data'!$W$2:$W$1780,MATCH($A5,'SKU Data'!$V$2:$V$1780,0)),"") -> 1 - Fix first | C5: =IFERROR(INDEX('SKU Data'!$A$2:$A$1780,MATCH($A5,'SKU Data'!$V$2:$V$1780,0)),"") -> AUMJ-NW-008 | D5: =IFERROR(INDEX('SKU Data'!$B$2:$B$1780,MATCH($A5,'SKU Data'!$V$2:$V$1780,0)),"") -> Golden Hour Bouquet in Mason Jar | E5: =IFERROR(INDEX('SKU Data'!$D$2:$D$1780,MATCH($A5,'SKU Data'!$V$2:$V$1780,0)),"") -> AUMJ | F5: =IFERROR(INDEX('SKU Data'!$E$2:$E$1780,MATCH($A5,'SKU Data'!$V$2:$V$1780,0)),"") -> 503 | G5: =IFERROR(INDEX('SKU Data'!$F$2:$F$1780,MATCH($A5,'SKU Data'!$V$2:$V$1780,0)),"") -> 40 | H5: =IFERROR(INDEX('SKU Data'!$J$2:$J$1780,MATCH($A5,'SKU Data'!$V$2:$V$1780,0)),"") -> 0.079522863 | I5: =IFERROR(INDEX('SKU Data'!$H$2:$H$1780,MATCH($A5,'SKU Data'!$V$2:$V$1780,0)),"") -> 3723.61 | J5: =IFERROR(INDEX('SKU Data'!$K$2:$K$1780,MATCH($A5,'SKU Data'!$V$2:$V$1780,0)),"") -> 0.075984613 | K5: =IFERROR(INDEX('SKU Data'!$L$2:$L$1780,MATCH($A5,'SKU Data'!$V$2:$V$1780,0)),"") -> 0.0074417331 | L5: =IFERROR(INDEX('SKU Data'!$M$2:$M$1780,MATCH($A5,'SKU Data'!$V$2:$V$1780,0)),"") -> 0.00028908023 | M5: =IFERROR(H5/Settings!$B$3,"") -> 2.5664002 | N5: =IFERROR(INDEX('SKU Data'!$O$2:$O$1780,MATCH($A5,'SKU Data'!$V$2:$V$1780,0)),"") -> 6.28211 | O5: =IFERROR(INDEX('SKU Data'!$X$2:$X$1780,MATCH($A5,'SKU Data'!$V$2:$V$1780,0)),"") -> HIGH RATE
A6: 2 | B6: =IFERROR(INDEX('SKU Data'!$W$2:$W$1780,MATCH($A6,'SKU Data'!$V$2:$V$1780,0)),"") -> 1 - Fix first | C6: =IFERROR(INDEX('SKU Data'!$A$2:$A$1780,MATCH($A6,'SKU Data'!$V$2:$V$1780,0)),"") -> AU0511-17 | D6: =IFERROR(INDEX('SKU Data'!$B$2:$B$1780,MATCH($A6,'SKU Data'!$V$2:$V$1780,0)),"") -> Summer Blooms | E6: =IFERROR(INDEX('SKU Data'!$D$2:$D$1780,MATCH($A6,'SKU Data'!$V$2:$V$1780,0)),"") -> AU | F6: =IFERROR(INDEX('SKU Data'!$E$2:$E$1780,MATCH($A6,'SKU Data'!$V$2:$V$1780,0)),"") -> 1560 | G6: =IFERROR(INDEX('SKU Data'!$F$2:$F$1780,MATCH($A6,'SKU Data'!$V$2:$V$1780,0)),"") -> 97 | H6: =IFERROR(INDEX('SKU Data'!$J$2:$J$1780,MATCH($A6,'SKU Data'!$V$2:$V$1780,0)),"") -> 0.062179487 | I6: =IFERROR(INDEX('SKU Data'!$H$2:$H$1780,MATCH($A6,'SKU Data'!$V$2:$V$1780,0)),"") -> 5315.16 | J6: =IFERROR(INDEX('SKU Data'!$K$2:$K$1780,MATCH($A6,'SKU Data'!$V$2:$V$1780,0)),"") -> 0.060010493 | K6: =IFERROR(INDEX('SKU Data'!$L$2:$L$1780,MATCH($A6,'SKU Data'!$V$2:$V$1780,0)),"") -> 0.010622488 | L6: =IFERROR(INDEX('SKU Data'!$M$2:$M$1780,MATCH($A6,'SKU Data'!$V$2:$V$1780,0)),"") -> 0.00041263926 | M6: =IFERROR(H6/Settings!$B$3,"") -> 2.0066864 | N6: =IFERROR(INDEX('SKU Data'!$O$2:$O$1780,MATCH($A6,'SKU Data'!$V$2:$V$1780,0)),"") -> 7.1100935 | O6: =IFERROR(INDEX('SKU Data'!$X$2:$X$1780,MATCH($A6,'SKU Data'!$V$2:$V$1780,0)),"") -> HIGH RATE
A7: 3 | B7: =IFERROR(INDEX('SKU Data'!$W$2:$W$1780,MATCH($A7,'SKU Data'!$V$2:$V$1780,0)),"") -> 1 - Fix first | C7: =IFERROR(INDEX('SKU Data'!$A$2:$A$1780,MATCH($A7,'SKU Data'!$V$2:$V$1780,0)),"") -> AU501-05 | D7: =IFERROR(INDEX('SKU Data'!$B$2:$B$1780,MATCH($A7,'SKU Data'!$V$2:$V$1780,0)),"") -> Half Dozen Red Roses, Card & Teddy | E7: =IFERROR(INDEX('SKU Data'!$D$2:$D$1780,MATCH($A7,'SKU Data'!$V$2:$V$1780,0)),"") -> AU | F7: =IFERROR(INDEX('SKU Data'!$E$2:$E$1780,MATCH($A7,'SKU Data'!$V$2:$V$1780,0)),"") -> 390 | G7: =IFERROR(INDEX('SKU Data'!$F$2:$F$1780,MATCH($A7,'SKU Data'!$V$2:$V$1780,0)),"") -> 34 | H7: =IFERROR(INDEX('SKU Data'!$J$2:$J$1780,MATCH($A7,'SKU Data'!$V$2:$V$1780,0)),"") -> 0.087179487 | I7: =IFERROR(INDEX('SKU Data'!$H$2:$H$1780,MATCH($A7,'SKU Data'!$V$2:$V$1780,0)),"") -> 2661.08 | J7: =IFERROR(INDEX('SKU Data'!$K$2:$K$1780,MATCH($A7,'SKU Data'!$V$2:$V$1780,0)),"") -> 0.078840928 | K7: =IFERROR(INDEX('SKU Data'!$L$2:$L$1780,MATCH($A7,'SKU Data'!$V$2:$V$1780,0)),"") -> 0.0053182388 | L7: =IFERROR(INDEX('SKU Data'!$M$2:$M$1780,MATCH($A7,'SKU Data'!$V$2:$V$1780,0)),"") -> 0.00020659135 | M7: =IFERROR(H7/Settings!$B$3,"") -> 2.8134984 | N7: =IFERROR(INDEX('SKU Data'!$O$2:$O$1780,MATCH($A7,'SKU Data'!$V$2:$V$1780,0)),"") -> 6.4042505 | O7: =IFERROR(INDEX('SKU Data'!$X$2:$X$1780,MATCH($A7,'SKU Data'!$V$2:$V$1780,0)),"") -> HIGH RATE
A8: 4 | B8: =IFERROR(INDEX('SKU Data'!$W$2:$W$1780,MATCH($A8,'SKU Data'!$V$2:$V$1780,0)),"") -> 1 - Fix first | C8: =IFERROR(INDEX('SKU Data'!$A$2:$A$1780,MATCH($A8,'SKU Data'!$V$2:$V$1780,0)),"") -> DC-02B | D8: =IFERROR(INDEX('SKU Data'!$B$2:$B$1780,MATCH($A8,'SKU Data'!$V$2:$V$1780,0)),"") -> Birthday Designer Collection II | E8: =IFERROR(INDEX('SKU Data'!$D$2:$D$1780,MATCH($A8,'SKU Data'!$V$2:$V$1780,0)),"") -> DC | F8: =IFERROR(INDEX('SKU Data'!$E$2:$E$1780,MATCH($A8,'SKU Data'!$V$2:$V$1780,0)),"") -> 322 | G8: =IFERROR(INDEX('SKU Data'!$F$2:$F$1780,MATCH($A8,'SKU Data'!$V$2:$V$1780,0)),"") -> 28 | H8: =IFERROR(INDEX('SKU Data'!$J$2:$J$1780,MATCH($A8,'SKU Data'!$V$2:$V$1780,0)),"") -> 0.086956522 | I8: =IFERROR(INDEX('SKU Data'!$H$2:$H$1780,MATCH($A8,'SKU Data'!$V$2:$V$1780,0)),"") -> 2889.28 | J8: =IFERROR(INDEX('SKU Data'!$K$2:$K$1780,MATCH($A8,'SKU Data'!$V$2:$V$1780,0)),"") -> 0.083097281 | K8: =IFERROR(INDEX('SKU Data'!$L$2:$L$1780,MATCH($A8,'SKU Data'!$V$2:$V$1780,0)),"") -> 0.0057743025 | L8: =IFERROR(INDEX('SKU Data'!$M$2:$M$1780,MATCH($A8,'SKU Data'!$V$2:$V$1780,0)),"") -> 0.00022430752 | M8: =IFERROR(H8/Settings!$B$3,"") -> 2.8063028 | N8: =IFERROR(INDEX('SKU Data'!$O$2:$O$1780,MATCH($A8,'SKU Data'!$V$2:$V$1780,0)),"") -> 5.7961192 | O8: =IFERROR(INDEX('SKU Data'!$X$2:$X$1780,MATCH($A8,'SKU Data'!$V$2:$V$1780,0)),"") -> HIGH RATE
A9: 5 | B9: =IFERROR(INDEX('SKU Data'!$W$2:$W$1780,MATCH($A9,'SKU Data'!$V$2:$V$1780,0)),"") -> 1 - Fix first | C9: =IFERROR(INDEX('SKU Data'!$A$2:$A$1780,MATCH($A9,'SKU Data'!$V$2:$V$1780,0)),"") -> AUMJ-NW-019 | D9: =IFERROR(INDEX('SKU Data'!$B$2:$B$1780,MATCH($A9,'SKU Data'!$V$2:$V$1780,0)),"") -> Garden Party Bouquet in Mason Jar | E9: =IFERROR(INDEX('SKU Data'!$D$2:$D$1780,MATCH($A9,'SKU Data'!$V$2:$V$1780,0)),"") -> AUMJ | F9: =IFERROR(INDEX('SKU Data'!$E$2:$E$1780,MATCH($A9,'SKU Data'!$V$2:$V$1780,0)),"") -> 1250 | G9: =IFERROR(INDEX('SKU Data'!$F$2:$F$1780,MATCH($A9,'SKU Data'!$V$2:$V$1780,0)),"") -> 74 | H9: =IFERROR(INDEX('SKU Data'!$J$2:$J$1780,MATCH($A9,'SKU Data'!$V$2:$V$1780,0)),"") -> 0.0592 | I9: =IFERROR(INDEX('SKU Data'!$H$2:$H$1780,MATCH($A9,'SKU Data'!$V$2:$V$1780,0)),"") -> 8226.91 | J9: =IFERROR(INDEX('SKU Data'!$K$2:$K$1780,MATCH($A9,'SKU Data'!$V$2:$V$1780,0)),"") -> 0.059694511 | K9: =IFERROR(INDEX('SKU Data'!$L$2:$L$1780,MATCH($A9,'SKU Data'!$V$2:$V$1780,0)),"") -> 0.016441697 | L9: =IFERROR(INDEX('SKU Data'!$M$2:$M$1780,MATCH($A9,'SKU Data'!$V$2:$V$1780,0)),"") -> 0.00063869122 | M9: =IFERROR(H9/Settings!$B$3,"") -> 1.9105309 | N9: =IFERROR(INDEX('SKU Data'!$O$2:$O$1780,MATCH($A9,'SKU Data'!$V$2:$V$1780,0)),"") -> 5.7566329 | O9: =IFERROR(INDEX('SKU Data'!$X$2:$X$1780,MATCH($A9,'SKU Data'!$V$2:$V$1780,0)),"") -> HIGH RATE
A10: 6 | B10: =IFERROR(INDEX('SKU Data'!$W$2:$W$1780,MATCH($A10,'SKU Data'!$V$2:$V$1780,0)),"") -> 1 - Fix first | C10: =IFERROR(INDEX('SKU Data'!$A$2:$A$1780,MATCH($A10,'SKU Data'!$V$2:$V$1780,0)),"") -> AU100-545 | D10: =IFERROR(INDEX('SKU Data'!$B$2:$B$1780,MATCH($A10,'SKU Data'!$V$2:$V$1780,0)),"") -> Gentle Thoughts Spray | E10: =IFERROR(INDEX('SKU Data'!$D$2:$D$1780,MATCH($A10,'SKU Data'!$V$2:$V$1780,0)),"") -> AU | F10: =IFERROR(INDEX('SKU Data'!$E$2:$E$1780,MATCH($A10,'SKU Data'!$V$2:$V$1780,0)),"") -> 128 | G10: =IFERROR(INDEX('SKU Data'!$F$2:$F$1780,MATCH($A10,'SKU Data'!$V$2:$V$1780,0)),"") -> 15 | H10: =IFERROR(INDEX('SKU Data'!$J$2:$J$1780,MATCH($A10,'SKU Data'!$V$2:$V$1780,0)),"") -> 0.1171875 | I10: =IFERROR(INDEX('SKU Data'!$H$2:$H$1780,MATCH($A10,'SKU Data'!$V$2:$V$1780,0)),"") -> 2729.11 | J10: =IFERROR(INDEX('SKU Data'!$K$2:$K$1780,MATCH($A10,'SKU Data'!$V$2:$V$1780,0)),"") -> 0.10651399 | K10: =IFERROR(INDEX('SKU Data'!$L$2:$L$1780,MATCH($A10,'SKU Data'!$V$2:$V$1780,0)),"") -> 0.0054541985 | L10: =IFERROR(INDEX('SKU Data'!$M$2:$M$1780,MATCH($A10,'SKU Data'!$V$2:$V$1780,0)),"") -> 0.00021187282 | M10: =IFERROR(H10/Settings!$B$3,"") -> 3.7819315 | N10: =IFERROR(INDEX('SKU Data'!$O$2:$O$1780,MATCH($A10,'SKU Data'!$V$2:$V$1780,0)),"") -> 5.6282093 | O10: =IFERROR(INDEX('SKU Data'!$X$2:$X$1780,MATCH($A10,'SKU Data'!$V$2:$V$1780,0)),"") -> HIGH RATE
A11: 7 | B11: =IFERROR(INDEX('SKU Data'!$W$2:$W$1780,MATCH($A11,'SKU Data'!$V$2:$V$1780,0)),"") -> 1 - Fix first | C11: =IFERROR(INDEX('SKU Data'!$A$2:$A$1780,MATCH($A11,'SKU Data'!$V$2:$V$1780,0)),"") -> AU11-10 | D11: =IFERROR(INDEX('SKU Data'!$B$2:$B$1780,MATCH($A11,'SKU Data'!$V$2:$V$1780,0)),"") -> Ten Long Stemmed Red Roses | E11: =IFERROR(INDEX('SKU Data'!$D$2:$D$1780,MATCH($A11,'SKU Data'!$V$2:$V$1780,0)),"") -> AU | F11: =IFERROR(INDEX('SKU Data'!$E$2:$E$1780,MATCH($A11,'SKU Data'!$V$2:$V$1780,0)),"") -> 651 | G11: =IFERROR(INDEX('SKU Data'!$F$2:$F$1780,MATCH($A11,'SKU Data'!$V$2:$V$1780,0)),"") -> 41 | H11: =IFERROR(INDEX('SKU Data'!$J$2:$J$1780,MATCH($A11,'SKU Data'!$V$2:$V$1780,0)),"") -> 0.062980031 | I11: =IFERROR(INDEX('SKU Data'!$H$2:$H$1780,MATCH($A11,'SKU Data'!$V$2:$V$1780,0)),"") -> 3718.19 | J11: =IFERROR(INDEX('SKU Data'!$K$2:$K$1780,MATCH($A11,'SKU Data'!$V$2:$V$1780,0)),"") -> 0.059146759 | K11: =IFERROR(INDEX('SKU Data'!$L$2:$L$1780,MATCH($A11,'SKU Data'!$V$2:$V$1780,0)),"") -> 0.007430901 | L11: =IFERROR(INDEX('SKU Data'!$M$2:$M$1780,MATCH($A11,'SKU Data'!$V$2:$V$1780,0)),"") -> 0.00028865945 | M11: =IFERROR(H11/Settings!$B$3,"") -> 2.0325219 | N11: =IFERROR(INDEX('SKU Data'!$O$2:$O$1780,MATCH($A11,'SKU Data'!$V$2:$V$1780,0)),"") -> 4.7109511 | O11: =IFERROR(INDEX('SKU Data'!$X$2:$X$1780,MATCH($A11,'SKU Data'!$V$2:$V$1780,0)),"") -> HIGH RATE
A12: 8 | B12: =IFERROR(INDEX('SKU Data'!$W$2:$W$1780,MATCH($A12,'SKU Data'!$V$2:$V$1780,0)),"") -> 1 - Fix first | C12: =IFERROR(INDEX('SKU Data'!$A$2:$A$1780,MATCH($A12,'SKU Data'!$V$2:$V$1780,0)),"") -> AU200-61 | D12: =IFERROR(INDEX('SKU Data'!$B$2:$B$1780,MATCH($A12,'SKU Data'!$V$2:$V$1780,0)),"") -> Country Roads | E12: =IFERROR(INDEX('SKU Data'!$D$2:$D$1780,MATCH($A12,'SKU Data'!$V$2:$V$1780,0)),"") -> AU | F12: =IFERROR(INDEX('SKU Data'!$E$2:$E$1780,MATCH($A12,'SKU Data'!$V$2:$V$1780,0)),"") -> 360 | G12: =IFERROR(INDEX('SKU Data'!$F$2:$F$1780,MATCH($A12,'SKU Data'!$V$2:$V$1780,0)),"") -> 25 | H12: =IFERROR(INDEX('SKU Data'!$J$2:$J$1780,MATCH($A12,'SKU Data'!$V$2:$V$1780,0)),"") -> 0.069444444 | I12: =IFERROR(INDEX('SKU Data'!$H$2:$H$1780,MATCH($A12,'SKU Data'!$V$2:$V$1780,0)),"") -> 3303.38 | J12: =IFERROR(INDEX('SKU Data'!$K$2:$K$1780,MATCH($A12,'SKU Data'!$V$2:$V$1780,0)),"") -> 0.069155547 | K12: =IFERROR(INDEX('SKU Data'!$L$2:$L$1780,MATCH($A12,'SKU Data'!$V$2:$V$1780,0)),"") -> 0.0066018923 | L12: =IFERROR(INDEX('SKU Data'!$M$2:$M$1780,MATCH($A12,'SKU Data'!$V$2:$V$1780,0)),"") -> 0.00025645593 | M12: =IFERROR(H12/Settings!$B$3,"") -> 2.2411446 | N12: =IFERROR(INDEX('SKU Data'!$O$2:$O$1780,MATCH($A12,'SKU Data'!$V$2:$V$1780,0)),"") -> 4.2110699 | O12: =IFERROR(INDEX('SKU Data'!$X$2:$X$1780,MATCH($A12,'SKU Data'!$V$2:$V$1780,0)),"") -> HIGH RATE
A13: 9 | B13: =IFERROR(INDEX('SKU Data'!$W$2:$W$1780,MATCH($A13,'SKU Data'!$V$2:$V$1780,0)),"") -> 1 - Fix first | C13: =IFERROR(INDEX('SKU Data'!$A$2:$A$1780,MATCH($A13,'SKU Data'!$V$2:$V$1780,0)),"") -> AUMJ-NW-005 | D13: =IFERROR(INDEX('SKU Data'!$B$2:$B$1780,MATCH($A13,'SKU Data'!$V$2:$V$1780,0)),"") -> Native Flowers Bouquet in Mason Jar | E13: =IFERROR(INDEX('SKU Data'!$D$2:$D$1780,MATCH($A13,'SKU Data'!$V$2:$V$1780,0)),"") -> AUMJ | F13: =IFERROR(INDEX('SKU Data'!$E$2:$E$1780,MATCH($A13,'SKU Data'!$V$2:$V$1780,0)),"") -> 6304 | G13: =IFERROR(INDEX('SKU Data'!$F$2:$F$1780,MATCH($A13,'SKU Data'!$V$2:$V$1780,0)),"") -> 335 | H13: =IFERROR(INDEX('SKU Data'!$J$2:$J$1780,MATCH($A13,'SKU Data'!$V$2:$V$1780,0)),"") -> 0.053140863 | I13: =IFERROR(INDEX('SKU Data'!$H$2:$H$1780,MATCH($A13,'SKU Data'!$V$2:$V$1780,0)),"") -> 30439.34 | J13: =IFERROR(INDEX('SKU Data'!$K$2:$K$1780,MATCH($A13,'SKU Data'!$V$2:$V$1780,0)),"") -> 0.051522022 | K13: =IFERROR(INDEX('SKU Data'!$L$2:$L$1780,MATCH($A13,'SKU Data'!$V$2:$V$1780,0)),"") -> 0.060833826 | L13: =IFERROR(INDEX('SKU Data'!$M$2:$M$1780,MATCH($A13,'SKU Data'!$V$2:$V$1780,0)),"") -> 0.0023631399 | M13: =IFERROR(H13/Settings!$B$3,"") -> 1.7149875 | N13: =IFERROR(INDEX('SKU Data'!$O$2:$O$1780,MATCH($A13,'SKU Data'!$V$2:$V$1780,0)),"") -> 10.151387 | O13: =IFERROR(INDEX('SKU Data'!$X$2:$X$1780,MATCH($A13,'SKU Data'!$V$2:$V$1780,0)),"") -> HIGH RATE
A14: 10 | B14: =IFERROR(INDEX('SKU Data'!$W$2:$W$1780,MATCH($A14,'SKU Data'!$V$2:$V$1780,0)),"") -> 1 - Fix first | C14: =IFERROR(INDEX('SKU Data'!$A$2:$A$1780,MATCH($A14,'SKU Data'!$V$2:$V$1780,0)),"") -> AUMJ-NW-015 | D14: =IFERROR(INDEX('SKU Data'!$B$2:$B$1780,MATCH($A14,'SKU Data'!$V$2:$V$1780,0)),"") -> Walking on Sunshine Bouquet in Mason Jar | E14: =IFERROR(INDEX('SKU Data'!$D$2:$D$1780,MATCH($A14,'SKU Data'!$V$2:$V$1780,0)),"") -> AUMJ | F14: =IFERROR(INDEX('SKU Data'!$E$2:$E$1780,MATCH($A14,'SKU Data'!$V$2:$V$1780,0)),"") -> 487 | G14: =IFERROR(INDEX('SKU Data'!$F$2:$F$1780,MATCH($A14,'SKU Data'!$V$2:$V$1780,0)),"") -> 33 | H14: =IFERROR(INDEX('SKU Data'!$J$2:$J$1780,MATCH($A14,'SKU Data'!$V$2:$V$1780,0)),"") -> 0.067761807 | I14: =IFERROR(INDEX('SKU Data'!$H$2:$H$1780,MATCH($A14,'SKU Data'!$V$2:$V$1780,0)),"") -> 2389.19 | J14: =IFERROR(INDEX('SKU Data'!$K$2:$K$1780,MATCH($A14,'SKU Data'!$V$2:$V$1780,0)),"") -> 0.059885392 | K14: =IFERROR(INDEX('SKU Data'!$L$2:$L$1780,MATCH($A14,'SKU Data'!$V$2:$V$1780,0)),"") -> 0.0047748594 | L14: =IFERROR(INDEX('SKU Data'!$M$2:$M$1780,MATCH($A14,'SKU Data'!$V$2:$V$1780,0)),"") -> 0.00018548333 | M14: =IFERROR(H14/Settings!$B$3,"") -> 2.1868417 | N14: =IFERROR(INDEX('SKU Data'!$O$2:$O$1780,MATCH($A14,'SKU Data'!$V$2:$V$1780,0)),"") -> 4.6835601 | O14: =IFERROR(INDEX('SKU Data'!$X$2:$X$1780,MATCH($A14,'SKU Data'!$V$2:$V$1780,0)),"") -> HIGH RATE
A15: 11 | B15: =IFERROR(INDEX('SKU Data'!$W$2:$W$1780,MATCH($A15,'SKU Data'!$V$2:$V$1780,0)),"") -> 1 - Fix first | C15: =IFERROR(INDEX('SKU Data'!$A$2:$A$1780,MATCH($A15,'SKU Data'!$V$2:$V$1780,0)),"") -> AUMJ-NW-007 | D15: =IFERROR(INDEX('SKU Data'!$B$2:$B$1780,MATCH($A15,'SKU Data'!$V$2:$V$1780,0)),"") -> Pick-Me-Up Bouquet in Mason Jar | E15: =IFERROR(INDEX('SKU Data'!$D$2:$D$1780,MATCH($A15,'SKU Data'!$V$2:$V$1780,0)),"") -> AUMJ | F15: =IFERROR(INDEX('SKU Data'!$E$2:$E$1780,MATCH($A15,'SKU Data'!$V$2:$V$1780,0)),"") -> 789 | G15: =IFERROR(INDEX('SKU Data'!$F$2:$F$1780,MATCH($A15,'SKU Data'!$V$2:$V$1780,0)),"") -> 48 | H15: =IFERROR(INDEX('SKU Data'!$J$2:$J$1780,MATCH($A15,'SKU Data'!$V$2:$V$1780,0)),"") -> 0.060836502 | I15: =IFERROR(INDEX('SKU Data'!$H$2:$H$1780,MATCH($A15,'SKU Data'!$V$2:$V$1780,0)),"") -> 3223.36 | J15: =IFERROR(INDEX('SKU Data'!$K$2:$K$1780,MATCH($A15,'SKU Data'!$V$2:$V$1780,0)),"") -> 0.057669221 | K15: =IFERROR(INDEX('SKU Data'!$L$2:$L$1780,MATCH($A15,'SKU Data'!$V$2:$V$1780,0)),"") -> 0.0064419702 | L15: =IFERROR(INDEX('SKU Data'!$M$2:$M$1780,MATCH($A15,'SKU Data'!$V$2:$V$1780,0)),"") -> 0.00025024362 | M15: =IFERROR(H15/Settings!$B$3,"") -> 1.9633449 | N15: =IFERROR(INDEX('SKU Data'!$O$2:$O$1780,MATCH($A15,'SKU Data'!$V$2:$V$1780,0)),"") -> 4.8388163 | O15: =IFERROR(INDEX('SKU Data'!$X$2:$X$1780,MATCH($A15,'SKU Data'!$V$2:$V$1780,0)),"") -> HIGH RATE
A16: 12 | B16: =IFERROR(INDEX('SKU Data'!$W$2:$W$1780,MATCH($A16,'SKU Data'!$V$2:$V$1780,0)),"") | C16: =IFERROR(INDEX('SKU Data'!$A$2:$A$1780,MATCH($A16,'SKU Data'!$V$2:$V$1780,0)),"") | D16: =IFERROR(INDEX('SKU Data'!$B$2:$B$1780,MATCH($A16,'SKU Data'!$V$2:$V$1780,0)),"") | E16: =IFERROR(INDEX('SKU Data'!$D$2:$D$1780,MATCH($A16,'SKU Data'!$V$2:$V$1780,0)),"") | F16: =IFERROR(INDEX('SKU Data'!$E$2:$E$1780,MATCH($A16,'SKU Data'!$V$2:$V$1780,0)),"") | G16: =IFERROR(INDEX('SKU Data'!$F$2:$F$1780,MATCH($A16,'SKU Data'!$V$2:$V$1780,0)),"") | H16: =IFERROR(INDEX('SKU Data'!$J$2:$J$1780,MATCH($A16,'SKU Data'!$V$2:$V$1780,0)),"") | I16: =IFERROR(INDEX('SKU Data'!$H$2:$H$1780,MATCH($A16,'SKU Data'!$V$2:$V$1780,0)),"") | J16: =IFERROR(INDEX('SKU Data'!$K$2:$K$1780,MATCH($A16,'SKU Data'!$V$2:$V$1780,0)),"") | K16: =IFERROR(INDEX('SKU Data'!$L$2:$L$1780,MATCH($A16,'SKU Data'!$V$2:$V$1780,0)),"") | L16: =IFERROR(INDEX('SKU Data'!$M$2:$M$1780,MATCH($A16,'SKU Data'!$V$2:$V$1780,0)),"") | M16: =IFERROR(H16/Settings!$B$3,"") | N16: =IFERROR(INDEX('SKU Data'!$O$2:$O$1780,MATCH($A16,'SKU Data'!$V$2:$V$1780,0)),"") | O16: =IFERROR(INDEX('SKU Data'!$X$2:$X$1780,MATCH($A16,'SKU Data'!$V$2:$V$1780,0)),"")
... A104: 100 | B104: =IFERROR(INDEX('SKU Data'!$W$2:$W$1780,MATCH($A104,'SKU Data'!$V$2:$V$1780,0)),"") -> 2 - Review | C104: =IFERROR(INDEX('SKU Data'!$A$2:$A$1780,MATCH($A104,'SKU Data'!$V$2:$V$1780,0)),"") -> DCS-02 | D104: =IFERROR(INDEX('SKU Data'!$B$2:$B$1780,MATCH($A104,'SKU Data'!$V$2:$V$1780,0)),"") -> Designer Sympathy Collection II | E104: =IFERROR(INDEX('SKU Data'!$D$2:$D$1780,MATCH($A104,'SKU Data'!$V$2:$V$1780,0)),"") -> DCS | F104: =IFERROR(INDEX('SKU Data'!$E$2:$E$1780,MATCH($A104,'SKU Data'!$V$2:$V$1780,0)),"") -> 136 | G104: =IFERROR(INDEX('SKU Data'!$F$2:$F$1780,MATCH($A104,'SKU Data'!$V$2:$V$1780,0)),"") -> 8 | H104: =IFERROR(INDEX('SKU Data'!$J$2:$J$1780,MATCH($A104,'SKU Data'!$V$2:$V$1780,0)),"") -> 0.058823529 | I104: =IFERROR(INDEX('SKU Data'!$H$2:$H$1780,MATCH($A104,'SKU Data'!$V$2:$V$1780,0)),"") -> 798.41 | J104: =IFERROR(INDEX('SKU Data'!$K$2:$K$1780,MATCH($A104,'SKU Data'!$V$2:$V$1780,0)),"") -> 0.049994333 | K104: =IFERROR(INDEX('SKU Data'!$L$2:$L$1780,MATCH($A104,'SKU Data'!$V$2:$V$1780,0)),"") -> 0.0015956435 | L104: =IFERROR(INDEX('SKU Data'!$M$2:$M$1780,MATCH($A104,'SKU Data'!$V$2:$V$1780,0)),"") -> 6.1984082e-05 | M104: =IFERROR(H104/Settings!$B$3,"") -> 1.8983813 | N104: =IFERROR(INDEX('SKU Data'!$O$2:$O$1780,MATCH($A104,'SKU Data'!$V$2:$V$1780,0)),"") -> 1.8734796 | O104: =IFERROR(INDEX('SKU Data'!$X$2:$X$1780,MATCH($A104,'SKU Data'!$V$2:$V$1780,0)),"")

Sheet Rankings
A1: Rankings - the three lenses requested
A2: Top 25 each. Live formulas on SKU Data. Rate ranking only includes SKUs with at least the minimum volume in Settings.
A3: 1) BY QUANTITY - most refunded units
A4: # | B4: SKU | C4: Product | D4: Brand / family | E4: Qty ordered | F4: Refunded units | G4: Refund rate (units) | H4: Refund $ | I4: Refund rate ($ own gross) | J4: % of total revenue | K4: % of SKU-attrib. refund $ | L4: Cumulative % of refunds | M4: Baseline rate
A5: 1 | B5: =IFERROR(INDEX('SKU Data'!$A$2:$A$1780,MATCH($A5,'SKU Data'!$Y$2:$Y$1780,0)),"") -> AUSGF16-115 | C5: =IFERROR(INDEX('SKU Data'!$B$2:$B$1780,MATCH($A5,'SKU Data'!$Y$2:$Y$1780,0)),"") -> Delicate Elegance | D5: =IFERROR(INDEX('SKU Data'!$D$2:$D$1780,MATCH($A5,'SKU Data'!$Y$2:$Y$1780,0)),"") -> AUSGF | E5: =IFERROR(INDEX('SKU Data'!$E$2:$E$1780,MATCH($A5,'SKU Data'!$Y$2:$Y$1780,0)),"") -> 11490 | F5: =IFERROR(INDEX('SKU Data'!$F$2:$F$1780,MATCH($A5,'SKU Data'!$Y$2:$Y$1780,0)),"") -> 419 | G5: =IFERROR(INDEX('SKU Data'!$J$2:$J$1780,MATCH($A5,'SKU Data'!$Y$2:$Y$1780,0)),"") -> 0.036466493 | H5: =IFERROR(INDEX('SKU Data'!$H$2:$H$1780,MATCH($A5,'SKU Data'!$Y$2:$Y$1780,0)),"") -> 25834.89 | I5: =IFERROR(INDEX('SKU Data'!$K$2:$K$1780,MATCH($A5,'SKU Data'!$Y$2:$Y$1780,0)),"") -> 0.035459214 | J5: =IFERROR(INDEX('SKU Data'!$M$2:$M$1780,MATCH($A5,'SKU Data'!$Y$2:$Y$1780,0)),"") -> 0.0020056762 | K5: =IFERROR(INDEX('SKU Data'!$L$2:$L$1780,MATCH($A5,'SKU Data'!$Y$2:$Y$1780,0)),"") -> 0.051631711 | M5: =Settings!$B$3 -> 0.030986151
A6: 2 | B6: =IFERROR(INDEX('SKU Data'!$A$2:$A$1780,MATCH($A6,'SKU Data'!$Y$2:$Y$1780,0)),"") -> AURP05 | C6: =IFERROR(INDEX('SKU Data'!$B$2:$B$1780,MATCH($A6,'SKU Data'!$Y$2:$Y$1780,0)),"") -> Full Size Greeting Card | D6: =IFERROR(INDEX('SKU Data'!$D$2:$D$1780,MATCH($A6,'SKU Data'!$Y$2:$Y$1780,0)),"") -> AURP | E6: =IFERROR(INDEX('SKU Data'!$E$2:$E$1780,MATCH($A6,'SKU Data'!$Y$2:$Y$1780,0)),"") -> 11080 | F6: =IFERROR(INDEX('SKU Data'!$F$2:$F$1780,MATCH($A6,'SKU Data'!$Y$2:$Y$1780,0)),"") -> 410 | G6: =IFERROR(INDEX('SKU Data'!$J$2:$J$1780,MATCH($A6,'SKU Data'!$Y$2:$Y$1780,0)),"") -> 0.03700361 | H6: =IFERROR(INDEX('SKU Data'!$H$2:$H$1780,MATCH($A6,'SKU Data'!$Y$2:$Y$1780,0)),"") -> 1427.63 | I6: =IFERROR(INDEX('SKU Data'!$K$2:$K$1780,MATCH($A6,'SKU Data'!$Y$2:$Y$1780,0)),"") -> 0.03432841 | J6: =IFERROR(INDEX('SKU Data'!$M$2:$M$1780,MATCH($A6,'SKU Data'!$Y$2:$Y$1780,0)),"") -> 0.0001108332 | K6: =IFERROR(INDEX('SKU Data'!$L$2:$L$1780,MATCH($A6,'SKU Data'!$Y$2:$Y$1780,0)),"") -> 0.0028531563 | M6: =Settings!$B$3 -> 0.030986151
A7: 3 | B7: =IFERROR(INDEX('SKU Data'!$A$2:$A$1780,MATCH($A7,'SKU Data'!$Y$2:$Y$1780,0)),"") -> RP19 | C7: =IFERROR(INDEX('SKU Data'!$B$2:$B$1780,MATCH($A7,'SKU Data'!$Y$2:$Y$1780,0)),"") -> Full Size Birthday Card | D7: =IFERROR(INDEX('SKU Data'!$D$2:$D$1780,MATCH($A7,'SKU Data'!$Y$2:$Y$1780,0)),"") -> RP | E7: =IFERROR(INDEX('SKU Data'!$E$2:$E$1780,MATCH($A7,'SKU Data'!$Y$2:$Y$1780,0)),"") -> 6456 | F7: =IFERROR(INDEX('SKU Data'!$F$2:$F$1780,MATCH($A7,'SKU Data'!$Y$2:$Y$1780,0)),"") -> 336 | G7: =IFERROR(INDEX('SKU Data'!$J$2:$J$1780,MATCH($A7,'SKU Data'!$Y$2:$Y$1780,0)),"") -> 0.05204461 | H7: =IFERROR(INDEX('SKU Data'!$H$2:$H$1780,MATCH($A7,'SKU Data'!$Y$2:$Y$1780,0)),"") -> 1172.41 | I7: =IFERROR(INDEX('SKU Data'!$K$2:$K$1780,MATCH($A7,'SKU Data'!$Y$2:$Y$1780,0)),"") -> 0.048685818 | J7: =IFERROR(INDEX('SKU Data'!$M$2:$M$1780,MATCH($A7,'SKU Data'!$Y$2:$Y$1780,0)),"") -> 9.1019347e-05 | K7: =IFERROR(INDEX('SKU Data'!$L$2:$L$1780,MATCH($A7,'SKU Data'!$Y$2:$Y$1780,0)),"") -> 0.0023430924 | M7: =Settings!$B$3 -> 0.030986151
A8: 4 | B8: =IFERROR(INDEX('SKU Data'!$A$2:$A$1780,MATCH($A8,'SKU Data'!$Y$2:$Y$1780,0)),"") -> AUMJ-NW-005 | C8: =IFERROR(INDEX('SKU Data'!$B$2:$B$1780,MATCH($A8,'SKU Data'!$Y$2:$Y$1780,0)),"") -> Native Flowers Bouquet in Mason Jar | D8: =IFERROR(INDEX('SKU Data'!$D$2:$D$1780,MATCH($A8,'SKU Data'!$Y$2:$Y$1780,0)),"") -> AUMJ | E8: =IFERROR(INDEX('SKU Data'!$E$2:$E$1780,MATCH($A8,'SKU Data'!$Y$2:$Y$1780,0)),"") -> 6304 | F8: =IFERROR(INDEX('SKU Data'!$F$2:$F$1780,MATCH($A8,'SKU Data'!$Y$2:$Y$1780,0)),"") -> 335 | G8: =IFERROR(INDEX('SKU Data'!$J$2:$J$1780,MATCH($A8,'SKU Data'!$Y$2:$Y$1780,0)),"") -> 0.053140863 | H8: =IFERROR(INDEX('SKU Data'!$H$2:$H$1780,MATCH($A8,'SKU Data'!$Y$2:$Y$1780,0)),"") -> 30439.34 | I8: =IFERROR(INDEX('SKU Data'!$K$2:$K$1780,MATCH($A8,'SKU Data'!$Y$2:$Y$1780,0)),"") -> 0.051522022 | J8: =IFERROR(INDEX('SKU Data'!$M$2:$M$1780,MATCH($A8,'SKU Data'!$Y$2:$Y$1780,0)),"") -> 0.0023631399 | K8: =IFERROR(INDEX('SKU Data'!$L$2:$L$1780,MATCH($A8,'SKU Data'!$Y$2:$Y$1780,0)),"") -> 0.060833826 | M8: =Settings!$B$3 -> 0.030986151
A9: 5 | B9: =IFERROR(INDEX('SKU Data'!$A$2:$A$1780,MATCH($A9,'SKU Data'!$Y$2:$Y$1780,0)),"") -> SC01 | C9: =IFERROR(INDEX('SKU Data'!$B$2:$B$1780,MATCH($A9,'SKU Data'!$Y$2:$Y$1780,0)),"") -> Full Size Sympathy Card | D9: =IFERROR(INDEX('SKU Data'!$D$2:$D$1780,MATCH($A9,'SKU Data'!$Y$2:$Y$1780,0)),"") -> SC | E9: =IFERROR(INDEX('SKU Data'!$E$2:$E$1780,MATCH($A9,'SKU Data'!$Y$2:$Y$1780,0)),"") -> 8341 | F9: =IFERROR(INDEX('SKU Data'!$F$2:$F$1780,MATCH($A9,'SKU Data'!$Y$2:$Y$1780,0)),"") -> 329 | G9: =IFERROR(INDEX('SKU Data'!$J$2:$J$1780,MATCH($A9,'SKU Data'!$Y$2:$Y$1780,0)),"") -> 0.039443712 | H9: =IFERROR(INDEX('SKU Data'!$H$2:$H$1780,MATCH($A9,'SKU Data'!$Y$2:$Y$1780,0)),"") -> 1189.07 | I9: =IFERROR(INDEX('SKU Data'!$K$2:$K$1780,MATCH($A9,'SKU Data'!$Y$2:$Y$1780,0)),"") -> 0.037598279 | J9: =IFERROR(INDEX('SKU Data'!$M$2:$M$1780,MATCH($A9,'SKU Data'!$Y$2:$Y$1780,0)),"") -> 9.2312736e-05 | K9: =IFERROR(INDEX('SKU Data'!$L$2:$L$1780,MATCH($A9,'SKU Data'!$Y$2:$Y$1780,0)),"") -> 0.0023763878 | M9: =Settings!$B$3 -> 0.030986151
A10: 6 | B10: =IFERROR(INDEX('SKU Data'!$A$2:$A$1780,MATCH($A10,'SKU Data'!$Y$2:$Y$1780,0)),"") -> AUSMJ100-11 | C10: =IFERROR(INDEX('SKU Data'!$B$2:$B$1780,MATCH($A10,'SKU Data'!$Y$2:$Y$1780,0)),"") -> Breathtaking Blooms In Mason Jar | D10: =IFERROR(INDEX('SKU Data'!$D$2:$D$1780,MATCH($A10,'SKU Data'!$Y$2:$Y$1780,0)),"") -> AUSMJ | E10: =IFERROR(INDEX('SKU Data'!$E$2:$E$1780,MATCH($A10,'SKU Data'!$Y$2:$Y$1780,0)),"") -> 4959 | F10: =IFERROR(INDEX('SKU Data'!$F$2:$F$1780,MATCH($A10,'SKU Data'!$Y$2:$Y$1780,0)),"") -> 203 | G10: =IFERROR(INDEX('SKU Data'!$J$2:$J$1780,MATCH($A10,'SKU Data'!$Y$2:$Y$1780,0)),"") -> 0.040935673 | H10: =IFERROR(INDEX('SKU Data'!$H$2:$H$1780,MATCH($A10,'SKU Data'!$Y$2:$Y$1780,0)),"") -> 13653.88 | I10: =IFERROR(INDEX('SKU Data'!$K$2:$K$1780,MATCH($A10,'SKU Data'!$Y$2:$Y$1780,0)),"") -> 0.039004288 | J10: =IFERROR(INDEX('SKU Data'!$M$2:$M$1780,MATCH($A10,'SKU Data'!$Y$2:$Y$1780,0)),"") -> 0.0010600108 | K10: =IFERROR(INDEX('SKU Data'!$L$2:$L$1780,MATCH($A10,'SKU Data'!$Y$2:$Y$1780,0)),"") -> 0.02728764 | M10: =Settings!$B$3 -> 0.030986151
A11: 7 | B11: =IFERROR(INDEX('SKU Data'!$A$2:$A$1780,MATCH($A11,'SKU Data'!$Y$2:$Y$1780,0)),"") -> AUMJ-NW-017 | C11: =IFERROR(INDEX('SKU Data'!$B$2:$B$1780,MATCH($A11,'SKU Data'!$Y$2:$Y$1780,0)),"") -> Pastel Buttercup Bouquet in Mason Jar | D11: =IFERROR(INDEX('SKU Data'!$D$2:$D$1780,MATCH($A11,'SKU Data'!$Y$2:$Y$1780,0)),"") -> AUMJ | E11: =IFERROR(INDEX('SKU Data'!$E$2:$E$1780,MATCH($A11,'SKU Data'!$Y$2:$Y$1780,0)),"") -> 3907 | F11: =IFERROR(INDEX('SKU Data'!$F$2:$F$1780,MATCH($A11,'SKU Data'!$Y$2:$Y$1780,0)),"") -> 172 | G11: =IFERROR(INDEX('SKU Data'!$J$2:$J$1780,MATCH($A11,'SKU Data'!$Y$2:$Y$1780,0)),"") -> 0.044023547 | H11: =IFERROR(INDEX('SKU Data'!$H$2:$H$1780,MATCH($A11,'SKU Data'!$Y$2:$Y$1780,0)),"") -> 14074.44 | I11: =IFERROR(INDEX('SKU Data'!$K$2:$K$1780,MATCH($A11,'SKU Data'!$Y$2:$Y$1780,0)),"") -> 0.040285179 | J11: =IFERROR(INDEX('SKU Data'!$M$2:$M$1780,MATCH($A11,'SKU Data'!$Y$2:$Y$1780,0)),"") -> 0.0010926607 | K11: =IFERROR(INDEX('SKU Data'!$L$2:$L$1780,MATCH($A11,'SKU Data'!$Y$2:$Y$1780,0)),"") -> 0.028128141 | M11: =Settings!$B$3 -> 0.030986151
A12: 8 | B12: =IFERROR(INDEX('SKU Data'!$A$2:$A$1780,MATCH($A12,'SKU Data'!$Y$2:$Y$1780,0)),"") -> AUSRP-16sp | C12: =IFERROR(INDEX('SKU Data'!$B$2:$B$1780,MATCH($A12,'SKU Data'!$Y$2:$Y$1780,0)),"") -> Truffles & Card | D12: =IFERROR(INDEX('SKU Data'!$D$2:$D$1780,MATCH($A12,'SKU Data'!$Y$2:$Y$1780,0)),"") -> AUSRP | E12: =IFERROR(INDEX('SKU Data'!$E$2:$E$1780,MATCH($A12,'SKU Data'!$Y$2:$Y$1780,0)),"") -> 2919 | F12: =IFERROR(INDEX('SKU Data'!$F$2:$F$1780,MATCH($A12,'SKU Data'!$Y$2:$Y$1780,0)),"") -> 152 | G12: =IFERROR(INDEX('SKU Data'!$J$2:$J$1780,MATCH($A12,'SKU Data'!$Y$2:$Y$1780,0)),"") -> 0.052072628 | H12: =IFERROR(INDEX('SKU Data'!$H$2:$H$1780,MATCH($A12,'SKU Data'!$Y$2:$Y$1780,0)),"") -> 1385.93 | I12: =IFERROR(INDEX('SKU Data'!$K$2:$K$1780,MATCH($A12,'SKU Data'!$Y$2:$Y$1780,0)),"") -> 0.047612504 | J12: =IFERROR(INDEX('SKU Data'!$M$2:$M$1780,MATCH($A12,'SKU Data'!$Y$2:$Y$1780,0)),"") -> 0.00010759584 | K12: =IFERROR(INDEX('SKU Data'!$L$2:$L$1780,MATCH($A12,'SKU Data'!$Y$2:$Y$1780,0)),"") -> 0.0027698178 | M12: =Settings!$B$3 -> 0.030986151
A13: 9 | B13: =IFERROR(INDEX('SKU Data'!$A$2:$A$1780,MATCH($A13,'SKU Data'!$Y$2:$Y$1780,0)),"") -> AU11-43 | C13: =IFERROR(INDEX('SKU Data'!$B$2:$B$1780,MATCH($A13,'SKU Data'!$Y$2:$Y$1780,0)),"") -> Warm Embrace | D13: =IFERROR(INDEX('SKU Data'!$D$2:$D$1780,MATCH($A13,'SKU Data'!$Y$2:$Y$1780,0)),"") -> AU | E13: =IFERROR(INDEX('SKU Data'!$E$2:$E$1780,MATCH($A13,'SKU Data'!$Y$2:$Y$1780,0)),"") -> 2594 | F13: =IFERROR(INDEX('SKU Data'!$F$2:$F$1780,MATCH($A13,'SKU Data'!$Y$2:$Y$1780,0)),"") -> 129 | G13: =IFERROR(INDEX('SKU Data'!$J$2:$J$1780,MATCH($A13,'SKU Data'!$Y$2:$Y$1780,0)),"") -> 0.049730146 | H13: =IFERROR(INDEX('SKU Data'!$H$2:$H$1780,MATCH($A13,'SKU Data'!$Y$2:$Y$1780,0)),"") -> 11840.22 | I13: =IFERROR(INDEX('SKU Data'!$K$2:$K$1780,MATCH($A13,'SKU Data'!$Y$2:$Y$1780,0)),"") -> 0.047722296 | J13: =IFERROR(INDEX('SKU Data'!$M$2:$M$1780,MATCH($A13,'SKU Data'!$Y$2:$Y$1780,0)),"") -> 0.00091920838 | K13: =IFERROR(INDEX('SKU Data'!$L$2:$L$1780,MATCH($A13,'SKU Data'!$Y$2:$Y$1780,0)),"") -> 0.023662993 | M13: =Settings!$B$3 -> 0.030986151
A14: 10 | B14: =IFERROR(INDEX('SKU Data'!$A$2:$A$1780,MATCH($A14,'SKU Data'!$Y$2:$Y$1780,0)),"") -> AUCH25-04 | C14: =IFERROR(INDEX('SKU Data'!$B$2:$B$1780,MATCH($A14,'SKU Data'!$Y$2:$Y$1780,0)),"") -> Snowy Rose in Mason Jar | D14: =IFERROR(INDEX('SKU Data'!$D$2:$D$1780,MATCH($A14,'SKU Data'!$Y$2:$Y$1780,0)),"") -> AUCH | E14: =IFERROR(INDEX('SKU Data'!$E$2:$E$1780,MATCH($A14,'SKU Data'!$Y$2:$Y$1780,0)),"") -> 2531 | F14: =IFERROR(INDEX('SKU Data'!$F$2:$F$1780,MATCH($A14,'SKU Data'!$Y$2:$Y$1780,0)),"") -> 116 | G14: =IFERROR(INDEX('SKU Data'!$J$2:$J$1780,MATCH($A14,'SKU Data'!$Y$2:$Y$1780,0)),"") -> 0.045831687 | H14: =IFERROR(INDEX('SKU Data'!$H$2:$H$1780,MATCH($A14,'SKU Data'!$Y$2:$Y$1780,0)),"") -> 5309.56 | I14: =IFERROR(INDEX('SKU Data'!$K$2:$K$1780,MATCH($A14,'SKU Data'!$Y$2:$Y$1780,0)),"") -> 0.042930038 | J14: =IFERROR(INDEX('SKU Data'!$M$2:$M$1780,MATCH($A14,'SKU Data'!$Y$2:$Y$1780,0)),"") -> 0.00041220451 | K14: =IFERROR(INDEX('SKU Data'!$L$2:$L$1780,MATCH($A14,'SKU Data'!$Y$2:$Y$1780,0)),"") -> 0.010611296 | M14: =Settings!$B$3 -> 0.030986151
A15: 11 | B15: =IFERROR(INDEX('SKU Data'!$A$2:$A$1780,MATCH($A15,'SKU Data'!$Y$2:$Y$1780,0)),"") -> AUMJ-NW-011 | C15: =IFERROR(INDEX('SKU Data'!$B$2:$B$1780,MATCH($A15,'SKU Data'!$Y$2:$Y$1780,0)),"") -> Best Birthday Ever Bouquet in Mason Jar | D15: =IFERROR(INDEX('SKU Data'!$D$2:$D$1780,MATCH($A15,'SKU Data'!$Y$2:$Y$1780,0)),"") -> AUMJ | E15: =IFERROR(INDEX('SKU Data'!$E$2:$E$1780,MATCH($A15,'SKU Data'!$Y$2:$Y$1780,0)),"") -> 2143 | F15: =IFERROR(INDEX('SKU Data'!$F$2:$F$1780,MATCH($A15,'SKU Data'!$Y$2:$Y$1780,0)),"") -> 115 | G15: =IFERROR(INDEX('SKU Data'!$J$2:$J$1780,MATCH($A15,'SKU Data'!$Y$2:$Y$1780,0)),"") -> 0.053663089 | H15: =IFERROR(INDEX('SKU Data'!$H$2:$H$1780,MATCH($A15,'SKU Data'!$Y$2:$Y$1780,0)),"") -> 9879.04 | I15: =IFERROR(INDEX('SKU Data'!$K$2:$K$1780,MATCH($A15,'SKU Data'!$Y$2:$Y$1780,0)),"") -> 0.053490444 | J15: =IFERROR(INDEX('SKU Data'!$M$2:$M$1780,MATCH($A15,'SKU Data'!$Y$2:$Y$1780,0)),"") -> 0.00076695335 | K15: =IFERROR(INDEX('SKU Data'!$L$2:$L$1780,MATCH($A15,'SKU Data'!$Y$2:$Y$1780,0)),"") -> 0.019743523 | M15: =Settings!$B$3 -> 0.030986151
A16: 12 | B16: =IFERROR(INDEX('SKU Data'!$A$2:$A$1780,MATCH($A16,'SKU Data'!$Y$2:$Y$1780,0)),"") -> AURP03 | C16: =IFERROR(INDEX('SKU Data'!$B$2:$B$1780,MATCH($A16,'SKU Data'!$Y$2:$Y$1780,0)),"") -> Glass Vase | D16: =IFERROR(INDEX('SKU Data'!$D$2:$D$1780,MATCH($A16,'SKU Data'!$Y$2:$Y$1780,0)),"") -> AURP | E16: =IFERROR(INDEX('SKU Data'!$E$2:$E$1780,MATCH($A16,'SKU Data'!$Y$2:$Y$1780,0)),"") -> 2409 | F16: =IFERROR(INDEX('SKU Data'!$F$2:$F$1780,MATCH($A16,'SKU Data'!$Y$2:$Y$1780,0)),"") -> 112 | G16: =IFERROR(INDEX('SKU Data'!$J$2:$J$1780,MATCH($A16,'SKU Data'!$Y$2:$Y$1780,0)),"") -> 0.04649232 | H16: =IFERROR(INDEX('SKU Data'!$H$2:$H$1780,MATCH($A16,'SKU Data'!$Y$2:$Y$1780,0)),"") -> 1180.39 | I16: =IFERROR(INDEX('SKU Data'!$K$2:$K$1780,MATCH($A16,'SKU Data'!$Y$2:$Y$1780,0)),"") -> 0.043241847 | J16: =IFERROR(INDEX('SKU Data'!$M$2:$M$1780,MATCH($A16,'SKU Data'!$Y$2:$Y$1780,0)),"") -> 9.163887e-05 | K16: =IFERROR(INDEX('SKU Data'!$L$2:$L$1780,MATCH($A16,'SKU Data'!$Y$2:$Y$1780,0)),"") -> 0.0023590406 | M16: =Settings!$B$3 -> 0.030986151
... A29: 25 | B29: =IFERROR(INDEX('SKU Data'!$A$2:$A$1780,MATCH($A29,'SKU Data'!$Y$2:$Y$1780,0)),"") -> AU222-80 | C29: =IFERROR(INDEX('SKU Data'!$B$2:$B$1780,MATCH($A29,'SKU Data'!$Y$2:$Y$1780,0)),"") -> Wild Spirits | D29: =IFERROR(INDEX('SKU Data'!$D$2:$D$1780,MATCH($A29,'SKU Data'!$Y$2:$Y$1780,0)),"") -> AU | E29: =IFERROR(INDEX('SKU Data'!$E$2:$E$1780,MATCH($A29,'SKU Data'!$Y$2:$Y$1780,0)),"") -> 1727 | F29: =IFERROR(INDEX('SKU Data'!$F$2:$F$1780,MATCH($A29,'SKU Data'!$Y$2:$Y$1780,0)),"") -> 80 | G29: =IFERROR(INDEX('SKU Data'!$J$2:$J$1780,MATCH($A29,'SKU Data'!$Y$2:$Y$1780,0)),"") -> 0.046323104 | H29: =IFERROR(INDEX('SKU Data'!$H$2:$H$1780,MATCH($A29,'SKU Data'!$Y$2:$Y$1780,0)),"") -> 6215.17 | I29: =IFERROR(INDEX('SKU Data'!$K$2:$K$1780,MATCH($A29,'SKU Data'!$Y$2:$Y$1780,0)),"") -> 0.044132978 | J29: =IFERROR(INDEX('SKU Data'!$M$2:$M$1780,MATCH($A29,'SKU Data'!$Y$2:$Y$1780,0)),"") -> 0.000482511 | K29: =IFERROR(INDEX('SKU Data'!$L$2:$L$1780,MATCH($A29,'SKU Data'!$Y$2:$Y$1780,0)),"") -> 0.012421182 | M29: =Settings!$B$3 -> 0.030986151
A32: 2) BY REVENUE IMPACT - largest refund $ (as % of total revenue)
A33: # | B33: SKU | C33: Product | D33: Brand / family | E33: Qty ordered | F33: Refunded units | G33: Refund rate (units) | H33: Refund $ | I33: Refund rate ($ own gross) | J33: % of total revenue | K33: % of SKU-attrib. refund $ | L33: Cumulative % of refunds | M33: Baseline rate
A34: 1 | B34: =IFERROR(INDEX('SKU Data'!$A$2:$A$1780,MATCH($A34,'SKU Data'!$Z$2:$Z$1780,0)),"") -> AUMJ-NW-005 | C34: =IFERROR(INDEX('SKU Data'!$B$2:$B$1780,MATCH($A34,'SKU Data'!$Z$2:$Z$1780,0)),"") -> Native Flowers Bouquet in Mason Jar | D34: =IFERROR(INDEX('SKU Data'!$D$2:$D$1780,MATCH($A34,'SKU Data'!$Z$2:$Z$1780,0)),"") -> AUMJ | E34: =IFERROR(INDEX('SKU Data'!$E$2:$E$1780,MATCH($A34,'SKU Data'!$Z$2:$Z$1780,0)),"") -> 6304 | F34: =IFERROR(INDEX('SKU Data'!$F$2:$F$1780,MATCH($A34,'SKU Data'!$Z$2:$Z$1780,0)),"") -> 335 | G34: =IFERROR(INDEX('SKU Data'!$J$2:$J$1780,MATCH($A34,'SKU Data'!$Z$2:$Z$1780,0)),"") -> 0.053140863 | H34: =IFERROR(INDEX('SKU Data'!$H$2:$H$1780,MATCH($A34,'SKU Data'!$Z$2:$Z$1780,0)),"") -> 30439.34 | I34: =IFERROR(INDEX('SKU Data'!$K$2:$K$1780,MATCH($A34,'SKU Data'!$Z$2:$Z$1780,0)),"") -> 0.051522022 | J34: =IFERROR(INDEX('SKU Data'!$M$2:$M$1780,MATCH($A34,'SKU Data'!$Z$2:$Z$1780,0)),"") -> 0.0023631399 | K34: =IFERROR(INDEX('SKU Data'!$L$2:$L$1780,MATCH($A34,'SKU Data'!$Z$2:$Z$1780,0)),"") -> 0.060833826 | L34: =SUM($K$34:K34) -> 0.060833826 | M34: =Settings!$B$3 -> 0.030986151
A35: 2 | B35: =IFERROR(INDEX('SKU Data'!$A$2:$A$1780,MATCH($A35,'SKU Data'!$Z$2:$Z$1780,0)),"") -> AUSGF16-115 | C35: =IFERROR(INDEX('SKU Data'!$B$2:$B$1780,MATCH($A35,'SKU Data'!$Z$2:$Z$1780,0)),"") -> Delicate Elegance | D35: =IFERROR(INDEX('SKU Data'!$D$2:$D$1780,MATCH($A35,'SKU Data'!$Z$2:$Z$1780,0)),"") -> AUSGF | E35: =IFERROR(INDEX('SKU Data'!$E$2:$E$1780,MATCH($A35,'SKU Data'!$Z$2:$Z$1780,0)),"") -> 11490 | F35: =IFERROR(INDEX('SKU Data'!$F$2:$F$1780,MATCH($A35,'SKU Data'!$Z$2:$Z$1780,0)),"") -> 419 | G35: =IFERROR(INDEX('SKU Data'!$J$2:$J$1780,MATCH($A35,'SKU Data'!$Z$2:$Z$1780,0)),"") -> 0.036466493 | H35: =IFERROR(INDEX('SKU Data'!$H$2:$H$1780,MATCH($A35,'SKU Data'!$Z$2:$Z$1780,0)),"") -> 25834.89 | I35: =IFERROR(INDEX('SKU Data'!$K$2:$K$1780,MATCH($A35,'SKU Data'!$Z$2:$Z$1780,0)),"") -> 0.035459214 | J35: =IFERROR(INDEX('SKU Data'!$M$2:$M$1780,MATCH($A35,'SKU Data'!$Z$2:$Z$1780,0)),"") -> 0.0020056762 | K35: =IFERROR(INDEX('SKU Data'!$L$2:$L$1780,MATCH($A35,'SKU Data'!$Z$2:$Z$1780,0)),"") -> 0.051631711 | L35: =SUM($K$34:K35) -> 0.11246554 | M35: =Settings!$B$3 -> 0.030986151
A36: 3 | B36: =IFERROR(INDEX('SKU Data'!$A$2:$A$1780,MATCH($A36,'SKU Data'!$Z$2:$Z$1780,0)),"") -> AUMJ-NW-017 | C36: =IFERROR(INDEX('SKU Data'!$B$2:$B$1780,MATCH($A36,'SKU Data'!$Z$2:$Z$1780,0)),"") -> Pastel Buttercup Bouquet in Mason Jar | D36: =IFERROR(INDEX('SKU Data'!$D$2:$D$1780,MATCH($A36,'SKU Data'!$Z$2:$Z$1780,0)),"") -> AUMJ | E36: =IFERROR(INDEX('SKU Data'!$E$2:$E$1780,MATCH($A36,'SKU Data'!$Z$2:$Z$1780,0)),"") -> 3907 | F36: =IFERROR(INDEX('SKU Data'!$F$2:$F$1780,MATCH($A36,'SKU Data'!$Z$2:$Z$1780,0)),"") -> 172 | G36: =IFERROR(INDEX('SKU Data'!$J$2:$J$1780,MATCH($A36,'SKU Data'!$Z$2:$Z$1780,0)),"") -> 0.044023547 | H36: =IFERROR(INDEX('SKU Data'!$H$2:$H$1780,MATCH($A36,'SKU Data'!$Z$2:$Z$1780,0)),"") -> 14074.44 | I36: =IFERROR(INDEX('SKU Data'!$K$2:$K$1780,MATCH($A36,'SKU Data'!$Z$2:$Z$1780,0)),"") -> 0.040285179 | J36: =IFERROR(INDEX('SKU Data'!$M$2:$M$1780,MATCH($A36,'SKU Data'!$Z$2:$Z$1780,0)),"") -> 0.0010926607 | K36: =IFERROR(INDEX('SKU Data'!$L$2:$L$1780,MATCH($A36,'SKU Data'!$Z$2:$Z$1780,0)),"") -> 0.028128141 | L36: =SUM($K$34:K36) -> 0.14059368 | M36: =Settings!$B$3 -> 0.030986151
A37: 4 | B37: =IFERROR(INDEX('SKU Data'!$A$2:$A$1780,MATCH($A37,'SKU Data'!$Z$2:$Z$1780,0)),"") -> AUSMJ100-11 | C37: =IFERROR(INDEX('SKU Data'!$B$2:$B$1780,MATCH($A37,'SKU Data'!$Z$2:$Z$1780,0)),"") -> Breathtaking Blooms In Mason Jar | D37: =IFERROR(INDEX('SKU Data'!$D$2:$D$1780,MATCH($A37,'SKU Data'!$Z$2:$Z$1780,0)),"") -> AUSMJ | E37: =IFERROR(INDEX('SKU Data'!$E$2:$E$1780,MATCH($A37,'SKU Data'!$Z$2:$Z$1780,0)),"") -> 4959 | F37: =IFERROR(INDEX('SKU Data'!$F$2:$F$1780,MATCH($A37,'SKU Data'!$Z$2:$Z$1780,0)),"") -> 203 | G37: =IFERROR(INDEX('SKU Data'!$J$2:$J$1780,MATCH($A37,'SKU Data'!$Z$2:$Z$1780,0)),"") -> 0.040935673 | H37: =IFERROR(INDEX('SKU Data'!$H$2:$H$1780,MATCH($A37,'SKU Data'!$Z$2:$Z$1780,0)),"") -> 13653.88 | I37: =IFERROR(INDEX('SKU Data'!$K$2:$K$1780,MATCH($A37,'SKU Data'!$Z$2:$Z$1780,0)),"") -> 0.039004288 | J37: =IFERROR(INDEX('SKU Data'!$M$2:$M$1780,MATCH($A37,'SKU Data'!$Z$2:$Z$1780,0)),"") -> 0.0010600108 | K37: =IFERROR(INDEX('SKU Data'!$L$2:$L$1780,MATCH($A37,'SKU Data'!$Z$2:$Z$1780,0)),"") -> 0.02728764 | L37: =SUM($K$34:K37) -> 0.16788132 | M37: =Settings!$B$3 -> 0.030986151
A38: 5 | B38: =IFERROR(INDEX('SKU Data'!$A$2:$A$1780,MATCH($A38,'SKU Data'!$Z$2:$Z$1780,0)),"") -> AU11-43 | C38: =IFERROR(INDEX('SKU Data'!$B$2:$B$1780,MATCH($A38,'SKU Data'!$Z$2:$Z$1780,0)),"") -> Warm Embrace | D38: =IFERROR(INDEX('SKU Data'!$D$2:$D$1780,MATCH($A38,'SKU Data'!$Z$2:$Z$1780,0)),"") -> AU | E38: =IFERROR(INDEX('SKU Data'!$E$2:$E$1780,MATCH($A38,'SKU Data'!$Z$2:$Z$1780,0)),"") -> 2594 | F38: =IFERROR(INDEX('SKU Data'!$F$2:$F$1780,MATCH($A38,'SKU Data'!$Z$2:$Z$1780,0)),"") -> 129 | G38: =IFERROR(INDEX('SKU Data'!$J$2:$J$1780,MATCH($A38,'SKU Data'!$Z$2:$Z$1780,0)),"") -> 0.049730146 | H38: =IFERROR(INDEX('SKU Data'!$H$2:$H$1780,MATCH($A38,'SKU Data'!$Z$2:$Z$1780,0)),"") -> 11840.22 | I38: =IFERROR(INDEX('SKU Data'!$K$2:$K$1780,MATCH($A38,'SKU Data'!$Z$2:$Z$1780,0)),"") -> 0.047722296 | J38: =IFERROR(INDEX('SKU Data'!$M$2:$M$1780,MATCH($A38,'SKU Data'!$Z$2:$Z$1780,0)),"") -> 0.00091920838 | K38: =IFERROR(INDEX('SKU Data'!$L$2:$L$1780,MATCH($A38,'SKU Data'!$Z$2:$Z$1780,0)),"") -> 0.023662993 | L38: =SUM($K$34:K38) -> 0.19154431 | M38: =Settings!$B$3 -> 0.030986151
A39: 6 | B39: =IFERROR(INDEX('SKU Data'!$A$2:$A$1780,MATCH($A39,'SKU Data'!$Z$2:$Z$1780,0)),"") -> AUMJ-NW-011 | C39: =IFERROR(INDEX('SKU Data'!$B$2:$B$1780,MATCH($A39,'SKU Data'!$Z$2:$Z$1780,0)),"") -> Best Birthday Ever Bouquet in Mason Jar | D39: =IFERROR(INDEX('SKU Data'!$D$2:$D$1780,MATCH($A39,'SKU Data'!$Z$2:$Z$1780,0)),"") -> AUMJ | E39: =IFERROR(INDEX('SKU Data'!$E$2:$E$1780,MATCH($A39,'SKU Data'!$Z$2:$Z$1780,0)),"") -> 2143 | F39: =IFERROR(INDEX('SKU Data'!$F$2:$F$1780,MATCH($A39,'SKU Data'!$Z$2:$Z$1780,0)),"") -> 115 | G39: =IFERROR(INDEX('SKU Data'!$J$2:$J$1780,MATCH($A39,'SKU Data'!$Z$2:$Z$1780,0)),"") -> 0.053663089 | H39: =IFERROR(INDEX('SKU Data'!$H$2:$H$1780,MATCH($A39,'SKU Data'!$Z$2:$Z$1780,0)),"") -> 9879.04 | I39: =IFERROR(INDEX('SKU Data'!$K$2:$K$1780,MATCH($A39,'SKU Data'!$Z$2:$Z$1780,0)),"") -> 0.053490444 | J39: =IFERROR(INDEX('SKU Data'!$M$2:$M$1780,MATCH($A39,'SKU Data'!$Z$2:$Z$1780,0)),"") -> 0.00076695335 | K39: =IFERROR(INDEX('SKU Data'!$L$2:$L$1780,MATCH($A39,'SKU Data'!$Z$2:$Z$1780,0)),"") -> 0.019743523 | L39: =SUM($K$34:K39) -> 0.21128783 | M39: =Settings!$B$3 -> 0.030986151
A40: 7 | B40: =IFERROR(INDEX('SKU Data'!$A$2:$A$1780,MATCH($A40,'SKU Data'!$Z$2:$Z$1780,0)),"") -> AU112-10 | C40: =IFERROR(INDEX('SKU Data'!$B$2:$B$1780,MATCH($A40,'SKU Data'!$Z$2:$Z$1780,0)),"") -> Lavender Love | D40: =IFERROR(INDEX('SKU Data'!$D$2:$D$1780,MATCH($A40,'SKU Data'!$Z$2:$Z$1780,0)),"") -> AU | E40: =IFERROR(INDEX('SKU Data'!$E$2:$E$1780,MATCH($A40,'SKU Data'!$Z$2:$Z$1780,0)),"") -> 2208 | F40: =IFERROR(INDEX('SKU Data'!$F$2:$F$1780,MATCH($A40,'SKU Data'!$Z$2:$Z$1780,0)),"") -> 108 | G40: =IFERROR(INDEX('SKU Data'!$J$2:$J$1780,MATCH($A40,'SKU Data'!$Z$2:$Z$1780,0)),"") -> 0.048913043 | H40: =IFERROR(INDEX('SKU Data'!$H$2:$H$1780,MATCH($A40,'SKU Data'!$Z$2:$Z$1780,0)),"") -> 9388.55 | I40: =IFERROR(INDEX('SKU Data'!$K$2:$K$1780,MATCH($A40,'SKU Data'!$Z$2:$Z$1780,0)),"") -> 0.046067461 | J40: =IFERROR(INDEX('SKU Data'!$M$2:$M$1780,MATCH($A40,'SKU Data'!$Z$2:$Z$1780,0)),"") -> 0.00072887445 | K40: =IFERROR(INDEX('SKU Data'!$L$2:$L$1780,MATCH($A40,'SKU Data'!$Z$2:$Z$1780,0)),"") -> 0.018763265 | L40: =SUM($K$34:K40) -> 0.2300511 | M40: =Settings!$B$3 -> 0.030986151
A41: 8 | B41: =IFERROR(INDEX('SKU Data'!$A$2:$A$1780,MATCH($A41,'SKU Data'!$Z$2:$Z$1780,0)),"") -> AUMJ-NW-003 | C41: =IFERROR(INDEX('SKU Data'!$B$2:$B$1780,MATCH($A41,'SKU Data'!$Z$2:$Z$1780,0)),"") -> 50 Blooms of Surprise Bud Roses in Mason Jar | D41: =IFERROR(INDEX('SKU Data'!$D$2:$D$1780,MATCH($A41,'SKU Data'!$Z$2:$Z$1780,0)),"") -> AUMJ | E41: =IFERROR(INDEX('SKU Data'!$E$2:$E$1780,MATCH($A41,'SKU Data'!$Z$2:$Z$1780,0)),"") -> 2769 | F41: =IFERROR(INDEX('SKU Data'!$F$2:$F$1780,MATCH($A41,'SKU Data'!$Z$2:$Z$1780,0)),"") -> 106 | G41: =IFERROR(INDEX('SKU Data'!$J$2:$J$1780,MATCH($A41,'SKU Data'!$Z$2:$Z$1780,0)),"") -> 0.038280968 | H41: =IFERROR(INDEX('SKU Data'!$H$2:$H$1780,MATCH($A41,'SKU Data'!$Z$2:$Z$1780,0)),"") -> 8978.84 | I41: =IFERROR(INDEX('SKU Data'!$K$2:$K$1780,MATCH($A41,'SKU Data'!$Z$2:$Z$1780,0)),"") -> 0.037401582 | J41: =IFERROR(INDEX('SKU Data'!$M$2:$M$1780,MATCH($A41,'SKU Data'!$Z$2:$Z$1780,0)),"") -> 0.00069706686 | K41: =IFERROR(INDEX('SKU Data'!$L$2:$L$1780,MATCH($A41,'SKU Data'!$Z$2:$Z$1780,0)),"") -> 0.017944449 | L41: =SUM($K$34:K41) -> 0.24799555 | M41: =Settings!$B$3 -> 0.030986151
A42: 9 | B42: =IFERROR(INDEX('SKU Data'!$A$2:$A$1780,MATCH($A42,'SKU Data'!$Z$2:$Z$1780,0)),"") -> DC-04S | C42: =IFERROR(INDEX('SKU Data'!$B$2:$B$1780,MATCH($A42,'SKU Data'!$Z$2:$Z$1780,0)),"") -> Designer Sympathy Collection IV | D42: =IFERROR(INDEX('SKU Data'!$D$2:$D$1780,MATCH($A42,'SKU Data'!$Z$2:$Z$1780,0)),"") -> DC | E42: =IFERROR(INDEX('SKU Data'!$E$2:$E$1780,MATCH($A42,'SKU Data'!$Z$2:$Z$1780,0)),"") -> 1695 | F42: =IFERROR(INDEX('SKU Data'!$F$2:$F$1780,MATCH($A42,'SKU Data'!$Z$2:$Z$1780,0)),"") -> 75 | G42: =IFERROR(INDEX('SKU Data'!$J$2:$J$1780,MATCH($A42,'SKU Data'!$Z$2:$Z$1780,0)),"") -> 0.044247788 | H42: =IFERROR(INDEX('SKU Data'!$H$2:$H$1780,MATCH($A42,'SKU Data'!$Z$2:$Z$1780,0)),"") -> 8683.47 | I42: =IFERROR(INDEX('SKU Data'!$K$2:$K$1780,MATCH($A42,'SKU Data'!$Z$2:$Z$1780,0)),"") -> 0.03898614 | J42: =IFERROR(INDEX('SKU Data'!$M$2:$M$1780,MATCH($A42,'SKU Data'!$Z$2:$Z$1780,0)),"") -> 0.00067413599 | K42: =IFERROR(INDEX('SKU Data'!$L$2:$L$1780,MATCH($A42,'SKU Data'!$Z$2:$Z$1780,0)),"") -> 0.017354144 | L42: =SUM($K$34:K42) -> 0.26534969 | M42: =Settings!$B$3 -> 0.030986151
A43: 10 | B43: =IFERROR(INDEX('SKU Data'!$A$2:$A$1780,MATCH($A43,'SKU Data'!$Z$2:$Z$1780,0)),"") -> AUMJ-NW-019 | C43: =IFERROR(INDEX('SKU Data'!$B$2:$B$1780,MATCH($A43,'SKU Data'!$Z$2:$Z$1780,0)),"") -> Garden Party Bouquet in Mason Jar | D43: =IFERROR(INDEX('SKU Data'!$D$2:$D$1780,MATCH($A43,'SKU Data'!$Z$2:$Z$1780,0)),"") -> AUMJ | E43: =IFERROR(INDEX('SKU Data'!$E$2:$E$1780,MATCH($A43,'SKU Data'!$Z$2:$Z$1780,0)),"") -> 1250 | F43: =IFERROR(INDEX('SKU Data'!$F$2:$F$1780,MATCH($A43,'SKU Data'!$Z$2:$Z$1780,0)),"") -> 74 | G43: =IFERROR(INDEX('SKU Data'!$J$2:$J$1780,MATCH($A43,'SKU Data'!$Z$2:$Z$1780,0)),"") -> 0.0592 | H43: =IFERROR(INDEX('SKU Data'!$H$2:$H$1780,MATCH($A43,'SKU Data'!$Z$2:$Z$1780,0)),"") -> 8226.91 | I43: =IFERROR(INDEX('SKU Data'!$K$2:$K$1780,MATCH($A43,'SKU Data'!$Z$2:$Z$1780,0)),"") -> 0.059694511 | J43: =IFERROR(INDEX('SKU Data'!$M$2:$M$1780,MATCH($A43,'SKU Data'!$Z$2:$Z$1780,0)),"") -> 0.00063869122 | K43: =IFERROR(INDEX('SKU Data'!$L$2:$L$1780,MATCH($A43,'SKU Data'!$Z$2:$Z$1780,0)),"") -> 0.016441697 | L43: =SUM($K$34:K43) -> 0.28179139 | M43: =Settings!$B$3 -> 0.030986151
A44: 11 | B44: =IFERROR(INDEX('SKU Data'!$A$2:$A$1780,MATCH($A44,'SKU Data'!$Z$2:$Z$1780,0)),"") -> GF16-100 | C44: =IFERROR(INDEX('SKU Data'!$B$2:$B$1780,MATCH($A44,'SKU Data'!$Z$2:$Z$1780,0)),"") -> Blushing Elegance | D44: =IFERROR(INDEX('SKU Data'!$D$2:$D$1780,MATCH($A44,'SKU Data'!$Z$2:$Z$1780,0)),"") -> GF | E44: =IFERROR(INDEX('SKU Data'!$E$2:$E$1780,MATCH($A44,'SKU Data'!$Z$2:$Z$1780,0)),"") -> 1333 | F44: =IFERROR(INDEX('SKU Data'!$F$2:$F$1780,MATCH($A44,'SKU Data'!$Z$2:$Z$1780,0)),"") -> 70 | G44: =IFERROR(INDEX('SKU Data'!$J$2:$J$1780,MATCH($A44,'SKU Data'!$Z$2:$Z$1780,0)),"") -> 0.052513128 | H44: =IFERROR(INDEX('SKU Data'!$H$2:$H$1780,MATCH($A44,'SKU Data'!$Z$2:$Z$1780,0)),"") -> 6992.71 | I44: =IFERROR(INDEX('SKU Data'!$K$2:$K$1780,MATCH($A44,'SKU Data'!$Z$2:$Z$1780,0)),"") -> 0.046691952 | J44: =IFERROR(INDEX('SKU Data'!$M$2:$M$1780,MATCH($A44,'SKU Data'!$Z$2:$Z$1780,0)),"") -> 0.00054287485 | K44: =IFERROR(INDEX('SKU Data'!$L$2:$L$1780,MATCH($A44,'SKU Data'!$Z$2:$Z$1780,0)),"") -> 0.013975116 | L44: =SUM($K$34:K44) -> 0.29576651 | M44: =Settings!$B$3 -> 0.030986151
A45: 12 | B45: =IFERROR(INDEX('SKU Data'!$A$2:$A$1780,MATCH($A45,'SKU Data'!$Z$2:$Z$1780,0)),"") -> GF16-110 | C45: =IFERROR(INDEX('SKU Data'!$B$2:$B$1780,MATCH($A45,'SKU Data'!$Z$2:$Z$1780,0)),"") -> Pastel Harmony | D45: =IFERROR(INDEX('SKU Data'!$D$2:$D$1780,MATCH($A45,'SKU Data'!$Z$2:$Z$1780,0)),"") -> GF | E45: =IFERROR(INDEX('SKU Data'!$E$2:$E$1780,MATCH($A45,'SKU Data'!$Z$2:$Z$1780,0)),"") -> 1130 | F45: =IFERROR(INDEX('SKU Data'!$F$2:$F$1780,MATCH($A45,'SKU Data'!$Z$2:$Z$1780,0)),"") -> 56 | G45: =IFERROR(INDEX('SKU Data'!$J$2:$J$1780,MATCH($A45,'SKU Data'!$Z$2:$Z$1780,0)),"") -> 0.049557522 | H45: =IFERROR(INDEX('SKU Data'!$H$2:$H$1780,MATCH($A45,'SKU Data'!$Z$2:$Z$1780,0)),"") -> 6386.94 | I45: =IFERROR(INDEX('SKU Data'!$K$2:$K$1780,MATCH($A45,'SKU Data'!$Z$2:$Z$1780,0)),"") -> 0.046227485 | J45: =IFERROR(INDEX('SKU Data'!$M$2:$M$1780,MATCH($A45,'SKU Data'!$Z$2:$Z$1780,0)),"") -> 0.00049584626 | K45: =IFERROR(INDEX('SKU Data'!$L$2:$L$1780,MATCH($A45,'SKU Data'!$Z$2:$Z$1780,0)),"") -> 0.012764469 | L45: =SUM($K$34:K45) -> 0.30853097 | M45: =Settings!$B$3 -> 0.030986151
... A58: 25 | B58: =IFERROR(INDEX('SKU Data'!$A$2:$A$1780,MATCH($A58,'SKU Data'!$Z$2:$Z$1780,0)),"") -> DC-01S | C58: =IFERROR(INDEX('SKU Data'!$B$2:$B$1780,MATCH($A58,'SKU Data'!$Z$2:$Z$1780,0)),"") -> Designer Sympathy Collection I | D58: =IFERROR(INDEX('SKU Data'!$D$2:$D$1780,MATCH($A58,'SKU Data'!$Z$2:$Z$1780,0)),"") -> DC | E58: =IFERROR(INDEX('SKU Data'!$E$2:$E$1780,MATCH($A58,'SKU Data'!$Z$2:$Z$1780,0)),"") -> 1991 | F58: =IFERROR(INDEX('SKU Data'!$F$2:$F$1780,MATCH($A58,'SKU Data'!$Z$2:$Z$1780,0)),"") -> 60 | G58: =IFERROR(INDEX('SKU Data'!$J$2:$J$1780,MATCH($A58,'SKU Data'!$Z$2:$Z$1780,0)),"") -> 0.03013561 | H58: =IFERROR(INDEX('SKU Data'!$H$2:$H$1780,MATCH($A58,'SKU Data'!$Z$2:$Z$1780,0)),"") -> 4255.73 | I58: =IFERROR(INDEX('SKU Data'!$K$2:$K$1780,MATCH($A58,'SKU Data'!$Z$2:$Z$1780,0)),"") -> 0.026901897 | J58: =IFERROR(INDEX('SKU Data'!$M$2:$M$1780,MATCH($A58,'SKU Data'!$Z$2:$Z$1780,0)),"") -> 0.00033039105 | K58: =IFERROR(INDEX('SKU Data'!$L$2:$L$1780,MATCH($A58,'SKU Data'!$Z$2:$Z$1780,0)),"") -> 0.008505189 | L58: =SUM($K$34:K58) -> 0.44728161 | M58: =Settings!$B$3 -> 0.030986151
A61: 3) BY OWN REFUND RATE - highest rate on the SKU's own sales (min volume applies)
A62: # | B62: SKU | C62: Product | D62: Brand / family | E62: Qty ordered | F62: Refunded units | G62: Refund rate (units) | H62: Refund $ | I62: Refund rate ($ own gross) | J62: % of total revenue | K62: % of SKU-attrib. refund $ | L62: Cumulative % of refunds | M62: Baseline rate
A63: 1 | B63: =IFERROR(INDEX('SKU Data'!$A$2:$A$1780,MATCH($A63,'SKU Data'!$AA$2:$AA$1780,0)),"") -> DCA-02-00 | C63: =IFERROR(INDEX('SKU Data'!$B$2:$B$1780,MATCH($A63,'SKU Data'!$AA$2:$AA$1780,0)),"") -> Anniversary Designer Collection II | D63: =IFERROR(INDEX('SKU Data'!$D$2:$D$1780,MATCH($A63,'SKU Data'!$AA$2:$AA$1780,0)),"") -> Other (small prefixes) | E63: =IFERROR(INDEX('SKU Data'!$E$2:$E$1780,MATCH($A63,'SKU Data'!$AA$2:$AA$1780,0)),"") -> 38 | F63: =IFERROR(INDEX('SKU Data'!$F$2:$F$1780,MATCH($A63,'SKU Data'!$AA$2:$AA$1780,0)),"") -> 8 | G63: =IFERROR(INDEX('SKU Data'!$J$2:$J$1780,MATCH($A63,'SKU Data'!$AA$2:$AA$1780,0)),"") -> 0.21052632 | H63: =IFERROR(INDEX('SKU Data'!$H$2:$H$1780,MATCH($A63,'SKU Data'!$AA$2:$AA$1780,0)),"") -> 735.3 | I63: =IFERROR(INDEX('SKU Data'!$K$2:$K$1780,MATCH($A63,'SKU Data'!$AA$2:$AA$1780,0)),"") -> 0.18217495 | J63: =IFERROR(INDEX('SKU Data'!$M$2:$M$1780,MATCH($A63,'SKU Data'!$AA$2:$AA$1780,0)),"") -> 5.7084575e-05 | K63: =IFERROR(INDEX('SKU Data'!$L$2:$L$1780,MATCH($A63,'SKU Data'!$AA$2:$AA$1780,0)),"") -> 0.0014695165 | M63: =Settings!$B$3 -> 0.030986151
A64: 2 | B64: =IFERROR(INDEX('SKU Data'!$A$2:$A$1780,MATCH($A64,'SKU Data'!$AA$2:$AA$1780,0)),"") -> AU100-571 | C64: =IFERROR(INDEX('SKU Data'!$B$2:$B$1780,MATCH($A64,'SKU Data'!$AA$2:$AA$1780,0)),"") -> Hope & Honour Cross | D64: =IFERROR(INDEX('SKU Data'!$D$2:$D$1780,MATCH($A64,'SKU Data'!$AA$2:$AA$1780,0)),"") -> AU | E64: =IFERROR(INDEX('SKU Data'!$E$2:$E$1780,MATCH($A64,'SKU Data'!$AA$2:$AA$1780,0)),"") -> 37 | F64: =IFERROR(INDEX('SKU Data'!$F$2:$F$1780,MATCH($A64,'SKU Data'!$AA$2:$AA$1780,0)),"") -> 7 | G64: =IFERROR(INDEX('SKU Data'!$J$2:$J$1780,MATCH($A64,'SKU Data'!$AA$2:$AA$1780,0)),"") -> 0.18918919 | H64: =IFERROR(INDEX('SKU Data'!$H$2:$H$1780,MATCH($A64,'SKU Data'!$AA$2:$AA$1780,0)),"") -> 1720.43 | I64: =IFERROR(INDEX('SKU Data'!$K$2:$K$1780,MATCH($A64,'SKU Data'!$AA$2:$AA$1780,0)),"") -> 0.18258994 | J64: =IFERROR(INDEX('SKU Data'!$M$2:$M$1780,MATCH($A64,'SKU Data'!$AA$2:$AA$1780,0)),"") -> 0.00013356455 | K64: =IFERROR(INDEX('SKU Data'!$L$2:$L$1780,MATCH($A64,'SKU Data'!$AA$2:$AA$1780,0)),"") -> 0.0034383249 | M64: =Settings!$B$3 -> 0.030986151
A65: 3 | B65: =IFERROR(INDEX('SKU Data'!$A$2:$A$1780,MATCH($A65,'SKU Data'!$AA$2:$AA$1780,0)),"") -> AU100-582 | C65: =IFERROR(INDEX('SKU Data'!$B$2:$B$1780,MATCH($A65,'SKU Data'!$AA$2:$AA$1780,0)),"") -> Rose Garden Heart | D65: =IFERROR(INDEX('SKU Data'!$D$2:$D$1780,MATCH($A65,'SKU Data'!$AA$2:$AA$1780,0)),"") -> AU | E65: =IFERROR(INDEX('SKU Data'!$E$2:$E$1780,MATCH($A65,'SKU Data'!$AA$2:$AA$1780,0)),"") -> 40 | F65: =IFERROR(INDEX('SKU Data'!$F$2:$F$1780,MATCH($A65,'SKU Data'!$AA$2:$AA$1780,0)),"") -> 6 | G65: =IFERROR(INDEX('SKU Data'!$J$2:$J$1780,MATCH($A65,'SKU Data'!$AA$2:$AA$1780,0)),"") -> 0.15 | H65: =IFERROR(INDEX('SKU Data'!$H$2:$H$1780,MATCH($A65,'SKU Data'!$AA$2:$AA$1780,0)),"") -> 1504.25 | I65: =IFERROR(INDEX('SKU Data'!$K$2:$K$1780,MATCH($A65,'SKU Data'!$AA$2:$AA$1780,0)),"") -> 0.13422079 | J65: =IFERROR(INDEX('SKU Data'!$M$2:$M$1780,MATCH($A65,'SKU Data'!$AA$2:$AA$1780,0)),"") -> 0.00011678155 | K65: =IFERROR(INDEX('SKU Data'!$L$2:$L$1780,MATCH($A65,'SKU Data'!$AA$2:$AA$1780,0)),"") -> 0.0030062834 | M65: =Settings!$B$3 -> 0.030986151
A66: 4 | B66: =IFERROR(INDEX('SKU Data'!$A$2:$A$1780,MATCH($A66,'SKU Data'!$AA$2:$AA$1780,0)),"") -> DCB-03 | C66: =IFERROR(INDEX('SKU Data'!$B$2:$B$1780,MATCH($A66,'SKU Data'!$AA$2:$AA$1780,0)),"") -> Birthday Designer Collection III | D66: =IFERROR(INDEX('SKU Data'!$D$2:$D$1780,MATCH($A66,'SKU Data'!$AA$2:$AA$1780,0)),"") -> DCB | E66: =IFERROR(INDEX('SKU Data'!$E$2:$E$1780,MATCH($A66,'SKU Data'!$AA$2:$AA$1780,0)),"") -> 35 | F66: =IFERROR(INDEX('SKU Data'!$F$2:$F$1780,MATCH($A66,'SKU Data'!$AA$2:$AA$1780,0)),"") -> 5 | G66: =IFERROR(INDEX('SKU Data'!$J$2:$J$1780,MATCH($A66,'SKU Data'!$AA$2:$AA$1780,0)),"") -> 0.14285714 | H66: =IFERROR(INDEX('SKU Data'!$H$2:$H$1780,MATCH($A66,'SKU Data'!$AA$2:$AA$1780,0)),"") -> 619.12 | I66: =IFERROR(INDEX('SKU Data'!$K$2:$K$1780,MATCH($A66,'SKU Data'!$AA$2:$AA$1780,0)),"") -> 0.11773946 | J66: =IFERROR(INDEX('SKU Data'!$M$2:$M$1780,MATCH($A66,'SKU Data'!$AA$2:$AA$1780,0)),"") -> 4.806501e-05 | K66: =IFERROR(INDEX('SKU Data'!$L$2:$L$1780,MATCH($A66,'SKU Data'!$AA$2:$AA$1780,0)),"") -> 0.0012373277 | M66: =Settings!$B$3 -> 0.030986151
A67: 5 | B67: =IFERROR(INDEX('SKU Data'!$A$2:$A$1780,MATCH($A67,'SKU Data'!$AA$2:$AA$1780,0)),"") -> AU1211-02 | C67: =IFERROR(INDEX('SKU Data'!$B$2:$B$1780,MATCH($A67,'SKU Data'!$AA$2:$AA$1780,0)),"") -> Three Dozen White Roses | D67: =IFERROR(INDEX('SKU Data'!$D$2:$D$1780,MATCH($A67,'SKU Data'!$AA$2:$AA$1780,0)),"") -> AU | E67: =IFERROR(INDEX('SKU Data'!$E$2:$E$1780,MATCH($A67,'SKU Data'!$AA$2:$AA$1780,0)),"") -> 40 | F67: =IFERROR(INDEX('SKU Data'!$F$2:$F$1780,MATCH($A67,'SKU Data'!$AA$2:$AA$1780,0)),"") -> 5 | G67: =IFERROR(INDEX('SKU Data'!$J$2:$J$1780,MATCH($A67,'SKU Data'!$AA$2:$AA$1780,0)),"") -> 0.125 | H67: =IFERROR(INDEX('SKU Data'!$H$2:$H$1780,MATCH($A67,'SKU Data'!$AA$2:$AA$1780,0)),"") -> 1187.73 | I67: =IFERROR(INDEX('SKU Data'!$K$2:$K$1780,MATCH($A67,'SKU Data'!$AA$2:$AA$1780,0)),"") -> 0.1173237 | J67: =IFERROR(INDEX('SKU Data'!$M$2:$M$1780,MATCH($A67,'SKU Data'!$AA$2:$AA$1780,0)),"") -> 9.2208706e-05 | K67: =IFERROR(INDEX('SKU Data'!$L$2:$L$1780,MATCH($A67,'SKU Data'!$AA$2:$AA$1780,0)),"") -> 0.0023737098 | M67: =Settings!$B$3 -> 0.030986151
A68: 6 | B68: =IFERROR(INDEX('SKU Data'!$A$2:$A$1780,MATCH($A68,'SKU Data'!$AA$2:$AA$1780,0)),"") -> DCA-01-00 | C68: =IFERROR(INDEX('SKU Data'!$B$2:$B$1780,MATCH($A68,'SKU Data'!$AA$2:$AA$1780,0)),"") -> Anniversary Designer Collection I | D68: =IFERROR(INDEX('SKU Data'!$D$2:$D$1780,MATCH($A68,'SKU Data'!$AA$2:$AA$1780,0)),"") -> Other (small prefixes) | E68: =IFERROR(INDEX('SKU Data'!$E$2:$E$1780,MATCH($A68,'SKU Data'!$AA$2:$AA$1780,0)),"") -> 41 | F68: =IFERROR(INDEX('SKU Data'!$F$2:$F$1780,MATCH($A68,'SKU Data'!$AA$2:$AA$1780,0)),"") -> 5 | G68: =IFERROR(INDEX('SKU Data'!$J$2:$J$1780,MATCH($A68,'SKU Data'!$AA$2:$AA$1780,0)),"") -> 0.12195122 | H68: =IFERROR(INDEX('SKU Data'!$H$2:$H$1780,MATCH($A68,'SKU Data'!$AA$2:$AA$1780,0)),"") -> 381.59 | I68: =IFERROR(INDEX('SKU Data'!$K$2:$K$1780,MATCH($A68,'SKU Data'!$AA$2:$AA$1780,0)),"") -> 0.11925284 | J68: =IFERROR(INDEX('SKU Data'!$M$2:$M$1780,MATCH($A68,'SKU Data'!$AA$2:$AA$1780,0)),"") -> 2.9624511e-05 | K68: =IFERROR(INDEX('SKU Data'!$L$2:$L$1780,MATCH($A68,'SKU Data'!$AA$2:$AA$1780,0)),"") -> 0.00076261771 | M68: =Settings!$B$3 -> 0.030986151
A69: 7 | B69: =IFERROR(INDEX('SKU Data'!$A$2:$A$1780,MATCH($A69,'SKU Data'!$AA$2:$AA$1780,0)),"") -> AU100-545 | C69: =IFERROR(INDEX('SKU Data'!$B$2:$B$1780,MATCH($A69,'SKU Data'!$AA$2:$AA$1780,0)),"") -> Gentle Thoughts Spray | D69: =IFERROR(INDEX('SKU Data'!$D$2:$D$1780,MATCH($A69,'SKU Data'!$AA$2:$AA$1780,0)),"") -> AU | E69: =IFERROR(INDEX('SKU Data'!$E$2:$E$1780,MATCH($A69,'SKU Data'!$AA$2:$AA$1780,0)),"") -> 128 | F69: =IFERROR(INDEX('SKU Data'!$F$2:$F$1780,MATCH($A69,'SKU Data'!$AA$2:$AA$1780,0)),"") -> 15 | G69: =IFERROR(INDEX('SKU Data'!$J$2:$J$1780,MATCH($A69,'SKU Data'!$AA$2:$AA$1780,0)),"") -> 0.1171875 | H69: =IFERROR(INDEX('SKU Data'!$H$2:$H$1780,MATCH($A69,'SKU Data'!$AA$2:$AA$1780,0)),"") -> 2729.11 | I69: =IFERROR(INDEX('SKU Data'!$K$2:$K$1780,MATCH($A69,'SKU Data'!$AA$2:$AA$1780,0)),"") -> 0.10651399 | J69: =IFERROR(INDEX('SKU Data'!$M$2:$M$1780,MATCH($A69,'SKU Data'!$AA$2:$AA$1780,0)),"") -> 0.00021187282 | K69: =IFERROR(INDEX('SKU Data'!$L$2:$L$1780,MATCH($A69,'SKU Data'!$AA$2:$AA$1780,0)),"") -> 0.0054541985 | M69: =Settings!$B$3 -> 0.030986151
A70: 8 | B70: =IFERROR(INDEX('SKU Data'!$A$2:$A$1780,MATCH($A70,'SKU Data'!$AA$2:$AA$1780,0)),"") -> GF60-10 | C70: =IFERROR(INDEX('SKU Data'!$B$2:$B$1780,MATCH($A70,'SKU Data'!$AA$2:$AA$1780,0)),"") -> Gorgeous Gerberas | D70: =IFERROR(INDEX('SKU Data'!$D$2:$D$1780,MATCH($A70,'SKU Data'!$AA$2:$AA$1780,0)),"") -> GF | E70: =IFERROR(INDEX('SKU Data'!$E$2:$E$1780,MATCH($A70,'SKU Data'!$AA$2:$AA$1780,0)),"") -> 77 | F70: =IFERROR(INDEX('SKU Data'!$F$2:$F$1780,MATCH($A70,'SKU Data'!$AA$2:$AA$1780,0)),"") -> 9 | G70: =IFERROR(INDEX('SKU Data'!$J$2:$J$1780,MATCH($A70,'SKU Data'!$AA$2:$AA$1780,0)),"") -> 0.11688312 | H70: =IFERROR(INDEX('SKU Data'!$H$2:$H$1780,MATCH($A70,'SKU Data'!$AA$2:$AA$1780,0)),"") -> 417.6 | I70: =IFERROR(INDEX('SKU Data'!$K$2:$K$1780,MATCH($A70,'SKU Data'!$AA$2:$AA$1780,0)),"") -> 0.11103843 | J70: =IFERROR(INDEX('SKU Data'!$M$2:$M$1780,MATCH($A70,'SKU Data'!$AA$2:$AA$1780,0)),"") -> 3.2420126e-05 | K70: =IFERROR(INDEX('SKU Data'!$L$2:$L$1780,MATCH($A70,'SKU Data'!$AA$2:$AA$1780,0)),"") -> 0.00083458464 | M70: =Settings!$B$3 -> 0.030986151
A71: 9 | B71: =IFERROR(INDEX('SKU Data'!$A$2:$A$1780,MATCH($A71,'SKU Data'!$AA$2:$AA$1780,0)),"") -> AU189-01 | C71: =IFERROR(INDEX('SKU Data'!$B$2:$B$1780,MATCH($A71,'SKU Data'!$AA$2:$AA$1780,0)),"") -> Classic Sympathy Wreath | D71: =IFERROR(INDEX('SKU Data'!$D$2:$D$1780,MATCH($A71,'SKU Data'!$AA$2:$AA$1780,0)),"") -> AU | E71: =IFERROR(INDEX('SKU Data'!$E$2:$E$1780,MATCH($A71,'SKU Data'!$AA$2:$AA$1780,0)),"") -> 97 | F71: =IFERROR(INDEX('SKU Data'!$F$2:$F$1780,MATCH($A71,'SKU Data'!$AA$2:$AA$1780,0)),"") -> 11 | G71: =IFERROR(INDEX('SKU Data'!$J$2:$J$1780,MATCH($A71,'SKU Data'!$AA$2:$AA$1780,0)),"") -> 0.11340206 | H71: =IFERROR(INDEX('SKU Data'!$H$2:$H$1780,MATCH($A71,'SKU Data'!$AA$2:$AA$1780,0)),"") -> 2932.31 | I71: =IFERROR(INDEX('SKU Data'!$K$2:$K$1780,MATCH($A71,'SKU Data'!$AA$2:$AA$1780,0)),"") -> 0.10250642 | J71: =IFERROR(INDEX('SKU Data'!$M$2:$M$1780,MATCH($A71,'SKU Data'!$AA$2:$AA$1780,0)),"") -> 0.00022764813 | K71: =IFERROR(INDEX('SKU Data'!$L$2:$L$1780,MATCH($A71,'SKU Data'!$AA$2:$AA$1780,0)),"") -> 0.0058602991 | M71: =Settings!$B$3 -> 0.030986151
A72: 10 | B72: =IFERROR(INDEX('SKU Data'!$A$2:$A$1780,MATCH($A72,'SKU Data'!$AA$2:$AA$1780,0)),"") -> RP-10 | C72: =IFERROR(INDEX('SKU Data'!$B$2:$B$1780,MATCH($A72,'SKU Data'!$AA$2:$AA$1780,0)),"") -> Vase and Card Combo | D72: =IFERROR(INDEX('SKU Data'!$D$2:$D$1780,MATCH($A72,'SKU Data'!$AA$2:$AA$1780,0)),"") -> RP | E72: =IFERROR(INDEX('SKU Data'!$E$2:$E$1780,MATCH($A72,'SKU Data'!$AA$2:$AA$1780,0)),"") -> 54 | F72: =IFERROR(INDEX('SKU Data'!$F$2:$F$1780,MATCH($A72,'SKU Data'!$AA$2:$AA$1780,0)),"") -> 6 | G72: =IFERROR(INDEX('SKU Data'!$J$2:$J$1780,MATCH($A72,'SKU Data'!$AA$2:$AA$1780,0)),"") -> 0.11111111 | H72: =IFERROR(INDEX('SKU Data'!$H$2:$H$1780,MATCH($A72,'SKU Data'!$AA$2:$AA$1780,0)),"") -> 70.62 | I72: =IFERROR(INDEX('SKU Data'!$K$2:$K$1780,MATCH($A72,'SKU Data'!$AA$2:$AA$1780,0)),"") -> 0.11008917 | J72: =IFERROR(INDEX('SKU Data'!$M$2:$M$1780,MATCH($A72,'SKU Data'!$AA$2:$AA$1780,0)),"") -> 5.4825413e-06 | K72: =IFERROR(INDEX('SKU Data'!$L$2:$L$1780,MATCH($A72,'SKU Data'!$AA$2:$AA$1780,0)),"") -> 0.00014113594 | M72: =Settings!$B$3 -> 0.030986151
A73: 11 | B73: =IFERROR(INDEX('SKU Data'!$A$2:$A$1780,MATCH($A73,'SKU Data'!$AA$2:$AA$1780,0)),"") -> GF10-01 | C73: =IFERROR(INDEX('SKU Data'!$B$2:$B$1780,MATCH($A73,'SKU Data'!$AA$2:$AA$1780,0)),"") -> Half Dozen Long Stem Red Roses | D73: =IFERROR(INDEX('SKU Data'!$D$2:$D$1780,MATCH($A73,'SKU Data'!$AA$2:$AA$1780,0)),"") -> GF | E73: =IFERROR(INDEX('SKU Data'!$E$2:$E$1780,MATCH($A73,'SKU Data'!$AA$2:$AA$1780,0)),"") -> 38 | F73: =IFERROR(INDEX('SKU Data'!$F$2:$F$1780,MATCH($A73,'SKU Data'!$AA$2:$AA$1780,0)),"") -> 4 | G73: =IFERROR(INDEX('SKU Data'!$J$2:$J$1780,MATCH($A73,'SKU Data'!$AA$2:$AA$1780,0)),"") -> 0.10526316 | H73: =IFERROR(INDEX('SKU Data'!$H$2:$H$1780,MATCH($A73,'SKU Data'!$AA$2:$AA$1780,0)),"") -> 276.64 | I73: =IFERROR(INDEX('SKU Data'!$K$2:$K$1780,MATCH($A73,'SKU Data'!$AA$2:$AA$1780,0)),"") -> 0.10466102 | J73: =IFERROR(INDEX('SKU Data'!$M$2:$M$1780,MATCH($A73,'SKU Data'!$AA$2:$AA$1780,0)),"") -> 2.147678e-05 | K73: =IFERROR(INDEX('SKU Data'!$L$2:$L$1780,MATCH($A73,'SKU Data'!$AA$2:$AA$1780,0)),"") -> 0.00055287236 | M73: =Settings!$B$3 -> 0.030986151
A74: 12 | B74: =IFERROR(INDEX('SKU Data'!$A$2:$A$1780,MATCH($A74,'SKU Data'!$AA$2:$AA$1780,0)),"") -> AU11-97 | C74: =IFERROR(INDEX('SKU Data'!$B$2:$B$1780,MATCH($A74,'SKU Data'!$AA$2:$AA$1780,0)),"") -> Premium White and Red Roses | D74: =IFERROR(INDEX('SKU Data'!$D$2:$D$1780,MATCH($A74,'SKU Data'!$AA$2:$AA$1780,0)),"") -> AU | E74: =IFERROR(INDEX('SKU Data'!$E$2:$E$1780,MATCH($A74,'SKU Data'!$AA$2:$AA$1780,0)),"") -> 115 | F74: =IFERROR(INDEX('SKU Data'!$F$2:$F$1780,MATCH($A74,'SKU Data'!$AA$2:$AA$1780,0)),"") -> 12 | G74: =IFERROR(INDEX('SKU Data'!$J$2:$J$1780,MATCH($A74,'SKU Data'!$AA$2:$AA$1780,0)),"") -> 0.10434783 | H74: =IFERROR(INDEX('SKU Data'!$H$2:$H$1780,MATCH($A74,'SKU Data'!$AA$2:$AA$1780,0)),"") -> 2215.18 | I74: =IFERROR(INDEX('SKU Data'!$K$2:$K$1780,MATCH($A74,'SKU Data'!$AA$2:$AA$1780,0)),"") -> 0.10043817 | J74: =IFERROR(INDEX('SKU Data'!$M$2:$M$1780,MATCH($A74,'SKU Data'!$AA$2:$AA$1780,0)),"") -> 0.00017197417 | K74: =IFERROR(INDEX('SKU Data'!$L$2:$L$1780,MATCH($A74,'SKU Data'!$AA$2:$AA$1780,0)),"") -> 0.0044270958 | M74: =Settings!$B$3 -> 0.030986151
... A87: 25 | B87: =IFERROR(INDEX('SKU Data'!$A$2:$A$1780,MATCH($A87,'SKU Data'!$AA$2:$AA$1780,0)),"") -> RP02-50 | C87: =IFERROR(INDEX('SKU Data'!$B$2:$B$1780,MATCH($A87,'SKU Data'!$AA$2:$AA$1780,0)),"") -> Blue Vase | D87: =IFERROR(INDEX('SKU Data'!$D$2:$D$1780,MATCH($A87,'SKU Data'!$AA$2:$AA$1780,0)),"") -> RP | E87: =IFERROR(INDEX('SKU Data'!$E$2:$E$1780,MATCH($A87,'SKU Data'!$AA$2:$AA$1780,0)),"") -> 406 | F87: =IFERROR(INDEX('SKU Data'!$F$2:$F$1780,MATCH($A87,'SKU Data'!$AA$2:$AA$1780,0)),"") -> 35 | G87: =IFERROR(INDEX('SKU Data'!$J$2:$J$1780,MATCH($A87,'SKU Data'!$AA$2:$AA$1780,0)),"") -> 0.086206897 | H87: =IFERROR(INDEX('SKU Data'!$H$2:$H$1780,MATCH($A87,'SKU Data'!$AA$2:$AA$1780,0)),"") -> 358.96 | I87: =IFERROR(INDEX('SKU Data'!$K$2:$K$1780,MATCH($A87,'SKU Data'!$AA$2:$AA$1780,0)),"") -> 0.081392027 | J87: =IFERROR(INDEX('SKU Data'!$M$2:$M$1780,MATCH($A87,'SKU Data'!$AA$2:$AA$1780,0)),"") -> 2.7867644e-05 | K87: =IFERROR(INDEX('SKU Data'!$L$2:$L$1780,MATCH($A87,'SKU Data'!$AA$2:$AA$1780,0)),"") -> 0.00071739105 | M87: =Settings!$B$3 -> 0.030986151

Sheet Brands
A1: Brands / SKU families - where refunds concentrate
A2: Sorted by refund $ at build time. Numbers are live SUMIFS on SKU Data (so Brand Map edits flow through). Comments are analyst notes written from the data at export date.
A4: Brand / family | B4: # SKUs | C4: Qty ordered | D4: Refunded units | E4: Gross sales $ | F4: Refund $ | G4: Refund rate (units) | H4: Refund rate ($ own gross) | I4: % of total refund $ | J4: % of total revenue | K4: Rate vs baseline | L4: z-score | M4: Flag | N4: Comment 1 | O4: Comment 2 | P4: Comment 3 | Q4: Baseline rate
A5: AU | B5: =COUNTIF('SKU Data'!$D$2:$D$1780,$A5) -> 663 | C5: =SUMIFS('SKU Data'!$E$2:$E$1780,'SKU Data'!$D$2:$D$1780,$A5) -> 34789 | D5: =SUMIFS('SKU Data'!$F$2:$F$1780,'SKU Data'!$D$2:$D$1780,$A5) -> 1495 | E5: =SUMIFS('SKU Data'!$G$2:$G$1780,'SKU Data'!$D$2:$D$1780,$A5) -> 3320223.9 | F5: =SUMIFS('SKU Data'!$H$2:$H$1780,'SKU Data'!$D$2:$D$1780,$A5) -> 140542.79 | G5: =IF(C5>0,D5/C5,0) -> 0.042973354 | H5: =IF(E5>0,F5/E5,0) -> 0.042329311 | I5: =F5/Settings!$B$16 -> 0.28087848 | J5: =F5/Settings!$B$20 -> 0.010910955 | K5: =G5/Settings!$B$3 -> 1.3868568 | L5: =IF(C5>0,(D5-C5*Settings!$B$3)/SQRT(C5*Settings!$B$3*(1-Settings!$B$3)),0) -> 12.90298 | M5: =IF(AND(C5>=Settings!$B$4,D5>=Settings!$B$5,L5>=Settings!$B$6),"HIGH RATE",IF(AND(C5>=Settings!$B$4,L5<=-Settings!$B$6),"BEST-IN-CLASS","")) -> HIGH RATE | N5: Refund rate 4.3% vs 3.1% portfolio (1.4x); family = 28% of SKU-attributed refund $ on 26% of gross sales. | O5: Concentration: top 3 SKUs = 20% of family refunds (AU11-43, AU112-10, AU222-80). | P5: Attention: 18 SKU(s) statistically above baseline; worst = AU0511-17 (Summer Blooms) at 6.2% on 1,560 units. | Q5: =Settings!$B$3 -> 0.030986151
A6: AUMJ | B6: =COUNTIF('SKU Data'!$D$2:$D$1780,$A6) -> 179 | C6: =SUMIFS('SKU Data'!$E$2:$E$1780,'SKU Data'!$D$2:$D$1780,$A6) -> 27140 | D6: =SUMIFS('SKU Data'!$F$2:$F$1780,'SKU Data'!$D$2:$D$1780,$A6) -> 1290 | E6: =SUMIFS('SKU Data'!$G$2:$G$1780,'SKU Data'!$D$2:$D$1780,$A6) -> 2546998.7 | F6: =SUMIFS('SKU Data'!$H$2:$H$1780,'SKU Data'!$D$2:$D$1780,$A6) -> 116048.49 | G6: =IF(C6>0,D6/C6,0) -> 0.047531319 | H6: =IF(E6>0,F6/E6,0) -> 0.045562838 | I6: =F6/Settings!$B$16 -> 0.23192598 | J6: =F6/Settings!$B$20 -> 0.0090093549 | K6: =G6/Settings!$B$3 -> 1.5339536 | L6: =IF(C6>0,(D6-C6*Settings!$B$3)/SQRT(C6*Settings!$B$3*(1-Settings!$B$3)),0) -> 15.729948 | M6: =IF(AND(C6>=Settings!$B$4,D6>=Settings!$B$5,L6>=Settings!$B$6),"HIGH RATE",IF(AND(C6>=Settings!$B$4,L6<=-Settings!$B$6),"BEST-IN-CLASS","")) -> HIGH RATE | N6: Refund rate 4.8% vs 3.1% portfolio (1.5x); family = 23% of SKU-attributed refund $ on 20% of gross sales. | O6: Concentration: top 3 SKUs = 47% of family refunds (AUMJ-NW-005, AUMJ-NW-017, AUMJ-NW-011). | P6: Attention: 9 SKU(s) statistically above baseline; worst = AUMJ-NW-005 (Native Flowers Bouquet in Mason ) at 5.3% on 6,304 units. | Q6: =Settings!$B$3 -> 0.030986151
A7: DC | B7: =COUNTIF('SKU Data'!$D$2:$D$1780,$A7) -> 17 | C7: =SUMIFS('SKU Data'!$E$2:$E$1780,'SKU Data'!$D$2:$D$1780,$A7) -> 8500 | D7: =SUMIFS('SKU Data'!$F$2:$F$1780,'SKU Data'!$D$2:$D$1780,$A7) -> 322 | E7: =SUMIFS('SKU Data'!$G$2:$G$1780,'SKU Data'!$D$2:$D$1780,$A7) -> 882818.48 | F7: =SUMIFS('SKU Data'!$H$2:$H$1780,'SKU Data'!$D$2:$D$1780,$A7) -> 30948.36 | G7: =IF(C7>0,D7/C7,0) -> 0.037882353 | H7: =IF(E7>0,F7/E7,0) -> 0.035056312 | I7: =F7/Settings!$B$16 -> 0.061851116 | J7: =F7/Settings!$B$20 -> 0.0024026574 | K7: =G7/Settings!$B$3 -> 1.2225575 | L7: =IF(C7>0,(D7-C7*Settings!$B$3)/SQRT(C7*Settings!$B$3*(1-Settings!$B$3)),0) -> 3.6691935 | M7: =IF(AND(C7>=Settings!$B$4,D7>=Settings!$B$5,L7>=Settings!$B$6),"HIGH RATE",IF(AND(C7>=Settings!$B$4,L7<=-Settings!$B$6),"BEST-IN-CLASS","")) -> HIGH RATE | N7: Refund rate 3.8% vs 3.1% portfolio (1.2x); family = 6% of SKU-attributed refund $ on 7% of gross sales. | O7: Concentration: top 3 SKUs = 63% of family refunds (DC-04S, DC-02S, DC-03S). | P7: Attention: 2 SKU(s) statistically above baseline; worst = DC-02B (Birthday Designer Collection II) at 8.7% on 322 units. | Q7: =Settings!$B$3 -> 0.030986151
A8: AUSGF | B8: =COUNTIF('SKU Data'!$D$2:$D$1780,$A8) -> 10 | C8: =SUMIFS('SKU Data'!$E$2:$E$1780,'SKU Data'!$D$2:$D$1780,$A8) -> 12849 | D8: =SUMIFS('SKU Data'!$F$2:$F$1780,'SKU Data'!$D$2:$D$1780,$A8) -> 461 | E8: =SUMIFS('SKU Data'!$G$2:$G$1780,'SKU Data'!$D$2:$D$1780,$A8) -> 846240.52 | F8: =SUMIFS('SKU Data'!$H$2:$H$1780,'SKU Data'!$D$2:$D$1780,$A8) -> 29423.06 | G8: =IF(C8>0,D8/C8,0) -> 0.035878278 | H8: =IF(E8>0,F8/E8,0) -> 0.034769146 | I8: =F8/Settings!$B$16 -> 0.058802764 | J8: =F8/Settings!$B$20 -> 0.0022842416 | K8: =G8/Settings!$B$3 -> 1.1578811 | L8: =IF(C8>0,(D8-C8*Settings!$B$3)/SQRT(C8*Settings!$B$3*(1-Settings!$B$3)),0) -> 3.2002478 | M8: =IF(AND(C8>=Settings!$B$4,D8>=Settings!$B$5,L8>=Settings!$B$6),"HIGH RATE",IF(AND(C8>=Settings!$B$4,L8<=-Settings!$B$6),"BEST-IN-CLASS","")) -> HIGH RATE | N8: Refund rate 3.6% vs 3.1% portfolio (1.2x); family = 6% of SKU-attributed refund $ on 7% of gross sales. | O8: Concentration: top 3 SKUs = 100% of family refunds (AUSGF16-115, AUSGF16-110, AUSGF16-115-REG). | P8: Attention: 1 SKU(s) statistically above baseline; worst = AUSGF16-115 (Delicate Elegance) at 3.6% on 11,490 units. | Q8: =Settings!$B$3 -> 0.030986151
A9: MJ | B9: =COUNTIF('SKU Data'!$D$2:$D$1780,$A9) -> 36 | C9: =SUMIFS('SKU Data'!$E$2:$E$1780,'SKU Data'!$D$2:$D$1780,$A9) -> 14780 | D9: =SUMIFS('SKU Data'!$F$2:$F$1780,'SKU Data'!$D$2:$D$1780,$A9) -> 456 | E9: =SUMIFS('SKU Data'!$G$2:$G$1780,'SKU Data'!$D$2:$D$1780,$A9) -> 922462.45 | F9: =SUMIFS('SKU Data'!$H$2:$H$1780,'SKU Data'!$D$2:$D$1780,$A9) -> 28997.07 | G9: =IF(C9>0,D9/C9,0) -> 0.030852503 | H9: =IF(E9>0,F9/E9,0) -> 0.031434418 | I9: =F9/Settings!$B$16 -> 0.057951411 | J9: =F9/Settings!$B$20 -> 0.0022511701 | K9: =G9/Settings!$B$3 -> 0.99568686 | L9: =IF(C9>0,(D9-C9*Settings!$B$3)/SQRT(C9*Settings!$B$3*(1-Settings!$B$3)),0) -> -0.093766971 | M9: =IF(AND(C9>=Settings!$B$4,D9>=Settings!$B$5,L9>=Settings!$B$6),"HIGH RATE",IF(AND(C9>=Settings!$B$4,L9<=-Settings!$B$6),"BEST-IN-CLASS","")) | N9: Refund rate 3.1% vs 3.1% portfolio (1.0x); family = 6% of SKU-attributed refund $ on 7% of gross sales. | O9: Concentration: top 3 SKUs = 54% of family refunds (MJ100-17, MJ100-04, MJ100-62). | P9: Attention: 2 SKU(s) statistically above baseline; worst = MJ100-17 (Thirty Blooms of Alstroemeria in) at 5.0% on 2,096 units. | Q9: =Settings!$B$3 -> 0.030986151
A10: GF | B10: =COUNTIF('SKU Data'!$D$2:$D$1780,$A10) -> 35 | C10: =SUMIFS('SKU Data'!$E$2:$E$1780,'SKU Data'!$D$2:$D$1780,$A10) -> 4520 | D10: =SUMIFS('SKU Data'!$F$2:$F$1780,'SKU Data'!$D$2:$D$1780,$A10) -> 234 | E10: =SUMIFS('SKU Data'!$G$2:$G$1780,'SKU Data'!$D$2:$D$1780,$A10) -> 437700.62 | F10: =SUMIFS('SKU Data'!$H$2:$H$1780,'SKU Data'!$D$2:$D$1780,$A10) -> 21202.65 | G10: =IF(C10>0,D10/C10,0) -> 0.051769912 | H10: =IF(E10>0,F10/E10,0) -> 0.048440987 | I10: =F10/Settings!$B$16 -> 0.042374057 | J10: =F10/Settings!$B$20 -> 0.001646055 | K10: =G10/Settings!$B$3 -> 1.6707435 | L10: =IF(C10>0,(D10-C10*Settings!$B$3)/SQRT(C10*Settings!$B$3*(1-Settings!$B$3)),0) -> 8.0638889 | M10: =IF(AND(C10>=Settings!$B$4,D10>=Settings!$B$5,L10>=Settings!$B$6),"HIGH RATE",IF(AND(C10>=Settings!$B$4,L10<=-Settings!$B$6),"BEST-IN-CLASS","")) -> HIGH RATE | N10: Refund rate 5.2% vs 3.1% portfolio (1.7x); family = 4% of SKU-attributed refund $ on 3% of gross sales. | O10: Concentration: top 3 SKUs = 77% of family refunds (GF16-100, GF16-110, GF16-105). | P10: Attention: 4 SKU(s) statistically above baseline; worst = GF16-100 (Blushing Elegance) at 5.3% on 1,333 units. | Q10: =Settings!$B$3 -> 0.030986151
A11: AURP | B11: =COUNTIF('SKU Data'!$D$2:$D$1780,$A11) -> 40 | C11: =SUMIFS('SKU Data'!$E$2:$E$1780,'SKU Data'!$D$2:$D$1780,$A11) -> 36296 | D11: =SUMIFS('SKU Data'!$F$2:$F$1780,'SKU Data'!$D$2:$D$1780,$A11) -> 1515 | E11: =SUMIFS('SKU Data'!$G$2:$G$1780,'SKU Data'!$D$2:$D$1780,$A11) -> 477893.02 | F11: =SUMIFS('SKU Data'!$H$2:$H$1780,'SKU Data'!$D$2:$D$1780,$A11) -> 17576.19 | G11: =IF(C11>0,D11/C11,0) -> 0.041740137 | H11: =IF(E11>0,F11/E11,0) -> 0.036778503 | I11: =F11/Settings!$B$16 -> 0.035126481 | J11: =F11/Settings!$B$20 -> 0.001364517 | K11: =G11/Settings!$B$3 -> 1.3470578 | L11: =IF(C11>0,(D11-C11*Settings!$B$3)/SQRT(C11*Settings!$B$3*(1-Settings!$B$3)),0) -> 11.823608 | M11: =IF(AND(C11>=Settings!$B$4,D11>=Settings!$B$5,L11>=Settings!$B$6),"HIGH RATE",IF(AND(C11>=Settings!$B$4,L11<=-Settings!$B$6),"BEST-IN-CLASS","")) -> HIGH RATE | N11: Refund rate 4.2% vs 3.1% portfolio (1.3x); family = 4% of SKU-attributed refund $ on 4% of gross sales. | O11: Concentration: top 3 SKUs = 36% of family refunds (AURP-B29, AURP-C02, AURP05). | P11: Attention: 8 SKU(s) statistically above baseline; worst = AURP04 (Glass Vase (Hand blown)) at 5.2% on 1,997 units. | Q11: =Settings!$B$3 -> 0.030986151
A12: AUSMJ | B12: =COUNTIF('SKU Data'!$D$2:$D$1780,$A12) -> 5 | C12: =SUMIFS('SKU Data'!$E$2:$E$1780,'SKU Data'!$D$2:$D$1780,$A12) -> 5043 | D12: =SUMIFS('SKU Data'!$F$2:$F$1780,'SKU Data'!$D$2:$D$1780,$A12) -> 205 | E12: =SUMIFS('SKU Data'!$G$2:$G$1780,'SKU Data'!$D$2:$D$1780,$A12) -> 355681.8 | F12: =SUMIFS('SKU Data'!$H$2:$H$1780,'SKU Data'!$D$2:$D$1780,$A12) -> 13788.78 | G12: =IF(C12>0,D12/C12,0) -> 0.040650407 | H12: =IF(E12>0,F12/E12,0) -> 0.038767179 | I12: =F12/Settings!$B$16 -> 0.027557241 | J12: =F12/Settings!$B$20 -> 0.0010704837 | K12: =G12/Settings!$B$3 -> 1.3118895 | L12: =IF(C12>0,(D12-C12*Settings!$B$3)/SQRT(C12*Settings!$B$3*(1-Settings!$B$3)),0) -> 3.9606282 | M12: =IF(AND(C12>=Settings!$B$4,D12>=Settings!$B$5,L12>=Settings!$B$6),"HIGH RATE",IF(AND(C12>=Settings!$B$4,L12<=-Settings!$B$6),"BEST-IN-CLASS","")) -> HIGH RATE | N12: Refund rate 4.1% vs 3.1% portfolio (1.3x); family = 3% of SKU-attributed refund $ on 3% of gross sales. | O12: Concentration: top 3 SKUs = 100% of family refunds (AUSMJ100-11, AUSMJ100-11-DEL, AUSMJ100-11-REG). | P12: Attention: 1 SKU(s) statistically above baseline; worst = AUSMJ100-11 (Breathtaking Blooms In Mason Jar) at 4.1% on 4,959 units. | Q12: =Settings!$B$3 -> 0.030986151
A13: AUDNAT | B13: =COUNTIF('SKU Data'!$D$2:$D$1780,$A13) -> 6 | C13: =SUMIFS('SKU Data'!$E$2:$E$1780,'SKU Data'!$D$2:$D$1780,$A13) -> 3058 | D13: =SUMIFS('SKU Data'!$F$2:$F$1780,'SKU Data'!$D$2:$D$1780,$A13) -> 133 | E13: =SUMIFS('SKU Data'!$G$2:$G$1780,'SKU Data'!$D$2:$D$1780,$A13) -> 336513.04 | F13: =SUMIFS('SKU Data'!$H$2:$H$1780,'SKU Data'!$D$2:$D$1780,$A13) -> 13631.3 | G13: =IF(C13>0,D13/C13,0) -> 0.043492479 | H13: =IF(E13>0,F13/E13,0) -> 0.040507494 | I13: =F13/Settings!$B$16 -> 0.027242514 | J13: =F13/Settings!$B$20 -> 0.0010582578 | K13: =G13/Settings!$B$3 -> 1.4036102 | L13: =IF(C13>0,(D13-C13*Settings!$B$3)/SQRT(C13*Settings!$B$3*(1-Settings!$B$3)),0) -> 3.9911655 | M13: =IF(AND(C13>=Settings!$B$4,D13>=Settings!$B$5,L13>=Settings!$B$6),"HIGH RATE",IF(AND(C13>=Settings!$B$4,L13<=-Settings!$B$6),"BEST-IN-CLASS","")) -> HIGH RATE | N13: Refund rate 4.3% vs 3.1% portfolio (1.4x); family = 3% of SKU-attributed refund $ on 3% of gross sales. | O13: Concentration: top 3 SKUs = 96% of family refunds (AUDNAT-02, AUDNAT-03, AUDNAT-01). | P13: Attention: 1 SKU(s) statistically above baseline; worst = AUDNAT-02 (Native Flowers Bouquet Designer ) at 4.8% on 1,279 units. | Q13: =Settings!$B$3 -> 0.030986151
A14: FYF | B14: =COUNTIF('SKU Data'!$D$2:$D$1780,$A14) -> 257 | C14: =SUMIFS('SKU Data'!$E$2:$E$1780,'SKU Data'!$D$2:$D$1780,$A14) -> 2106 | D14: =SUMIFS('SKU Data'!$F$2:$F$1780,'SKU Data'!$D$2:$D$1780,$A14) -> 92 | E14: =SUMIFS('SKU Data'!$G$2:$G$1780,'SKU Data'!$D$2:$D$1780,$A14) -> 199931.55 | F14: =SUMIFS('SKU Data'!$H$2:$H$1780,'SKU Data'!$D$2:$D$1780,$A14) -> 8627.52 | G14: =IF(C14>0,D14/C14,0) -> 0.04368471 | H14: =IF(E14>0,F14/E14,0) -> 0.043152369 | I14: =F14/Settings!$B$16 -> 0.017242327 | J14: =F14/Settings!$B$20 -> 0.00066979234 | K14: =G14/Settings!$B$3 -> 1.409814 | L14: =IF(C14>0,(D14-C14*Settings!$B$3)/SQRT(C14*Settings!$B$3*(1-Settings!$B$3)),0) -> 3.3630616 | M14: =IF(AND(C14>=Settings!$B$4,D14>=Settings!$B$5,L14>=Settings!$B$6),"HIGH RATE",IF(AND(C14>=Settings!$B$4,L14<=-Settings!$B$6),"BEST-IN-CLASS","")) -> HIGH RATE | N14: Refund rate 4.4% vs 3.1% portfolio (1.4x); family = 2% of SKU-attributed refund $ on 2% of gross sales. | O14: Concentration: top 3 SKUs = 17% of family refunds (FYF-what-a-treat-in-mason-jar-mixed-bouquet-C, FYF-beautiful-in-blue-bouquet-in-mason-jar-C, FYF-lavender-love-bouquet-C). | P14: No SKU statistically above baseline at current thresholds - watch only if volume grows. | Q14: =Settings!$B$3 -> 0.030986151
A15: AUBC | B15: =COUNTIF('SKU Data'!$D$2:$D$1780,$A15) -> 8 | C15: =SUMIFS('SKU Data'!$E$2:$E$1780,'SKU Data'!$D$2:$D$1780,$A15) -> 1395 | D15: =SUMIFS('SKU Data'!$F$2:$F$1780,'SKU Data'!$D$2:$D$1780,$A15) -> 71 | E15: =SUMIFS('SKU Data'!$G$2:$G$1780,'SKU Data'!$D$2:$D$1780,$A15) -> 173710.23 | F15: =SUMIFS('SKU Data'!$H$2:$H$1780,'SKU Data'!$D$2:$D$1780,$A15) -> 8477.07 | G15: =IF(C15>0,D15/C15,0) -> 0.050896057 | H15: =IF(E15>0,F15/E15,0) -> 0.048800062 | I15: =F15/Settings!$B$16 -> 0.016941649 | J15: =F15/Settings!$B$20 -> 0.00065811225 | K15: =G15/Settings!$B$3 -> 1.6425421 | L15: =IF(C15>0,(D15-C15*Settings!$B$3)/SQRT(C15*Settings!$B$3*(1-Settings!$B$3)),0) -> 4.2914841 | M15: =IF(AND(C15>=Settings!$B$4,D15>=Settings!$B$5,L15>=Settings!$B$6),"HIGH RATE",IF(AND(C15>=Settings!$B$4,L15<=-Settings!$B$6),"BEST-IN-CLASS","")) -> HIGH RATE | N15: Refund rate 5.1% vs 3.1% portfolio (1.6x); family = 2% of SKU-attributed refund $ on 1% of gross sales. | O15: Concentration: top 3 SKUs = 92% of family refunds (AUBC-02, AUBC-01, AUBC-04). | P15: Attention: 1 SKU(s) statistically above baseline; worst = AUBC-02 (Birthday Combo II) at 5.8% on 621 units. | Q15: =Settings!$B$3 -> 0.030986151
A16: Other (small prefixes) | B16: =COUNTIF('SKU Data'!$D$2:$D$1780,$A16) -> 220 | C16: =SUMIFS('SKU Data'!$E$2:$E$1780,'SKU Data'!$D$2:$D$1780,$A16) -> 5567 | D16: =SUMIFS('SKU Data'!$F$2:$F$1780,'SKU Data'!$D$2:$D$1780,$A16) -> 144 | E16: =SUMIFS('SKU Data'!$G$2:$G$1780,'SKU Data'!$D$2:$D$1780,$A16) -> 350462.46 | F16: =SUMIFS('SKU Data'!$H$2:$H$1780,'SKU Data'!$D$2:$D$1780,$A16) -> 8443.98 | G16: =IF(C16>0,D16/C16,0) -> 0.025866715 | H16: =IF(E16>0,F16/E16,0) -> 0.024093822 | I16: =F16/Settings!$B$16 -> 0.016875517 | J16: =F16/Settings!$B$20 -> 0.00065554332 | K16: =G16/Settings!$B$3 -> 0.83478308 | L16: =IF(C16>0,(D16-C16*Settings!$B$3)/SQRT(C16*Settings!$B$3*(1-Settings!$B$3)),0) -> -2.2043673 | M16: =IF(AND(C16>=Settings!$B$4,D16>=Settings!$B$5,L16>=Settings!$B$6),"HIGH RATE",IF(AND(C16>=Settings!$B$4,L16<=-Settings!$B$6),"BEST-IN-CLASS","")) | N16: Refund rate 2.6% vs 3.1% portfolio (0.8x); family = 2% of SKU-attributed refund $ on 3% of gross sales. | O16: Concentration: top 3 SKUs = 24% of family refunds (DCA-02-00, VDB-S1, AUG-12). | P16: Attention: 2 SKU(s) statistically above baseline; worst = DCA-02-00 (Anniversary Designer Collection ) at 21.1% on 38 units. | Q16: =Settings!$B$3 -> 0.030986151
... A44: Free / add-on / admin items | B44: =COUNTIF('SKU Data'!$D$2:$D$1780,$A44) -> 18 | C44: =SUMIFS('SKU Data'!$E$2:$E$1780,'SKU Data'!$D$2:$D$1780,$A44) -> 63216 | D44: =SUMIFS('SKU Data'!$F$2:$F$1780,'SKU Data'!$D$2:$D$1780,$A44) -> 0 | E44: =SUMIFS('SKU Data'!$G$2:$G$1780,'SKU Data'!$D$2:$D$1780,$A44) -> 56344.7 | F44: =SUMIFS('SKU Data'!$H$2:$H$1780,'SKU Data'!$D$2:$D$1780,$A44) -> 0 | G44: =IF(C44>0,D44/C44,0) -> 0 | H44: =IF(E44>0,F44/E44,0) -> 0 | I44: =F44/Settings!$B$16 -> 0 | J44: =F44/Settings!$B$20 -> 0 | K44: =G44/Settings!$B$3 -> 0 | L44: =IF(C44>0,(D44-C44*Settings!$B$3)/SQRT(C44*Settings!$B$3*(1-Settings!$B$3)),0) -> -44.960624 | M44: =IF(AND(C44>=Settings!$B$4,D44>=Settings!$B$5,L44>=Settings!$B$6),"HIGH RATE",IF(AND(C44>=Settings!$B$4,L44<=-Settings!$B$6),"BEST-IN-CLASS","")) -> BEST-IN-CLASS | N44: Refund rate 0.0% vs 3.1% portfolio (0.0x); family = 0% of SKU-attributed refund $ on 0% of gross sales. | O44: No refunds recorded. | P44: Best-in-class: significantly BELOW baseline - use as the benchmark for fixes elsewhere. | Q44: =Settings!$B$3 -> 0.030986151

Sheet B-AU
A1: Brand / family: AU
A3: Gross sales $ | B3: Refund $ | C3: Refunded units | D3: Refund rate (units) | E3: vs portfolio baseline | F3: % of total refund $
A4: =Brands!E5 -> 3320223.9 | B4: =Brands!F5 -> 140542.79 | C4: =Brands!D5 -> 1495 | D4: =Brands!G5 -> 0.042973354 | E4: =Brands!K5 -> 1.3868568 | F4: =Brands!I5 -> 0.28087848
A6: What to pay attention to
A7: 1. Refund rate 4.3% vs 3.1% portfolio (1.4x); family = 28% of SKU-attributed refund $ on 26% of gross sales.
A8: 2. Concentration: top 3 SKUs = 20% of family refunds (AU11-43, AU112-10, AU222-80).
A9: 3. Attention: 18 SKU(s) statistically above baseline; worst = AU0511-17 (Summer Blooms) at 6.2% on 1,560 units.
A11: Top 15 SKUs in this family by refund $
A12: SKU | B12: Product | C12: Qty ordered | D12: Refunded units | E12: Refund rate (units) | F12: Refund $ | G12: Refund rate ($) | H12: z-score | I12: Tier | J12: Flag
A13: AU11-43 | B13: =IFERROR(INDEX('SKU Data'!$B$2:$B$1780,MATCH($A13,'SKU Data'!$A$2:$A$1780,0)),"") -> Warm Embrace | C13: =IFERROR(INDEX('SKU Data'!$E$2:$E$1780,MATCH($A13,'SKU Data'!$A$2:$A$1780,0)),"") -> 2594 | D13: =IFERROR(INDEX('SKU Data'!$F$2:$F$1780,MATCH($A13,'SKU Data'!$A$2:$A$1780,0)),"") -> 129 | E13: =IFERROR(INDEX('SKU Data'!$J$2:$J$1780,MATCH($A13,'SKU Data'!$A$2:$A$1780,0)),"") -> 0.049730146 | F13: =IFERROR(INDEX('SKU Data'!$H$2:$H$1780,MATCH($A13,'SKU Data'!$A$2:$A$1780,0)),"") -> 11840.22 | G13: =IFERROR(INDEX('SKU Data'!$K$2:$K$1780,MATCH($A13,'SKU Data'!$A$2:$A$1780,0)),"") -> 0.047722296 | H13: =IFERROR(INDEX('SKU Data'!$O$2:$O$1780,MATCH($A13,'SKU Data'!$A$2:$A$1780,0)),"") -> 5.5093244 | I13: =IFERROR(INDEX('SKU Data'!$W$2:$W$1780,MATCH($A13,'SKU Data'!$A$2:$A$1780,0)),"") -> 1 - Fix first | J13: =IFERROR(INDEX('SKU Data'!$X$2:$X$1780,MATCH($A13,'SKU Data'!$A$2:$A$1780,0)),"") -> HIGH RATE
A14: AU112-10 | B14: =IFERROR(INDEX('SKU Data'!$B$2:$B$1780,MATCH($A14,'SKU Data'!$A$2:$A$1780,0)),"") -> Lavender Love | C14: =IFERROR(INDEX('SKU Data'!$E$2:$E$1780,MATCH($A14,'SKU Data'!$A$2:$A$1780,0)),"") -> 2208 | D14: =IFERROR(INDEX('SKU Data'!$F$2:$F$1780,MATCH($A14,'SKU Data'!$A$2:$A$1780,0)),"") -> 108 | E14: =IFERROR(INDEX('SKU Data'!$J$2:$J$1780,MATCH($A14,'SKU Data'!$A$2:$A$1780,0)),"") -> 0.048913043 | F14: =IFERROR(INDEX('SKU Data'!$H$2:$H$1780,MATCH($A14,'SKU Data'!$A$2:$A$1780,0)),"") -> 9388.55 | G14: =IFERROR(INDEX('SKU Data'!$K$2:$K$1780,MATCH($A14,'SKU Data'!$A$2:$A$1780,0)),"") -> 0.046067461 | H14: =IFERROR(INDEX('SKU Data'!$O$2:$O$1780,MATCH($A14,'SKU Data'!$A$2:$A$1780,0)),"") -> 4.8613371 | I14: =IFERROR(INDEX('SKU Data'!$W$2:$W$1780,MATCH($A14,'SKU Data'!$A$2:$A$1780,0)),"") -> 2 - Review | J14: =IFERROR(INDEX('SKU Data'!$X$2:$X$1780,MATCH($A14,'SKU Data'!$A$2:$A$1780,0)),"") -> HIGH RATE
A15: AU222-80 | B15: =IFERROR(INDEX('SKU Data'!$B$2:$B$1780,MATCH($A15,'SKU Data'!$A$2:$A$1780,0)),"") -> Wild Spirits | C15: =IFERROR(INDEX('SKU Data'!$E$2:$E$1780,MATCH($A15,'SKU Data'!$A$2:$A$1780,0)),"") -> 1727 | D15: =IFERROR(INDEX('SKU Data'!$F$2:$F$1780,MATCH($A15,'SKU Data'!$A$2:$A$1780,0)),"") -> 80 | E15: =IFERROR(INDEX('SKU Data'!$J$2:$J$1780,MATCH($A15,'SKU Data'!$A$2:$A$1780,0)),"") -> 0.046323104 | F15: =IFERROR(INDEX('SKU Data'!$H$2:$H$1780,MATCH($A15,'SKU Data'!$A$2:$A$1780,0)),"") -> 6215.17 | G15: =IFERROR(INDEX('SKU Data'!$K$2:$K$1780,MATCH($A15,'SKU Data'!$A$2:$A$1780,0)),"") -> 0.044132978 | H15: =IFERROR(INDEX('SKU Data'!$O$2:$O$1780,MATCH($A15,'SKU Data'!$A$2:$A$1780,0)),"") -> 3.6782093 | I15: =IFERROR(INDEX('SKU Data'!$W$2:$W$1780,MATCH($A15,'SKU Data'!$A$2:$A$1780,0)),"") -> 2 - Review | J15: =IFERROR(INDEX('SKU Data'!$X$2:$X$1780,MATCH($A15,'SKU Data'!$A$2:$A$1780,0)),"") -> HIGH RATE
A16: AU0511-17 | B16: =IFERROR(INDEX('SKU Data'!$B$2:$B$1780,MATCH($A16,'SKU Data'!$A$2:$A$1780,0)),"") -> Summer Blooms | C16: =IFERROR(INDEX('SKU Data'!$E$2:$E$1780,MATCH($A16,'SKU Data'!$A$2:$A$1780,0)),"") -> 1560 | D16: =IFERROR(INDEX('SKU Data'!$F$2:$F$1780,MATCH($A16,'SKU Data'!$A$2:$A$1780,0)),"") -> 97 | E16: =IFERROR(INDEX('SKU Data'!$J$2:$J$1780,MATCH($A16,'SKU Data'!$A$2:$A$1780,0)),"") -> 0.062179487 | F16: =IFERROR(INDEX('SKU Data'!$H$2:$H$1780,MATCH($A16,'SKU Data'!$A$2:$A$1780,0)),"") -> 5315.16 | G16: =IFERROR(INDEX('SKU Data'!$K$2:$K$1780,MATCH($A16,'SKU Data'!$A$2:$A$1780,0)),"") -> 0.060010493 | H16: =IFERROR(INDEX('SKU Data'!$O$2:$O$1780,MATCH($A16,'SKU Data'!$A$2:$A$1780,0)),"") -> 7.1100935 | I16: =IFERROR(INDEX('SKU Data'!$W$2:$W$1780,MATCH($A16,'SKU Data'!$A$2:$A$1780,0)),"") -> 1 - Fix first | J16: =IFERROR(INDEX('SKU Data'!$X$2:$X$1780,MATCH($A16,'SKU Data'!$A$2:$A$1780,0)),"") -> HIGH RATE
A17: AU11-10 | B17: =IFERROR(INDEX('SKU Data'!$B$2:$B$1780,MATCH($A17,'SKU Data'!$A$2:$A$1780,0)),"") -> Ten Long Stemmed Red Roses | C17: =IFERROR(INDEX('SKU Data'!$E$2:$E$1780,MATCH($A17,'SKU Data'!$A$2:$A$1780,0)),"") -> 651 | D17: =IFERROR(INDEX('SKU Data'!$F$2:$F$1780,MATCH($A17,'SKU Data'!$A$2:$A$1780,0)),"") -> 41 | E17: =IFERROR(INDEX('SKU Data'!$J$2:$J$1780,MATCH($A17,'SKU Data'!$A$2:$A$1780,0)),"") -> 0.062980031 | F17: =IFERROR(INDEX('SKU Data'!$H$2:$H$1780,MATCH($A17,'SKU Data'!$A$2:$A$1780,0)),"") -> 3718.19 | G17: =IFERROR(INDEX('SKU Data'!$K$2:$K$1780,MATCH($A17,'SKU Data'!$A$2:$A$1780,0)),"") -> 0.059146759 | H17: =IFERROR(INDEX('SKU Data'!$O$2:$O$1780,MATCH($A17,'SKU Data'!$A$2:$A$1780,0)),"") -> 4.7109511 | I17: =IFERROR(INDEX('SKU Data'!$W$2:$W$1780,MATCH($A17,'SKU Data'!$A$2:$A$1780,0)),"") -> 1 - Fix first | J17: =IFERROR(INDEX('SKU Data'!$X$2:$X$1780,MATCH($A17,'SKU Data'!$A$2:$A$1780,0)),"") -> HIGH RATE
A18: AU15-50 | B18: =IFERROR(INDEX('SKU Data'!$B$2:$B$1780,MATCH($A18,'SKU Data'!$A$2:$A$1780,0)),"") -> 50 Blooms of Peruvian Lilies | C18: =IFERROR(INDEX('SKU Data'!$E$2:$E$1780,MATCH($A18,'SKU Data'!$A$2:$A$1780,0)),"") -> 1158 | D18: =IFERROR(INDEX('SKU Data'!$F$2:$F$1780,MATCH($A18,'SKU Data'!$A$2:$A$1780,0)),"") -> 55 | E18: =IFERROR(INDEX('SKU Data'!$J$2:$J$1780,MATCH($A18,'SKU Data'!$A$2:$A$1780,0)),"") -> 0.047495682 | F18: =IFERROR(INDEX('SKU Data'!$H$2:$H$1780,MATCH($A18,'SKU Data'!$A$2:$A$1780,0)),"") -> 3653.51 | G18: =IFERROR(INDEX('SKU Data'!$K$2:$K$1780,MATCH($A18,'SKU Data'!$A$2:$A$1780,0)),"") -> 0.043086217 | H18: =IFERROR(INDEX('SKU Data'!$O$2:$O$1780,MATCH($A18,'SKU Data'!$A$2:$A$1780,0)),"") -> 3.2422031 | I18: =IFERROR(INDEX('SKU Data'!$W$2:$W$1780,MATCH($A18,'SKU Data'!$A$2:$A$1780,0)),"") -> 2 - Review | J18: =IFERROR(INDEX('SKU Data'!$X$2:$X$1780,MATCH($A18,'SKU Data'!$A$2:$A$1780,0)),"") -> HIGH RATE
A19: AU100-48 | B19: =IFERROR(INDEX('SKU Data'!$B$2:$B$1780,MATCH($A19,'SKU Data'!$A$2:$A$1780,0)),"") -> Pretty in Pink | C19: =IFERROR(INDEX('SKU Data'!$E$2:$E$1780,MATCH($A19,'SKU Data'!$A$2:$A$1780,0)),"") -> 598 | D19: =IFERROR(INDEX('SKU Data'!$F$2:$F$1780,MATCH($A19,'SKU Data'!$A$2:$A$1780,0)),"") -> 36 | E19: =IFERROR(INDEX('SKU Data'!$J$2:$J$1780,MATCH($A19,'SKU Data'!$A$2:$A$1780,0)),"") -> 0.060200669 | F19: =IFERROR(INDEX('SKU Data'!$H$2:$H$1780,MATCH($A19,'SKU Data'!$A$2:$A$1780,0)),"") -> 3306.37 | G19: =IFERROR(INDEX('SKU Data'!$K$2:$K$1780,MATCH($A19,'SKU Data'!$A$2:$A$1780,0)),"") -> 0.0569165 | H19: =IFERROR(INDEX('SKU Data'!$O$2:$O$1780,MATCH($A19,'SKU Data'!$A$2:$A$1780,0)),"") -> 4.1228782 | I19: =IFERROR(INDEX('SKU Data'!$W$2:$W$1780,MATCH($A19,'SKU Data'!$A$2:$A$1780,0)),"") -> 1 - Fix first | J19: =IFERROR(INDEX('SKU Data'!$X$2:$X$1780,MATCH($A19,'SKU Data'!$A$2:$A$1780,0)),"") -> HIGH RATE
A20: AU200-61 | B20: =IFERROR(INDEX('SKU Data'!$B$2:$B$1780,MATCH($A20,'SKU Data'!$A$2:$A$1780,0)),"") -> Country Roads | C20: =IFERROR(INDEX('SKU Data'!$E$2:$E$1780,MATCH($A20,'SKU Data'!$A$2:$A$1780,0)),"") -> 360 | D20: =IFERROR(INDEX('SKU Data'!$F$2:$F$1780,MATCH($A20,'SKU Data'!$A$2:$A$1780,0)),"") -> 25 | E20: =IFERROR(INDEX('SKU Data'!$J$2:$J$1780,MATCH($A20,'SKU Data'!$A$2:$A$1780,0)),"") -> 0.069444444 | F20: =IFERROR(INDEX('SKU Data'!$H$2:$H$1780,MATCH($A20,'SKU Data'!$A$2:$A$1780,0)),"") -> 3303.38 | G20: =IFERROR(INDEX('SKU Data'!$K$2:$K$1780,MATCH($A20,'SKU Data'!$A$2:$A$1780,0)),"") -> 0.069155547 | H20: =IFERROR(INDEX('SKU Data'!$O$2:$O$1780,MATCH($A20,'SKU Data'!$A$2:$A$1780,0)),"") -> 4.2110699 | I20: =IFERROR(INDEX('SKU Data'!$W$2:$W$1780,MATCH($A20,'SKU Data'!$A$2:$A$1780,0)),"") -> 1 - Fix first | J20: =IFERROR(INDEX('SKU Data'!$X$2:$X$1780,MATCH($A20,'SKU Data'!$A$2:$A$1780,0)),"") -> HIGH RATE
A21: AU1111-20 | B21: =IFERROR(INDEX('SKU Data'!$B$2:$B$1780,MATCH($A21,'SKU Data'!$A$2:$A$1780,0)),"") -> Half Dozen Red Roses | C21: =IFERROR(INDEX('SKU Data'!$E$2:$E$1780,MATCH($A21,'SKU Data'!$A$2:$A$1780,0)),"") -> 959 | D21: =IFERROR(INDEX('SKU Data'!$F$2:$F$1780,MATCH($A21,'SKU Data'!$A$2:$A$1780,0)),"") -> 46 | E21: =IFERROR(INDEX('SKU Data'!$J$2:$J$1780,MATCH($A21,'SKU Data'!$A$2:$A$1780,0)),"") -> 0.047966632 | F21: =IFERROR(INDEX('SKU Data'!$H$2:$H$1780,MATCH($A21,'SKU Data'!$A$2:$A$1780,0)),"") -> 3175.22 | G21: =IFERROR(INDEX('SKU Data'!$K$2:$K$1780,MATCH($A21,'SKU Data'!$A$2:$A$1780,0)),"") -> 0.046137652 | H21: =IFERROR(INDEX('SKU Data'!$O$2:$O$1780,MATCH($A21,'SKU Data'!$A$2:$A$1780,0)),"") -> 3.0346631 | I21: =IFERROR(INDEX('SKU Data'!$W$2:$W$1780,MATCH($A21,'SKU Data'!$A$2:$A$1780,0)),"") -> 2 - Review | J21: =IFERROR(INDEX('SKU Data'!$X$2:$X$1780,MATCH($A21,'SKU Data'!$A$2:$A$1780,0)),"") -> HIGH RATE
A22: AU112-12 | B22: =IFERROR(INDEX('SKU Data'!$B$2:$B$1780,MATCH($A22,'SKU Data'!$A$2:$A$1780,0)),"") -> Beautiful in Blue | C22: =IFERROR(INDEX('SKU Data'!$E$2:$E$1780,MATCH($A22,'SKU Data'!$A$2:$A$1780,0)),"") -> 495 | D22: =IFERROR(INDEX('SKU Data'!$F$2:$F$1780,MATCH($A22,'SKU Data'!$A$2:$A$1780,0)),"") -> 24 | E22: =IFERROR(INDEX('SKU Data'!$J$2:$J$1780,MATCH($A22,'SKU Data'!$A$2:$A$1780,0)),"") -> 0.048484848 | F22: =IFERROR(INDEX('SKU Data'!$H$2:$H$1780,MATCH($A22,'SKU Data'!$A$2:$A$1780,0)),"") -> 3157.91 | G22: =IFERROR(INDEX('SKU Data'!$K$2:$K$1780,MATCH($A22,'SKU Data'!$A$2:$A$1780,0)),"") -> 0.045499728 | H22: =IFERROR(INDEX('SKU Data'!$O$2:$O$1780,MATCH($A22,'SKU Data'!$A$2:$A$1780,0)),"") -> 2.2467746 | I22: =IFERROR(INDEX('SKU Data'!$W$2:$W$1780,MATCH($A22,'SKU Data'!$A$2:$A$1780,0)),"") -> 2 - Review | J22: =IFERROR(INDEX('SKU Data'!$X$2:$X$1780,MATCH($A22,'SKU Data'!$A$2:$A$1780,0)),"")
A23: AU189-01 | B23: =IFERROR(INDEX('SKU Data'!$B$2:$B$1780,MATCH($A23,'SKU Data'!$A$2:$A$1780,0)),"") -> Classic Sympathy Wreath | C23: =IFERROR(INDEX('SKU Data'!$E$2:$E$1780,MATCH($A23,'SKU Data'!$A$2:$A$1780,0)),"") -> 97 | D23: =IFERROR(INDEX('SKU Data'!$F$2:$F$1780,MATCH($A23,'SKU Data'!$A$2:$A$1780,0)),"") -> 11 | E23: =IFERROR(INDEX('SKU Data'!$J$2:$J$1780,MATCH($A23,'SKU Data'!$A$2:$A$1780,0)),"") -> 0.11340206 | F23: =IFERROR(INDEX('SKU Data'!$H$2:$H$1780,MATCH($A23,'SKU Data'!$A$2:$A$1780,0)),"") -> 2932.31 | G23: =IFERROR(INDEX('SKU Data'!$K$2:$K$1780,MATCH($A23,'SKU Data'!$A$2:$A$1780,0)),"") -> 0.10250642 | H23: =IFERROR(INDEX('SKU Data'!$O$2:$O$1780,MATCH($A23,'SKU Data'!$A$2:$A$1780,0)),"") -> 4.6843369 | I23: =IFERROR(INDEX('SKU Data'!$W$2:$W$1780,MATCH($A23,'SKU Data'!$A$2:$A$1780,0)),"") -> 1 - Fix first | J23: =IFERROR(INDEX('SKU Data'!$X$2:$X$1780,MATCH($A23,'SKU Data'!$A$2:$A$1780,0)),"") -> HIGH RATE
A24: AU100-545 | B24: =IFERROR(INDEX('SKU Data'!$B$2:$B$1780,MATCH($A24,'SKU Data'!$A$2:$A$1780,0)),"") -> Gentle Thoughts Spray | C24: =IFERROR(INDEX('SKU Data'!$E$2:$E$1780,MATCH($A24,'SKU Data'!$A$2:$A$1780,0)),"") -> 128 | D24: =IFERROR(INDEX('SKU Data'!$F$2:$F$1780,MATCH($A24,'SKU Data'!$A$2:$A$1780,0)),"") -> 15 | E24: =IFERROR(INDEX('SKU Data'!$J$2:$J$1780,MATCH($A24,'SKU Data'!$A$2:$A$1780,0)),"") -> 0.1171875 | F24: =IFERROR(INDEX('SKU Data'!$H$2:$H$1780,MATCH($A24,'SKU Data'!$A$2:$A$1780,0)),"") -> 2729.11 | G24: =IFERROR(INDEX('SKU Data'!$K$2:$K$1780,MATCH($A24,'SKU Data'!$A$2:$A$1780,0)),"") -> 0.10651399 | H24: =IFERROR(INDEX('SKU Data'!$O$2:$O$1780,MATCH($A24,'SKU Data'!$A$2:$A$1780,0)),"") -> 5.6282093 | I24: =IFERROR(INDEX('SKU Data'!$W$2:$W$1780,MATCH($A24,'SKU Data'!$A$2:$A$1780,0)),"") -> 1 - Fix first | J24: =IFERROR(INDEX('SKU Data'!$X$2:$X$1780,MATCH($A24,'SKU Data'!$A$2:$A$1780,0)),"") -> HIGH RATE
... A27: AU120-71 | B27: =IFERROR(INDEX('SKU Data'!$B$2:$B$1780,MATCH($A27,'SKU Data'!$A$2:$A$1780,0)),"") -> Sizzling Bouquet | C27: =IFERROR(INDEX('SKU Data'!$E$2:$E$1780,MATCH($A27,'SKU Data'!$A$2:$A$1780,0)),"") -> 342 | D27: =IFERROR(INDEX('SKU Data'!$F$2:$F$1780,MATCH($A27,'SKU Data'!$A$2:$A$1780,0)),"") -> 23 | E27: =IFERROR(INDEX('SKU Data'!$J$2:$J$1780,MATCH($A27,'SKU Data'!$A$2:$A$1780,0)),"") -> 0.067251462 | F27: =IFERROR(INDEX('SKU Data'!$H$2:$H$1780,MATCH($A27,'SKU Data'!$A$2:$A$1780,0)),"") -> 2216.75 | G27: =IFERROR(INDEX('SKU Data'!$K$2:$K$1780,MATCH($A27,'SKU Data'!$A$2:$A$1780,0)),"") -> 0.062221575 | H27: =IFERROR(INDEX('SKU Data'!$O$2:$O$1780,MATCH($A27,'SKU Data'!$A$2:$A$1780,0)),"") -> 3.8703982 | I27: =IFERROR(INDEX('SKU Data'!$W$2:$W$1780,MATCH($A27,'SKU Data'!$A$2:$A$1780,0)),"") -> 1 - Fix first | J27: =IFERROR(INDEX('SKU Data'!$X$2:$X$1780,MATCH($A27,'SKU Data'!$A$2:$A$1780,0)),"") -> HIGH RATE

Sheet B-AUMJ
A1: Brand / family: AUMJ
A3: Gross sales $ | B3: Refund $ | C3: Refunded units | D3: Refund rate (units) | E3: vs portfolio baseline | F3: % of total refund $
A4: =Brands!E6 -> 2546998.7 | B4: =Brands!F6 -> 116048.49 | C4: =Brands!D6 -> 1290 | D4: =Brands!G6 -> 0.047531319 | E4: =Brands!K6 -> 1.5339536 | F4: =Brands!I6 -> 0.23192598
A6: What to pay attention to
A7: 1. Refund rate 4.8% vs 3.1% portfolio (1.5x); family = 23% of SKU-attributed refund $ on 20% of gross sales.
A8: 2. Concentration: top 3 SKUs = 47% of family refunds (AUMJ-NW-005, AUMJ-NW-017, AUMJ-NW-011).
A9: 3. Attention: 9 SKU(s) statistically above baseline; worst = AUMJ-NW-005 (Native Flowers Bouquet in Mason ) at 5.3% on 6,304 units.
A11: Top 15 SKUs in this family by refund $
A12: SKU | B12: Product | C12: Qty ordered | D12: Refunded units | E12: Refund rate (units) | F12: Refund $ | G12: Refund rate ($) | H12: z-score | I12: Tier | J12: Flag
A13: AUMJ-NW-005 | B13: =IFERROR(INDEX('SKU Data'!$B$2:$B$1780,MATCH($A13,'SKU Data'!$A$2:$A$1780,0)),"") -> Native Flowers Bouquet in Mason Jar | C13: =IFERROR(INDEX('SKU Data'!$E$2:$E$1780,MATCH($A13,'SKU Data'!$A$2:$A$1780,0)),"") -> 6304 | D13: =IFERROR(INDEX('SKU Data'!$F$2:$F$1780,MATCH($A13,'SKU Data'!$A$2:$A$1780,0)),"") -> 335 | E13: =IFERROR(INDEX('SKU Data'!$J$2:$J$1780,MATCH($A13,'SKU Data'!$A$2:$A$1780,0)),"") -> 0.053140863 | F13: =IFERROR(INDEX('SKU Data'!$H$2:$H$1780,MATCH($A13,'SKU Data'!$A$2:$A$1780,0)),"") -> 30439.34 | G13: =IFERROR(INDEX('SKU Data'!$K$2:$K$1780,MATCH($A13,'SKU Data'!$A$2:$A$1780,0)),"") -> 0.051522022 | H13: =IFERROR(INDEX('SKU Data'!$O$2:$O$1780,MATCH($A13,'SKU Data'!$A$2:$A$1780,0)),"") -> 10.151387 | I13: =IFERROR(INDEX('SKU Data'!$W$2:$W$1780,MATCH($A13,'SKU Data'!$A$2:$A$1780,0)),"") -> 1 - Fix first | J13: =IFERROR(INDEX('SKU Data'!$X$2:$X$1780,MATCH($A13,'SKU Data'!$A$2:$A$1780,0)),"") -> HIGH RATE
A14: AUMJ-NW-017 | B14: =IFERROR(INDEX('SKU Data'!$B$2:$B$1780,MATCH($A14,'SKU Data'!$A$2:$A$1780,0)),"") -> Pastel Buttercup Bouquet in Mason Jar | C14: =IFERROR(INDEX('SKU Data'!$E$2:$E$1780,MATCH($A14,'SKU Data'!$A$2:$A$1780,0)),"") -> 3907 | D14: =IFERROR(INDEX('SKU Data'!$F$2:$F$1780,MATCH($A14,'SKU Data'!$A$2:$A$1780,0)),"") -> 172 | E14: =IFERROR(INDEX('SKU Data'!$J$2:$J$1780,MATCH($A14,'SKU Data'!$A$2:$A$1780,0)),"") -> 0.044023547 | F14: =IFERROR(INDEX('SKU Data'!$H$2:$H$1780,MATCH($A14,'SKU Data'!$A$2:$A$1780,0)),"") -> 14074.44 | G14: =IFERROR(INDEX('SKU Data'!$K$2:$K$1780,MATCH($A14,'SKU Data'!$A$2:$A$1780,0)),"") -> 0.040285179 | H14: =IFERROR(INDEX('SKU Data'!$O$2:$O$1780,MATCH($A14,'SKU Data'!$A$2:$A$1780,0)),"") -> 4.7028786 | I14: =IFERROR(INDEX('SKU Data'!$W$2:$W$1780,MATCH($A14,'SKU Data'!$A$2:$A$1780,0)),"") -> 2 - Review | J14: =IFERROR(INDEX('SKU Data'!$X$2:$X$1780,MATCH($A14,'SKU Data'!$A$2:$A$1780,0)),"") -> HIGH RATE
A15: AUMJ-NW-011 | B15: =IFERROR(INDEX('SKU Data'!$B$2:$B$1780,MATCH($A15,'SKU Data'!$A$2:$A$1780,0)),"") -> Best Birthday Ever Bouquet in Mason Jar | C15: =IFERROR(INDEX('SKU Data'!$E$2:$E$1780,MATCH($A15,'SKU Data'!$A$2:$A$1780,0)),"") -> 2143 | D15: =IFERROR(INDEX('SKU Data'!$F$2:$F$1780,MATCH($A15,'SKU Data'!$A$2:$A$1780,0)),"") -> 115 | E15: =IFERROR(INDEX('SKU Data'!$J$2:$J$1780,MATCH($A15,'SKU Data'!$A$2:$A$1780,0)),"") -> 0.053663089 | F15: =IFERROR(INDEX('SKU Data'!$H$2:$H$1780,MATCH($A15,'SKU Data'!$A$2:$A$1780,0)),"") -> 9879.04 | G15: =IFERROR(INDEX('SKU Data'!$K$2:$K$1780,MATCH($A15,'SKU Data'!$A$2:$A$1780,0)),"") -> 0.053490444 | H15: =IFERROR(INDEX('SKU Data'!$O$2:$O$1780,MATCH($A15,'SKU Data'!$A$2:$A$1780,0)),"") -> 6.058243 | I15: =IFERROR(INDEX('SKU Data'!$W$2:$W$1780,MATCH($A15,'SKU Data'!$A$2:$A$1780,0)),"") -> 1 - Fix first | J15: =IFERROR(INDEX('SKU Data'!$X$2:$X$1780,MATCH($A15,'SKU Data'!$A$2:$A$1780,0)),"") -> HIGH RATE
A16: AUMJ-NW-003 | B16: =IFERROR(INDEX('SKU Data'!$B$2:$B$1780,MATCH($A16,'SKU Data'!$A$2:$A$1780,0)),"") -> 50 Blooms of Surprise Bud Roses in Mason Jar | C16: =IFERROR(INDEX('SKU Data'!$E$2:$E$1780,MATCH($A16,'SKU Data'!$A$2:$A$1780,0)),"") -> 2769 | D16: =IFERROR(INDEX('SKU Data'!$F$2:$F$1780,MATCH($A16,'SKU Data'!$A$2:$A$1780,0)),"") -> 106 | E16: =IFERROR(INDEX('SKU Data'!$J$2:$J$1780,MATCH($A16,'SKU Data'!$A$2:$A$1780,0)),"") -> 0.038280968 | F16: =IFERROR(INDEX('SKU Data'!$H$2:$H$1780,MATCH($A16,'SKU Data'!$A$2:$A$1780,0)),"") -> 8978.84 | G16: =IFERROR(INDEX('SKU Data'!$K$2:$K$1780,MATCH($A16,'SKU Data'!$A$2:$A$1780,0)),"") -> 0.037401582 | H16: =IFERROR(INDEX('SKU Data'!$O$2:$O$1780,MATCH($A16,'SKU Data'!$A$2:$A$1780,0)),"") -> 2.215272 | I16: =IFERROR(INDEX('SKU Data'!$W$2:$W$1780,MATCH($A16,'SKU Data'!$A$2:$A$1780,0)),"") -> 2 - Review | J16: =IFERROR(INDEX('SKU Data'!$X$2:$X$1780,MATCH($A16,'SKU Data'!$A$2:$A$1780,0)),"")
A17: AUMJ-NW-019 | B17: =IFERROR(INDEX('SKU Data'!$B$2:$B$1780,MATCH($A17,'SKU Data'!$A$2:$A$1780,0)),"") -> Garden Party Bouquet in Mason Jar | C17: =IFERROR(INDEX('SKU Data'!$E$2:$E$1780,MATCH($A17,'SKU Data'!$A$2:$A$1780,0)),"") -> 1250 | D17: =IFERROR(INDEX('SKU Data'!$F$2:$F$1780,MATCH($A17,'SKU Data'!$A$2:$A$1780,0)),"") -> 74 | E17: =IFERROR(INDEX('SKU Data'!$J$2:$J$1780,MATCH($A17,'SKU Data'!$A$2:$A$1780,0)),"") -> 0.0592 | F17: =IFERROR(INDEX('SKU Data'!$H$2:$H$1780,MATCH($A17,'SKU Data'!$A$2:$A$1780,0)),"") -> 8226.91 | G17: =IFERROR(INDEX('SKU Data'!$K$2:$K$1780,MATCH($A17,'SKU Data'!$A$2:$A$1780,0)),"") -> 0.059694511 | H17: =IFERROR(INDEX('SKU Data'!$O$2:$O$1780,MATCH($A17,'SKU Data'!$A$2:$A$1780,0)),"") -> 5.7566329 | I17: =IFERROR(INDEX('SKU Data'!$W$2:$W$1780,MATCH($A17,'SKU Data'!$A$2:$A$1780,0)),"") -> 1 - Fix first | J17: =IFERROR(INDEX('SKU Data'!$X$2:$X$1780,MATCH($A17,'SKU Data'!$A$2:$A$1780,0)),"") -> HIGH RATE
A18: AUMJ-NW-030 | B18: =IFERROR(INDEX('SKU Data'!$B$2:$B$1780,MATCH($A18,'SKU Data'!$A$2:$A$1780,0)),"") -> Cloud Nine Bouquet in Mason Jar | C18: =IFERROR(INDEX('SKU Data'!$E$2:$E$1780,MATCH($A18,'SKU Data'!$A$2:$A$1780,0)),"") -> 1600 | D18: =IFERROR(INDEX('SKU Data'!$F$2:$F$1780,MATCH($A18,'SKU Data'!$A$2:$A$1780,0)),"") -> 55 | E18: =IFERROR(INDEX('SKU Data'!$J$2:$J$1780,MATCH($A18,'SKU Data'!$A$2:$A$1780,0)),"") -> 0.034375 | F18: =IFERROR(INDEX('SKU Data'!$H$2:$H$1780,MATCH($A18,'SKU Data'!$A$2:$A$1780,0)),"") -> 5585.45 | G18: =IFERROR(INDEX('SKU Data'!$K$2:$K$1780,MATCH($A18,'SKU Data'!$A$2:$A$1780,0)),"") -> 0.032683827 | H18: =IFERROR(INDEX('SKU Data'!$O$2:$O$1780,MATCH($A18,'SKU Data'!$A$2:$A$1780,0)),"") -> 0.78228209 | I18: =IFERROR(INDEX('SKU Data'!$W$2:$W$1780,MATCH($A18,'SKU Data'!$A$2:$A$1780,0)),"") -> 3 - Monitor | J18: =IFERROR(INDEX('SKU Data'!$X$2:$X$1780,MATCH($A18,'SKU Data'!$A$2:$A$1780,0)),"")
A19: AUMJ-NW-008 | B19: =IFERROR(INDEX('SKU Data'!$B$2:$B$1780,MATCH($A19,'SKU Data'!$A$2:$A$1780,0)),"") -> Golden Hour Bouquet in Mason Jar | C19: =IFERROR(INDEX('SKU Data'!$E$2:$E$1780,MATCH($A19,'SKU Data'!$A$2:$A$1780,0)),"") -> 503 | D19: =IFERROR(INDEX('SKU Data'!$F$2:$F$1780,MATCH($A19,'SKU Data'!$A$2:$A$1780,0)),"") -> 40 | E19: =IFERROR(INDEX('SKU Data'!$J$2:$J$1780,MATCH($A19,'SKU Data'!$A$2:$A$1780,0)),"") -> 0.079522863 | F19: =IFERROR(INDEX('SKU Data'!$H$2:$H$1780,MATCH($A19,'SKU Data'!$A$2:$A$1780,0)),"") -> 3723.61 | G19: =IFERROR(INDEX('SKU Data'!$K$2:$K$1780,MATCH($A19,'SKU Data'!$A$2:$A$1780,0)),"") -> 0.075984613 | H19: =IFERROR(INDEX('SKU Data'!$O$2:$O$1780,MATCH($A19,'SKU Data'!$A$2:$A$1780,0)),"") -> 6.28211 | I19: =IFERROR(INDEX('SKU Data'!$W$2:$W$1780,MATCH($A19,'SKU Data'!$A$2:$A$1780,0)),"") -> 1 - Fix first | J19: =IFERROR(INDEX('SKU Data'!$X$2:$X$1780,MATCH($A19,'SKU Data'!$A$2:$A$1780,0)),"") -> HIGH RATE
A20: AUMJ-NW-025 | B20: =IFERROR(INDEX('SKU Data'!$B$2:$B$1780,MATCH($A20,'SKU Data'!$A$2:$A$1780,0)),"") -> New Baby Girl Bouquet in Mason Jar | C20: =IFERROR(INDEX('SKU Data'!$E$2:$E$1780,MATCH($A20,'SKU Data'!$A$2:$A$1780,0)),"") -> 852 | D20: =IFERROR(INDEX('SKU Data'!$F$2:$F$1780,MATCH($A20,'SKU Data'!$A$2:$A$1780,0)),"") -> 34 | E20: =IFERROR(INDEX('SKU Data'!$J$2:$J$1780,MATCH($A20,'SKU Data'!$A$2:$A$1780,0)),"") -> 0.039906103 | F20: =IFERROR(INDEX('SKU Data'!$H$2:$H$1780,MATCH($A20,'SKU Data'!$A$2:$A$1780,0)),"") -> 3293.44 | G20: =IFERROR(INDEX('SKU Data'!$K$2:$K$1780,MATCH($A20,'SKU Data'!$A$2:$A$1780,0)),"") -> 0.036090836 | H20: =IFERROR(INDEX('SKU Data'!$O$2:$O$1780,MATCH($A20,'SKU Data'!$A$2:$A$1780,0)),"") -> 1.5025659 | I20: =IFERROR(INDEX('SKU Data'!$W$2:$W$1780,MATCH($A20,'SKU Data'!$A$2:$A$1780,0)),"") -> 3 - Monitor | J20: =IFERROR(INDEX('SKU Data'!$X$2:$X$1780,MATCH($A20,'SKU Data'!$A$2:$A$1780,0)),"")
A21: AUMJ-NW-007 | B21: =IFERROR(INDEX('SKU Data'!$B$2:$B$1780,MATCH($A21,'SKU Data'!$A$2:$A$1780,0)),"") -> Pick-Me-Up Bouquet in Mason Jar | C21: =IFERROR(INDEX('SKU Data'!$E$2:$E$1780,MATCH($A21,'SKU Data'!$A$2:$A$1780,0)),"") -> 789 | D21: =IFERROR(INDEX('SKU Data'!$F$2:$F$1780,MATCH($A21,'SKU Data'!$A$2:$A$1780,0)),"") -> 48 | E21: =IFERROR(INDEX('SKU Data'!$J$2:$J$1780,MATCH($A21,'SKU Data'!$A$2:$A$1780,0)),"") -> 0.060836502 | F21: =IFERROR(INDEX('SKU Data'!$H$2:$H$1780,MATCH($A21,'SKU Data'!$A$2:$A$1780,0)),"") -> 3223.36 | G21: =IFERROR(INDEX('SKU Data'!$K$2:$K$1780,MATCH($A21,'SKU Data'!$A$2:$A$1780,0)),"") -> 0.057669221 | H21: =IFERROR(INDEX('SKU Data'!$O$2:$O$1780,MATCH($A21,'SKU Data'!$A$2:$A$1780,0)),"") -> 4.8388163 | I21: =IFERROR(INDEX('SKU Data'!$W$2:$W$1780,MATCH($A21,'SKU Data'!$A$2:$A$1780,0)),"") -> 1 - Fix first | J21: =IFERROR(INDEX('SKU Data'!$X$2:$X$1780,MATCH($A21,'SKU Data'!$A$2:$A$1780,0)),"") -> HIGH RATE
A22: AUMJ-NW-028 | B22: =IFERROR(INDEX('SKU Data'!$B$2:$B$1780,MATCH($A22,'SKU Data'!$A$2:$A$1780,0)),"") -> Mellow Yellow Bouquet in Mason Jar | C22: =IFERROR(INDEX('SKU Data'!$E$2:$E$1780,MATCH($A22,'SKU Data'!$A$2:$A$1780,0)),"") -> 373 | D22: =IFERROR(INDEX('SKU Data'!$F$2:$F$1780,MATCH($A22,'SKU Data'!$A$2:$A$1780,0)),"") -> 25 | E22: =IFERROR(INDEX('SKU Data'!$J$2:$J$1780,MATCH($A22,'SKU Data'!$A$2:$A$1780,0)),"") -> 0.067024129 | F22: =IFERROR(INDEX('SKU Data'!$H$2:$H$1780,MATCH($A22,'SKU Data'!$A$2:$A$1780,0)),"") -> 2874.25 | G22: =IFERROR(INDEX('SKU Data'!$K$2:$K$1780,MATCH($A22,'SKU Data'!$A$2:$A$1780,0)),"") -> 0.06119725 | H22: =IFERROR(INDEX('SKU Data'!$O$2:$O$1780,MATCH($A22,'SKU Data'!$A$2:$A$1780,0)),"") -> 4.0166688 | I22: =IFERROR(INDEX('SKU Data'!$W$2:$W$1780,MATCH($A22,'SKU Data'!$A$2:$A$1780,0)),"") -> 1 - Fix first | J22: =IFERROR(INDEX('SKU Data'!$X$2:$X$1780,MATCH($A22,'SKU Data'!$A$2:$A$1780,0)),"") -> HIGH RATE
A23: AUMJ-NW-020 | B23: =IFERROR(INDEX('SKU Data'!$B$2:$B$1780,MATCH($A23,'SKU Data'!$A$2:$A$1780,0)),"") -> Spring Fling Bouquet in Mason Jar | C23: =IFERROR(INDEX('SKU Data'!$E$2:$E$1780,MATCH($A23,'SKU Data'!$A$2:$A$1780,0)),"") -> 509 | D23: =IFERROR(INDEX('SKU Data'!$F$2:$F$1780,MATCH($A23,'SKU Data'!$A$2:$A$1780,0)),"") -> 24 | E23: =IFERROR(INDEX('SKU Data'!$J$2:$J$1780,MATCH($A23,'SKU Data'!$A$2:$A$1780,0)),"") -> 0.047151277 | F23: =IFERROR(INDEX('SKU Data'!$H$2:$H$1780,MATCH($A23,'SKU Data'!$A$2:$A$1780,0)),"") -> 2561.34 | G23: =IFERROR(INDEX('SKU Data'!$K$2:$K$1780,MATCH($A23,'SKU Data'!$A$2:$A$1780,0)),"") -> 0.045763188 | H23: =IFERROR(INDEX('SKU Data'!$O$2:$O$1780,MATCH($A23,'SKU Data'!$A$2:$A$1780,0)),"") -> 2.104695 | I23: =IFERROR(INDEX('SKU Data'!$W$2:$W$1780,MATCH($A23,'SKU Data'!$A$2:$A$1780,0)),"") -> 2 - Review | J23: =IFERROR(INDEX('SKU Data'!$X$2:$X$1780,MATCH($A23,'SKU Data'!$A$2:$A$1780,0)),"")
A24: AUMJ-NW-016 | B24: =IFERROR(INDEX('SKU Data'!$B$2:$B$1780,MATCH($A24,'SKU Data'!$A$2:$A$1780,0)),"") -> Grandeur Bouquet in Mason Jar | C24: =IFERROR(INDEX('SKU Data'!$E$2:$E$1780,MATCH($A24,'SKU Data'!$A$2:$A$1780,0)),"") -> 554 | D24: =IFERROR(INDEX('SKU Data'!$F$2:$F$1780,MATCH($A24,'SKU Data'!$A$2:$A$1780,0)),"") -> 27 | E24: =IFERROR(INDEX('SKU Data'!$J$2:$J$1780,MATCH($A24,'SKU Data'!$A$2:$A$1780,0)),"") -> 0.048736462 | F24: =IFERROR(INDEX('SKU Data'!$H$2:$H$1780,MATCH($A24,'SKU Data'!$A$2:$A$1780,0)),"") -> 2469.52 | G24: =IFERROR(INDEX('SKU Data'!$K$2:$K$1780,MATCH($A24,'SKU Data'!$A$2:$A$1780,0)),"") -> 0.045982807 | H24: =IFERROR(INDEX('SKU Data'!$O$2:$O$1780,MATCH($A24,'SKU Data'!$A$2:$A$1780,0)),"") -> 2.4110823 | I24: =IFERROR(INDEX('SKU Data'!$W$2:$W$1780,MATCH($A24,'SKU Data'!$A$2:$A$1780,0)),"") -> 2 - Review | J24: =IFERROR(INDEX('SKU Data'!$X$2:$X$1780,MATCH($A24,'SKU Data'!$A$2:$A$1780,0)),"")
... A27: AUMJ-NW-024 | B27: =IFERROR(INDEX('SKU Data'!$B$2:$B$1780,MATCH($A27,'SKU Data'!$A$2:$A$1780,0)),"") -> Cherry Bomb Bouquet in Mason Jar | C27: =IFERROR(INDEX('SKU Data'!$E$2:$E$1780,MATCH($A27,'SKU Data'!$A$2:$A$1780,0)),"") -> 171 | D27: =IFERROR(INDEX('SKU Data'!$F$2:$F$1780,MATCH($A27,'SKU Data'!$A$2:$A$1780,0)),"") -> 16 | E27: =IFERROR(INDEX('SKU Data'!$J$2:$J$1780,MATCH($A27,'SKU Data'!$A$2:$A$1780,0)),"") -> 0.093567251 | F27: =IFERROR(INDEX('SKU Data'!$H$2:$H$1780,MATCH($A27,'SKU Data'!$A$2:$A$1780,0)),"") -> 1832.99 | G27: =IFERROR(INDEX('SKU Data'!$K$2:$K$1780,MATCH($A27,'SKU Data'!$A$2:$A$1780,0)),"") -> 0.094639542 | H27: =IFERROR(INDEX('SKU Data'!$O$2:$O$1780,MATCH($A27,'SKU Data'!$A$2:$A$1780,0)),"") -> 4.7227226 | I27: =IFERROR(INDEX('SKU Data'!$W$2:$W$1780,MATCH($A27,'SKU Data'!$A$2:$A$1780,0)),"") -> 1 - Fix first | J27: =IFERROR(INDEX('SKU Data'!$X$2:$X$1780,MATCH($A27,'SKU Data'!$A$2:$A$1780,0)),"") -> HIGH RATE

Sheet B-DC
A1: Brand / family: DC
A3: Gross sales $ | B3: Refund $ | C3: Refunded units | D3: Refund rate (units) | E3: vs portfolio baseline | F3: % of total refund $
A4: =Brands!E7 -> 882818.48 | B4: =Brands!F7 -> 30948.36 | C4: =Brands!D7 -> 322 | D4: =Brands!G7 -> 0.037882353 | E4: =Brands!K7 -> 1.2225575 | F4: =Brands!I7 -> 0.061851116
A6: What to pay attention to
A7: 1. Refund rate 3.8% vs 3.1% portfolio (1.2x); family = 6% of SKU-attributed refund $ on 7% of gross sales.
A8: 2. Concentration: top 3 SKUs = 63% of family refunds (DC-04S, DC-02S, DC-03S).
A9: 3. Attention: 2 SKU(s) statistically above baseline; worst = DC-02B (Birthday Designer Collection II) at 8.7% on 322 units.
A11: Top 15 SKUs in this family by refund $
A12: SKU | B12: Product | C12: Qty ordered | D12: Refunded units | E12: Refund rate (units) | F12: Refund $ | G12: Refund rate ($) | H12: z-score | I12: Tier | J12: Flag
A13: DC-04S | B13: =IFERROR(INDEX('SKU Data'!$B$2:$B$1780,MATCH($A13,'SKU Data'!$A$2:$A$1780,0)),"") -> Designer Sympathy Collection IV | C13: =IFERROR(INDEX('SKU Data'!$E$2:$E$1780,MATCH($A13,'SKU Data'!$A$2:$A$1780,0)),"") -> 1695 | D13: =IFERROR(INDEX('SKU Data'!$F$2:$F$1780,MATCH($A13,'SKU Data'!$A$2:$A$1780,0)),"") -> 75 | E13: =IFERROR(INDEX('SKU Data'!$J$2:$J$1780,MATCH($A13,'SKU Data'!$A$2:$A$1780,0)),"") -> 0.044247788 | F13: =IFERROR(INDEX('SKU Data'!$H$2:$H$1780,MATCH($A13,'SKU Data'!$A$2:$A$1780,0)),"") -> 8683.47 | G13: =IFERROR(INDEX('SKU Data'!$K$2:$K$1780,MATCH($A13,'SKU Data'!$A$2:$A$1780,0)),"") -> 0.03898614 | H13: =IFERROR(INDEX('SKU Data'!$O$2:$O$1780,MATCH($A13,'SKU Data'!$A$2:$A$1780,0)),"") -> 3.1508894 | I13: =IFERROR(INDEX('SKU Data'!$W$2:$W$1780,MATCH($A13,'SKU Data'!$A$2:$A$1780,0)),"") -> 2 - Review | J13: =IFERROR(INDEX('SKU Data'!$X$2:$X$1780,MATCH($A13,'SKU Data'!$A$2:$A$1780,0)),"") -> HIGH RATE
A14: DC-02S | B14: =IFERROR(INDEX('SKU Data'!$B$2:$B$1780,MATCH($A14,'SKU Data'!$A$2:$A$1780,0)),"") -> Designer Sympathy Collection II | C14: =IFERROR(INDEX('SKU Data'!$E$2:$E$1780,MATCH($A14,'SKU Data'!$A$2:$A$1780,0)),"") -> 1482 | D14: =IFERROR(INDEX('SKU Data'!$F$2:$F$1780,MATCH($A14,'SKU Data'!$A$2:$A$1780,0)),"") -> 62 | E14: =IFERROR(INDEX('SKU Data'!$J$2:$J$1780,MATCH($A14,'SKU Data'!$A$2:$A$1780,0)),"") -> 0.041835358 | F14: =IFERROR(INDEX('SKU Data'!$H$2:$H$1780,MATCH($A14,'SKU Data'!$A$2:$A$1780,0)),"") -> 6122.41 | G14: =IFERROR(INDEX('SKU Data'!$K$2:$K$1780,MATCH($A14,'SKU Data'!$A$2:$A$1780,0)),"") -> 0.037779655 | H14: =IFERROR(INDEX('SKU Data'!$O$2:$O$1780,MATCH($A14,'SKU Data'!$A$2:$A$1780,0)),"") -> 2.410312 | I14: =IFERROR(INDEX('SKU Data'!$W$2:$W$1780,MATCH($A14,'SKU Data'!$A$2:$A$1780,0)),"") -> 2 - Review | J14: =IFERROR(INDEX('SKU Data'!$X$2:$X$1780,MATCH($A14,'SKU Data'!$A$2:$A$1780,0)),"")
A15: DC-03S | B15: =IFERROR(INDEX('SKU Data'!$B$2:$B$1780,MATCH($A15,'SKU Data'!$A$2:$A$1780,0)),"") -> Designer Sympathy Collection III | C15: =IFERROR(INDEX('SKU Data'!$E$2:$E$1780,MATCH($A15,'SKU Data'!$A$2:$A$1780,0)),"") -> 995 | D15: =IFERROR(INDEX('SKU Data'!$F$2:$F$1780,MATCH($A15,'SKU Data'!$A$2:$A$1780,0)),"") -> 39 | E15: =IFERROR(INDEX('SKU Data'!$J$2:$J$1780,MATCH($A15,'SKU Data'!$A$2:$A$1780,0)),"") -> 0.03919598 | F15: =IFERROR(INDEX('SKU Data'!$H$2:$H$1780,MATCH($A15,'SKU Data'!$A$2:$A$1780,0)),"") -> 4565.17 | G15: =IFERROR(INDEX('SKU Data'!$K$2:$K$1780,MATCH($A15,'SKU Data'!$A$2:$A$1780,0)),"") -> 0.035758937 | H15: =IFERROR(INDEX('SKU Data'!$O$2:$O$1780,MATCH($A15,'SKU Data'!$A$2:$A$1780,0)),"") -> 1.4945031 | I15: =IFERROR(INDEX('SKU Data'!$W$2:$W$1780,MATCH($A15,'SKU Data'!$A$2:$A$1780,0)),"") -> 2 - Review | J15: =IFERROR(INDEX('SKU Data'!$X$2:$X$1780,MATCH($A15,'SKU Data'!$A$2:$A$1780,0)),"")
A16: DC-01S | B16: =IFERROR(INDEX('SKU Data'!$B$2:$B$1780,MATCH($A16,'SKU Data'!$A$2:$A$1780,0)),"") -> Designer Sympathy Collection I | C16: =IFERROR(INDEX('SKU Data'!$E$2:$E$1780,MATCH($A16,'SKU Data'!$A$2:$A$1780,0)),"") -> 1991 | D16: =IFERROR(INDEX('SKU Data'!$F$2:$F$1780,MATCH($A16,'SKU Data'!$A$2:$A$1780,0)),"") -> 60 | E16: =IFERROR(INDEX('SKU Data'!$J$2:$J$1780,MATCH($A16,'SKU Data'!$A$2:$A$1780,0)),"") -> 0.03013561 | F16: =IFERROR(INDEX('SKU Data'!$H$2:$H$1780,MATCH($A16,'SKU Data'!$A$2:$A$1780,0)),"") -> 4255.73 | G16: =IFERROR(INDEX('SKU Data'!$K$2:$K$1780,MATCH($A16,'SKU Data'!$A$2:$A$1780,0)),"") -> 0.026901897 | H16: =IFERROR(INDEX('SKU Data'!$O$2:$O$1780,MATCH($A16,'SKU Data'!$A$2:$A$1780,0)),"") -> -0.2190191 | I16: =IFERROR(INDEX('SKU Data'!$W$2:$W$1780,MATCH($A16,'SKU Data'!$A$2:$A$1780,0)),"") -> 3 - Monitor | J16: =IFERROR(INDEX('SKU Data'!$X$2:$X$1780,MATCH($A16,'SKU Data'!$A$2:$A$1780,0)),"")
A17: DC-02B | B17: =IFERROR(INDEX('SKU Data'!$B$2:$B$1780,MATCH($A17,'SKU Data'!$A$2:$A$1780,0)),"") -> Birthday Designer Collection II | C17: =IFERROR(INDEX('SKU Data'!$E$2:$E$1780,MATCH($A17,'SKU Data'!$A$2:$A$1780,0)),"") -> 322 | D17: =IFERROR(INDEX('SKU Data'!$F$2:$F$1780,MATCH($A17,'SKU Data'!$A$2:$A$1780,0)),"") -> 28 | E17: =IFERROR(INDEX('SKU Data'!$J$2:$J$1780,MATCH($A17,'SKU Data'!$A$2:$A$1780,0)),"") -> 0.086956522 | F17: =IFERROR(INDEX('SKU Data'!$H$2:$H$1780,MATCH($A17,'SKU Data'!$A$2:$A$1780,0)),"") -> 2889.28 | G17: =IFERROR(INDEX('SKU Data'!$K$2:$K$1780,MATCH($A17,'SKU Data'!$A$2:$A$1780,0)),"") -> 0.083097281 | H17: =IFERROR(INDEX('SKU Data'!$O$2:$O$1780,MATCH($A17,'SKU Data'!$A$2:$A$1780,0)),"") -> 5.7961192 | I17: =IFERROR(INDEX('SKU Data'!$W$2:$W$1780,MATCH($A17,'SKU Data'!$A$2:$A$1780,0)),"") -> 1 - Fix first | J17: =IFERROR(INDEX('SKU Data'!$X$2:$X$1780,MATCH($A17,'SKU Data'!$A$2:$A$1780,0)),"") -> HIGH RATE
A18: DC-01B | B18: =IFERROR(INDEX('SKU Data'!$B$2:$B$1780,MATCH($A18,'SKU Data'!$A$2:$A$1780,0)),"") -> Birthday Designer Collection I | C18: =IFERROR(INDEX('SKU Data'!$E$2:$E$1780,MATCH($A18,'SKU Data'!$A$2:$A$1780,0)),"") -> 906 | D18: =IFERROR(INDEX('SKU Data'!$F$2:$F$1780,MATCH($A18,'SKU Data'!$A$2:$A$1780,0)),"") -> 36 | E18: =IFERROR(INDEX('SKU Data'!$J$2:$J$1780,MATCH($A18,'SKU Data'!$A$2:$A$1780,0)),"") -> 0.039735099 | F18: =IFERROR(INDEX('SKU Data'!$H$2:$H$1780,MATCH($A18,'SKU Data'!$A$2:$A$1780,0)),"") -> 2433.11 | G18: =IFERROR(INDEX('SKU Data'!$K$2:$K$1780,MATCH($A18,'SKU Data'!$A$2:$A$1780,0)),"") -> 0.034485984 | H18: =IFERROR(INDEX('SKU Data'!$O$2:$O$1780,MATCH($A18,'SKU Data'!$A$2:$A$1780,0)),"") -> 1.5197465 | I18: =IFERROR(INDEX('SKU Data'!$W$2:$W$1780,MATCH($A18,'SKU Data'!$A$2:$A$1780,0)),"") -> 3 - Monitor | J18: =IFERROR(INDEX('SKU Data'!$X$2:$X$1780,MATCH($A18,'SKU Data'!$A$2:$A$1780,0)),"")
A19: DC-01A | B19: =IFERROR(INDEX('SKU Data'!$B$2:$B$1780,MATCH($A19,'SKU Data'!$A$2:$A$1780,0)),"") -> Designer Collection Anniversary I | C19: =IFERROR(INDEX('SKU Data'!$E$2:$E$1780,MATCH($A19,'SKU Data'!$A$2:$A$1780,0)),"") -> 801 | D19: =IFERROR(INDEX('SKU Data'!$F$2:$F$1780,MATCH($A19,'SKU Data'!$A$2:$A$1780,0)),"") -> 9 | E19: =IFERROR(INDEX('SKU Data'!$J$2:$J$1780,MATCH($A19,'SKU Data'!$A$2:$A$1780,0)),"") -> 0.011235955 | F19: =IFERROR(INDEX('SKU Data'!$H$2:$H$1780,MATCH($A19,'SKU Data'!$A$2:$A$1780,0)),"") -> 669.8 | G19: =IFERROR(INDEX('SKU Data'!$K$2:$K$1780,MATCH($A19,'SKU Data'!$A$2:$A$1780,0)),"") -> 0.0097104719 | H19: =IFERROR(INDEX('SKU Data'!$O$2:$O$1780,MATCH($A19,'SKU Data'!$A$2:$A$1780,0)),"") -> -3.2258106 | I19: =IFERROR(INDEX('SKU Data'!$W$2:$W$1780,MATCH($A19,'SKU Data'!$A$2:$A$1780,0)),"") -> 3 - Monitor | J19: =IFERROR(INDEX('SKU Data'!$X$2:$X$1780,MATCH($A19,'SKU Data'!$A$2:$A$1780,0)),"")
A20: DC-02A | B20: =IFERROR(INDEX('SKU Data'!$B$2:$B$1780,MATCH($A20,'SKU Data'!$A$2:$A$1780,0)),"") -> Designer Collection Anniversary II | C20: =IFERROR(INDEX('SKU Data'!$E$2:$E$1780,MATCH($A20,'SKU Data'!$A$2:$A$1780,0)),"") -> 119 | D20: =IFERROR(INDEX('SKU Data'!$F$2:$F$1780,MATCH($A20,'SKU Data'!$A$2:$A$1780,0)),"") -> 6 | E20: =IFERROR(INDEX('SKU Data'!$J$2:$J$1780,MATCH($A20,'SKU Data'!$A$2:$A$1780,0)),"") -> 0.050420168 | F20: =IFERROR(INDEX('SKU Data'!$H$2:$H$1780,MATCH($A20,'SKU Data'!$A$2:$A$1780,0)),"") -> 466.03 | G20: =IFERROR(INDEX('SKU Data'!$K$2:$K$1780,MATCH($A20,'SKU Data'!$A$2:$A$1780,0)),"") -> 0.043523902 | H20: =IFERROR(INDEX('SKU Data'!$O$2:$O$1780,MATCH($A20,'SKU Data'!$A$2:$A$1780,0)),"") -> 1.2234529 | I20: =IFERROR(INDEX('SKU Data'!$W$2:$W$1780,MATCH($A20,'SKU Data'!$A$2:$A$1780,0)),"") -> 3 - Monitor | J20: =IFERROR(INDEX('SKU Data'!$X$2:$X$1780,MATCH($A20,'SKU Data'!$A$2:$A$1780,0)),"")
A21: DC-04B | B21: =IFERROR(INDEX('SKU Data'!$B$2:$B$1780,MATCH($A21,'SKU Data'!$A$2:$A$1780,0)),"") -> Birthday Designer Collection IV | C21: =IFERROR(INDEX('SKU Data'!$E$2:$E$1780,MATCH($A21,'SKU Data'!$A$2:$A$1780,0)),"") -> 72 | D21: =IFERROR(INDEX('SKU Data'!$F$2:$F$1780,MATCH($A21,'SKU Data'!$A$2:$A$1780,0)),"") -> 3 | E21: =IFERROR(INDEX('SKU Data'!$J$2:$J$1780,MATCH($A21,'SKU Data'!$A$2:$A$1780,0)),"") -> 0.041666667 | F21: =IFERROR(INDEX('SKU Data'!$H$2:$H$1780,MATCH($A21,'SKU Data'!$A$2:$A$1780,0)),"") -> 374.66 | G21: =IFERROR(INDEX('SKU Data'!$K$2:$K$1780,MATCH($A21,'SKU Data'!$A$2:$A$1780,0)),"") -> 0.032633216 | H21: =IFERROR(INDEX('SKU Data'!$O$2:$O$1780,MATCH($A21,'SKU Data'!$A$2:$A$1780,0)),"") -> 0.5230096 | I21: =IFERROR(INDEX('SKU Data'!$W$2:$W$1780,MATCH($A21,'SKU Data'!$A$2:$A$1780,0)),"") -> 3 - Monitor | J21: =IFERROR(INDEX('SKU Data'!$X$2:$X$1780,MATCH($A21,'SKU Data'!$A$2:$A$1780,0)),"")
A22: DC-03B | B22: =IFERROR(INDEX('SKU Data'!$B$2:$B$1780,MATCH($A22,'SKU Data'!$A$2:$A$1780,0)),"") -> Birthday Designer Collection III | C22: =IFERROR(INDEX('SKU Data'!$E$2:$E$1780,MATCH($A22,'SKU Data'!$A$2:$A$1780,0)),"") -> 64 | D22: =IFERROR(INDEX('SKU Data'!$F$2:$F$1780,MATCH($A22,'SKU Data'!$A$2:$A$1780,0)),"") -> 2 | E22: =IFERROR(INDEX('SKU Data'!$J$2:$J$1780,MATCH($A22,'SKU Data'!$A$2:$A$1780,0)),"") -> 0.03125 | F22: =IFERROR(INDEX('SKU Data'!$H$2:$H$1780,MATCH($A22,'SKU Data'!$A$2:$A$1780,0)),"") -> 251.51 | G22: =IFERROR(INDEX('SKU Data'!$K$2:$K$1780,MATCH($A22,'SKU Data'!$A$2:$A$1780,0)),"") -> 0.028706075 | H22: =IFERROR(INDEX('SKU Data'!$O$2:$O$1780,MATCH($A22,'SKU Data'!$A$2:$A$1780,0)),"") -> 0.01218138 | I22: =IFERROR(INDEX('SKU Data'!$W$2:$W$1780,MATCH($A22,'SKU Data'!$A$2:$A$1780,0)),"") -> 3 - Monitor | J22: =IFERROR(INDEX('SKU Data'!$X$2:$X$1780,MATCH($A22,'SKU Data'!$A$2:$A$1780,0)),"")
A23: DC-03A | B23: =IFERROR(INDEX('SKU Data'!$B$2:$B$1780,MATCH($A23,'SKU Data'!$A$2:$A$1780,0)),"") -> Designer Collection Anniversary III | C23: =IFERROR(INDEX('SKU Data'!$E$2:$E$1780,MATCH($A23,'SKU Data'!$A$2:$A$1780,0)),"") -> 47 | D23: =IFERROR(INDEX('SKU Data'!$F$2:$F$1780,MATCH($A23,'SKU Data'!$A$2:$A$1780,0)),"") -> 2 | E23: =IFERROR(INDEX('SKU Data'!$J$2:$J$1780,MATCH($A23,'SKU Data'!$A$2:$A$1780,0)),"") -> 0.042553191 | F23: =IFERROR(INDEX('SKU Data'!$H$2:$H$1780,MATCH($A23,'SKU Data'!$A$2:$A$1780,0)),"") -> 237.19 | G23: =IFERROR(INDEX('SKU Data'!$K$2:$K$1780,MATCH($A23,'SKU Data'!$A$2:$A$1780,0)),"") -> 0.039027432 | H23: =IFERROR(INDEX('SKU Data'!$O$2:$O$1780,MATCH($A23,'SKU Data'!$A$2:$A$1780,0)),"") -> 0.45763831 | I23: =IFERROR(INDEX('SKU Data'!$W$2:$W$1780,MATCH($A23,'SKU Data'!$A$2:$A$1780,0)),"") -> 3 - Monitor | J23: =IFERROR(INDEX('SKU Data'!$X$2:$X$1780,MATCH($A23,'SKU Data'!$A$2:$A$1780,0)),"")
A24: DC-03A-DLX | B24: =IFERROR(INDEX('SKU Data'!$B$2:$B$1780,MATCH($A24,'SKU Data'!$A$2:$A$1780,0)),"") -> Designer Collection Anniversary III | C24: =IFERROR(INDEX('SKU Data'!$E$2:$E$1780,MATCH($A24,'SKU Data'!$A$2:$A$1780,0)),"") -> 1 | D24: =IFERROR(INDEX('SKU Data'!$F$2:$F$1780,MATCH($A24,'SKU Data'!$A$2:$A$1780,0)),"") -> 0 | E24: =IFERROR(INDEX('SKU Data'!$J$2:$J$1780,MATCH($A24,'SKU Data'!$A$2:$A$1780,0)),"") -> 0 | F24: =IFERROR(INDEX('SKU Data'!$H$2:$H$1780,MATCH($A24,'SKU Data'!$A$2:$A$1780,0)),"") -> 0 | G24: =IFERROR(INDEX('SKU Data'!$K$2:$K$1780,MATCH($A24,'SKU Data'!$A$2:$A$1780,0)),"") -> 0 | H24: =IFERROR(INDEX('SKU Data'!$O$2:$O$1780,MATCH($A24,'SKU Data'!$A$2:$A$1780,0)),"") -> -0.17882113 | I24: =IFERROR(INDEX('SKU Data'!$W$2:$W$1780,MATCH($A24,'SKU Data'!$A$2:$A$1780,0)),"") | J24: =IFERROR(INDEX('SKU Data'!$X$2:$X$1780,MATCH($A24,'SKU Data'!$A$2:$A$1780,0)),"")
... A27: DC112-02 | B27: =IFERROR(INDEX('SKU Data'!$B$2:$B$1780,MATCH($A27,'SKU Data'!$A$2:$A$1780,0)),"") -> Designers Collection II | C27: =IFERROR(INDEX('SKU Data'!$E$2:$E$1780,MATCH($A27,'SKU Data'!$A$2:$A$1780,0)),"") -> 1 | D27: =IFERROR(INDEX('SKU Data'!$F$2:$F$1780,MATCH($A27,'SKU Data'!$A$2:$A$1780,0)),"") -> 0 | E27: =IFERROR(INDEX('SKU Data'!$J$2:$J$1780,MATCH($A27,'SKU Data'!$A$2:$A$1780,0)),"") -> 0 | F27: =IFERROR(INDEX('SKU Data'!$H$2:$H$1780,MATCH($A27,'SKU Data'!$A$2:$A$1780,0)),"") -> 0 | G27: =IFERROR(INDEX('SKU Data'!$K$2:$K$1780,MATCH($A27,'SKU Data'!$A$2:$A$1780,0)),"") -> 0 | H27: =IFERROR(INDEX('SKU Data'!$O$2:$O$1780,MATCH($A27,'SKU Data'!$A$2:$A$1780,0)),"") -> -0.17882113 | I27: =IFERROR(INDEX('SKU Data'!$W$2:$W$1780,MATCH($A27,'SKU Data'!$A$2:$A$1780,0)),"") | J27: =IFERROR(INDEX('SKU Data'!$X$2:$X$1780,MATCH($A27,'SKU Data'!$A$2:$A$1780,0)),"")

Sheet B-AUSGF
A1: Brand / family: AUSGF
A3: Gross sales $ | B3: Refund $ | C3: Refunded units | D3: Refund rate (units) | E3: vs portfolio baseline | F3: % of total refund $
A4: =Brands!E8 -> 846240.52 | B4: =Brands!F8 -> 29423.06 | C4: =Brands!D8 -> 461 | D4: =Brands!G8 -> 0.035878278 | E4: =Brands!K8 -> 1.1578811 | F4: =Brands!I8 -> 0.058802764
A6: What to pay attention to
A7: 1. Refund rate 3.6% vs 3.1% portfolio (1.2x); family = 6% of SKU-attributed refund $ on 7% of gross sales.
A8: 2. Concentration: top 3 SKUs = 100% of family refunds (AUSGF16-115, AUSGF16-110, AUSGF16-115-REG).
A9: 3. Attention: 1 SKU(s) statistically above baseline; worst = AUSGF16-115 (Delicate Elegance) at 3.6% on 11,490 units.
A11: Top 15 SKUs in this family by refund $
A12: SKU | B12: Product | C12: Qty ordered | D12: Refunded units | E12: Refund rate (units) | F12: Refund $ | G12: Refund rate ($) | H12: z-score | I12: Tier | J12: Flag
A13: AUSGF16-115 | B13: =IFERROR(INDEX('SKU Data'!$B$2:$B$1780,MATCH($A13,'SKU Data'!$A$2:$A$1780,0)),"") -> Delicate Elegance | C13: =IFERROR(INDEX('SKU Data'!$E$2:$E$1780,MATCH($A13,'SKU Data'!$A$2:$A$1780,0)),"") -> 11490 | D13: =IFERROR(INDEX('SKU Data'!$F$2:$F$1780,MATCH($A13,'SKU Data'!$A$2:$A$1780,0)),"") -> 419 | E13: =IFERROR(INDEX('SKU Data'!$J$2:$J$1780,MATCH($A13,'SKU Data'!$A$2:$A$1780,0)),"") -> 0.036466493 | F13: =IFERROR(INDEX('SKU Data'!$H$2:$H$1780,MATCH($A13,'SKU Data'!$A$2:$A$1780,0)),"") -> 25834.89 | G13: =IFERROR(INDEX('SKU Data'!$K$2:$K$1780,MATCH($A13,'SKU Data'!$A$2:$A$1780,0)),"") -> 0.035459214 | H13: =IFERROR(INDEX('SKU Data'!$O$2:$O$1780,MATCH($A13,'SKU Data'!$A$2:$A$1780,0)),"") -> 3.3901493 | I13: =IFERROR(INDEX('SKU Data'!$W$2:$W$1780,MATCH($A13,'SKU Data'!$A$2:$A$1780,0)),"") -> 2 - Review | J13: =IFERROR(INDEX('SKU Data'!$X$2:$X$1780,MATCH($A13,'SKU Data'!$A$2:$A$1780,0)),"") -> HIGH RATE
A14: AUSGF16-110 | B14: =IFERROR(INDEX('SKU Data'!$B$2:$B$1780,MATCH($A14,'SKU Data'!$A$2:$A$1780,0)),"") -> Pastel Harmony | C14: =IFERROR(INDEX('SKU Data'!$E$2:$E$1780,MATCH($A14,'SKU Data'!$A$2:$A$1780,0)),"") -> 1106 | D14: =IFERROR(INDEX('SKU Data'!$F$2:$F$1780,MATCH($A14,'SKU Data'!$A$2:$A$1780,0)),"") -> 40 | E14: =IFERROR(INDEX('SKU Data'!$J$2:$J$1780,MATCH($A14,'SKU Data'!$A$2:$A$1780,0)),"") -> 0.036166365 | F14: =IFERROR(INDEX('SKU Data'!$H$2:$H$1780,MATCH($A14,'SKU Data'!$A$2:$A$1780,0)),"") -> 3482.27 | G14: =IFERROR(INDEX('SKU Data'!$K$2:$K$1780,MATCH($A14,'SKU Data'!$A$2:$A$1780,0)),"") -> 0.0345406 | H14: =IFERROR(INDEX('SKU Data'!$O$2:$O$1780,MATCH($A14,'SKU Data'!$A$2:$A$1780,0)),"") -> 0.99420621 | I14: =IFERROR(INDEX('SKU Data'!$W$2:$W$1780,MATCH($A14,'SKU Data'!$A$2:$A$1780,0)),"") -> 3 - Monitor | J14: =IFERROR(INDEX('SKU Data'!$X$2:$X$1780,MATCH($A14,'SKU Data'!$A$2:$A$1780,0)),"")
A15: AUSGF16-115-REG | B15: =IFERROR(INDEX('SKU Data'!$B$2:$B$1780,MATCH($A15,'SKU Data'!$A$2:$A$1780,0)),"") -> Delicate Elegance | C15: =IFERROR(INDEX('SKU Data'!$E$2:$E$1780,MATCH($A15,'SKU Data'!$A$2:$A$1780,0)),"") -> 134 | D15: =IFERROR(INDEX('SKU Data'!$F$2:$F$1780,MATCH($A15,'SKU Data'!$A$2:$A$1780,0)),"") -> 2 | E15: =IFERROR(INDEX('SKU Data'!$J$2:$J$1780,MATCH($A15,'SKU Data'!$A$2:$A$1780,0)),"") -> 0.014925373 | F15: =IFERROR(INDEX('SKU Data'!$H$2:$H$1780,MATCH($A15,'SKU Data'!$A$2:$A$1780,0)),"") -> 105.9 | G15: =IFERROR(INDEX('SKU Data'!$K$2:$K$1780,MATCH($A15,'SKU Data'!$A$2:$A$1780,0)),"") -> 0.014925373 | H15: =IFERROR(INDEX('SKU Data'!$O$2:$O$1780,MATCH($A15,'SKU Data'!$A$2:$A$1780,0)),"") -> -1.072927 | I15: =IFERROR(INDEX('SKU Data'!$W$2:$W$1780,MATCH($A15,'SKU Data'!$A$2:$A$1780,0)),"") -> 3 - Monitor | J15: =IFERROR(INDEX('SKU Data'!$X$2:$X$1780,MATCH($A15,'SKU Data'!$A$2:$A$1780,0)),"")
A16: AUSGF16-110-DEL | B16: =IFERROR(INDEX('SKU Data'!$B$2:$B$1780,MATCH($A16,'SKU Data'!$A$2:$A$1780,0)),"") -> Pastel Harmony | C16: =IFERROR(INDEX('SKU Data'!$E$2:$E$1780,MATCH($A16,'SKU Data'!$A$2:$A$1780,0)),"") -> 10 | D16: =IFERROR(INDEX('SKU Data'!$F$2:$F$1780,MATCH($A16,'SKU Data'!$A$2:$A$1780,0)),"") -> 0 | E16: =IFERROR(INDEX('SKU Data'!$J$2:$J$1780,MATCH($A16,'SKU Data'!$A$2:$A$1780,0)),"") -> 0 | F16: =IFERROR(INDEX('SKU Data'!$H$2:$H$1780,MATCH($A16,'SKU Data'!$A$2:$A$1780,0)),"") -> 0 | G16: =IFERROR(INDEX('SKU Data'!$K$2:$K$1780,MATCH($A16,'SKU Data'!$A$2:$A$1780,0)),"") -> 0 | H16: =IFERROR(INDEX('SKU Data'!$O$2:$O$1780,MATCH($A16,'SKU Data'!$A$2:$A$1780,0)),"") -> -0.56548205 | I16: =IFERROR(INDEX('SKU Data'!$W$2:$W$1780,MATCH($A16,'SKU Data'!$A$2:$A$1780,0)),"") | J16: =IFERROR(INDEX('SKU Data'!$X$2:$X$1780,MATCH($A16,'SKU Data'!$A$2:$A$1780,0)),"")
A17: AUSGF16-110-GRA | B17: =IFERROR(INDEX('SKU Data'!$B$2:$B$1780,MATCH($A17,'SKU Data'!$A$2:$A$1780,0)),"") -> Pastel Harmony | C17: =IFERROR(INDEX('SKU Data'!$E$2:$E$1780,MATCH($A17,'SKU Data'!$A$2:$A$1780,0)),"") -> 5 | D17: =IFERROR(INDEX('SKU Data'!$F$2:$F$1780,MATCH($A17,'SKU Data'!$A$2:$A$1780,0)),"") -> 0 | E17: =IFERROR(INDEX('SKU Data'!$J$2:$J$1780,MATCH($A17,'SKU Data'!$A$2:$A$1780,0)),"") -> 0 | F17: =IFERROR(INDEX('SKU Data'!$H$2:$H$1780,MATCH($A17,'SKU Data'!$A$2:$A$1780,0)),"") -> 0 | G17: =IFERROR(INDEX('SKU Data'!$K$2:$K$1780,MATCH($A17,'SKU Data'!$A$2:$A$1780,0)),"") -> 0 | H17: =IFERROR(INDEX('SKU Data'!$O$2:$O$1780,MATCH($A17,'SKU Data'!$A$2:$A$1780,0)),"") -> -0.39985619 | I17: =IFERROR(INDEX('SKU Data'!$W$2:$W$1780,MATCH($A17,'SKU Data'!$A$2:$A$1780,0)),"") | J17: =IFERROR(INDEX('SKU Data'!$X$2:$X$1780,MATCH($A17,'SKU Data'!$A$2:$A$1780,0)),"")
A18: AUSGF16-110-PRE | B18: =IFERROR(INDEX('SKU Data'!$B$2:$B$1780,MATCH($A18,'SKU Data'!$A$2:$A$1780,0)),"") -> Pastel Harmony | C18: =IFERROR(INDEX('SKU Data'!$E$2:$E$1780,MATCH($A18,'SKU Data'!$A$2:$A$1780,0)),"") -> 3 | D18: =IFERROR(INDEX('SKU Data'!$F$2:$F$1780,MATCH($A18,'SKU Data'!$A$2:$A$1780,0)),"") -> 0 | E18: =IFERROR(INDEX('SKU Data'!$J$2:$J$1780,MATCH($A18,'SKU Data'!$A$2:$A$1780,0)),"") -> 0 | F18: =IFERROR(INDEX('SKU Data'!$H$2:$H$1780,MATCH($A18,'SKU Data'!$A$2:$A$1780,0)),"") -> 0 | G18: =IFERROR(INDEX('SKU Data'!$K$2:$K$1780,MATCH($A18,'SKU Data'!$A$2:$A$1780,0)),"") -> 0 | H18: =IFERROR(INDEX('SKU Data'!$O$2:$O$1780,MATCH($A18,'SKU Data'!$A$2:$A$1780,0)),"") -> -0.30972728 | I18: =IFERROR(INDEX('SKU Data'!$W$2:$W$1780,MATCH($A18,'SKU Data'!$A$2:$A$1780,0)),"") | J18: =IFERROR(INDEX('SKU Data'!$X$2:$X$1780,MATCH($A18,'SKU Data'!$A$2:$A$1780,0)),"")
A19: AUSGF16-110-REG | B19: =IFERROR(INDEX('SKU Data'!$B$2:$B$1780,MATCH($A19,'SKU Data'!$A$2:$A$1780,0)),"") -> Pastel Harmony | C19: =IFERROR(INDEX('SKU Data'!$E$2:$E$1780,MATCH($A19,'SKU Data'!$A$2:$A$1780,0)),"") -> 19 | D19: =IFERROR(INDEX('SKU Data'!$F$2:$F$1780,MATCH($A19,'SKU Data'!$A$2:$A$1780,0)),"") -> 0 | E19: =IFERROR(INDEX('SKU Data'!$J$2:$J$1780,MATCH($A19,'SKU Data'!$A$2:$A$1780,0)),"") -> 0 | F19: =IFERROR(INDEX('SKU Data'!$H$2:$H$1780,MATCH($A19,'SKU Data'!$A$2:$A$1780,0)),"") -> 0 | G19: =IFERROR(INDEX('SKU Data'!$K$2:$K$1780,MATCH($A19,'SKU Data'!$A$2:$A$1780,0)),"") -> 0 | H19: =IFERROR(INDEX('SKU Data'!$O$2:$O$1780,MATCH($A19,'SKU Data'!$A$2:$A$1780,0)),"") -> -0.77946322 | I19: =IFERROR(INDEX('SKU Data'!$W$2:$W$1780,MATCH($A19,'SKU Data'!$A$2:$A$1780,0)),"") | J19: =IFERROR(INDEX('SKU Data'!$X$2:$X$1780,MATCH($A19,'SKU Data'!$A$2:$A$1780,0)),"")
A20: AUSGF16-115-DEL | B20: =IFERROR(INDEX('SKU Data'!$B$2:$B$1780,MATCH($A20,'SKU Data'!$A$2:$A$1780,0)),"") -> Delicate Elegance | C20: =IFERROR(INDEX('SKU Data'!$E$2:$E$1780,MATCH($A20,'SKU Data'!$A$2:$A$1780,0)),"") -> 60 | D20: =IFERROR(INDEX('SKU Data'!$F$2:$F$1780,MATCH($A20,'SKU Data'!$A$2:$A$1780,0)),"") -> 0 | E20: =IFERROR(INDEX('SKU Data'!$J$2:$J$1780,MATCH($A20,'SKU Data'!$A$2:$A$1780,0)),"") -> 0 | F20: =IFERROR(INDEX('SKU Data'!$H$2:$H$1780,MATCH($A20,'SKU Data'!$A$2:$A$1780,0)),"") -> 0 | G20: =IFERROR(INDEX('SKU Data'!$K$2:$K$1780,MATCH($A20,'SKU Data'!$A$2:$A$1780,0)),"") -> 0 | H20: =IFERROR(INDEX('SKU Data'!$O$2:$O$1780,MATCH($A20,'SKU Data'!$A$2:$A$1780,0)),"") -> -1.3851425 | I20: =IFERROR(INDEX('SKU Data'!$W$2:$W$1780,MATCH($A20,'SKU Data'!$A$2:$A$1780,0)),"") | J20: =IFERROR(INDEX('SKU Data'!$X$2:$X$1780,MATCH($A20,'SKU Data'!$A$2:$A$1780,0)),"")
A21: AUSGF16-115-GRA | B21: =IFERROR(INDEX('SKU Data'!$B$2:$B$1780,MATCH($A21,'SKU Data'!$A$2:$A$1780,0)),"") -> Delicate Elegance | C21: =IFERROR(INDEX('SKU Data'!$E$2:$E$1780,MATCH($A21,'SKU Data'!$A$2:$A$1780,0)),"") -> 14 | D21: =IFERROR(INDEX('SKU Data'!$F$2:$F$1780,MATCH($A21,'SKU Data'!$A$2:$A$1780,0)),"") -> 0 | E21: =IFERROR(INDEX('SKU Data'!$J$2:$J$1780,MATCH($A21,'SKU Data'!$A$2:$A$1780,0)),"") -> 0 | F21: =IFERROR(INDEX('SKU Data'!$H$2:$H$1780,MATCH($A21,'SKU Data'!$A$2:$A$1780,0)),"") -> 0 | G21: =IFERROR(INDEX('SKU Data'!$K$2:$K$1780,MATCH($A21,'SKU Data'!$A$2:$A$1780,0)),"") -> 0 | H21: =IFERROR(INDEX('SKU Data'!$O$2:$O$1780,MATCH($A21,'SKU Data'!$A$2:$A$1780,0)),"") -> -0.66908739 | I21: =IFERROR(INDEX('SKU Data'!$W$2:$W$1780,MATCH($A21,'SKU Data'!$A$2:$A$1780,0)),"") | J21: =IFERROR(INDEX('SKU Data'!$X$2:$X$1780,MATCH($A21,'SKU Data'!$A$2:$A$1780,0)),"")
A22: AUSGF16-115-PRE | B22: =IFERROR(INDEX('SKU Data'!$B$2:$B$1780,MATCH($A22,'SKU Data'!$A$2:$A$1780,0)),"") -> Delicate Elegance | C22: =IFERROR(INDEX('SKU Data'!$E$2:$E$1780,MATCH($A22,'SKU Data'!$A$2:$A$1780,0)),"") -> 8 | D22: =IFERROR(INDEX('SKU Data'!$F$2:$F$1780,MATCH($A22,'SKU Data'!$A$2:$A$1780,0)),"") -> 0 | E22: =IFERROR(INDEX('SKU Data'!$J$2:$J$1780,MATCH($A22,'SKU Data'!$A$2:$A$1780,0)),"") -> 0 | F22: =IFERROR(INDEX('SKU Data'!$H$2:$H$1780,MATCH($A22,'SKU Data'!$A$2:$A$1780,0)),"") -> 0 | G22: =IFERROR(INDEX('SKU Data'!$K$2:$K$1780,MATCH($A22,'SKU Data'!$A$2:$A$1780,0)),"") -> 0 | H22: =IFERROR(INDEX('SKU Data'!$O$2:$O$1780,MATCH($A22,'SKU Data'!$A$2:$A$1780,0)),"") -> -0.50578252 | I22: =IFERROR(INDEX('SKU Data'!$W$2:$W$1780,MATCH($A22,'SKU Data'!$A$2:$A$1780,0)),"") | J22: =IFERROR(INDEX('SKU Data'!$X$2:$X$1780,MATCH($A22,'SKU Data'!$A$2:$A$1780,0)),"")

Sheet B-MJ
A1: Brand / family: MJ
A3: Gross sales $ | B3: Refund $ | C3: Refunded units | D3: Refund rate (units) | E3: vs portfolio baseline | F3: % of total refund $
A4: =Brands!E9 -> 922462.45 | B4: =Brands!F9 -> 28997.07 | C4: =Brands!D9 -> 456 | D4: =Brands!G9 -> 0.030852503 | E4: =Brands!K9 -> 0.99568686 | F4: =Brands!I9 -> 0.057951411
A6: What to pay attention to
A7: 1. Refund rate 3.1% vs 3.1% portfolio (1.0x); family = 6% of SKU-attributed refund $ on 7% of gross sales.
A8: 2. Concentration: top 3 SKUs = 54% of family refunds (MJ100-17, MJ100-04, MJ100-62).
A9: 3. Attention: 2 SKU(s) statistically above baseline; worst = MJ100-17 (Thirty Blooms of Alstroemeria in) at 5.0% on 2,096 units.
A11: Top 15 SKUs in this family by refund $
A12: SKU | B12: Product | C12: Qty ordered | D12: Refunded units | E12: Refund rate (units) | F12: Refund $ | G12: Refund rate ($) | H12: z-score | I12: Tier | J12: Flag
A13: MJ100-17 | B13: =IFERROR(INDEX('SKU Data'!$B$2:$B$1780,MATCH($A13,'SKU Data'!$A$2:$A$1780,0)),"") -> Thirty Blooms of Alstroemeria in Mason Jar | C13: =IFERROR(INDEX('SKU Data'!$E$2:$E$1780,MATCH($A13,'SKU Data'!$A$2:$A$1780,0)),"") -> 2096 | D13: =IFERROR(INDEX('SKU Data'!$F$2:$F$1780,MATCH($A13,'SKU Data'!$A$2:$A$1780,0)),"") -> 104 | E13: =IFERROR(INDEX('SKU Data'!$J$2:$J$1780,MATCH($A13,'SKU Data'!$A$2:$A$1780,0)),"") -> 0.049618321 | F13: =IFERROR(INDEX('SKU Data'!$H$2:$H$1780,MATCH($A13,'SKU Data'!$A$2:$A$1780,0)),"") -> 6020.46 | G13: =IFERROR(INDEX('SKU Data'!$K$2:$K$1780,MATCH($A13,'SKU Data'!$A$2:$A$1780,0)),"") -> 0.045982221 | H13: =IFERROR(INDEX('SKU Data'!$O$2:$O$1780,MATCH($A13,'SKU Data'!$A$2:$A$1780,0)),"") -> 4.9227781 | I13: =IFERROR(INDEX('SKU Data'!$W$2:$W$1780,MATCH($A13,'SKU Data'!$A$2:$A$1780,0)),"") -> 2 - Review | J13: =IFERROR(INDEX('SKU Data'!$X$2:$X$1780,MATCH($A13,'SKU Data'!$A$2:$A$1780,0)),"") -> HIGH RATE
A14: MJ100-04 | B14: =IFERROR(INDEX('SKU Data'!$B$2:$B$1780,MATCH($A14,'SKU Data'!$A$2:$A$1780,0)),"") -> What a Treat in Mason Jar | C14: =IFERROR(INDEX('SKU Data'!$E$2:$E$1780,MATCH($A14,'SKU Data'!$A$2:$A$1780,0)),"") -> 5316 | D14: =IFERROR(INDEX('SKU Data'!$F$2:$F$1780,MATCH($A14,'SKU Data'!$A$2:$A$1780,0)),"") -> 97 | E14: =IFERROR(INDEX('SKU Data'!$J$2:$J$1780,MATCH($A14,'SKU Data'!$A$2:$A$1780,0)),"") -> 0.018246802 | F14: =IFERROR(INDEX('SKU Data'!$H$2:$H$1780,MATCH($A14,'SKU Data'!$A$2:$A$1780,0)),"") -> 5347.79 | G14: =IFERROR(INDEX('SKU Data'!$K$2:$K$1780,MATCH($A14,'SKU Data'!$A$2:$A$1780,0)),"") -> 0.01843477 | H14: =IFERROR(INDEX('SKU Data'!$O$2:$O$1780,MATCH($A14,'SKU Data'!$A$2:$A$1780,0)),"") -> -5.3603224 | I14: =IFERROR(INDEX('SKU Data'!$W$2:$W$1780,MATCH($A14,'SKU Data'!$A$2:$A$1780,0)),"") -> 3 - Monitor | J14: =IFERROR(INDEX('SKU Data'!$X$2:$X$1780,MATCH($A14,'SKU Data'!$A$2:$A$1780,0)),"")
A15: MJ100-62 | B15: =IFERROR(INDEX('SKU Data'!$B$2:$B$1780,MATCH($A15,'SKU Data'!$A$2:$A$1780,0)),"") -> Peaceful Clouds in Mason Jar | C15: =IFERROR(INDEX('SKU Data'!$E$2:$E$1780,MATCH($A15,'SKU Data'!$A$2:$A$1780,0)),"") -> 3090 | D15: =IFERROR(INDEX('SKU Data'!$F$2:$F$1780,MATCH($A15,'SKU Data'!$A$2:$A$1780,0)),"") -> 70 | E15: =IFERROR(INDEX('SKU Data'!$J$2:$J$1780,MATCH($A15,'SKU Data'!$A$2:$A$1780,0)),"") -> 0.022653722 | F15: =IFERROR(INDEX('SKU Data'!$H$2:$H$1780,MATCH($A15,'SKU Data'!$A$2:$A$1780,0)),"") -> 4429.38 | G15: =IFERROR(INDEX('SKU Data'!$K$2:$K$1780,MATCH($A15,'SKU Data'!$A$2:$A$1780,0)),"") -> 0.024219375 | H15: =IFERROR(INDEX('SKU Data'!$O$2:$O$1780,MATCH($A15,'SKU Data'!$A$2:$A$1780,0)),"") -> -2.6730192 | I15: =IFERROR(INDEX('SKU Data'!$W$2:$W$1780,MATCH($A15,'SKU Data'!$A$2:$A$1780,0)),"") -> 3 - Monitor | J15: =IFERROR(INDEX('SKU Data'!$X$2:$X$1780,MATCH($A15,'SKU Data'!$A$2:$A$1780,0)),"")
A16: MJ100-20 | B16: =IFERROR(INDEX('SKU Data'!$B$2:$B$1780,MATCH($A16,'SKU Data'!$A$2:$A$1780,0)),"") -> Beautiful in Blue in Mason Jar | C16: =IFERROR(INDEX('SKU Data'!$E$2:$E$1780,MATCH($A16,'SKU Data'!$A$2:$A$1780,0)),"") -> 743 | D16: =IFERROR(INDEX('SKU Data'!$F$2:$F$1780,MATCH($A16,'SKU Data'!$A$2:$A$1780,0)),"") -> 41 | E16: =IFERROR(INDEX('SKU Data'!$J$2:$J$1780,MATCH($A16,'SKU Data'!$A$2:$A$1780,0)),"") -> 0.055181696 | F16: =IFERROR(INDEX('SKU Data'!$H$2:$H$1780,MATCH($A16,'SKU Data'!$A$2:$A$1780,0)),"") -> 3521.71 | G16: =IFERROR(INDEX('SKU Data'!$K$2:$K$1780,MATCH($A16,'SKU Data'!$A$2:$A$1780,0)),"") -> 0.051146572 | H16: =IFERROR(INDEX('SKU Data'!$O$2:$O$1780,MATCH($A16,'SKU Data'!$A$2:$A$1780,0)),"") -> 3.8061071 | I16: =IFERROR(INDEX('SKU Data'!$W$2:$W$1780,MATCH($A16,'SKU Data'!$A$2:$A$1780,0)),"") -> 1 - Fix first | J16: =IFERROR(INDEX('SKU Data'!$X$2:$X$1780,MATCH($A16,'SKU Data'!$A$2:$A$1780,0)),"") -> HIGH RATE
A17: MJ100-118 | B17: =IFERROR(INDEX('SKU Data'!$B$2:$B$1780,MATCH($A17,'SKU Data'!$A$2:$A$1780,0)),"") -> Blooms of Love in Mason Jar | C17: =IFERROR(INDEX('SKU Data'!$E$2:$E$1780,MATCH($A17,'SKU Data'!$A$2:$A$1780,0)),"") -> 1206 | D17: =IFERROR(INDEX('SKU Data'!$F$2:$F$1780,MATCH($A17,'SKU Data'!$A$2:$A$1780,0)),"") -> 47 | E17: =IFERROR(INDEX('SKU Data'!$J$2:$J$1780,MATCH($A17,'SKU Data'!$A$2:$A$1780,0)),"") -> 0.038971808 | F17: =IFERROR(INDEX('SKU Data'!$H$2:$H$1780,MATCH($A17,'SKU Data'!$A$2:$A$1780,0)),"") -> 3421.93 | G17: =IFERROR(INDEX('SKU Data'!$K$2:$K$1780,MATCH($A17,'SKU Data'!$A$2:$A$1780,0)),"") -> 0.03392384 | H17: =IFERROR(INDEX('SKU Data'!$O$2:$O$1780,MATCH($A17,'SKU Data'!$A$2:$A$1780,0)),"") -> 1.6004255 | I17: =IFERROR(INDEX('SKU Data'!$W$2:$W$1780,MATCH($A17,'SKU Data'!$A$2:$A$1780,0)),"") -> 3 - Monitor | J17: =IFERROR(INDEX('SKU Data'!$X$2:$X$1780,MATCH($A17,'SKU Data'!$A$2:$A$1780,0)),"")
A18: MJ100-11 | B18: =IFERROR(INDEX('SKU Data'!$B$2:$B$1780,MATCH($A18,'SKU Data'!$A$2:$A$1780,0)),"") -> Big Garden Energy | C18: =IFERROR(INDEX('SKU Data'!$E$2:$E$1780,MATCH($A18,'SKU Data'!$A$2:$A$1780,0)),"") -> 384 | D18: =IFERROR(INDEX('SKU Data'!$F$2:$F$1780,MATCH($A18,'SKU Data'!$A$2:$A$1780,0)),"") -> 20 | E18: =IFERROR(INDEX('SKU Data'!$J$2:$J$1780,MATCH($A18,'SKU Data'!$A$2:$A$1780,0)),"") -> 0.052083333 | F18: =IFERROR(INDEX('SKU Data'!$H$2:$H$1780,MATCH($A18,'SKU Data'!$A$2:$A$1780,0)),"") -> 1238.24 | G18: =IFERROR(INDEX('SKU Data'!$K$2:$K$1780,MATCH($A18,'SKU Data'!$A$2:$A$1780,0)),"") -> 0.050514738 | H18: =IFERROR(INDEX('SKU Data'!$O$2:$O$1780,MATCH($A18,'SKU Data'!$A$2:$A$1780,0)),"") -> 2.3858397 | I18: =IFERROR(INDEX('SKU Data'!$W$2:$W$1780,MATCH($A18,'SKU Data'!$A$2:$A$1780,0)),"") -> 2 - Review | J18: =IFERROR(INDEX('SKU Data'!$X$2:$X$1780,MATCH($A18,'SKU Data'!$A$2:$A$1780,0)),"")
A19: MJ100-01 | B19: =IFERROR(INDEX('SKU Data'!$B$2:$B$1780,MATCH($A19,'SKU Data'!$A$2:$A$1780,0)),"") -> Loud and Lovely | C19: =IFERROR(INDEX('SKU Data'!$E$2:$E$1780,MATCH($A19,'SKU Data'!$A$2:$A$1780,0)),"") -> 199 | D19: =IFERROR(INDEX('SKU Data'!$F$2:$F$1780,MATCH($A19,'SKU Data'!$A$2:$A$1780,0)),"") -> 11 | E19: =IFERROR(INDEX('SKU Data'!$J$2:$J$1780,MATCH($A19,'SKU Data'!$A$2:$A$1780,0)),"") -> 0.055276382 | F19: =IFERROR(INDEX('SKU Data'!$H$2:$H$1780,MATCH($A19,'SKU Data'!$A$2:$A$1780,0)),"") -> 1085.95 | G19: =IFERROR(INDEX('SKU Data'!$K$2:$K$1780,MATCH($A19,'SKU Data'!$A$2:$A$1780,0)),"") -> 0.057552314 | H19: =IFERROR(INDEX('SKU Data'!$O$2:$O$1780,MATCH($A19,'SKU Data'!$A$2:$A$1780,0)),"") -> 1.9774676 | I19: =IFERROR(INDEX('SKU Data'!$W$2:$W$1780,MATCH($A19,'SKU Data'!$A$2:$A$1780,0)),"") -> 2 - Review | J19: =IFERROR(INDEX('SKU Data'!$X$2:$X$1780,MATCH($A19,'SKU Data'!$A$2:$A$1780,0)),"")
A20: MJ100-09 | B20: =IFERROR(INDEX('SKU Data'!$B$2:$B$1780,MATCH($A20,'SKU Data'!$A$2:$A$1780,0)),"") -> Autumn Breeze In Mason Jar | C20: =IFERROR(INDEX('SKU Data'!$E$2:$E$1780,MATCH($A20,'SKU Data'!$A$2:$A$1780,0)),"") -> 496 | D20: =IFERROR(INDEX('SKU Data'!$F$2:$F$1780,MATCH($A20,'SKU Data'!$A$2:$A$1780,0)),"") -> 25 | E20: =IFERROR(INDEX('SKU Data'!$J$2:$J$1780,MATCH($A20,'SKU Data'!$A$2:$A$1780,0)),"") -> 0.050403226 | F20: =IFERROR(INDEX('SKU Data'!$H$2:$H$1780,MATCH($A20,'SKU Data'!$A$2:$A$1780,0)),"") -> 1085.57 | G20: =IFERROR(INDEX('SKU Data'!$K$2:$K$1780,MATCH($A20,'SKU Data'!$A$2:$A$1780,0)),"") -> 0.049336332 | H20: =IFERROR(INDEX('SKU Data'!$O$2:$O$1780,MATCH($A20,'SKU Data'!$A$2:$A$1780,0)),"") -> 2.4956049 | I20: =IFERROR(INDEX('SKU Data'!$W$2:$W$1780,MATCH($A20,'SKU Data'!$A$2:$A$1780,0)),"") -> 2 - Review | J20: =IFERROR(INDEX('SKU Data'!$X$2:$X$1780,MATCH($A20,'SKU Data'!$A$2:$A$1780,0)),"")
A21: MJ22-10 | B21: =IFERROR(INDEX('SKU Data'!$B$2:$B$1780,MATCH($A21,'SKU Data'!$A$2:$A$1780,0)),"") -> All the Pinks | C21: =IFERROR(INDEX('SKU Data'!$E$2:$E$1780,MATCH($A21,'SKU Data'!$A$2:$A$1780,0)),"") -> 204 | D21: =IFERROR(INDEX('SKU Data'!$F$2:$F$1780,MATCH($A21,'SKU Data'!$A$2:$A$1780,0)),"") -> 12 | E21: =IFERROR(INDEX('SKU Data'!$J$2:$J$1780,MATCH($A21,'SKU Data'!$A$2:$A$1780,0)),"") -> 0.058823529 | F21: =IFERROR(INDEX('SKU Data'!$H$2:$H$1780,MATCH($A21,'SKU Data'!$A$2:$A$1780,0)),"") -> 913.78 | G21: =IFERROR(INDEX('SKU Data'!$K$2:$K$1780,MATCH($A21,'SKU Data'!$A$2:$A$1780,0)),"") -> 0.06163345 | H21: =IFERROR(INDEX('SKU Data'!$O$2:$O$1780,MATCH($A21,'SKU Data'!$A$2:$A$1780,0)),"") -> 2.2945346 | I21: =IFERROR(INDEX('SKU Data'!$W$2:$W$1780,MATCH($A21,'SKU Data'!$A$2:$A$1780,0)),"") -> 2 - Review | J21: =IFERROR(INDEX('SKU Data'!$X$2:$X$1780,MATCH($A21,'SKU Data'!$A$2:$A$1780,0)),"")
A22: MJ102-53 | B22: =IFERROR(INDEX('SKU Data'!$B$2:$B$1780,MATCH($A22,'SKU Data'!$A$2:$A$1780,0)),"") -> Blow Out the Candles Bundle | C22: =IFERROR(INDEX('SKU Data'!$E$2:$E$1780,MATCH($A22,'SKU Data'!$A$2:$A$1780,0)),"") -> 130 | D22: =IFERROR(INDEX('SKU Data'!$F$2:$F$1780,MATCH($A22,'SKU Data'!$A$2:$A$1780,0)),"") -> 6 | E22: =IFERROR(INDEX('SKU Data'!$J$2:$J$1780,MATCH($A22,'SKU Data'!$A$2:$A$1780,0)),"") -> 0.046153846 | F22: =IFERROR(INDEX('SKU Data'!$H$2:$H$1780,MATCH($A22,'SKU Data'!$A$2:$A$1780,0)),"") -> 537.66 | G22: =IFERROR(INDEX('SKU Data'!$K$2:$K$1780,MATCH($A22,'SKU Data'!$A$2:$A$1780,0)),"") -> 0.043896883 | H22: =IFERROR(INDEX('SKU Data'!$O$2:$O$1780,MATCH($A22,'SKU Data'!$A$2:$A$1780,0)),"") -> 0.99802738 | I22: =IFERROR(INDEX('SKU Data'!$W$2:$W$1780,MATCH($A22,'SKU Data'!$A$2:$A$1780,0)),"") -> 3 - Monitor | J22: =IFERROR(INDEX('SKU Data'!$X$2:$X$1780,MATCH($A22,'SKU Data'!$A$2:$A$1780,0)),"")
A23: MJ11-30 | B23: =IFERROR(INDEX('SKU Data'!$B$2:$B$1780,MATCH($A23,'SKU Data'!$A$2:$A$1780,0)),"") -> Sweetheart Roses in Mason Jar | C23: =IFERROR(INDEX('SKU Data'!$E$2:$E$1780,MATCH($A23,'SKU Data'!$A$2:$A$1780,0)),"") -> 73 | D23: =IFERROR(INDEX('SKU Data'!$F$2:$F$1780,MATCH($A23,'SKU Data'!$A$2:$A$1780,0)),"") -> 4 | E23: =IFERROR(INDEX('SKU Data'!$J$2:$J$1780,MATCH($A23,'SKU Data'!$A$2:$A$1780,0)),"") -> 0.054794521 | F23: =IFERROR(INDEX('SKU Data'!$H$2:$H$1780,MATCH($A23,'SKU Data'!$A$2:$A$1780,0)),"") -> 272.1 | G23: =IFERROR(INDEX('SKU Data'!$K$2:$K$1780,MATCH($A23,'SKU Data'!$A$2:$A$1780,0)),"") -> 0.053670015 | H23: =IFERROR(INDEX('SKU Data'!$O$2:$O$1780,MATCH($A23,'SKU Data'!$A$2:$A$1780,0)),"") -> 1.1739302 | I23: =IFERROR(INDEX('SKU Data'!$W$2:$W$1780,MATCH($A23,'SKU Data'!$A$2:$A$1780,0)),"") -> 3 - Monitor | J23: =IFERROR(INDEX('SKU Data'!$X$2:$X$1780,MATCH($A23,'SKU Data'!$A$2:$A$1780,0)),"")
A24: MJ100-111 | B24: =IFERROR(INDEX('SKU Data'!$B$2:$B$1780,MATCH($A24,'SKU Data'!$A$2:$A$1780,0)),"") -> Enchanted Cottage in Mason Jar | C24: =IFERROR(INDEX('SKU Data'!$E$2:$E$1780,MATCH($A24,'SKU Data'!$A$2:$A$1780,0)),"") -> 57 | D24: =IFERROR(INDEX('SKU Data'!$F$2:$F$1780,MATCH($A24,'SKU Data'!$A$2:$A$1780,0)),"") -> 3 | E24: =IFERROR(INDEX('SKU Data'!$J$2:$J$1780,MATCH($A24,'SKU Data'!$A$2:$A$1780,0)),"") -> 0.052631579 | F24: =IFERROR(INDEX('SKU Data'!$H$2:$H$1780,MATCH($A24,'SKU Data'!$A$2:$A$1780,0)),"") -> 260.41 | G24: =IFERROR(INDEX('SKU Data'!$K$2:$K$1780,MATCH($A24,'SKU Data'!$A$2:$A$1780,0)),"") -> 0.047734617 | H24: =IFERROR(INDEX('SKU Data'!$O$2:$O$1780,MATCH($A24,'SKU Data'!$A$2:$A$1780,0)),"") -> 0.94309359 | I24: =IFERROR(INDEX('SKU Data'!$W$2:$W$1780,MATCH($A24,'SKU Data'!$A$2:$A$1780,0)),"") -> 3 - Monitor | J24: =IFERROR(INDEX('SKU Data'!$X$2:$X$1780,MATCH($A24,'SKU Data'!$A$2:$A$1780,0)),"")
... A27: MJ99-08 | B27: =IFERROR(INDEX('SKU Data'!$B$2:$B$1780,MATCH($A27,'SKU Data'!$A$2:$A$1780,0)),"") -> 50 Festive Peruvian Lilies | C27: =IFERROR(INDEX('SKU Data'!$E$2:$E$1780,MATCH($A27,'SKU Data'!$A$2:$A$1780,0)),"") -> 24 | D27: =IFERROR(INDEX('SKU Data'!$F$2:$F$1780,MATCH($A27,'SKU Data'!$A$2:$A$1780,0)),"") -> 1 | E27: =IFERROR(INDEX('SKU Data'!$J$2:$J$1780,MATCH($A27,'SKU Data'!$A$2:$A$1780,0)),"") -> 0.041666667 | F27: =IFERROR(INDEX('SKU Data'!$H$2:$H$1780,MATCH($A27,'SKU Data'!$A$2:$A$1780,0)),"") -> 114.71 | G27: =IFERROR(INDEX('SKU Data'!$K$2:$K$1780,MATCH($A27,'SKU Data'!$A$2:$A$1780,0)),"") -> 0.040513956 | H27: =IFERROR(INDEX('SKU Data'!$O$2:$O$1780,MATCH($A27,'SKU Data'!$A$2:$A$1780,0)),"") -> 0.30195973 | I27: =IFERROR(INDEX('SKU Data'!$W$2:$W$1780,MATCH($A27,'SKU Data'!$A$2:$A$1780,0)),"") -> 3 - Monitor | J27: =IFERROR(INDEX('SKU Data'!$X$2:$X$1780,MATCH($A27,'SKU Data'!$A$2:$A$1780,0)),"")

Sheet B-GF
A1: Brand / family: GF
A3: Gross sales $ | B3: Refund $ | C3: Refunded units | D3: Refund rate (units) | E3: vs portfolio baseline | F3: % of total refund $
A4: =Brands!E10 -> 437700.62 | B4: =Brands!F10 -> 21202.65 | C4: =Brands!D10 -> 234 | D4: =Brands!G10 -> 0.051769912 | E4: =Brands!K10 -> 1.6707435 | F4: =Brands!I10 -> 0.042374057
A6: What to pay attention to
A7: 1. Refund rate 5.2% vs 3.1% portfolio (1.7x); family = 4% of SKU-attributed refund $ on 3% of gross sales.
A8: 2. Concentration: top 3 SKUs = 77% of family refunds (GF16-100, GF16-110, GF16-105).
A9: 3. Attention: 4 SKU(s) statistically above baseline; worst = GF16-100 (Blushing Elegance) at 5.3% on 1,333 units.
A11: Top 15 SKUs in this family by refund $
A12: SKU | B12: Product | C12: Qty ordered | D12: Refunded units | E12: Refund rate (units) | F12: Refund $ | G12: Refund rate ($) | H12: z-score | I12: Tier | J12: Flag
A13: GF16-100 | B13: =IFERROR(INDEX('SKU Data'!$B$2:$B$1780,MATCH($A13,'SKU Data'!$A$2:$A$1780,0)),"") -> Blushing Elegance | C13: =IFERROR(INDEX('SKU Data'!$E$2:$E$1780,MATCH($A13,'SKU Data'!$A$2:$A$1780,0)),"") -> 1333 | D13: =IFERROR(INDEX('SKU Data'!$F$2:$F$1780,MATCH($A13,'SKU Data'!$A$2:$A$1780,0)),"") -> 70 | E13: =IFERROR(INDEX('SKU Data'!$J$2:$J$1780,MATCH($A13,'SKU Data'!$A$2:$A$1780,0)),"") -> 0.052513128 | F13: =IFERROR(INDEX('SKU Data'!$H$2:$H$1780,MATCH($A13,'SKU Data'!$A$2:$A$1780,0)),"") -> 6992.71 | G13: =IFERROR(INDEX('SKU Data'!$K$2:$K$1780,MATCH($A13,'SKU Data'!$A$2:$A$1780,0)),"") -> 0.046691952 | H13: =IFERROR(INDEX('SKU Data'!$O$2:$O$1780,MATCH($A13,'SKU Data'!$A$2:$A$1780,0)),"") -> 4.5357522 | I13: =IFERROR(INDEX('SKU Data'!$W$2:$W$1780,MATCH($A13,'SKU Data'!$A$2:$A$1780,0)),"") -> 1 - Fix first | J13: =IFERROR(INDEX('SKU Data'!$X$2:$X$1780,MATCH($A13,'SKU Data'!$A$2:$A$1780,0)),"") -> HIGH RATE
A14: GF16-110 | B14: =IFERROR(INDEX('SKU Data'!$B$2:$B$1780,MATCH($A14,'SKU Data'!$A$2:$A$1780,0)),"") -> Pastel Harmony | C14: =IFERROR(INDEX('SKU Data'!$E$2:$E$1780,MATCH($A14,'SKU Data'!$A$2:$A$1780,0)),"") -> 1130 | D14: =IFERROR(INDEX('SKU Data'!$F$2:$F$1780,MATCH($A14,'SKU Data'!$A$2:$A$1780,0)),"") -> 56 | E14: =IFERROR(INDEX('SKU Data'!$J$2:$J$1780,MATCH($A14,'SKU Data'!$A$2:$A$1780,0)),"") -> 0.049557522 | F14: =IFERROR(INDEX('SKU Data'!$H$2:$H$1780,MATCH($A14,'SKU Data'!$A$2:$A$1780,0)),"") -> 6386.94 | G14: =IFERROR(INDEX('SKU Data'!$K$2:$K$1780,MATCH($A14,'SKU Data'!$A$2:$A$1780,0)),"") -> 0.046227485 | H14: =IFERROR(INDEX('SKU Data'!$O$2:$O$1780,MATCH($A14,'SKU Data'!$A$2:$A$1780,0)),"") -> 3.6027521 | I14: =IFERROR(INDEX('SKU Data'!$W$2:$W$1780,MATCH($A14,'SKU Data'!$A$2:$A$1780,0)),"") -> 2 - Review | J14: =IFERROR(INDEX('SKU Data'!$X$2:$X$1780,MATCH($A14,'SKU Data'!$A$2:$A$1780,0)),"") -> HIGH RATE
A15: GF16-105 | B15: =IFERROR(INDEX('SKU Data'!$B$2:$B$1780,MATCH($A15,'SKU Data'!$A$2:$A$1780,0)),"") -> Sunset Serenade | C15: =IFERROR(INDEX('SKU Data'!$E$2:$E$1780,MATCH($A15,'SKU Data'!$A$2:$A$1780,0)),"") -> 946 | D15: =IFERROR(INDEX('SKU Data'!$F$2:$F$1780,MATCH($A15,'SKU Data'!$A$2:$A$1780,0)),"") -> 49 | E15: =IFERROR(INDEX('SKU Data'!$J$2:$J$1780,MATCH($A15,'SKU Data'!$A$2:$A$1780,0)),"") -> 0.05179704 | F15: =IFERROR(INDEX('SKU Data'!$H$2:$H$1780,MATCH($A15,'SKU Data'!$A$2:$A$1780,0)),"") -> 2843.02 | G15: =IFERROR(INDEX('SKU Data'!$K$2:$K$1780,MATCH($A15,'SKU Data'!$A$2:$A$1780,0)),"") -> 0.050355756 | H15: =IFERROR(INDEX('SKU Data'!$O$2:$O$1780,MATCH($A15,'SKU Data'!$A$2:$A$1780,0)),"") -> 3.6939192 | I15: =IFERROR(INDEX('SKU Data'!$W$2:$W$1780,MATCH($A15,'SKU Data'!$A$2:$A$1780,0)),"") -> 2 - Review | J15: =IFERROR(INDEX('SKU Data'!$X$2:$X$1780,MATCH($A15,'SKU Data'!$A$2:$A$1780,0)),"") -> HIGH RATE
A16: GF16-115 | B16: =IFERROR(INDEX('SKU Data'!$B$2:$B$1780,MATCH($A16,'SKU Data'!$A$2:$A$1780,0)),"") -> Delicate Elegance | C16: =IFERROR(INDEX('SKU Data'!$E$2:$E$1780,MATCH($A16,'SKU Data'!$A$2:$A$1780,0)),"") -> 685 | D16: =IFERROR(INDEX('SKU Data'!$F$2:$F$1780,MATCH($A16,'SKU Data'!$A$2:$A$1780,0)),"") -> 31 | E16: =IFERROR(INDEX('SKU Data'!$J$2:$J$1780,MATCH($A16,'SKU Data'!$A$2:$A$1780,0)),"") -> 0.045255474 | F16: =IFERROR(INDEX('SKU Data'!$H$2:$H$1780,MATCH($A16,'SKU Data'!$A$2:$A$1780,0)),"") -> 2403.45 | G16: =IFERROR(INDEX('SKU Data'!$K$2:$K$1780,MATCH($A16,'SKU Data'!$A$2:$A$1780,0)),"") -> 0.043712713 | H16: =IFERROR(INDEX('SKU Data'!$O$2:$O$1780,MATCH($A16,'SKU Data'!$A$2:$A$1780,0)),"") -> 2.1552609 | I16: =IFERROR(INDEX('SKU Data'!$W$2:$W$1780,MATCH($A16,'SKU Data'!$A$2:$A$1780,0)),"") -> 2 - Review | J16: =IFERROR(INDEX('SKU Data'!$X$2:$X$1780,MATCH($A16,'SKU Data'!$A$2:$A$1780,0)),"")
A17: GF10-15 | B17: =IFERROR(INDEX('SKU Data'!$B$2:$B$1780,MATCH($A17,'SKU Data'!$A$2:$A$1780,0)),"") -> Two Dozen Long Stem Red Roses | C17: =IFERROR(INDEX('SKU Data'!$E$2:$E$1780,MATCH($A17,'SKU Data'!$A$2:$A$1780,0)),"") -> 26 | D17: =IFERROR(INDEX('SKU Data'!$F$2:$F$1780,MATCH($A17,'SKU Data'!$A$2:$A$1780,0)),"") -> 5 | E17: =IFERROR(INDEX('SKU Data'!$J$2:$J$1780,MATCH($A17,'SKU Data'!$A$2:$A$1780,0)),"") -> 0.19230769 | F17: =IFERROR(INDEX('SKU Data'!$H$2:$H$1780,MATCH($A17,'SKU Data'!$A$2:$A$1780,0)),"") -> 751.83 | G17: =IFERROR(INDEX('SKU Data'!$K$2:$K$1780,MATCH($A17,'SKU Data'!$A$2:$A$1780,0)),"") -> 0.17983997 | H17: =IFERROR(INDEX('SKU Data'!$O$2:$O$1780,MATCH($A17,'SKU Data'!$A$2:$A$1780,0)),"") -> 4.7471202 | I17: =IFERROR(INDEX('SKU Data'!$W$2:$W$1780,MATCH($A17,'SKU Data'!$A$2:$A$1780,0)),"") -> 2 - Review | J17: =IFERROR(INDEX('SKU Data'!$X$2:$X$1780,MATCH($A17,'SKU Data'!$A$2:$A$1780,0)),"")
A18: GF60-10 | B18: =IFERROR(INDEX('SKU Data'!$B$2:$B$1780,MATCH($A18,'SKU Data'!$A$2:$A$1780,0)),"") -> Gorgeous Gerberas | C18: =IFERROR(INDEX('SKU Data'!$E$2:$E$1780,MATCH($A18,'SKU Data'!$A$2:$A$1780,0)),"") -> 77 | D18: =IFERROR(INDEX('SKU Data'!$F$2:$F$1780,MATCH($A18,'SKU Data'!$A$2:$A$1780,0)),"") -> 9 | E18: =IFERROR(INDEX('SKU Data'!$J$2:$J$1780,MATCH($A18,'SKU Data'!$A$2:$A$1780,0)),"") -> 0.11688312 | F18: =IFERROR(INDEX('SKU Data'!$H$2:$H$1780,MATCH($A18,'SKU Data'!$A$2:$A$1780,0)),"") -> 417.6 | G18: =IFERROR(INDEX('SKU Data'!$K$2:$K$1780,MATCH($A18,'SKU Data'!$A$2:$A$1780,0)),"") -> 0.11103843 | H18: =IFERROR(INDEX('SKU Data'!$O$2:$O$1780,MATCH($A18,'SKU Data'!$A$2:$A$1780,0)),"") -> 4.349851 | I18: =IFERROR(INDEX('SKU Data'!$W$2:$W$1780,MATCH($A18,'SKU Data'!$A$2:$A$1780,0)),"") -> 2 - Review | J18: =IFERROR(INDEX('SKU Data'!$X$2:$X$1780,MATCH($A18,'SKU Data'!$A$2:$A$1780,0)),"") -> HIGH RATE
A19: GF10-18 | B19: =IFERROR(INDEX('SKU Data'!$B$2:$B$1780,MATCH($A19,'SKU Data'!$A$2:$A$1780,0)),"") -> Three Dozen Long Stem Pink Roses | C19: =IFERROR(INDEX('SKU Data'!$E$2:$E$1780,MATCH($A19,'SKU Data'!$A$2:$A$1780,0)),"") -> 2 | D19: =IFERROR(INDEX('SKU Data'!$F$2:$F$1780,MATCH($A19,'SKU Data'!$A$2:$A$1780,0)),"") -> 1 | E19: =IFERROR(INDEX('SKU Data'!$J$2:$J$1780,MATCH($A19,'SKU Data'!$A$2:$A$1780,0)),"") -> 0.5 | F19: =IFERROR(INDEX('SKU Data'!$H$2:$H$1780,MATCH($A19,'SKU Data'!$A$2:$A$1780,0)),"") -> 290.86 | G19: =IFERROR(INDEX('SKU Data'!$K$2:$K$1780,MATCH($A19,'SKU Data'!$A$2:$A$1780,0)),"") -> 0.55173853 | H19: =IFERROR(INDEX('SKU Data'!$O$2:$O$1780,MATCH($A19,'SKU Data'!$A$2:$A$1780,0)),"") -> 3.8278231 | I19: =IFERROR(INDEX('SKU Data'!$W$2:$W$1780,MATCH($A19,'SKU Data'!$A$2:$A$1780,0)),"") -> 3 - Monitor | J19: =IFERROR(INDEX('SKU Data'!$X$2:$X$1780,MATCH($A19,'SKU Data'!$A$2:$A$1780,0)),"")
A20: GF10-01 | B20: =IFERROR(INDEX('SKU Data'!$B$2:$B$1780,MATCH($A20,'SKU Data'!$A$2:$A$1780,0)),"") -> Half Dozen Long Stem Red Roses | C20: =IFERROR(INDEX('SKU Data'!$E$2:$E$1780,MATCH($A20,'SKU Data'!$A$2:$A$1780,0)),"") -> 38 | D20: =IFERROR(INDEX('SKU Data'!$F$2:$F$1780,MATCH($A20,'SKU Data'!$A$2:$A$1780,0)),"") -> 4 | E20: =IFERROR(INDEX('SKU Data'!$J$2:$J$1780,MATCH($A20,'SKU Data'!$A$2:$A$1780,0)),"") -> 0.10526316 | F20: =IFERROR(INDEX('SKU Data'!$H$2:$H$1780,MATCH($A20,'SKU Data'!$A$2:$A$1780,0)),"") -> 276.64 | G20: =IFERROR(INDEX('SKU Data'!$K$2:$K$1780,MATCH($A20,'SKU Data'!$A$2:$A$1780,0)),"") -> 0.10466102 | H20: =IFERROR(INDEX('SKU Data'!$O$2:$O$1780,MATCH($A20,'SKU Data'!$A$2:$A$1780,0)),"") -> 2.6423928 | I20: =IFERROR(INDEX('SKU Data'!$W$2:$W$1780,MATCH($A20,'SKU Data'!$A$2:$A$1780,0)),"") -> 3 - Monitor | J20: =IFERROR(INDEX('SKU Data'!$X$2:$X$1780,MATCH($A20,'SKU Data'!$A$2:$A$1780,0)),"")
A21: GF10-17 | B21: =IFERROR(INDEX('SKU Data'!$B$2:$B$1780,MATCH($A21,'SKU Data'!$A$2:$A$1780,0)),"") -> Three Dozen Long Stemmed White Roses | C21: =IFERROR(INDEX('SKU Data'!$E$2:$E$1780,MATCH($A21,'SKU Data'!$A$2:$A$1780,0)),"") -> 6 | D21: =IFERROR(INDEX('SKU Data'!$F$2:$F$1780,MATCH($A21,'SKU Data'!$A$2:$A$1780,0)),"") -> 1 | E21: =IFERROR(INDEX('SKU Data'!$J$2:$J$1780,MATCH($A21,'SKU Data'!$A$2:$A$1780,0)),"") -> 0.16666667 | F21: =IFERROR(INDEX('SKU Data'!$H$2:$H$1780,MATCH($A21,'SKU Data'!$A$2:$A$1780,0)),"") -> 231.78 | G21: =IFERROR(INDEX('SKU Data'!$K$2:$K$1780,MATCH($A21,'SKU Data'!$A$2:$A$1780,0)),"") -> 0.15269881 | H21: =IFERROR(INDEX('SKU Data'!$O$2:$O$1780,MATCH($A21,'SKU Data'!$A$2:$A$1780,0)),"") -> 1.917981 | I21: =IFERROR(INDEX('SKU Data'!$W$2:$W$1780,MATCH($A21,'SKU Data'!$A$2:$A$1780,0)),"") -> 3 - Monitor | J21: =IFERROR(INDEX('SKU Data'!$X$2:$X$1780,MATCH($A21,'SKU Data'!$A$2:$A$1780,0)),"")
A22: GF60-12 | B22: =IFERROR(INDEX('SKU Data'!$B$2:$B$1780,MATCH($A22,'SKU Data'!$A$2:$A$1780,0)),"") -> Gerbera Brights | C22: =IFERROR(INDEX('SKU Data'!$E$2:$E$1780,MATCH($A22,'SKU Data'!$A$2:$A$1780,0)),"") -> 11 | D22: =IFERROR(INDEX('SKU Data'!$F$2:$F$1780,MATCH($A22,'SKU Data'!$A$2:$A$1780,0)),"") -> 3 | E22: =IFERROR(INDEX('SKU Data'!$J$2:$J$1780,MATCH($A22,'SKU Data'!$A$2:$A$1780,0)),"") -> 0.27272727 | F22: =IFERROR(INDEX('SKU Data'!$H$2:$H$1780,MATCH($A22,'SKU Data'!$A$2:$A$1780,0)),"") -> 189.87 | G22: =IFERROR(INDEX('SKU Data'!$K$2:$K$1780,MATCH($A22,'SKU Data'!$A$2:$A$1780,0)),"") -> 0.28094343 | H22: =IFERROR(INDEX('SKU Data'!$O$2:$O$1780,MATCH($A22,'SKU Data'!$A$2:$A$1780,0)),"") -> 4.6269847 | I22: =IFERROR(INDEX('SKU Data'!$W$2:$W$1780,MATCH($A22,'SKU Data'!$A$2:$A$1780,0)),"") -> 3 - Monitor | J22: =IFERROR(INDEX('SKU Data'!$X$2:$X$1780,MATCH($A22,'SKU Data'!$A$2:$A$1780,0)),"")
A23: GF16-110-DEL | B23: =IFERROR(INDEX('SKU Data'!$B$2:$B$1780,MATCH($A23,'SKU Data'!$A$2:$A$1780,0)),"") -> Pastel Harmony | C23: =IFERROR(INDEX('SKU Data'!$E$2:$E$1780,MATCH($A23,'SKU Data'!$A$2:$A$1780,0)),"") -> 14 | D23: =IFERROR(INDEX('SKU Data'!$F$2:$F$1780,MATCH($A23,'SKU Data'!$A$2:$A$1780,0)),"") -> 1 | E23: =IFERROR(INDEX('SKU Data'!$J$2:$J$1780,MATCH($A23,'SKU Data'!$A$2:$A$1780,0)),"") -> 0.071428571 | F23: =IFERROR(INDEX('SKU Data'!$H$2:$H$1780,MATCH($A23,'SKU Data'!$A$2:$A$1780,0)),"") -> 124.95 | G23: =IFERROR(INDEX('SKU Data'!$K$2:$K$1780,MATCH($A23,'SKU Data'!$A$2:$A$1780,0)),"") -> 0.071428571 | H23: =IFERROR(INDEX('SKU Data'!$O$2:$O$1780,MATCH($A23,'SKU Data'!$A$2:$A$1780,0)),"") -> 0.87327765 | I23: =IFERROR(INDEX('SKU Data'!$W$2:$W$1780,MATCH($A23,'SKU Data'!$A$2:$A$1780,0)),"") -> 3 - Monitor | J23: =IFERROR(INDEX('SKU Data'!$X$2:$X$1780,MATCH($A23,'SKU Data'!$A$2:$A$1780,0)),"")
A24: GF10-30 | B24: =IFERROR(INDEX('SKU Data'!$B$2:$B$1780,MATCH($A24,'SKU Data'!$A$2:$A$1780,0)),"") -> Harmony Blooms | C24: =IFERROR(INDEX('SKU Data'!$E$2:$E$1780,MATCH($A24,'SKU Data'!$A$2:$A$1780,0)),"") -> 52 | D24: =IFERROR(INDEX('SKU Data'!$F$2:$F$1780,MATCH($A24,'SKU Data'!$A$2:$A$1780,0)),"") -> 2 | E24: =IFERROR(INDEX('SKU Data'!$J$2:$J$1780,MATCH($A24,'SKU Data'!$A$2:$A$1780,0)),"") -> 0.038461538 | F24: =IFERROR(INDEX('SKU Data'!$H$2:$H$1780,MATCH($A24,'SKU Data'!$A$2:$A$1780,0)),"") -> 117.64 | G24: =IFERROR(INDEX('SKU Data'!$K$2:$K$1780,MATCH($A24,'SKU Data'!$A$2:$A$1780,0)),"") -> 0.03290298 | H24: =IFERROR(INDEX('SKU Data'!$O$2:$O$1780,MATCH($A24,'SKU Data'!$A$2:$A$1780,0)),"") -> 0.31109037 | I24: =IFERROR(INDEX('SKU Data'!$W$2:$W$1780,MATCH($A24,'SKU Data'!$A$2:$A$1780,0)),"") -> 3 - Monitor | J24: =IFERROR(INDEX('SKU Data'!$X$2:$X$1780,MATCH($A24,'SKU Data'!$A$2:$A$1780,0)),"")
... A27: GF10-02 | B27: =IFERROR(INDEX('SKU Data'!$B$2:$B$1780,MATCH($A27,'SKU Data'!$A$2:$A$1780,0)),"") -> One Dozen Boxed Red Roses | C27: =IFERROR(INDEX('SKU Data'!$E$2:$E$1780,MATCH($A27,'SKU Data'!$A$2:$A$1780,0)),"") -> 1 | D27: =IFERROR(INDEX('SKU Data'!$F$2:$F$1780,MATCH($A27,'SKU Data'!$A$2:$A$1780,0)),"") -> 0 | E27: =IFERROR(INDEX('SKU Data'!$J$2:$J$1780,MATCH($A27,'SKU Data'!$A$2:$A$1780,0)),"") -> 0 | F27: =IFERROR(INDEX('SKU Data'!$H$2:$H$1780,MATCH($A27,'SKU Data'!$A$2:$A$1780,0)),"") -> 0 | G27: =IFERROR(INDEX('SKU Data'!$K$2:$K$1780,MATCH($A27,'SKU Data'!$A$2:$A$1780,0)),"") -> 0 | H27: =IFERROR(INDEX('SKU Data'!$O$2:$O$1780,MATCH($A27,'SKU Data'!$A$2:$A$1780,0)),"") -> -0.17882113 | I27: =IFERROR(INDEX('SKU Data'!$W$2:$W$1780,MATCH($A27,'SKU Data'!$A$2:$A$1780,0)),"") | J27: =IFERROR(INDEX('SKU Data'!$X$2:$X$1780,MATCH($A27,'SKU Data'!$A$2:$A$1780,0)),"")

Sheet B-AURP
A1: Brand / family: AURP
A3: Gross sales $ | B3: Refund $ | C3: Refunded units | D3: Refund rate (units) | E3: vs portfolio baseline | F3: % of total refund $
A4: =Brands!E11 -> 477893.02 | B4: =Brands!F11 -> 17576.19 | C4: =Brands!D11 -> 1515 | D4: =Brands!G11 -> 0.041740137 | E4: =Brands!K11 -> 1.3470578 | F4: =Brands!I11 -> 0.035126481
A6: What to pay attention to
A7: 1. Refund rate 4.2% vs 3.1% portfolio (1.3x); family = 4% of SKU-attributed refund $ on 4% of gross sales.
A8: 2. Concentration: top 3 SKUs = 36% of family refunds (AURP-B29, AURP-C02, AURP05).
A9: 3. Attention: 8 SKU(s) statistically above baseline; worst = AURP04 (Glass Vase (Hand blown)) at 5.2% on 1,997 units.
A11: Top 15 SKUs in this family by refund $
A12: SKU | B12: Product | C12: Qty ordered | D12: Refunded units | E12: Refund rate (units) | F12: Refund $ | G12: Refund rate ($) | H12: z-score | I12: Tier | J12: Flag
A13: AURP-B29 | B13: =IFERROR(INDEX('SKU Data'!$B$2:$B$1780,MATCH($A13,'SKU Data'!$A$2:$A$1780,0)),"") -> The Birthday Bundle | C13: =IFERROR(INDEX('SKU Data'!$E$2:$E$1780,MATCH($A13,'SKU Data'!$A$2:$A$1780,0)),"") -> 1309 | D13: =IFERROR(INDEX('SKU Data'!$F$2:$F$1780,MATCH($A13,'SKU Data'!$A$2:$A$1780,0)),"") -> 41 | E13: =IFERROR(INDEX('SKU Data'!$J$2:$J$1780,MATCH($A13,'SKU Data'!$A$2:$A$1780,0)),"") -> 0.03132162 | F13: =IFERROR(INDEX('SKU Data'!$H$2:$H$1780,MATCH($A13,'SKU Data'!$A$2:$A$1780,0)),"") -> 2915.48 | G13: =IFERROR(INDEX('SKU Data'!$K$2:$K$1780,MATCH($A13,'SKU Data'!$A$2:$A$1780,0)),"") -> 0.026656982 | H13: =IFERROR(INDEX('SKU Data'!$O$2:$O$1780,MATCH($A13,'SKU Data'!$A$2:$A$1780,0)),"") -> 0.070044289 | I13: =IFERROR(INDEX('SKU Data'!$W$2:$W$1780,MATCH($A13,'SKU Data'!$A$2:$A$1780,0)),"") -> 3 - Monitor | J13: =IFERROR(INDEX('SKU Data'!$X$2:$X$1780,MATCH($A13,'SKU Data'!$A$2:$A$1780,0)),"")
A14: AURP-C02 | B14: =IFERROR(INDEX('SKU Data'!$B$2:$B$1780,MATCH($A14,'SKU Data'!$A$2:$A$1780,0)),"") -> Large Box of Premium Chocolates | C14: =IFERROR(INDEX('SKU Data'!$E$2:$E$1780,MATCH($A14,'SKU Data'!$A$2:$A$1780,0)),"") -> 2392 | D14: =IFERROR(INDEX('SKU Data'!$F$2:$F$1780,MATCH($A14,'SKU Data'!$A$2:$A$1780,0)),"") -> 96 | E14: =IFERROR(INDEX('SKU Data'!$J$2:$J$1780,MATCH($A14,'SKU Data'!$A$2:$A$1780,0)),"") -> 0.040133779 | F14: =IFERROR(INDEX('SKU Data'!$H$2:$H$1780,MATCH($A14,'SKU Data'!$A$2:$A$1780,0)),"") -> 1962.91 | G14: =IFERROR(INDEX('SKU Data'!$K$2:$K$1780,MATCH($A14,'SKU Data'!$A$2:$A$1780,0)),"") -> 0.037203686 | H14: =IFERROR(INDEX('SKU Data'!$O$2:$O$1780,MATCH($A14,'SKU Data'!$A$2:$A$1780,0)),"") -> 2.5819051 | I14: =IFERROR(INDEX('SKU Data'!$W$2:$W$1780,MATCH($A14,'SKU Data'!$A$2:$A$1780,0)),"") -> 2 - Review | J14: =IFERROR(INDEX('SKU Data'!$X$2:$X$1780,MATCH($A14,'SKU Data'!$A$2:$A$1780,0)),"")
A15: AURP05 | B15: =IFERROR(INDEX('SKU Data'!$B$2:$B$1780,MATCH($A15,'SKU Data'!$A$2:$A$1780,0)),"") -> Full Size Greeting Card | C15: =IFERROR(INDEX('SKU Data'!$E$2:$E$1780,MATCH($A15,'SKU Data'!$A$2:$A$1780,0)),"") -> 11080 | D15: =IFERROR(INDEX('SKU Data'!$F$2:$F$1780,MATCH($A15,'SKU Data'!$A$2:$A$1780,0)),"") -> 410 | E15: =IFERROR(INDEX('SKU Data'!$J$2:$J$1780,MATCH($A15,'SKU Data'!$A$2:$A$1780,0)),"") -> 0.03700361 | F15: =IFERROR(INDEX('SKU Data'!$H$2:$H$1780,MATCH($A15,'SKU Data'!$A$2:$A$1780,0)),"") -> 1427.63 | G15: =IFERROR(INDEX('SKU Data'!$K$2:$K$1780,MATCH($A15,'SKU Data'!$A$2:$A$1780,0)),"") -> 0.03432841 | H15: =IFERROR(INDEX('SKU Data'!$O$2:$O$1780,MATCH($A15,'SKU Data'!$A$2:$A$1780,0)),"") -> 3.6553942 | I15: =IFERROR(INDEX('SKU Data'!$W$2:$W$1780,MATCH($A15,'SKU Data'!$A$2:$A$1780,0)),"") -> 3 - Monitor | J15: =IFERROR(INDEX('SKU Data'!$X$2:$X$1780,MATCH($A15,'SKU Data'!$A$2:$A$1780,0)),"") -> HIGH RATE
A16: AURP-13sp | B16: =IFERROR(INDEX('SKU Data'!$B$2:$B$1780,MATCH($A16,'SKU Data'!$A$2:$A$1780,0)),"") -> Chocolates & Teddy | C16: =IFERROR(INDEX('SKU Data'!$E$2:$E$1780,MATCH($A16,'SKU Data'!$A$2:$A$1780,0)),"") -> 1589 | D16: =IFERROR(INDEX('SKU Data'!$F$2:$F$1780,MATCH($A16,'SKU Data'!$A$2:$A$1780,0)),"") -> 85 | E16: =IFERROR(INDEX('SKU Data'!$J$2:$J$1780,MATCH($A16,'SKU Data'!$A$2:$A$1780,0)),"") -> 0.053492763 | F16: =IFERROR(INDEX('SKU Data'!$H$2:$H$1780,MATCH($A16,'SKU Data'!$A$2:$A$1780,0)),"") -> 1209.72 | G16: =IFERROR(INDEX('SKU Data'!$K$2:$K$1780,MATCH($A16,'SKU Data'!$A$2:$A$1780,0)),"") -> 0.05022534 | H16: =IFERROR(INDEX('SKU Data'!$O$2:$O$1780,MATCH($A16,'SKU Data'!$A$2:$A$1780,0)),"") -> 5.1775375 | I16: =IFERROR(INDEX('SKU Data'!$W$2:$W$1780,MATCH($A16,'SKU Data'!$A$2:$A$1780,0)),"") -> 2 - Review | J16: =IFERROR(INDEX('SKU Data'!$X$2:$X$1780,MATCH($A16,'SKU Data'!$A$2:$A$1780,0)),"") -> HIGH RATE
A17: AURP03 | B17: =IFERROR(INDEX('SKU Data'!$B$2:$B$1780,MATCH($A17,'SKU Data'!$A$2:$A$1780,0)),"") -> Glass Vase | C17: =IFERROR(INDEX('SKU Data'!$E$2:$E$1780,MATCH($A17,'SKU Data'!$A$2:$A$1780,0)),"") -> 2409 | D17: =IFERROR(INDEX('SKU Data'!$F$2:$F$1780,MATCH($A17,'SKU Data'!$A$2:$A$1780,0)),"") -> 112 | E17: =IFERROR(INDEX('SKU Data'!$J$2:$J$1780,MATCH($A17,'SKU Data'!$A$2:$A$1780,0)),"") -> 0.04649232 | F17: =IFERROR(INDEX('SKU Data'!$H$2:$H$1780,MATCH($A17,'SKU Data'!$A$2:$A$1780,0)),"") -> 1180.39 | G17: =IFERROR(INDEX('SKU Data'!$K$2:$K$1780,MATCH($A17,'SKU Data'!$A$2:$A$1780,0)),"") -> 0.043241847 | H17: =IFERROR(INDEX('SKU Data'!$O$2:$O$1780,MATCH($A17,'SKU Data'!$A$2:$A$1780,0)),"") -> 4.3921192 | I17: =IFERROR(INDEX('SKU Data'!$W$2:$W$1780,MATCH($A17,'SKU Data'!$A$2:$A$1780,0)),"") -> 2 - Review | J17: =IFERROR(INDEX('SKU Data'!$X$2:$X$1780,MATCH($A17,'SKU Data'!$A$2:$A$1780,0)),"") -> HIGH RATE
A18: AURP02-30 | B18: =IFERROR(INDEX('SKU Data'!$B$2:$B$1780,MATCH($A18,'SKU Data'!$A$2:$A$1780,0)),"") -> Belgium Truffles | C18: =IFERROR(INDEX('SKU Data'!$E$2:$E$1780,MATCH($A18,'SKU Data'!$A$2:$A$1780,0)),"") -> 1815 | D18: =IFERROR(INDEX('SKU Data'!$F$2:$F$1780,MATCH($A18,'SKU Data'!$A$2:$A$1780,0)),"") -> 93 | E18: =IFERROR(INDEX('SKU Data'!$J$2:$J$1780,MATCH($A18,'SKU Data'!$A$2:$A$1780,0)),"") -> 0.051239669 | F18: =IFERROR(INDEX('SKU Data'!$H$2:$H$1780,MATCH($A18,'SKU Data'!$A$2:$A$1780,0)),"") -> 820.3 | G18: =IFERROR(INDEX('SKU Data'!$K$2:$K$1780,MATCH($A18,'SKU Data'!$A$2:$A$1780,0)),"") -> 0.047649751 | H18: =IFERROR(INDEX('SKU Data'!$O$2:$O$1780,MATCH($A18,'SKU Data'!$A$2:$A$1780,0)),"") -> 4.9795487 | I18: =IFERROR(INDEX('SKU Data'!$W$2:$W$1780,MATCH($A18,'SKU Data'!$A$2:$A$1780,0)),"") -> 2 - Review | J18: =IFERROR(INDEX('SKU Data'!$X$2:$X$1780,MATCH($A18,'SKU Data'!$A$2:$A$1780,0)),"") -> HIGH RATE
A19: AURP04 | B19: =IFERROR(INDEX('SKU Data'!$B$2:$B$1780,MATCH($A19,'SKU Data'!$A$2:$A$1780,0)),"") -> Glass Vase (Hand blown) | C19: =IFERROR(INDEX('SKU Data'!$E$2:$E$1780,MATCH($A19,'SKU Data'!$A$2:$A$1780,0)),"") -> 1997 | D19: =IFERROR(INDEX('SKU Data'!$F$2:$F$1780,MATCH($A19,'SKU Data'!$A$2:$A$1780,0)),"") -> 104 | E19: =IFERROR(INDEX('SKU Data'!$J$2:$J$1780,MATCH($A19,'SKU Data'!$A$2:$A$1780,0)),"") -> 0.052078117 | F19: =IFERROR(INDEX('SKU Data'!$H$2:$H$1780,MATCH($A19,'SKU Data'!$A$2:$A$1780,0)),"") -> 811.9 | G19: =IFERROR(INDEX('SKU Data'!$K$2:$K$1780,MATCH($A19,'SKU Data'!$A$2:$A$1780,0)),"") -> 0.04880999 | H19: =IFERROR(INDEX('SKU Data'!$O$2:$O$1780,MATCH($A19,'SKU Data'!$A$2:$A$1780,0)),"") -> 5.4394788 | I19: =IFERROR(INDEX('SKU Data'!$W$2:$W$1780,MATCH($A19,'SKU Data'!$A$2:$A$1780,0)),"") -> 2 - Review | J19: =IFERROR(INDEX('SKU Data'!$X$2:$X$1780,MATCH($A19,'SKU Data'!$A$2:$A$1780,0)),"") -> HIGH RATE
A20: AURP-B1 | B20: =IFERROR(INDEX('SKU Data'!$B$2:$B$1780,MATCH($A20,'SKU Data'!$A$2:$A$1780,0)),"") -> I Love You Balloon | C20: =IFERROR(INDEX('SKU Data'!$E$2:$E$1780,MATCH($A20,'SKU Data'!$A$2:$A$1780,0)),"") -> 1872 | D20: =IFERROR(INDEX('SKU Data'!$F$2:$F$1780,MATCH($A20,'SKU Data'!$A$2:$A$1780,0)),"") -> 92 | E20: =IFERROR(INDEX('SKU Data'!$J$2:$J$1780,MATCH($A20,'SKU Data'!$A$2:$A$1780,0)),"") -> 0.049145299 | F20: =IFERROR(INDEX('SKU Data'!$H$2:$H$1780,MATCH($A20,'SKU Data'!$A$2:$A$1780,0)),"") -> 750.47 | G20: =IFERROR(INDEX('SKU Data'!$K$2:$K$1780,MATCH($A20,'SKU Data'!$A$2:$A$1780,0)),"") -> 0.046376151 | H20: =IFERROR(INDEX('SKU Data'!$O$2:$O$1780,MATCH($A20,'SKU Data'!$A$2:$A$1780,0)),"") -> 4.5341886 | I20: =IFERROR(INDEX('SKU Data'!$W$2:$W$1780,MATCH($A20,'SKU Data'!$A$2:$A$1780,0)),"") -> 2 - Review | J20: =IFERROR(INDEX('SKU Data'!$X$2:$X$1780,MATCH($A20,'SKU Data'!$A$2:$A$1780,0)),"") -> HIGH RATE
A21: AURP-12 | B21: =IFERROR(INDEX('SKU Data'!$B$2:$B$1780,MATCH($A21,'SKU Data'!$A$2:$A$1780,0)),"") -> Card & Teddy | C21: =IFERROR(INDEX('SKU Data'!$E$2:$E$1780,MATCH($A21,'SKU Data'!$A$2:$A$1780,0)),"") -> 1443 | D21: =IFERROR(INDEX('SKU Data'!$F$2:$F$1780,MATCH($A21,'SKU Data'!$A$2:$A$1780,0)),"") -> 48 | E21: =IFERROR(INDEX('SKU Data'!$J$2:$J$1780,MATCH($A21,'SKU Data'!$A$2:$A$1780,0)),"") -> 0.033264033 | F21: =IFERROR(INDEX('SKU Data'!$H$2:$H$1780,MATCH($A21,'SKU Data'!$A$2:$A$1780,0)),"") -> 743.79 | G21: =IFERROR(INDEX('SKU Data'!$K$2:$K$1780,MATCH($A21,'SKU Data'!$A$2:$A$1780,0)),"") -> 0.031495746 | H21: =IFERROR(INDEX('SKU Data'!$O$2:$O$1780,MATCH($A21,'SKU Data'!$A$2:$A$1780,0)),"") -> 0.49936214 | I21: =IFERROR(INDEX('SKU Data'!$W$2:$W$1780,MATCH($A21,'SKU Data'!$A$2:$A$1780,0)),"") -> 3 - Monitor | J21: =IFERROR(INDEX('SKU Data'!$X$2:$X$1780,MATCH($A21,'SKU Data'!$A$2:$A$1780,0)),"")
A22: AURP-C01 | B22: =IFERROR(INDEX('SKU Data'!$B$2:$B$1780,MATCH($A22,'SKU Data'!$A$2:$A$1780,0)),"") -> Premium Chocolates | C22: =IFERROR(INDEX('SKU Data'!$E$2:$E$1780,MATCH($A22,'SKU Data'!$A$2:$A$1780,0)),"") -> 1440 | D22: =IFERROR(INDEX('SKU Data'!$F$2:$F$1780,MATCH($A22,'SKU Data'!$A$2:$A$1780,0)),"") -> 51 | E22: =IFERROR(INDEX('SKU Data'!$J$2:$J$1780,MATCH($A22,'SKU Data'!$A$2:$A$1780,0)),"") -> 0.035416667 | F22: =IFERROR(INDEX('SKU Data'!$H$2:$H$1780,MATCH($A22,'SKU Data'!$A$2:$A$1780,0)),"") -> 710.97 | G22: =IFERROR(INDEX('SKU Data'!$K$2:$K$1780,MATCH($A22,'SKU Data'!$A$2:$A$1780,0)),"") -> 0.031184057 | H22: =IFERROR(INDEX('SKU Data'!$O$2:$O$1780,MATCH($A22,'SKU Data'!$A$2:$A$1780,0)),"") -> 0.97025682 | I22: =IFERROR(INDEX('SKU Data'!$W$2:$W$1780,MATCH($A22,'SKU Data'!$A$2:$A$1780,0)),"") -> 3 - Monitor | J22: =IFERROR(INDEX('SKU Data'!$X$2:$X$1780,MATCH($A22,'SKU Data'!$A$2:$A$1780,0)),"")
A23: AURP06 | B23: =IFERROR(INDEX('SKU Data'!$B$2:$B$1780,MATCH($A23,'SKU Data'!$A$2:$A$1780,0)),"") -> Teddy Bear | C23: =IFERROR(INDEX('SKU Data'!$E$2:$E$1780,MATCH($A23,'SKU Data'!$A$2:$A$1780,0)),"") -> 1548 | D23: =IFERROR(INDEX('SKU Data'!$F$2:$F$1780,MATCH($A23,'SKU Data'!$A$2:$A$1780,0)),"") -> 67 | E23: =IFERROR(INDEX('SKU Data'!$J$2:$J$1780,MATCH($A23,'SKU Data'!$A$2:$A$1780,0)),"") -> 0.043281654 | F23: =IFERROR(INDEX('SKU Data'!$H$2:$H$1780,MATCH($A23,'SKU Data'!$A$2:$A$1780,0)),"") -> 700.65 | G23: =IFERROR(INDEX('SKU Data'!$K$2:$K$1780,MATCH($A23,'SKU Data'!$A$2:$A$1780,0)),"") -> 0.039520486 | H23: =IFERROR(INDEX('SKU Data'!$O$2:$O$1780,MATCH($A23,'SKU Data'!$A$2:$A$1780,0)),"") -> 2.7917914 | I23: =IFERROR(INDEX('SKU Data'!$W$2:$W$1780,MATCH($A23,'SKU Data'!$A$2:$A$1780,0)),"") -> 3 - Monitor | J23: =IFERROR(INDEX('SKU Data'!$X$2:$X$1780,MATCH($A23,'SKU Data'!$A$2:$A$1780,0)),"")
A24: AURP-10sp | B24: =IFERROR(INDEX('SKU Data'!$B$2:$B$1780,MATCH($A24,'SKU Data'!$A$2:$A$1780,0)),"") -> Vase & Card | C24: =IFERROR(INDEX('SKU Data'!$E$2:$E$1780,MATCH($A24,'SKU Data'!$A$2:$A$1780,0)),"") -> 761 | D24: =IFERROR(INDEX('SKU Data'!$F$2:$F$1780,MATCH($A24,'SKU Data'!$A$2:$A$1780,0)),"") -> 35 | E24: =IFERROR(INDEX('SKU Data'!$J$2:$J$1780,MATCH($A24,'SKU Data'!$A$2:$A$1780,0)),"") -> 0.045992116 | F24: =IFERROR(INDEX('SKU Data'!$H$2:$H$1780,MATCH($A24,'SKU Data'!$A$2:$A$1780,0)),"") -> 612.2 | G24: =IFERROR(INDEX('SKU Data'!$K$2:$K$1780,MATCH($A24,'SKU Data'!$A$2:$A$1780,0)),"") -> 0.052429691 | H24: =IFERROR(INDEX('SKU Data'!$O$2:$O$1780,MATCH($A24,'SKU Data'!$A$2:$A$1780,0)),"") -> 2.3889521 | I24: =IFERROR(INDEX('SKU Data'!$W$2:$W$1780,MATCH($A24,'SKU Data'!$A$2:$A$1780,0)),"") -> 3 - Monitor | J24: =IFERROR(INDEX('SKU Data'!$X$2:$X$1780,MATCH($A24,'SKU Data'!$A$2:$A$1780,0)),"")
... A27: AURP-80 | B27: =IFERROR(INDEX('SKU Data'!$B$2:$B$1780,MATCH($A27,'SKU Data'!$A$2:$A$1780,0)),"") -> Large Chocolates Special | C27: =IFERROR(INDEX('SKU Data'!$E$2:$E$1780,MATCH($A27,'SKU Data'!$A$2:$A$1780,0)),"") -> 505 | D27: =IFERROR(INDEX('SKU Data'!$F$2:$F$1780,MATCH($A27,'SKU Data'!$A$2:$A$1780,0)),"") -> 24 | E27: =IFERROR(INDEX('SKU Data'!$J$2:$J$1780,MATCH($A27,'SKU Data'!$A$2:$A$1780,0)),"") -> 0.047524752 | F27: =IFERROR(INDEX('SKU Data'!$H$2:$H$1780,MATCH($A27,'SKU Data'!$A$2:$A$1780,0)),"") -> 507.78 | G27: =IFERROR(INDEX('SKU Data'!$K$2:$K$1780,MATCH($A27,'SKU Data'!$A$2:$A$1780,0)),"") -> 0.045131266 | H27: =IFERROR(INDEX('SKU Data'!$O$2:$O$1780,MATCH($A27,'SKU Data'!$A$2:$A$1780,0)),"") -> 2.1448438 | I27: =IFERROR(INDEX('SKU Data'!$W$2:$W$1780,MATCH($A27,'SKU Data'!$A$2:$A$1780,0)),"") -> 3 - Monitor | J27: =IFERROR(INDEX('SKU Data'!$X$2:$X$1780,MATCH($A27,'SKU Data'!$A$2:$A$1780,0)),"")

Sheet B-AUSMJ
A1: Brand / family: AUSMJ
A3: Gross sales $ | B3: Refund $ | C3: Refunded units | D3: Refund rate (units) | E3: vs portfolio baseline | F3: % of total refund $
A4: =Brands!E12 -> 355681.8 | B4: =Brands!F12 -> 13788.78 | C4: =Brands!D12 -> 205 | D4: =Brands!G12 -> 0.040650407 | E4: =Brands!K12 -> 1.3118895 | F4: =Brands!I12 -> 0.027557241
A6: What to pay attention to
A7: 1. Refund rate 4.1% vs 3.1% portfolio (1.3x); family = 3% of SKU-attributed refund $ on 3% of gross sales.
A8: 2. Concentration: top 3 SKUs = 100% of family refunds (AUSMJ100-11, AUSMJ100-11-DEL, AUSMJ100-11-REG).
A9: 3. Attention: 1 SKU(s) statistically above baseline; worst = AUSMJ100-11 (Breathtaking Blooms In Mason Jar) at 4.1% on 4,959 units.
A11: Top 15 SKUs in this family by refund $
A12: SKU | B12: Product | C12: Qty ordered | D12: Refunded units | E12: Refund rate (units) | F12: Refund $ | G12: Refund rate ($) | H12: z-score | I12: Tier | J12: Flag
A13: AUSMJ100-11 | B13: =IFERROR(INDEX('SKU Data'!$B$2:$B$1780,MATCH($A13,'SKU Data'!$A$2:$A$1780,0)),"") -> Breathtaking Blooms In Mason Jar | C13: =IFERROR(INDEX('SKU Data'!$E$2:$E$1780,MATCH($A13,'SKU Data'!$A$2:$A$1780,0)),"") -> 4959 | D13: =IFERROR(INDEX('SKU Data'!$F$2:$F$1780,MATCH($A13,'SKU Data'!$A$2:$A$1780,0)),"") -> 203 | E13: =IFERROR(INDEX('SKU Data'!$J$2:$J$1780,MATCH($A13,'SKU Data'!$A$2:$A$1780,0)),"") -> 0.040935673 | F13: =IFERROR(INDEX('SKU Data'!$H$2:$H$1780,MATCH($A13,'SKU Data'!$A$2:$A$1780,0)),"") -> 13653.88 | G13: =IFERROR(INDEX('SKU Data'!$K$2:$K$1780,MATCH($A13,'SKU Data'!$A$2:$A$1780,0)),"") -> 0.039004288 | H13: =IFERROR(INDEX('SKU Data'!$O$2:$O$1780,MATCH($A13,'SKU Data'!$A$2:$A$1780,0)),"") -> 4.0434347 | I13: =IFERROR(INDEX('SKU Data'!$W$2:$W$1780,MATCH($A13,'SKU Data'!$A$2:$A$1780,0)),"") -> 2 - Review | J13: =IFERROR(INDEX('SKU Data'!$X$2:$X$1780,MATCH($A13,'SKU Data'!$A$2:$A$1780,0)),"") -> HIGH RATE
A14: AUSMJ100-11-DEL | B14: =IFERROR(INDEX('SKU Data'!$B$2:$B$1780,MATCH($A14,'SKU Data'!$A$2:$A$1780,0)),"") -> Breathtaking Blooms In Mason Jar | C14: =IFERROR(INDEX('SKU Data'!$E$2:$E$1780,MATCH($A14,'SKU Data'!$A$2:$A$1780,0)),"") -> 23 | D14: =IFERROR(INDEX('SKU Data'!$F$2:$F$1780,MATCH($A14,'SKU Data'!$A$2:$A$1780,0)),"") -> 1 | E14: =IFERROR(INDEX('SKU Data'!$J$2:$J$1780,MATCH($A14,'SKU Data'!$A$2:$A$1780,0)),"") -> 0.043478261 | F14: =IFERROR(INDEX('SKU Data'!$H$2:$H$1780,MATCH($A14,'SKU Data'!$A$2:$A$1780,0)),"") -> 74.95 | G14: =IFERROR(INDEX('SKU Data'!$K$2:$K$1780,MATCH($A14,'SKU Data'!$A$2:$A$1780,0)),"") -> 0.043478261 | H14: =IFERROR(INDEX('SKU Data'!$O$2:$O$1780,MATCH($A14,'SKU Data'!$A$2:$A$1780,0)),"") -> 0.34574101 | I14: =IFERROR(INDEX('SKU Data'!$W$2:$W$1780,MATCH($A14,'SKU Data'!$A$2:$A$1780,0)),"") -> 3 - Monitor | J14: =IFERROR(INDEX('SKU Data'!$X$2:$X$1780,MATCH($A14,'SKU Data'!$A$2:$A$1780,0)),"")
A15: AUSMJ100-11-REG | B15: =IFERROR(INDEX('SKU Data'!$B$2:$B$1780,MATCH($A15,'SKU Data'!$A$2:$A$1780,0)),"") -> Breathtaking Blooms In Mason Jar | C15: =IFERROR(INDEX('SKU Data'!$E$2:$E$1780,MATCH($A15,'SKU Data'!$A$2:$A$1780,0)),"") -> 54 | D15: =IFERROR(INDEX('SKU Data'!$F$2:$F$1780,MATCH($A15,'SKU Data'!$A$2:$A$1780,0)),"") -> 1 | E15: =IFERROR(INDEX('SKU Data'!$J$2:$J$1780,MATCH($A15,'SKU Data'!$A$2:$A$1780,0)),"") -> 0.018518519 | F15: =IFERROR(INDEX('SKU Data'!$H$2:$H$1780,MATCH($A15,'SKU Data'!$A$2:$A$1780,0)),"") -> 59.95 | G15: =IFERROR(INDEX('SKU Data'!$K$2:$K$1780,MATCH($A15,'SKU Data'!$A$2:$A$1780,0)),"") -> 0.018518519 | H15: =IFERROR(INDEX('SKU Data'!$O$2:$O$1780,MATCH($A15,'SKU Data'!$A$2:$A$1780,0)),"") -> -0.5287277 | I15: =IFERROR(INDEX('SKU Data'!$W$2:$W$1780,MATCH($A15,'SKU Data'!$A$2:$A$1780,0)),"") -> 3 - Monitor | J15: =IFERROR(INDEX('SKU Data'!$X$2:$X$1780,MATCH($A15,'SKU Data'!$A$2:$A$1780,0)),"")
A16: AUSMJ100-11-GRA | B16: =IFERROR(INDEX('SKU Data'!$B$2:$B$1780,MATCH($A16,'SKU Data'!$A$2:$A$1780,0)),"") -> Breathtaking Blooms In Mason Jar | C16: =IFERROR(INDEX('SKU Data'!$E$2:$E$1780,MATCH($A16,'SKU Data'!$A$2:$A$1780,0)),"") -> 5 | D16: =IFERROR(INDEX('SKU Data'!$F$2:$F$1780,MATCH($A16,'SKU Data'!$A$2:$A$1780,0)),"") -> 0 | E16: =IFERROR(INDEX('SKU Data'!$J$2:$J$1780,MATCH($A16,'SKU Data'!$A$2:$A$1780,0)),"") -> 0 | F16: =IFERROR(INDEX('SKU Data'!$H$2:$H$1780,MATCH($A16,'SKU Data'!$A$2:$A$1780,0)),"") -> 0 | G16: =IFERROR(INDEX('SKU Data'!$K$2:$K$1780,MATCH($A16,'SKU Data'!$A$2:$A$1780,0)),"") -> 0 | H16: =IFERROR(INDEX('SKU Data'!$O$2:$O$1780,MATCH($A16,'SKU Data'!$A$2:$A$1780,0)),"") -> -0.39985619 | I16: =IFERROR(INDEX('SKU Data'!$W$2:$W$1780,MATCH($A16,'SKU Data'!$A$2:$A$1780,0)),"") | J16: =IFERROR(INDEX('SKU Data'!$X$2:$X$1780,MATCH($A16,'SKU Data'!$A$2:$A$1780,0)),"")
A17: AUSMJ100-11-PRE | B17: =IFERROR(INDEX('SKU Data'!$B$2:$B$1780,MATCH($A17,'SKU Data'!$A$2:$A$1780,0)),"") -> Breathtaking Blooms In Mason Jar | C17: =IFERROR(INDEX('SKU Data'!$E$2:$E$1780,MATCH($A17,'SKU Data'!$A$2:$A$1780,0)),"") -> 2 | D17: =IFERROR(INDEX('SKU Data'!$F$2:$F$1780,MATCH($A17,'SKU Data'!$A$2:$A$1780,0)),"") -> 0 | E17: =IFERROR(INDEX('SKU Data'!$J$2:$J$1780,MATCH($A17,'SKU Data'!$A$2:$A$1780,0)),"") -> 0 | F17: =IFERROR(INDEX('SKU Data'!$H$2:$H$1780,MATCH($A17,'SKU Data'!$A$2:$A$1780,0)),"") -> 0 | G17: =IFERROR(INDEX('SKU Data'!$K$2:$K$1780,MATCH($A17,'SKU Data'!$A$2:$A$1780,0)),"") -> 0 | H17: =IFERROR(INDEX('SKU Data'!$O$2:$O$1780,MATCH($A17,'SKU Data'!$A$2:$A$1780,0)),"") -> -0.25289126 | I17: =IFERROR(INDEX('SKU Data'!$W$2:$W$1780,MATCH($A17,'SKU Data'!$A$2:$A$1780,0)),"") | J17: =IFERROR(INDEX('SKU Data'!$X$2:$X$1780,MATCH($A17,'SKU Data'!$A$2:$A$1780,0)),"")

Sheet Anomalies
A1: Anomaly detection
A2: Method: each SKU / brand refund count is compared with what the portfolio baseline rate predicts for its volume (binomial z-score). z >= 3 with min volume & refunds (Settings) = HIGH RATE. Caveat: refunds can cluster by order, so true significance is somewhat weaker than z implies - treat as a prioritisation signal, not proof.
A4: A) TIME anomalies (sudden spikes by date / month)
A5: NOT TESTABLE with this file. The export is one total per SKU for 2026-01-01 to 2026-10-10 - it has no date, month, order or store column, so a sudden increase on a given day/month cannot be seen. To enable it, re-export the same report with 'Day' or 'Month' added as a dimension (and 'Store/Vendor' if available). Once provided, I will add a monthly trend and spike detection (month-over-month and vs. trailing average) per brand and per SKU.
A7: B) DATA anomalies
A8: Finding | F8: Why it matters / next step
A9: Refund line with NO SKU and NO product title: $542,320 ex-tax = 52% of all reversals in the export ($1,045,073). Gross sales and units on that line are 0. | F9: Biggest single item in the file; cannot be ranked by product. Likely order-level / non-line refunds (shipping, tips, adjustments, or refunds booked without line items) - to be confirmed. Ask for the refund report by order with refund reason.
A10: 326 lines have a title but blank SKU (custom / manual orders, e.g. 'CO-...'): refunds $2,385 on 430 units - refund rate 11.4%, ~3.5x the baseline. | F10: Small in $, but a high rate: manual orders have no SKU control. Excluded from SKU ranking.
A11: 424 SKUs appear on more than one row because the title at time of sale changed. Rows were merged by SKU (title = highest-sales name). | F11: Check whether renamed products were also repriced or re-specified - a rename plus a spec change can drive refunds.
A12: Several 'products' are add-ons (vase, card, balloon, teddy, chocolates: RP*, AURP*, AUSRP*, SC*, VDB*) with refund rates of 5-8%. | F12: Likely refunded together with the parent order rather than on their own merit - verify before blaming the add-on.
A14: C) SKU anomalies - refund rate significantly above baseline (top 40 by z-score, live)
A15: # | B15: SKU | C15: Product | D15: Brand / family | E15: Qty ordered | F15: Refunded units | G15: Refund rate | H15: Rate vs baseline | I15: z-score | J15: Refund $ | K15: Tier
A16: 1 | B16: =IFERROR(INDEX('SKU Data'!$A$2:$A$1780,MATCH($A16,'SKU Data'!$AB$2:$AB$1780,0)),"") -> AUMJ-NW-005 | C16: =IFERROR(INDEX('SKU Data'!$B$2:$B$1780,MATCH($A16,'SKU Data'!$AB$2:$AB$1780,0)),"") -> Native Flowers Bouquet in Mason Jar | D16: =IFERROR(INDEX('SKU Data'!$D$2:$D$1780,MATCH($A16,'SKU Data'!$AB$2:$AB$1780,0)),"") -> AUMJ | E16: =IFERROR(INDEX('SKU Data'!$E$2:$E$1780,MATCH($A16,'SKU Data'!$AB$2:$AB$1780,0)),"") -> 6304 | F16: =IFERROR(INDEX('SKU Data'!$F$2:$F$1780,MATCH($A16,'SKU Data'!$AB$2:$AB$1780,0)),"") -> 335 | G16: =IFERROR(INDEX('SKU Data'!$J$2:$J$1780,MATCH($A16,'SKU Data'!$AB$2:$AB$1780,0)),"") -> 0.053140863 | H16: =IFERROR(G16/Settings!$B$3,"") -> 1.7149875 | I16: =IFERROR(INDEX('SKU Data'!$O$2:$O$1780,MATCH($A16,'SKU Data'!$AB$2:$AB$1780,0)),"") -> 10.151387 | J16: =IFERROR(INDEX('SKU Data'!$H$2:$H$1780,MATCH($A16,'SKU Data'!$AB$2:$AB$1780,0)),"") -> 30439.34 | K16: =IFERROR(INDEX('SKU Data'!$W$2:$W$1780,MATCH($A16,'SKU Data'!$AB$2:$AB$1780,0)),"") -> 1 - Fix first
A17: 2 | B17: =IFERROR(INDEX('SKU Data'!$A$2:$A$1780,MATCH($A17,'SKU Data'!$AB$2:$AB$1780,0)),"") -> RP19 | C17: =IFERROR(INDEX('SKU Data'!$B$2:$B$1780,MATCH($A17,'SKU Data'!$AB$2:$AB$1780,0)),"") -> Full Size Birthday Card | D17: =IFERROR(INDEX('SKU Data'!$D$2:$D$1780,MATCH($A17,'SKU Data'!$AB$2:$AB$1780,0)),"") -> RP | E17: =IFERROR(INDEX('SKU Data'!$E$2:$E$1780,MATCH($A17,'SKU Data'!$AB$2:$AB$1780,0)),"") -> 6456 | F17: =IFERROR(INDEX('SKU Data'!$F$2:$F$1780,MATCH($A17,'SKU Data'!$AB$2:$AB$1780,0)),"") -> 336 | G17: =IFERROR(INDEX('SKU Data'!$J$2:$J$1780,MATCH($A17,'SKU Data'!$AB$2:$AB$1780,0)),"") -> 0.05204461 | H17: =IFERROR(G17/Settings!$B$3,"") -> 1.6796087 | I17: =IFERROR(INDEX('SKU Data'!$O$2:$O$1780,MATCH($A17,'SKU Data'!$AB$2:$AB$1780,0)),"") -> 9.7647141 | J17: =IFERROR(INDEX('SKU Data'!$H$2:$H$1780,MATCH($A17,'SKU Data'!$AB$2:$AB$1780,0)),"") -> 1172.41 | K17: =IFERROR(INDEX('SKU Data'!$W$2:$W$1780,MATCH($A17,'SKU Data'!$AB$2:$AB$1780,0)),"") -> 2 - Review
A18: 3 | B18: =IFERROR(INDEX('SKU Data'!$A$2:$A$1780,MATCH($A18,'SKU Data'!$AB$2:$AB$1780,0)),"") -> RP03S | C18: =IFERROR(INDEX('SKU Data'!$B$2:$B$1780,MATCH($A18,'SKU Data'!$AB$2:$AB$1780,0)),"") -> Clear Glass Vase | D18: =IFERROR(INDEX('SKU Data'!$D$2:$D$1780,MATCH($A18,'SKU Data'!$AB$2:$AB$1780,0)),"") -> RP | E18: =IFERROR(INDEX('SKU Data'!$E$2:$E$1780,MATCH($A18,'SKU Data'!$AB$2:$AB$1780,0)),"") -> 1096 | F18: =IFERROR(INDEX('SKU Data'!$F$2:$F$1780,MATCH($A18,'SKU Data'!$AB$2:$AB$1780,0)),"") -> 88 | G18: =IFERROR(INDEX('SKU Data'!$J$2:$J$1780,MATCH($A18,'SKU Data'!$AB$2:$AB$1780,0)),"") -> 0.080291971 | H18: =IFERROR(G18/Settings!$B$3,"") -> 2.5912212 | I18: =IFERROR(INDEX('SKU Data'!$O$2:$O$1780,MATCH($A18,'SKU Data'!$AB$2:$AB$1780,0)),"") -> 9.4200813 | J18: =IFERROR(INDEX('SKU Data'!$H$2:$H$1780,MATCH($A18,'SKU Data'!$AB$2:$AB$1780,0)),"") -> 748.77 | K18: =IFERROR(INDEX('SKU Data'!$W$2:$W$1780,MATCH($A18,'SKU Data'!$AB$2:$AB$1780,0)),"") -> 1 - Fix first
A19: 4 | B19: =IFERROR(INDEX('SKU Data'!$A$2:$A$1780,MATCH($A19,'SKU Data'!$AB$2:$AB$1780,0)),"") -> AU0511-17 | C19: =IFERROR(INDEX('SKU Data'!$B$2:$B$1780,MATCH($A19,'SKU Data'!$AB$2:$AB$1780,0)),"") -> Summer Blooms | D19: =IFERROR(INDEX('SKU Data'!$D$2:$D$1780,MATCH($A19,'SKU Data'!$AB$2:$AB$1780,0)),"") -> AU | E19: =IFERROR(INDEX('SKU Data'!$E$2:$E$1780,MATCH($A19,'SKU Data'!$AB$2:$AB$1780,0)),"") -> 1560 | F19: =IFERROR(INDEX('SKU Data'!$F$2:$F$1780,MATCH($A19,'SKU Data'!$AB$2:$AB$1780,0)),"") -> 97 | G19: =IFERROR(INDEX('SKU Data'!$J$2:$J$1780,MATCH($A19,'SKU Data'!$AB$2:$AB$1780,0)),"") -> 0.062179487 | H19: =IFERROR(G19/Settings!$B$3,"") -> 2.0066864 | I19: =IFERROR(INDEX('SKU Data'!$O$2:$O$1780,MATCH($A19,'SKU Data'!$AB$2:$AB$1780,0)),"") -> 7.1100935 | J19: =IFERROR(INDEX('SKU Data'!$H$2:$H$1780,MATCH($A19,'SKU Data'!$AB$2:$AB$1780,0)),"") -> 5315.16 | K19: =IFERROR(INDEX('SKU Data'!$W$2:$W$1780,MATCH($A19,'SKU Data'!$AB$2:$AB$1780,0)),"") -> 1 - Fix first
A20: 5 | B20: =IFERROR(INDEX('SKU Data'!$A$2:$A$1780,MATCH($A20,'SKU Data'!$AB$2:$AB$1780,0)),"") -> AUSRP-16sp | C20: =IFERROR(INDEX('SKU Data'!$B$2:$B$1780,MATCH($A20,'SKU Data'!$AB$2:$AB$1780,0)),"") -> Truffles & Card | D20: =IFERROR(INDEX('SKU Data'!$D$2:$D$1780,MATCH($A20,'SKU Data'!$AB$2:$AB$1780,0)),"") -> AUSRP | E20: =IFERROR(INDEX('SKU Data'!$E$2:$E$1780,MATCH($A20,'SKU Data'!$AB$2:$AB$1780,0)),"") -> 2919 | F20: =IFERROR(INDEX('SKU Data'!$F$2:$F$1780,MATCH($A20,'SKU Data'!$AB$2:$AB$1780,0)),"") -> 152 | G20: =IFERROR(INDEX('SKU Data'!$J$2:$J$1780,MATCH($A20,'SKU Data'!$AB$2:$AB$1780,0)),"") -> 0.052072628 | H20: =IFERROR(G20/Settings!$B$3,"") -> 1.6805129 | I20: =IFERROR(INDEX('SKU Data'!$O$2:$O$1780,MATCH($A20,'SKU Data'!$AB$2:$AB$1780,0)),"") -> 6.5746442 | J20: =IFERROR(INDEX('SKU Data'!$H$2:$H$1780,MATCH($A20,'SKU Data'!$AB$2:$AB$1780,0)),"") -> 1385.93 | K20: =IFERROR(INDEX('SKU Data'!$W$2:$W$1780,MATCH($A20,'SKU Data'!$AB$2:$AB$1780,0)),"") -> 2 - Review
A21: 6 | B21: =IFERROR(INDEX('SKU Data'!$A$2:$A$1780,MATCH($A21,'SKU Data'!$AB$2:$AB$1780,0)),"") -> RP02-50 | C21: =IFERROR(INDEX('SKU Data'!$B$2:$B$1780,MATCH($A21,'SKU Data'!$AB$2:$AB$1780,0)),"") -> Blue Vase | D21: =IFERROR(INDEX('SKU Data'!$D$2:$D$1780,MATCH($A21,'SKU Data'!$AB$2:$AB$1780,0)),"") -> RP | E21: =IFERROR(INDEX('SKU Data'!$E$2:$E$1780,MATCH($A21,'SKU Data'!$AB$2:$AB$1780,0)),"") -> 406 | F21: =IFERROR(INDEX('SKU Data'!$F$2:$F$1780,MATCH($A21,'SKU Data'!$AB$2:$AB$1780,0)),"") -> 35 | G21: =IFERROR(INDEX('SKU Data'!$J$2:$J$1780,MATCH($A21,'SKU Data'!$AB$2:$AB$1780,0)),"") -> 0.086206897 | H21: =IFERROR(G21/Settings!$B$3,"") -> 2.7821105 | I21: =IFERROR(INDEX('SKU Data'!$O$2:$O$1780,MATCH($A21,'SKU Data'!$AB$2:$AB$1780,0)),"") -> 6.4212041 | J21: =IFERROR(INDEX('SKU Data'!$H$2:$H$1780,MATCH($A21,'SKU Data'!$AB$2:$AB$1780,0)),"") -> 358.96 | K21: =IFERROR(INDEX('SKU Data'!$W$2:$W$1780,MATCH($A21,'SKU Data'!$AB$2:$AB$1780,0)),"") -> 2 - Review
A22: 7 | B22: =IFERROR(INDEX('SKU Data'!$A$2:$A$1780,MATCH($A22,'SKU Data'!$AB$2:$AB$1780,0)),"") -> AU501-05 | C22: =IFERROR(INDEX('SKU Data'!$B$2:$B$1780,MATCH($A22,'SKU Data'!$AB$2:$AB$1780,0)),"") -> Half Dozen Red Roses, Card & Teddy | D22: =IFERROR(INDEX('SKU Data'!$D$2:$D$1780,MATCH($A22,'SKU Data'!$AB$2:$AB$1780,0)),"") -> AU | E22: =IFERROR(INDEX('SKU Data'!$E$2:$E$1780,MATCH($A22,'SKU Data'!$AB$2:$AB$1780,0)),"") -> 390 | F22: =IFERROR(INDEX('SKU Data'!$F$2:$F$1780,MATCH($A22,'SKU Data'!$AB$2:$AB$1780,0)),"") -> 34 | G22: =IFERROR(INDEX('SKU Data'!$J$2:$J$1780,MATCH($A22,'SKU Data'!$AB$2:$AB$1780,0)),"") -> 0.087179487 | H22: =IFERROR(G22/Settings!$B$3,"") -> 2.8134984 | I22: =IFERROR(INDEX('SKU Data'!$O$2:$O$1780,MATCH($A22,'SKU Data'!$AB$2:$AB$1780,0)),"") -> 6.4042505 | J22: =IFERROR(INDEX('SKU Data'!$H$2:$H$1780,MATCH($A22,'SKU Data'!$AB$2:$AB$1780,0)),"") -> 2661.08 | K22: =IFERROR(INDEX('SKU Data'!$W$2:$W$1780,MATCH($A22,'SKU Data'!$AB$2:$AB$1780,0)),"") -> 1 - Fix first
A23: 8 | B23: =IFERROR(INDEX('SKU Data'!$A$2:$A$1780,MATCH($A23,'SKU Data'!$AB$2:$AB$1780,0)),"") -> DCA-02-00 | C23: =IFERROR(INDEX('SKU Data'!$B$2:$B$1780,MATCH($A23,'SKU Data'!$AB$2:$AB$1780,0)),"") -> Anniversary Designer Collection II | D23: =IFERROR(INDEX('SKU Data'!$D$2:$D$1780,MATCH($A23,'SKU Data'!$AB$2:$AB$1780,0)),"") -> Other (small prefixes) | E23: =IFERROR(INDEX('SKU Data'!$E$2:$E$1780,MATCH($A23,'SKU Data'!$AB$2:$AB$1780,0)),"") -> 38 | F23: =IFERROR(INDEX('SKU Data'!$F$2:$F$1780,MATCH($A23,'SKU Data'!$AB$2:$AB$1780,0)),"") -> 8 | G23: =IFERROR(INDEX('SKU Data'!$J$2:$J$1780,MATCH($A23,'SKU Data'!$AB$2:$AB$1780,0)),"") -> 0.21052632 | H23: =IFERROR(G23/Settings!$B$3,"") -> 6.7942067 | I23: =IFERROR(INDEX('SKU Data'!$O$2:$O$1780,MATCH($A23,'SKU Data'!$AB$2:$AB$1780,0)),"") -> 6.3871131 | J23: =IFERROR(INDEX('SKU Data'!$H$2:$H$1780,MATCH($A23,'SKU Data'!$AB$2:$AB$1780,0)),"") -> 735.3 | K23: =IFERROR(INDEX('SKU Data'!$W$2:$W$1780,MATCH($A23,'SKU Data'!$AB$2:$AB$1780,0)),"") -> 2 - Review
A24: 9 | B24: =IFERROR(INDEX('SKU Data'!$A$2:$A$1780,MATCH($A24,'SKU Data'!$AB$2:$AB$1780,0)),"") -> AUMJ-NW-008 | C24: =IFERROR(INDEX('SKU Data'!$B$2:$B$1780,MATCH($A24,'SKU Data'!$AB$2:$AB$1780,0)),"") -> Golden Hour Bouquet in Mason Jar | D24: =IFERROR(INDEX('SKU Data'!$D$2:$D$1780,MATCH($A24,'SKU Data'!$AB$2:$AB$1780,0)),"") -> AUMJ | E24: =IFERROR(INDEX('SKU Data'!$E$2:$E$1780,MATCH($A24,'SKU Data'!$AB$2:$AB$1780,0)),"") -> 503 | F24: =IFERROR(INDEX('SKU Data'!$F$2:$F$1780,MATCH($A24,'SKU Data'!$AB$2:$AB$1780,0)),"") -> 40 | G24: =IFERROR(INDEX('SKU Data'!$J$2:$J$1780,MATCH($A24,'SKU Data'!$AB$2:$AB$1780,0)),"") -> 0.079522863 | H24: =IFERROR(G24/Settings!$B$3,"") -> 2.5664002 | I24: =IFERROR(INDEX('SKU Data'!$O$2:$O$1780,MATCH($A24,'SKU Data'!$AB$2:$AB$1780,0)),"") -> 6.28211 | J24: =IFERROR(INDEX('SKU Data'!$H$2:$H$1780,MATCH($A24,'SKU Data'!$AB$2:$AB$1780,0)),"") -> 3723.61 | K24: =IFERROR(INDEX('SKU Data'!$W$2:$W$1780,MATCH($A24,'SKU Data'!$AB$2:$AB$1780,0)),"") -> 1 - Fix first
A25: 10 | B25: =IFERROR(INDEX('SKU Data'!$A$2:$A$1780,MATCH($A25,'SKU Data'!$AB$2:$AB$1780,0)),"") -> AUMJ-NW-011 | C25: =IFERROR(INDEX('SKU Data'!$B$2:$B$1780,MATCH($A25,'SKU Data'!$AB$2:$AB$1780,0)),"") -> Best Birthday Ever Bouquet in Mason Jar | D25: =IFERROR(INDEX('SKU Data'!$D$2:$D$1780,MATCH($A25,'SKU Data'!$AB$2:$AB$1780,0)),"") -> AUMJ | E25: =IFERROR(INDEX('SKU Data'!$E$2:$E$1780,MATCH($A25,'SKU Data'!$AB$2:$AB$1780,0)),"") -> 2143 | F25: =IFERROR(INDEX('SKU Data'!$F$2:$F$1780,MATCH($A25,'SKU Data'!$AB$2:$AB$1780,0)),"") -> 115 | G25: =IFERROR(INDEX('SKU Data'!$J$2:$J$1780,MATCH($A25,'SKU Data'!$AB$2:$AB$1780,0)),"") -> 0.053663089 | H25: =IFERROR(G25/Settings!$B$3,"") -> 1.7318411 | I25: =IFERROR(INDEX('SKU Data'!$O$2:$O$1780,MATCH($A25,'SKU Data'!$AB$2:$AB$1780,0)),"") -> 6.058243 | J25: =IFERROR(INDEX('SKU Data'!$H$2:$H$1780,MATCH($A25,'SKU Data'!$AB$2:$AB$1780,0)),"") -> 9879.04 | K25: =IFERROR(INDEX('SKU Data'!$W$2:$W$1780,MATCH($A25,'SKU Data'!$AB$2:$AB$1780,0)),"") -> 1 - Fix first
A26: 11 | B26: =IFERROR(INDEX('SKU Data'!$A$2:$A$1780,MATCH($A26,'SKU Data'!$AB$2:$AB$1780,0)),"") -> DC-02B | C26: =IFERROR(INDEX('SKU Data'!$B$2:$B$1780,MATCH($A26,'SKU Data'!$AB$2:$AB$1780,0)),"") -> Birthday Designer Collection II | D26: =IFERROR(INDEX('SKU Data'!$D$2:$D$1780,MATCH($A26,'SKU Data'!$AB$2:$AB$1780,0)),"") -> DC | E26: =IFERROR(INDEX('SKU Data'!$E$2:$E$1780,MATCH($A26,'SKU Data'!$AB$2:$AB$1780,0)),"") -> 322 | F26: =IFERROR(INDEX('SKU Data'!$F$2:$F$1780,MATCH($A26,'SKU Data'!$AB$2:$AB$1780,0)),"") -> 28 | G26: =IFERROR(INDEX('SKU Data'!$J$2:$J$1780,MATCH($A26,'SKU Data'!$AB$2:$AB$1780,0)),"") -> 0.086956522 | H26: =IFERROR(G26/Settings!$B$3,"") -> 2.8063028 | I26: =IFERROR(INDEX('SKU Data'!$O$2:$O$1780,MATCH($A26,'SKU Data'!$AB$2:$AB$1780,0)),"") -> 5.7961192 | J26: =IFERROR(INDEX('SKU Data'!$H$2:$H$1780,MATCH($A26,'SKU Data'!$AB$2:$AB$1780,0)),"") -> 2889.28 | K26: =IFERROR(INDEX('SKU Data'!$W$2:$W$1780,MATCH($A26,'SKU Data'!$AB$2:$AB$1780,0)),"") -> 1 - Fix first
A27: 12 | B27: =IFERROR(INDEX('SKU Data'!$A$2:$A$1780,MATCH($A27,'SKU Data'!$AB$2:$AB$1780,0)),"") -> AUMJ-NW-019 | C27: =IFERROR(INDEX('SKU Data'!$B$2:$B$1780,MATCH($A27,'SKU Data'!$AB$2:$AB$1780,0)),"") -> Garden Party Bouquet in Mason Jar | D27: =IFERROR(INDEX('SKU Data'!$D$2:$D$1780,MATCH($A27,'SKU Data'!$AB$2:$AB$1780,0)),"") -> AUMJ | E27: =IFERROR(INDEX('SKU Data'!$E$2:$E$1780,MATCH($A27,'SKU Data'!$AB$2:$AB$1780,0)),"") -> 1250 | F27: =IFERROR(INDEX('SKU Data'!$F$2:$F$1780,MATCH($A27,'SKU Data'!$AB$2:$AB$1780,0)),"") -> 74 | G27: =IFERROR(INDEX('SKU Data'!$J$2:$J$1780,MATCH($A27,'SKU Data'!$AB$2:$AB$1780,0)),"") -> 0.0592 | H27: =IFERROR(G27/Settings!$B$3,"") -> 1.9105309 | I27: =IFERROR(INDEX('SKU Data'!$O$2:$O$1780,MATCH($A27,'SKU Data'!$AB$2:$AB$1780,0)),"") -> 5.7566329 | J27: =IFERROR(INDEX('SKU Data'!$H$2:$H$1780,MATCH($A27,'SKU Data'!$AB$2:$AB$1780,0)),"") -> 8226.91 | K27: =IFERROR(INDEX('SKU Data'!$W$2:$W$1780,MATCH($A27,'SKU Data'!$AB$2:$AB$1780,0)),"") -> 1 - Fix first
... A55: 40 | B55: =IFERROR(INDEX('SKU Data'!$A$2:$A$1780,MATCH($A55,'SKU Data'!$AB$2:$AB$1780,0)),"") -> AUSMJ100-11 | C55: =IFERROR(INDEX('SKU Data'!$B$2:$B$1780,MATCH($A55,'SKU Data'!$AB$2:$AB$1780,0)),"") -> Breathtaking Blooms In Mason Jar | D55: =IFERROR(INDEX('SKU Data'!$D$2:$D$1780,MATCH($A55,'SKU Data'!$AB$2:$AB$1780,0)),"") -> AUSMJ | E55: =IFERROR(INDEX('SKU Data'!$E$2:$E$1780,MATCH($A55,'SKU Data'!$AB$2:$AB$1780,0)),"") -> 4959 | F55: =IFERROR(INDEX('SKU Data'!$F$2:$F$1780,MATCH($A55,'SKU Data'!$AB$2:$AB$1780,0)),"") -> 203 | G55: =IFERROR(INDEX('SKU Data'!$J$2:$J$1780,MATCH($A55,'SKU Data'!$AB$2:$AB$1780,0)),"") -> 0.040935673 | H55: =IFERROR(G55/Settings!$B$3,"") -> 1.3210958 | I55: =IFERROR(INDEX('SKU Data'!$O$2:$O$1780,MATCH($A55,'SKU Data'!$AB$2:$AB$1780,0)),"") -> 4.0434347 | J55: =IFERROR(INDEX('SKU Data'!$H$2:$H$1780,MATCH($A55,'SKU Data'!$AB$2:$AB$1780,0)),"") -> 13653.88 | K55: =IFERROR(INDEX('SKU Data'!$W$2:$W$1780,MATCH($A55,'SKU Data'!$AB$2:$AB$1780,0)),"") -> 2 - Review
A56: Flagged SKUs in total (live): | D56: =COUNTIF('SKU Data'!$X$2:$X$1780,"HIGH RATE") -> 60
A58: D) Extreme rate but LOW volume (below min volume - watch, not yet significant)
A59: # | B59: SKU | C59: Product | D59: Brand / family | E59: Qty ordered | F59: Refunded units | G59: Refund rate | H59: Rate vs baseline | J59: Refund $ | K59: Tier
A60: 1 | B60: AU101-45 | C60: =IFERROR(INDEX('SKU Data'!$B$2:$B$1780,MATCH($B60,'SKU Data'!$A$2:$A$1780,0)),"") -> Rose and Lily Casket Arrangement | D60: =IFERROR(INDEX('SKU Data'!$D$2:$D$1780,MATCH($B60,'SKU Data'!$A$2:$A$1780,0)),"") -> AU | E60: =IFERROR(INDEX('SKU Data'!$E$2:$E$1780,MATCH($B60,'SKU Data'!$A$2:$A$1780,0)),"") -> 2 | F60: =IFERROR(INDEX('SKU Data'!$F$2:$F$1780,MATCH($B60,'SKU Data'!$A$2:$A$1780,0)),"") -> 2 | G60: =IFERROR(INDEX('SKU Data'!$J$2:$J$1780,MATCH($B60,'SKU Data'!$A$2:$A$1780,0)),"") -> 1 | H60: =IFERROR(G60/Settings!$B$3,"") -> 32.272482 | J60: =IFERROR(INDEX('SKU Data'!$H$2:$H$1780,MATCH($B60,'SKU Data'!$A$2:$A$1780,0)),"") -> 747.52 | K60: =IFERROR(INDEX('SKU Data'!$W$2:$W$1780,MATCH($B60,'SKU Data'!$A$2:$A$1780,0)),"") -> 3 - Monitor
A61: 2 | B61: FYF-blue-iris-bouquet-ten-stems-C | C61: =IFERROR(INDEX('SKU Data'!$B$2:$B$1780,MATCH($B61,'SKU Data'!$A$2:$A$1780,0)),"") -> Blue Iris Bouquet Ten Stems | D61: =IFERROR(INDEX('SKU Data'!$D$2:$D$1780,MATCH($B61,'SKU Data'!$A$2:$A$1780,0)),"") -> FYF | E61: =IFERROR(INDEX('SKU Data'!$E$2:$E$1780,MATCH($B61,'SKU Data'!$A$2:$A$1780,0)),"") -> 4 | F61: =IFERROR(INDEX('SKU Data'!$F$2:$F$1780,MATCH($B61,'SKU Data'!$A$2:$A$1780,0)),"") -> 2 | G61: =IFERROR(INDEX('SKU Data'!$J$2:$J$1780,MATCH($B61,'SKU Data'!$A$2:$A$1780,0)),"") -> 0.5 | H61: =IFERROR(G61/Settings!$B$3,"") -> 16.136241 | J61: =IFERROR(INDEX('SKU Data'!$H$2:$H$1780,MATCH($B61,'SKU Data'!$A$2:$A$1780,0)),"") -> 229.9 | K61: =IFERROR(INDEX('SKU Data'!$W$2:$W$1780,MATCH($B61,'SKU Data'!$A$2:$A$1780,0)),"") -> 3 - Monitor
A62: 3 | B62: AU115-12W | C62: =IFERROR(INDEX('SKU Data'!$B$2:$B$1780,MATCH($B62,'SKU Data'!$A$2:$A$1780,0)),"") -> Dozen Red Roses and White Wine Combo | D62: =IFERROR(INDEX('SKU Data'!$D$2:$D$1780,MATCH($B62,'SKU Data'!$A$2:$A$1780,0)),"") -> AU | E62: =IFERROR(INDEX('SKU Data'!$E$2:$E$1780,MATCH($B62,'SKU Data'!$A$2:$A$1780,0)),"") -> 6 | F62: =IFERROR(INDEX('SKU Data'!$F$2:$F$1780,MATCH($B62,'SKU Data'!$A$2:$A$1780,0)),"") -> 2 | G62: =IFERROR(INDEX('SKU Data'!$J$2:$J$1780,MATCH($B62,'SKU Data'!$A$2:$A$1780,0)),"") -> 0.33333333 | H62: =IFERROR(G62/Settings!$B$3,"") -> 10.757494 | J62: =IFERROR(INDEX('SKU Data'!$H$2:$H$1780,MATCH($B62,'SKU Data'!$A$2:$A$1780,0)),"") -> 310.83 | K62: =IFERROR(INDEX('SKU Data'!$W$2:$W$1780,MATCH($B62,'SKU Data'!$A$2:$A$1780,0)),"") -> 3 - Monitor
A63: 4 | B63: FYF-plush-teddy-bear-D-4 | C63: =IFERROR(INDEX('SKU Data'!$B$2:$B$1780,MATCH($B63,'SKU Data'!$A$2:$A$1780,0)),"") -> Plush Teddy Bear | D63: =IFERROR(INDEX('SKU Data'!$D$2:$D$1780,MATCH($B63,'SKU Data'!$A$2:$A$1780,0)),"") -> FYF | E63: =IFERROR(INDEX('SKU Data'!$E$2:$E$1780,MATCH($B63,'SKU Data'!$A$2:$A$1780,0)),"") -> 7 | F63: =IFERROR(INDEX('SKU Data'!$F$2:$F$1780,MATCH($B63,'SKU Data'!$A$2:$A$1780,0)),"") -> 2 | G63: =IFERROR(INDEX('SKU Data'!$J$2:$J$1780,MATCH($B63,'SKU Data'!$A$2:$A$1780,0)),"") -> 0.28571429 | H63: =IFERROR(G63/Settings!$B$3,"") -> 9.2207091 | J63: =IFERROR(INDEX('SKU Data'!$H$2:$H$1780,MATCH($B63,'SKU Data'!$A$2:$A$1780,0)),"") -> 89.9 | K63: =IFERROR(INDEX('SKU Data'!$W$2:$W$1780,MATCH($B63,'SKU Data'!$A$2:$A$1780,0)),"") -> 3 - Monitor
A64: 5 | B64: GF60-12 | C64: =IFERROR(INDEX('SKU Data'!$B$2:$B$1780,MATCH($B64,'SKU Data'!$A$2:$A$1780,0)),"") -> Gerbera Brights | D64: =IFERROR(INDEX('SKU Data'!$D$2:$D$1780,MATCH($B64,'SKU Data'!$A$2:$A$1780,0)),"") -> GF | E64: =IFERROR(INDEX('SKU Data'!$E$2:$E$1780,MATCH($B64,'SKU Data'!$A$2:$A$1780,0)),"") -> 11 | F64: =IFERROR(INDEX('SKU Data'!$F$2:$F$1780,MATCH($B64,'SKU Data'!$A$2:$A$1780,0)),"") -> 3 | G64: =IFERROR(INDEX('SKU Data'!$J$2:$J$1780,MATCH($B64,'SKU Data'!$A$2:$A$1780,0)),"") -> 0.27272727 | H64: =IFERROR(G64/Settings!$B$3,"") -> 8.801586 | J64: =IFERROR(INDEX('SKU Data'!$H$2:$H$1780,MATCH($B64,'SKU Data'!$A$2:$A$1780,0)),"") -> 189.87 | K64: =IFERROR(INDEX('SKU Data'!$W$2:$W$1780,MATCH($B64,'SKU Data'!$A$2:$A$1780,0)),"") -> 3 - Monitor
A65: 6 | B65: AUSGRT-04 | C65: =IFERROR(INDEX('SKU Data'!$B$2:$B$1780,MATCH($B65,'SKU Data'!$A$2:$A$1780,0)),"") -> Sunshine Gerbera Trio | D65: =IFERROR(INDEX('SKU Data'!$D$2:$D$1780,MATCH($B65,'SKU Data'!$A$2:$A$1780,0)),"") -> Other (small prefixes) | E65: =IFERROR(INDEX('SKU Data'!$E$2:$E$1780,MATCH($B65,'SKU Data'!$A$2:$A$1780,0)),"") -> 8 | F65: =IFERROR(INDEX('SKU Data'!$F$2:$F$1780,MATCH($B65,'SKU Data'!$A$2:$A$1780,0)),"") -> 2 | G65: =IFERROR(INDEX('SKU Data'!$J$2:$J$1780,MATCH($B65,'SKU Data'!$A$2:$A$1780,0)),"") -> 0.25 | H65: =IFERROR(G65/Settings!$B$3,"") -> 8.0681205 | J65: =IFERROR(INDEX('SKU Data'!$H$2:$H$1780,MATCH($B65,'SKU Data'!$A$2:$A$1780,0)),"") -> 84.9 | K65: =IFERROR(INDEX('SKU Data'!$W$2:$W$1780,MATCH($B65,'SKU Data'!$A$2:$A$1780,0)),"") -> 3 - Monitor
A66: 7 | B66: FYF-one-dozen-boxed-red-roses-nz-product-special-price-C | C66: =IFERROR(INDEX('SKU Data'!$B$2:$B$1780,MATCH($B66,'SKU Data'!$A$2:$A$1780,0)),"") -> One Dozen Boxed Red Roses (Nz Product Special Price) | D66: =IFERROR(INDEX('SKU Data'!$D$2:$D$1780,MATCH($B66,'SKU Data'!$A$2:$A$1780,0)),"") -> FYF | E66: =IFERROR(INDEX('SKU Data'!$E$2:$E$1780,MATCH($B66,'SKU Data'!$A$2:$A$1780,0)),"") -> 8 | F66: =IFERROR(INDEX('SKU Data'!$F$2:$F$1780,MATCH($B66,'SKU Data'!$A$2:$A$1780,0)),"") -> 2 | G66: =IFERROR(INDEX('SKU Data'!$J$2:$J$1780,MATCH($B66,'SKU Data'!$A$2:$A$1780,0)),"") -> 0.25 | H66: =IFERROR(G66/Settings!$B$3,"") -> 8.0681205 | J66: =IFERROR(INDEX('SKU Data'!$H$2:$H$1780,MATCH($B66,'SKU Data'!$A$2:$A$1780,0)),"") -> 109.9 | K66: =IFERROR(INDEX('SKU Data'!$W$2:$W$1780,MATCH($B66,'SKU Data'!$A$2:$A$1780,0)),"") -> 3 - Monitor
A67: 8 | B67: FYF-native-flowers-designer-bouquet-G-3 | C67: =IFERROR(INDEX('SKU Data'!$B$2:$B$1780,MATCH($B67,'SKU Data'!$A$2:$A$1780,0)),"") -> Native Flowers Designer Bouquet | D67: =IFERROR(INDEX('SKU Data'!$D$2:$D$1780,MATCH($B67,'SKU Data'!$A$2:$A$1780,0)),"") -> FYF | E67: =IFERROR(INDEX('SKU Data'!$E$2:$E$1780,MATCH($B67,'SKU Data'!$A$2:$A$1780,0)),"") -> 9 | F67: =IFERROR(INDEX('SKU Data'!$F$2:$F$1780,MATCH($B67,'SKU Data'!$A$2:$A$1780,0)),"") -> 2 | G67: =IFERROR(INDEX('SKU Data'!$J$2:$J$1780,MATCH($B67,'SKU Data'!$A$2:$A$1780,0)),"") -> 0.22222222 | H67: =IFERROR(G67/Settings!$B$3,"") -> 7.1716626 | J67: =IFERROR(INDEX('SKU Data'!$H$2:$H$1780,MATCH($B67,'SKU Data'!$A$2:$A$1780,0)),"") -> 269.9 | K67: =IFERROR(INDEX('SKU Data'!$W$2:$W$1780,MATCH($B67,'SKU Data'!$A$2:$A$1780,0)),"") -> 3 - Monitor
A69: E) BRAND / family anomalies (live from Brands tab)
